package com.tencent.mm.sdk.b;

import com.tencent.mm.a.a;

public final class d
{
  private final a E;
  private c<String, String> F;
  
  /* Error */
  public final String i(String paramString)
  {
    // Byte code:
    //   0: aload_1
    //   1: astore_3
    //   2: aload_1
    //   3: ldc 15
    //   5: invokevirtual 21	java/lang/String:startsWith	(Ljava/lang/String;)Z
    //   8: ifeq +184 -> 192
    //   11: aload_0
    //   12: getfield 23	com/tencent/mm/sdk/b/d:F	Lcom/tencent/mm/sdk/b/c;
    //   15: aload_1
    //   16: invokevirtual 29	com/tencent/mm/sdk/b/c:a	(Ljava/lang/Object;)Z
    //   19: ifeq +19 -> 38
    //   22: aload_0
    //   23: getfield 23	com/tencent/mm/sdk/b/d:F	Lcom/tencent/mm/sdk/b/c;
    //   26: aload_1
    //   27: invokevirtual 33	com/tencent/mm/sdk/b/c:get	(Ljava/lang/Object;)Ljava/lang/Object;
    //   30: checkcast 17	java/lang/String
    //   33: astore_3
    //   34: aload_3
    //   35: astore_1
    //   36: aload_1
    //   37: areturn
    //   38: aload_1
    //   39: iconst_1
    //   40: invokevirtual 37	java/lang/String:substring	(I)Ljava/lang/String;
    //   43: astore_3
    //   44: aload_3
    //   45: ldc 39
    //   47: invokevirtual 43	java/lang/String:split	(Ljava/lang/String;)[Ljava/lang/String;
    //   50: astore 4
    //   52: aload 4
    //   54: arraylength
    //   55: iconst_1
    //   56: if_icmple +145 -> 201
    //   59: aload 4
    //   61: iconst_0
    //   62: aaload
    //   63: astore 5
    //   65: aload 4
    //   67: iconst_0
    //   68: aaload
    //   69: invokestatic 49	java/lang/Integer:valueOf	(Ljava/lang/String;)Ljava/lang/Integer;
    //   72: invokevirtual 53	java/lang/Integer:intValue	()I
    //   75: istore_2
    //   76: aload_3
    //   77: aload 5
    //   79: invokevirtual 56	java/lang/String:length	()I
    //   82: iconst_1
    //   83: iadd
    //   84: aload 5
    //   86: invokevirtual 56	java/lang/String:length	()I
    //   89: iconst_1
    //   90: iadd
    //   91: iload_2
    //   92: iadd
    //   93: invokevirtual 59	java/lang/String:substring	(II)Ljava/lang/String;
    //   96: astore 4
    //   98: aload_3
    //   99: iload_2
    //   100: aload 5
    //   102: invokevirtual 56	java/lang/String:length	()I
    //   105: iconst_1
    //   106: iadd
    //   107: iadd
    //   108: invokevirtual 37	java/lang/String:substring	(I)Ljava/lang/String;
    //   111: astore 6
    //   113: new 61	java/lang/StringBuilder
    //   116: astore 5
    //   118: aload 5
    //   120: invokespecial 65	java/lang/StringBuilder:<init>	()V
    //   123: aload 5
    //   125: aload_0
    //   126: getfield 67	com/tencent/mm/sdk/b/d:E	Lcom/tencent/mm/a/a;
    //   129: aload 4
    //   131: invokevirtual 72	com/tencent/mm/a/a:h	(Ljava/lang/String;)Ljava/lang/String;
    //   134: invokevirtual 76	java/lang/StringBuilder:append	(Ljava/lang/String;)Ljava/lang/StringBuilder;
    //   137: aload 6
    //   139: invokevirtual 76	java/lang/StringBuilder:append	(Ljava/lang/String;)Ljava/lang/StringBuilder;
    //   142: invokevirtual 80	java/lang/StringBuilder:toString	()Ljava/lang/String;
    //   145: astore 4
    //   147: aload_0
    //   148: getfield 23	com/tencent/mm/sdk/b/d:F	Lcom/tencent/mm/sdk/b/c;
    //   151: aload_1
    //   152: aload 4
    //   154: invokevirtual 84	com/tencent/mm/sdk/b/c:put	(Ljava/lang/Object;Ljava/lang/Object;)Ljava/lang/Object;
    //   157: pop
    //   158: aload 4
    //   160: astore_1
    //   161: goto -125 -> 36
    //   164: astore 4
    //   166: aload_1
    //   167: astore_3
    //   168: aload 4
    //   170: astore_1
    //   171: aload_1
    //   172: invokevirtual 87	java/lang/Exception:printStackTrace	()V
    //   175: new 61	java/lang/StringBuilder
    //   178: dup
    //   179: ldc 89
    //   181: invokespecial 92	java/lang/StringBuilder:<init>	(Ljava/lang/String;)V
    //   184: aload_3
    //   185: invokevirtual 76	java/lang/StringBuilder:append	(Ljava/lang/String;)Ljava/lang/StringBuilder;
    //   188: invokevirtual 80	java/lang/StringBuilder:toString	()Ljava/lang/String;
    //   191: astore_3
    //   192: aload_3
    //   193: astore_1
    //   194: goto -158 -> 36
    //   197: astore_1
    //   198: goto -27 -> 171
    //   201: goto -9 -> 192
    // Local variable table:
    //   start	length	slot	name	signature
    //   0	204	0	this	d
    //   0	204	1	paramString	String
    //   75	33	2	i	int
    //   1	192	3	str1	String
    //   50	109	4	localObject	Object
    //   164	5	4	localException	Exception
    //   63	61	5	localStringBuilder	StringBuilder
    //   111	27	6	str2	String
    // Exception table:
    //   from	to	target	type
    //   2	34	164	java/lang/Exception
    //   38	44	164	java/lang/Exception
    //   44	59	197	java/lang/Exception
    //   65	158	197	java/lang/Exception
  }
}


/* Location:              /Users/hanlian/Downloads/WiFi万能钥匙dex1-dex2jar.jar!/com/tencent/mm/sdk/b/d.class
 * Java compiler version: 6 (50.0)
 * JD-Core Version:       0.7.1
 */