package com.c.d.a.a.a;

import com.b.b.h;
import com.b.b.m;
import com.b.b.m.a;
import com.b.b.v;
import com.b.b.x;

public final class c
{
  public static final class a
    extends m<a, a>
    implements c.b
  {
    private static final a m;
    private static volatile x<a> n;
    private String d = "";
    private String e = "";
    private String f = "";
    private String g = "";
    private String h = "";
    private String i = "";
    private String j = "";
    private String k = "";
    private int l;
    
    static
    {
      a locala = new a();
      m = locala;
      locala.e();
    }
    
    public static a l()
    {
      return (a)m.g();
    }
    
    /* Error */
    protected final Object a(int paramInt, Object paramObject1, Object paramObject2)
    {
      // Byte code:
      //   0: iconst_1
      //   1: istore 7
      //   3: iconst_0
      //   4: istore 4
      //   6: getstatic 81	com/c/d/a/a/a/c$1:a	[I
      //   9: iload_1
      //   10: iconst_1
      //   11: isub
      //   12: iaload
      //   13: tableswitch	default:+47->60, 1:+55->68, 2:+65->78, 3:+72->85, 4:+77->90, 5:+89->102, 6:+677->690, 7:+955->968, 8:+962->975
      //   60: new 83	java/lang/UnsupportedOperationException
      //   63: dup
      //   64: invokespecial 84	java/lang/UnsupportedOperationException:<init>	()V
      //   67: athrow
      //   68: new 2	com/c/d/a/a/a/c$a
      //   71: dup
      //   72: invokespecial 33	com/c/d/a/a/a/c$a:<init>	()V
      //   75: astore_2
      //   76: aload_2
      //   77: areturn
      //   78: getstatic 35	com/c/d/a/a/a/c$a:m	Lcom/c/d/a/a/a/c$a;
      //   81: astore_2
      //   82: goto -6 -> 76
      //   85: aconst_null
      //   86: astore_2
      //   87: goto -11 -> 76
      //   90: new 12	com/c/d/a/a/a/c$a$a
      //   93: dup
      //   94: iconst_0
      //   95: invokespecial 87	com/c/d/a/a/a/c$a$a:<init>	(B)V
      //   98: astore_2
      //   99: goto -23 -> 76
      //   102: aload_2
      //   103: checkcast 89	com/b/b/m$j
      //   106: astore_2
      //   107: aload_3
      //   108: checkcast 2	com/c/d/a/a/a/c$a
      //   111: astore_3
      //   112: aload_0
      //   113: getfield 43	com/c/d/a/a/a/c$a:d	Ljava/lang/String;
      //   116: invokevirtual 95	java/lang/String:isEmpty	()Z
      //   119: ifne +463 -> 582
      //   122: iconst_1
      //   123: istore 5
      //   125: aload_0
      //   126: getfield 43	com/c/d/a/a/a/c$a:d	Ljava/lang/String;
      //   129: astore 8
      //   131: aload_3
      //   132: getfield 43	com/c/d/a/a/a/c$a:d	Ljava/lang/String;
      //   135: invokevirtual 95	java/lang/String:isEmpty	()Z
      //   138: ifne +450 -> 588
      //   141: iconst_1
      //   142: istore 6
      //   144: aload_0
      //   145: aload_2
      //   146: iload 5
      //   148: aload 8
      //   150: iload 6
      //   152: aload_3
      //   153: getfield 43	com/c/d/a/a/a/c$a:d	Ljava/lang/String;
      //   156: invokeinterface 98 5 0
      //   161: putfield 43	com/c/d/a/a/a/c$a:d	Ljava/lang/String;
      //   164: aload_0
      //   165: getfield 45	com/c/d/a/a/a/c$a:e	Ljava/lang/String;
      //   168: invokevirtual 95	java/lang/String:isEmpty	()Z
      //   171: ifne +423 -> 594
      //   174: iconst_1
      //   175: istore 5
      //   177: aload_0
      //   178: getfield 45	com/c/d/a/a/a/c$a:e	Ljava/lang/String;
      //   181: astore 8
      //   183: aload_3
      //   184: getfield 45	com/c/d/a/a/a/c$a:e	Ljava/lang/String;
      //   187: invokevirtual 95	java/lang/String:isEmpty	()Z
      //   190: ifne +410 -> 600
      //   193: iconst_1
      //   194: istore 6
      //   196: aload_0
      //   197: aload_2
      //   198: iload 5
      //   200: aload 8
      //   202: iload 6
      //   204: aload_3
      //   205: getfield 45	com/c/d/a/a/a/c$a:e	Ljava/lang/String;
      //   208: invokeinterface 98 5 0
      //   213: putfield 45	com/c/d/a/a/a/c$a:e	Ljava/lang/String;
      //   216: aload_0
      //   217: getfield 47	com/c/d/a/a/a/c$a:f	Ljava/lang/String;
      //   220: invokevirtual 95	java/lang/String:isEmpty	()Z
      //   223: ifne +383 -> 606
      //   226: iconst_1
      //   227: istore 5
      //   229: aload_0
      //   230: getfield 47	com/c/d/a/a/a/c$a:f	Ljava/lang/String;
      //   233: astore 8
      //   235: aload_3
      //   236: getfield 47	com/c/d/a/a/a/c$a:f	Ljava/lang/String;
      //   239: invokevirtual 95	java/lang/String:isEmpty	()Z
      //   242: ifne +370 -> 612
      //   245: iconst_1
      //   246: istore 6
      //   248: aload_0
      //   249: aload_2
      //   250: iload 5
      //   252: aload 8
      //   254: iload 6
      //   256: aload_3
      //   257: getfield 47	com/c/d/a/a/a/c$a:f	Ljava/lang/String;
      //   260: invokeinterface 98 5 0
      //   265: putfield 47	com/c/d/a/a/a/c$a:f	Ljava/lang/String;
      //   268: aload_0
      //   269: getfield 49	com/c/d/a/a/a/c$a:g	Ljava/lang/String;
      //   272: invokevirtual 95	java/lang/String:isEmpty	()Z
      //   275: ifne +343 -> 618
      //   278: iconst_1
      //   279: istore 5
      //   281: aload_0
      //   282: getfield 49	com/c/d/a/a/a/c$a:g	Ljava/lang/String;
      //   285: astore 8
      //   287: aload_3
      //   288: getfield 49	com/c/d/a/a/a/c$a:g	Ljava/lang/String;
      //   291: invokevirtual 95	java/lang/String:isEmpty	()Z
      //   294: ifne +330 -> 624
      //   297: iconst_1
      //   298: istore 6
      //   300: aload_0
      //   301: aload_2
      //   302: iload 5
      //   304: aload 8
      //   306: iload 6
      //   308: aload_3
      //   309: getfield 49	com/c/d/a/a/a/c$a:g	Ljava/lang/String;
      //   312: invokeinterface 98 5 0
      //   317: putfield 49	com/c/d/a/a/a/c$a:g	Ljava/lang/String;
      //   320: aload_0
      //   321: getfield 51	com/c/d/a/a/a/c$a:h	Ljava/lang/String;
      //   324: invokevirtual 95	java/lang/String:isEmpty	()Z
      //   327: ifne +303 -> 630
      //   330: iconst_1
      //   331: istore 5
      //   333: aload_0
      //   334: getfield 51	com/c/d/a/a/a/c$a:h	Ljava/lang/String;
      //   337: astore 8
      //   339: aload_3
      //   340: getfield 51	com/c/d/a/a/a/c$a:h	Ljava/lang/String;
      //   343: invokevirtual 95	java/lang/String:isEmpty	()Z
      //   346: ifne +290 -> 636
      //   349: iconst_1
      //   350: istore 6
      //   352: aload_0
      //   353: aload_2
      //   354: iload 5
      //   356: aload 8
      //   358: iload 6
      //   360: aload_3
      //   361: getfield 51	com/c/d/a/a/a/c$a:h	Ljava/lang/String;
      //   364: invokeinterface 98 5 0
      //   369: putfield 51	com/c/d/a/a/a/c$a:h	Ljava/lang/String;
      //   372: aload_0
      //   373: getfield 53	com/c/d/a/a/a/c$a:i	Ljava/lang/String;
      //   376: invokevirtual 95	java/lang/String:isEmpty	()Z
      //   379: ifne +263 -> 642
      //   382: iconst_1
      //   383: istore 5
      //   385: aload_0
      //   386: getfield 53	com/c/d/a/a/a/c$a:i	Ljava/lang/String;
      //   389: astore 8
      //   391: aload_3
      //   392: getfield 53	com/c/d/a/a/a/c$a:i	Ljava/lang/String;
      //   395: invokevirtual 95	java/lang/String:isEmpty	()Z
      //   398: ifne +250 -> 648
      //   401: iconst_1
      //   402: istore 6
      //   404: aload_0
      //   405: aload_2
      //   406: iload 5
      //   408: aload 8
      //   410: iload 6
      //   412: aload_3
      //   413: getfield 53	com/c/d/a/a/a/c$a:i	Ljava/lang/String;
      //   416: invokeinterface 98 5 0
      //   421: putfield 53	com/c/d/a/a/a/c$a:i	Ljava/lang/String;
      //   424: aload_0
      //   425: getfield 55	com/c/d/a/a/a/c$a:j	Ljava/lang/String;
      //   428: invokevirtual 95	java/lang/String:isEmpty	()Z
      //   431: ifne +223 -> 654
      //   434: iconst_1
      //   435: istore 5
      //   437: aload_0
      //   438: getfield 55	com/c/d/a/a/a/c$a:j	Ljava/lang/String;
      //   441: astore 8
      //   443: aload_3
      //   444: getfield 55	com/c/d/a/a/a/c$a:j	Ljava/lang/String;
      //   447: invokevirtual 95	java/lang/String:isEmpty	()Z
      //   450: ifne +210 -> 660
      //   453: iconst_1
      //   454: istore 6
      //   456: aload_0
      //   457: aload_2
      //   458: iload 5
      //   460: aload 8
      //   462: iload 6
      //   464: aload_3
      //   465: getfield 55	com/c/d/a/a/a/c$a:j	Ljava/lang/String;
      //   468: invokeinterface 98 5 0
      //   473: putfield 55	com/c/d/a/a/a/c$a:j	Ljava/lang/String;
      //   476: aload_0
      //   477: getfield 57	com/c/d/a/a/a/c$a:k	Ljava/lang/String;
      //   480: invokevirtual 95	java/lang/String:isEmpty	()Z
      //   483: ifne +183 -> 666
      //   486: iconst_1
      //   487: istore 5
      //   489: aload_0
      //   490: getfield 57	com/c/d/a/a/a/c$a:k	Ljava/lang/String;
      //   493: astore 8
      //   495: aload_3
      //   496: getfield 57	com/c/d/a/a/a/c$a:k	Ljava/lang/String;
      //   499: invokevirtual 95	java/lang/String:isEmpty	()Z
      //   502: ifne +170 -> 672
      //   505: iconst_1
      //   506: istore 6
      //   508: aload_0
      //   509: aload_2
      //   510: iload 5
      //   512: aload 8
      //   514: iload 6
      //   516: aload_3
      //   517: getfield 57	com/c/d/a/a/a/c$a:k	Ljava/lang/String;
      //   520: invokeinterface 98 5 0
      //   525: putfield 57	com/c/d/a/a/a/c$a:k	Ljava/lang/String;
      //   528: aload_0
      //   529: getfield 60	com/c/d/a/a/a/c$a:l	I
      //   532: ifeq +146 -> 678
      //   535: iconst_1
      //   536: istore 5
      //   538: aload_0
      //   539: getfield 60	com/c/d/a/a/a/c$a:l	I
      //   542: istore_1
      //   543: aload_3
      //   544: getfield 60	com/c/d/a/a/a/c$a:l	I
      //   547: ifeq +137 -> 684
      //   550: iload 7
      //   552: istore 6
      //   554: aload_0
      //   555: aload_2
      //   556: iload 5
      //   558: iload_1
      //   559: iload 6
      //   561: aload_3
      //   562: getfield 60	com/c/d/a/a/a/c$a:l	I
      //   565: invokeinterface 101 5 0
      //   570: putfield 60	com/c/d/a/a/a/c$a:l	I
      //   573: getstatic 106	com/b/b/m$h:a	Lcom/b/b/m$h;
      //   576: astore_2
      //   577: aload_0
      //   578: astore_2
      //   579: goto -503 -> 76
      //   582: iconst_0
      //   583: istore 5
      //   585: goto -460 -> 125
      //   588: iconst_0
      //   589: istore 6
      //   591: goto -447 -> 144
      //   594: iconst_0
      //   595: istore 5
      //   597: goto -420 -> 177
      //   600: iconst_0
      //   601: istore 6
      //   603: goto -407 -> 196
      //   606: iconst_0
      //   607: istore 5
      //   609: goto -380 -> 229
      //   612: iconst_0
      //   613: istore 6
      //   615: goto -367 -> 248
      //   618: iconst_0
      //   619: istore 5
      //   621: goto -340 -> 281
      //   624: iconst_0
      //   625: istore 6
      //   627: goto -327 -> 300
      //   630: iconst_0
      //   631: istore 5
      //   633: goto -300 -> 333
      //   636: iconst_0
      //   637: istore 6
      //   639: goto -287 -> 352
      //   642: iconst_0
      //   643: istore 5
      //   645: goto -260 -> 385
      //   648: iconst_0
      //   649: istore 6
      //   651: goto -247 -> 404
      //   654: iconst_0
      //   655: istore 5
      //   657: goto -220 -> 437
      //   660: iconst_0
      //   661: istore 6
      //   663: goto -207 -> 456
      //   666: iconst_0
      //   667: istore 5
      //   669: goto -180 -> 489
      //   672: iconst_0
      //   673: istore 6
      //   675: goto -167 -> 508
      //   678: iconst_0
      //   679: istore 5
      //   681: goto -143 -> 538
      //   684: iconst_0
      //   685: istore 6
      //   687: goto -133 -> 554
      //   690: aload_2
      //   691: checkcast 108	com/b/b/g
      //   694: astore_2
      //   695: iload 4
      //   697: istore_1
      //   698: iload_1
      //   699: ifne +269 -> 968
      //   702: aload_2
      //   703: invokevirtual 111	com/b/b/g:a	()I
      //   706: istore 4
      //   708: iload 4
      //   710: lookupswitch	default:+90->800, 0:+104->814, 10:+109->819, 18:+139->849, 26:+181->891, 34:+192->902, 42:+203->913, 50:+214->924, 58:+225->935, 66:+236->946, 72:+247->957
      //   800: aload_2
      //   801: iload 4
      //   803: invokevirtual 114	com/b/b/g:b	(I)Z
      //   806: ifne -108 -> 698
      //   809: iconst_1
      //   810: istore_1
      //   811: goto -113 -> 698
      //   814: iconst_1
      //   815: istore_1
      //   816: goto -118 -> 698
      //   819: aload_0
      //   820: aload_2
      //   821: invokevirtual 117	com/b/b/g:k	()Ljava/lang/String;
      //   824: putfield 43	com/c/d/a/a/a/c$a:d	Ljava/lang/String;
      //   827: goto -129 -> 698
      //   830: astore_2
      //   831: new 119	java/lang/RuntimeException
      //   834: astore_3
      //   835: aload_3
      //   836: aload_2
      //   837: aload_0
      //   838: invokevirtual 122	com/b/b/o:a	(Lcom/b/b/u;)Lcom/b/b/o;
      //   841: invokespecial 125	java/lang/RuntimeException:<init>	(Ljava/lang/Throwable;)V
      //   844: aload_3
      //   845: athrow
      //   846: astore_2
      //   847: aload_2
      //   848: athrow
      //   849: aload_0
      //   850: aload_2
      //   851: invokevirtual 117	com/b/b/g:k	()Ljava/lang/String;
      //   854: putfield 45	com/c/d/a/a/a/c$a:e	Ljava/lang/String;
      //   857: goto -159 -> 698
      //   860: astore_2
      //   861: new 119	java/lang/RuntimeException
      //   864: astore 8
      //   866: new 74	com/b/b/o
      //   869: astore_3
      //   870: aload_3
      //   871: aload_2
      //   872: invokevirtual 128	java/io/IOException:getMessage	()Ljava/lang/String;
      //   875: invokespecial 131	com/b/b/o:<init>	(Ljava/lang/String;)V
      //   878: aload 8
      //   880: aload_3
      //   881: aload_0
      //   882: invokevirtual 122	com/b/b/o:a	(Lcom/b/b/u;)Lcom/b/b/o;
      //   885: invokespecial 125	java/lang/RuntimeException:<init>	(Ljava/lang/Throwable;)V
      //   888: aload 8
      //   890: athrow
      //   891: aload_0
      //   892: aload_2
      //   893: invokevirtual 117	com/b/b/g:k	()Ljava/lang/String;
      //   896: putfield 47	com/c/d/a/a/a/c$a:f	Ljava/lang/String;
      //   899: goto -201 -> 698
      //   902: aload_0
      //   903: aload_2
      //   904: invokevirtual 117	com/b/b/g:k	()Ljava/lang/String;
      //   907: putfield 49	com/c/d/a/a/a/c$a:g	Ljava/lang/String;
      //   910: goto -212 -> 698
      //   913: aload_0
      //   914: aload_2
      //   915: invokevirtual 117	com/b/b/g:k	()Ljava/lang/String;
      //   918: putfield 51	com/c/d/a/a/a/c$a:h	Ljava/lang/String;
      //   921: goto -223 -> 698
      //   924: aload_0
      //   925: aload_2
      //   926: invokevirtual 117	com/b/b/g:k	()Ljava/lang/String;
      //   929: putfield 53	com/c/d/a/a/a/c$a:i	Ljava/lang/String;
      //   932: goto -234 -> 698
      //   935: aload_0
      //   936: aload_2
      //   937: invokevirtual 117	com/b/b/g:k	()Ljava/lang/String;
      //   940: putfield 55	com/c/d/a/a/a/c$a:j	Ljava/lang/String;
      //   943: goto -245 -> 698
      //   946: aload_0
      //   947: aload_2
      //   948: invokevirtual 117	com/b/b/g:k	()Ljava/lang/String;
      //   951: putfield 57	com/c/d/a/a/a/c$a:k	Ljava/lang/String;
      //   954: goto -256 -> 698
      //   957: aload_0
      //   958: aload_2
      //   959: invokevirtual 133	com/b/b/g:f	()I
      //   962: putfield 60	com/c/d/a/a/a/c$a:l	I
      //   965: goto -267 -> 698
      //   968: getstatic 35	com/c/d/a/a/a/c$a:m	Lcom/c/d/a/a/a/c$a;
      //   971: astore_2
      //   972: goto -896 -> 76
      //   975: getstatic 135	com/c/d/a/a/a/c$a:n	Lcom/b/b/x;
      //   978: ifnonnull +30 -> 1008
      //   981: ldc 2
      //   983: monitorenter
      //   984: getstatic 135	com/c/d/a/a/a/c$a:n	Lcom/b/b/x;
      //   987: ifnonnull +18 -> 1005
      //   990: new 137	com/b/b/m$b
      //   993: astore_2
      //   994: aload_2
      //   995: getstatic 35	com/c/d/a/a/a/c$a:m	Lcom/c/d/a/a/a/c$a;
      //   998: invokespecial 140	com/b/b/m$b:<init>	(Lcom/b/b/m;)V
      //   1001: aload_2
      //   1002: putstatic 135	com/c/d/a/a/a/c$a:n	Lcom/b/b/x;
      //   1005: ldc 2
      //   1007: monitorexit
      //   1008: getstatic 135	com/c/d/a/a/a/c$a:n	Lcom/b/b/x;
      //   1011: astore_2
      //   1012: goto -936 -> 76
      //   1015: astore_2
      //   1016: ldc 2
      //   1018: monitorexit
      //   1019: aload_2
      //   1020: athrow
      // Local variable table:
      //   start	length	slot	name	signature
      //   0	1021	0	this	a
      //   0	1021	1	paramInt	int
      //   0	1021	2	paramObject1	Object
      //   0	1021	3	paramObject2	Object
      //   4	798	4	i1	int
      //   123	557	5	bool1	boolean
      //   142	544	6	bool2	boolean
      //   1	550	7	bool3	boolean
      //   129	760	8	localObject	Object
      // Exception table:
      //   from	to	target	type
      //   702	708	830	com/b/b/o
      //   800	809	830	com/b/b/o
      //   819	827	830	com/b/b/o
      //   849	857	830	com/b/b/o
      //   891	899	830	com/b/b/o
      //   902	910	830	com/b/b/o
      //   913	921	830	com/b/b/o
      //   924	932	830	com/b/b/o
      //   935	943	830	com/b/b/o
      //   946	954	830	com/b/b/o
      //   957	965	830	com/b/b/o
      //   702	708	846	finally
      //   800	809	846	finally
      //   819	827	846	finally
      //   831	846	846	finally
      //   849	857	846	finally
      //   861	891	846	finally
      //   891	899	846	finally
      //   902	910	846	finally
      //   913	921	846	finally
      //   924	932	846	finally
      //   935	943	846	finally
      //   946	954	846	finally
      //   957	965	846	finally
      //   702	708	860	java/io/IOException
      //   800	809	860	java/io/IOException
      //   819	827	860	java/io/IOException
      //   849	857	860	java/io/IOException
      //   891	899	860	java/io/IOException
      //   902	910	860	java/io/IOException
      //   913	921	860	java/io/IOException
      //   924	932	860	java/io/IOException
      //   935	943	860	java/io/IOException
      //   946	954	860	java/io/IOException
      //   957	965	860	java/io/IOException
      //   984	1005	1015	finally
      //   1005	1008	1015	finally
      //   1016	1019	1015	finally
    }
    
    public final void a(h paramh)
    {
      if (!this.d.isEmpty()) {
        paramh.a(1, this.d);
      }
      if (!this.e.isEmpty()) {
        paramh.a(2, this.e);
      }
      if (!this.f.isEmpty()) {
        paramh.a(3, this.f);
      }
      if (!this.g.isEmpty()) {
        paramh.a(4, this.g);
      }
      if (!this.h.isEmpty()) {
        paramh.a(5, this.h);
      }
      if (!this.i.isEmpty()) {
        paramh.a(6, this.i);
      }
      if (!this.j.isEmpty()) {
        paramh.a(7, this.j);
      }
      if (!this.k.isEmpty()) {
        paramh.a(8, this.k);
      }
      if (this.l != 0) {
        paramh.a(this.l);
      }
    }
    
    public final int k()
    {
      int i2 = this.c;
      if (i2 != -1) {}
      for (;;)
      {
        return i2;
        int i1 = 0;
        if (!this.d.isEmpty()) {
          i1 = h.b(1, this.d) + 0;
        }
        i2 = i1;
        if (!this.e.isEmpty()) {
          i2 = i1 + h.b(2, this.e);
        }
        i1 = i2;
        if (!this.f.isEmpty()) {
          i1 = i2 + h.b(3, this.f);
        }
        i2 = i1;
        if (!this.g.isEmpty()) {
          i2 = i1 + h.b(4, this.g);
        }
        i1 = i2;
        if (!this.h.isEmpty()) {
          i1 = i2 + h.b(5, this.h);
        }
        int i3 = i1;
        if (!this.i.isEmpty()) {
          i3 = i1 + h.b(6, this.i);
        }
        i2 = i3;
        if (!this.j.isEmpty()) {
          i2 = i3 + h.b(7, this.j);
        }
        i1 = i2;
        if (!this.k.isEmpty()) {
          i1 = i2 + h.b(8, this.k);
        }
        i2 = i1;
        if (this.l != 0) {
          i2 = i1 + h.e(this.l);
        }
        this.c = i2;
      }
    }
    
    public static final class a
      extends m.a<c.a, a>
      implements c.b
    {
      private a()
      {
        super();
      }
      
      public final a a(int paramInt)
      {
        b();
        c.a.a((c.a)this.a, paramInt);
        return this;
      }
      
      public final a a(String paramString)
      {
        b();
        c.a.a((c.a)this.a, paramString);
        return this;
      }
      
      public final a b(String paramString)
      {
        b();
        c.a.b((c.a)this.a, paramString);
        return this;
      }
      
      public final a c(String paramString)
      {
        b();
        c.a.c((c.a)this.a, paramString);
        return this;
      }
      
      public final a d(String paramString)
      {
        b();
        c.a.d((c.a)this.a, paramString);
        return this;
      }
      
      public final a e(String paramString)
      {
        b();
        c.a.e((c.a)this.a, paramString);
        return this;
      }
      
      public final a f(String paramString)
      {
        b();
        c.a.f((c.a)this.a, paramString);
        return this;
      }
      
      public final a g(String paramString)
      {
        b();
        c.a.g((c.a)this.a, paramString);
        return this;
      }
    }
  }
  
  public static abstract interface b
    extends v
  {}
}


/* Location:              /Users/hanlian/Downloads/WiFi万能钥匙dex1-dex2jar.jar!/com/c/d/a/a/a/c.class
 * Java compiler version: 6 (50.0)
 * JD-Core Version:       0.7.1
 */