package com.c.a.a.a.c.a.a.a;

import com.b.b.ak.a;
import com.b.b.h;
import com.b.b.m;
import com.b.b.m.a;
import com.b.b.r;
import com.b.b.t;
import com.b.b.v;
import com.b.b.x;
import java.util.Collections;
import java.util.Iterator;
import java.util.Map;
import java.util.Map.Entry;
import java.util.Set;

public final class b
{
  public static final class a
    extends m<a, d>
    implements b.b
  {
    private static final a g;
    private static volatile x<a> h;
    private int d;
    private t<String, a> e = t.a();
    private String f = "";
    
    static
    {
      a locala = new a();
      g = locala;
      locala.e();
    }
    
    public static a a(byte[] paramArrayOfByte)
    {
      return (a)m.a(g, paramArrayOfByte);
    }
    
    /* Error */
    protected final Object a(int paramInt, Object paramObject1, Object paramObject2)
    {
      // Byte code:
      //   0: iconst_1
      //   1: istore 6
      //   3: iconst_0
      //   4: istore 4
      //   6: getstatic 72	com/c/a/a/a/c/a/a/a/b$1:a	[I
      //   9: iload_1
      //   10: iconst_1
      //   11: isub
      //   12: iaload
      //   13: tableswitch	default:+47->60, 1:+55->68, 2:+65->78, 3:+72->85, 4:+84->97, 5:+96->109, 6:+214->227, 7:+391->404, 8:+398->411
      //   60: new 74	java/lang/UnsupportedOperationException
      //   63: dup
      //   64: invokespecial 75	java/lang/UnsupportedOperationException:<init>	()V
      //   67: athrow
      //   68: new 2	com/c/a/a/a/c/a/a/a/b$a
      //   71: dup
      //   72: invokespecial 39	com/c/a/a/a/c/a/a/a/b$a:<init>	()V
      //   75: astore_2
      //   76: aload_2
      //   77: areturn
      //   78: getstatic 41	com/c/a/a/a/c/a/a/a/b$a:g	Lcom/c/a/a/a/c/a/a/a/b$a;
      //   81: astore_2
      //   82: goto -6 -> 76
      //   85: aload_0
      //   86: getfield 52	com/c/a/a/a/c/a/a/a/b$a:e	Lcom/b/b/t;
      //   89: invokevirtual 77	com/b/b/t:c	()V
      //   92: aconst_null
      //   93: astore_2
      //   94: goto -18 -> 76
      //   97: new 22	com/c/a/a/a/c/a/a/a/b$a$d
      //   100: dup
      //   101: iconst_0
      //   102: invokespecial 80	com/c/a/a/a/c/a/a/a/b$a$d:<init>	(B)V
      //   105: astore_2
      //   106: goto -30 -> 76
      //   109: aload_2
      //   110: checkcast 82	com/b/b/m$j
      //   113: astore 7
      //   115: aload_3
      //   116: checkcast 2	com/c/a/a/a/c/a/a/a/b$a
      //   119: astore_3
      //   120: aload_0
      //   121: aload 7
      //   123: aload_0
      //   124: getfield 52	com/c/a/a/a/c/a/a/a/b$a:e	Lcom/b/b/t;
      //   127: aload_3
      //   128: getfield 52	com/c/a/a/a/c/a/a/a/b$a:e	Lcom/b/b/t;
      //   131: invokeinterface 85 3 0
      //   136: putfield 52	com/c/a/a/a/c/a/a/a/b$a:e	Lcom/b/b/t;
      //   139: aload_0
      //   140: getfield 56	com/c/a/a/a/c/a/a/a/b$a:f	Ljava/lang/String;
      //   143: invokevirtual 91	java/lang/String:isEmpty	()Z
      //   146: ifne +69 -> 215
      //   149: iconst_1
      //   150: istore 5
      //   152: aload_0
      //   153: getfield 56	com/c/a/a/a/c/a/a/a/b$a:f	Ljava/lang/String;
      //   156: astore_2
      //   157: aload_3
      //   158: getfield 56	com/c/a/a/a/c/a/a/a/b$a:f	Ljava/lang/String;
      //   161: invokevirtual 91	java/lang/String:isEmpty	()Z
      //   164: ifne +57 -> 221
      //   167: aload_0
      //   168: aload 7
      //   170: iload 5
      //   172: aload_2
      //   173: iload 6
      //   175: aload_3
      //   176: getfield 56	com/c/a/a/a/c/a/a/a/b$a:f	Ljava/lang/String;
      //   179: invokeinterface 94 5 0
      //   184: putfield 56	com/c/a/a/a/c/a/a/a/b$a:f	Ljava/lang/String;
      //   187: aload_0
      //   188: astore_2
      //   189: aload 7
      //   191: getstatic 99	com/b/b/m$h:a	Lcom/b/b/m$h;
      //   194: if_acmpne -118 -> 76
      //   197: aload_0
      //   198: aload_0
      //   199: getfield 101	com/c/a/a/a/c/a/a/a/b$a:d	I
      //   202: aload_3
      //   203: getfield 101	com/c/a/a/a/c/a/a/a/b$a:d	I
      //   206: ior
      //   207: putfield 101	com/c/a/a/a/c/a/a/a/b$a:d	I
      //   210: aload_0
      //   211: astore_2
      //   212: goto -136 -> 76
      //   215: iconst_0
      //   216: istore 5
      //   218: goto -66 -> 152
      //   221: iconst_0
      //   222: istore 6
      //   224: goto -57 -> 167
      //   227: aload_2
      //   228: checkcast 103	com/b/b/g
      //   231: astore_2
      //   232: aload_3
      //   233: checkcast 105	com/b/b/j
      //   236: astore_3
      //   237: iload 4
      //   239: istore_1
      //   240: iload_1
      //   241: ifne +163 -> 404
      //   244: aload_2
      //   245: invokevirtual 108	com/b/b/g:a	()I
      //   248: istore 4
      //   250: iload 4
      //   252: lookupswitch	default:+36->288, 0:+50->302, 10:+55->307, 18:+110->362
      //   288: aload_2
      //   289: iload 4
      //   291: invokevirtual 111	com/b/b/g:b	(I)Z
      //   294: ifne -54 -> 240
      //   297: iconst_1
      //   298: istore_1
      //   299: goto -59 -> 240
      //   302: iconst_1
      //   303: istore_1
      //   304: goto -64 -> 240
      //   307: aload_0
      //   308: getfield 52	com/c/a/a/a/c/a/a/a/b$a:e	Lcom/b/b/t;
      //   311: invokevirtual 113	com/b/b/t:d	()Z
      //   314: ifne +14 -> 328
      //   317: aload_0
      //   318: aload_0
      //   319: getfield 52	com/c/a/a/a/c/a/a/a/b$a:e	Lcom/b/b/t;
      //   322: invokevirtual 115	com/b/b/t:b	()Lcom/b/b/t;
      //   325: putfield 52	com/c/a/a/a/c/a/a/a/b$a:e	Lcom/b/b/t;
      //   328: getstatic 118	com/c/a/a/a/c/a/a/a/b$a$c:a	Lcom/b/b/r;
      //   331: aload_0
      //   332: getfield 52	com/c/a/a/a/c/a/a/a/b$a:e	Lcom/b/b/t;
      //   335: aload_2
      //   336: aload_3
      //   337: invokevirtual 123	com/b/b/r:a	(Lcom/b/b/t;Lcom/b/b/g;Lcom/b/b/j;)V
      //   340: goto -100 -> 240
      //   343: astore_3
      //   344: new 125	java/lang/RuntimeException
      //   347: astore_2
      //   348: aload_2
      //   349: aload_3
      //   350: aload_0
      //   351: invokevirtual 128	com/b/b/o:a	(Lcom/b/b/u;)Lcom/b/b/o;
      //   354: invokespecial 131	java/lang/RuntimeException:<init>	(Ljava/lang/Throwable;)V
      //   357: aload_2
      //   358: athrow
      //   359: astore_2
      //   360: aload_2
      //   361: athrow
      //   362: aload_0
      //   363: aload_2
      //   364: invokevirtual 135	com/b/b/g:k	()Ljava/lang/String;
      //   367: putfield 56	com/c/a/a/a/c/a/a/a/b$a:f	Ljava/lang/String;
      //   370: goto -130 -> 240
      //   373: astore_3
      //   374: new 125	java/lang/RuntimeException
      //   377: astore_2
      //   378: new 65	com/b/b/o
      //   381: astore 7
      //   383: aload 7
      //   385: aload_3
      //   386: invokevirtual 138	java/io/IOException:getMessage	()Ljava/lang/String;
      //   389: invokespecial 141	com/b/b/o:<init>	(Ljava/lang/String;)V
      //   392: aload_2
      //   393: aload 7
      //   395: aload_0
      //   396: invokevirtual 128	com/b/b/o:a	(Lcom/b/b/u;)Lcom/b/b/o;
      //   399: invokespecial 131	java/lang/RuntimeException:<init>	(Ljava/lang/Throwable;)V
      //   402: aload_2
      //   403: athrow
      //   404: getstatic 41	com/c/a/a/a/c/a/a/a/b$a:g	Lcom/c/a/a/a/c/a/a/a/b$a;
      //   407: astore_2
      //   408: goto -332 -> 76
      //   411: getstatic 143	com/c/a/a/a/c/a/a/a/b$a:h	Lcom/b/b/x;
      //   414: ifnonnull +30 -> 444
      //   417: ldc 2
      //   419: monitorenter
      //   420: getstatic 143	com/c/a/a/a/c/a/a/a/b$a:h	Lcom/b/b/x;
      //   423: ifnonnull +18 -> 441
      //   426: new 145	com/b/b/m$b
      //   429: astore_2
      //   430: aload_2
      //   431: getstatic 41	com/c/a/a/a/c/a/a/a/b$a:g	Lcom/c/a/a/a/c/a/a/a/b$a;
      //   434: invokespecial 148	com/b/b/m$b:<init>	(Lcom/b/b/m;)V
      //   437: aload_2
      //   438: putstatic 143	com/c/a/a/a/c/a/a/a/b$a:h	Lcom/b/b/x;
      //   441: ldc 2
      //   443: monitorexit
      //   444: getstatic 143	com/c/a/a/a/c/a/a/a/b$a:h	Lcom/b/b/x;
      //   447: astore_2
      //   448: goto -372 -> 76
      //   451: astore_2
      //   452: ldc 2
      //   454: monitorexit
      //   455: aload_2
      //   456: athrow
      // Local variable table:
      //   start	length	slot	name	signature
      //   0	457	0	this	a
      //   0	457	1	paramInt	int
      //   0	457	2	paramObject1	Object
      //   0	457	3	paramObject2	Object
      //   4	286	4	i	int
      //   150	67	5	bool1	boolean
      //   1	222	6	bool2	boolean
      //   113	281	7	localObject	Object
      // Exception table:
      //   from	to	target	type
      //   244	250	343	com/b/b/o
      //   288	297	343	com/b/b/o
      //   307	328	343	com/b/b/o
      //   328	340	343	com/b/b/o
      //   362	370	343	com/b/b/o
      //   244	250	359	finally
      //   288	297	359	finally
      //   307	328	359	finally
      //   328	340	359	finally
      //   344	359	359	finally
      //   362	370	359	finally
      //   374	404	359	finally
      //   244	250	373	java/io/IOException
      //   288	297	373	java/io/IOException
      //   307	328	373	java/io/IOException
      //   328	340	373	java/io/IOException
      //   362	370	373	java/io/IOException
      //   420	441	451	finally
      //   441	444	451	finally
      //   452	455	451	finally
    }
    
    public final void a(h paramh)
    {
      Iterator localIterator = this.e.entrySet().iterator();
      while (localIterator.hasNext())
      {
        Map.Entry localEntry = (Map.Entry)localIterator.next();
        c.a.a(paramh, 1, localEntry.getKey(), localEntry.getValue());
      }
      if (!this.f.isEmpty()) {
        paramh.a(2, this.f);
      }
    }
    
    public final int k()
    {
      int i = this.c;
      if (i != -1) {}
      for (;;)
      {
        return i;
        Iterator localIterator = this.e.entrySet().iterator();
        Map.Entry localEntry;
        for (int j = 0; localIterator.hasNext(); j = c.a.a(1, localEntry.getKey(), localEntry.getValue()) + j) {
          localEntry = (Map.Entry)localIterator.next();
        }
        i = j;
        if (!this.f.isEmpty()) {
          i = j + h.b(2, this.f);
        }
        this.c = i;
      }
    }
    
    public final Map<String, a> l()
    {
      return Collections.unmodifiableMap(this.e);
    }
    
    public final String m()
    {
      return this.f;
    }
    
    public static final class a
      extends m<a, a>
      implements b.a.b
    {
      private static final a A;
      private static volatile x<a> B;
      private String d = "";
      private String e = "";
      private String f = "";
      private String g = "";
      private String h = "";
      private String i = "";
      private String j = "";
      private String k = "";
      private String l = "";
      private String m = "";
      private String n = "";
      private String o = "";
      private String p = "";
      private String q = "";
      private String r = "";
      private String s = "";
      private String t = "";
      private String u = "";
      private String v = "";
      private String w = "";
      private String x = "";
      private String y = "";
      private String z = "";
      
      static
      {
        a locala = new a();
        A = locala;
        locala.e();
      }
      
      public static a I()
      {
        return A;
      }
      
      public final String A()
      {
        return this.s;
      }
      
      public final String B()
      {
        return this.t;
      }
      
      public final String C()
      {
        return this.u;
      }
      
      public final String D()
      {
        return this.v;
      }
      
      public final String E()
      {
        return this.w;
      }
      
      public final String F()
      {
        return this.x;
      }
      
      public final String G()
      {
        return this.y;
      }
      
      public final String H()
      {
        return this.z;
      }
      
      /* Error */
      protected final Object a(int paramInt, Object paramObject1, Object paramObject2)
      {
        // Byte code:
        //   0: iconst_1
        //   1: istore 7
        //   3: iconst_0
        //   4: istore 4
        //   6: getstatic 122	com/c/a/a/a/c/a/a/a/b$1:a	[I
        //   9: iload_1
        //   10: iconst_1
        //   11: isub
        //   12: iaload
        //   13: tableswitch	default:+47->60, 1:+55->68, 2:+65->78, 3:+72->85, 4:+77->90, 5:+89->102, 6:+1581->1594, 7:+2125->2138, 8:+2132->2145
        //   60: new 124	java/lang/UnsupportedOperationException
        //   63: dup
        //   64: invokespecial 125	java/lang/UnsupportedOperationException:<init>	()V
        //   67: athrow
        //   68: new 2	com/c/a/a/a/c/a/a/a/b$a$a
        //   71: dup
        //   72: invokespecial 48	com/c/a/a/a/c/a/a/a/b$a$a:<init>	()V
        //   75: astore_2
        //   76: aload_2
        //   77: areturn
        //   78: getstatic 50	com/c/a/a/a/c/a/a/a/b$a$a:A	Lcom/c/a/a/a/c/a/a/a/b$a$a;
        //   81: astore_2
        //   82: goto -6 -> 76
        //   85: aconst_null
        //   86: astore_2
        //   87: goto -11 -> 76
        //   90: new 14	com/c/a/a/a/c/a/a/a/b$a$a$a
        //   93: dup
        //   94: iconst_0
        //   95: invokespecial 128	com/c/a/a/a/c/a/a/a/b$a$a$a:<init>	(B)V
        //   98: astore_2
        //   99: goto -23 -> 76
        //   102: aload_2
        //   103: checkcast 130	com/b/b/m$j
        //   106: astore_2
        //   107: aload_3
        //   108: checkcast 2	com/c/a/a/a/c/a/a/a/b$a$a
        //   111: astore_3
        //   112: aload_0
        //   113: getfield 58	com/c/a/a/a/c/a/a/a/b$a$a:d	Ljava/lang/String;
        //   116: invokevirtual 136	java/lang/String:isEmpty	()Z
        //   119: ifne +1199 -> 1318
        //   122: iconst_1
        //   123: istore 5
        //   125: aload_0
        //   126: getfield 58	com/c/a/a/a/c/a/a/a/b$a$a:d	Ljava/lang/String;
        //   129: astore 8
        //   131: aload_3
        //   132: getfield 58	com/c/a/a/a/c/a/a/a/b$a$a:d	Ljava/lang/String;
        //   135: invokevirtual 136	java/lang/String:isEmpty	()Z
        //   138: ifne +1186 -> 1324
        //   141: iconst_1
        //   142: istore 6
        //   144: aload_0
        //   145: aload_2
        //   146: iload 5
        //   148: aload 8
        //   150: iload 6
        //   152: aload_3
        //   153: getfield 58	com/c/a/a/a/c/a/a/a/b$a$a:d	Ljava/lang/String;
        //   156: invokeinterface 139 5 0
        //   161: putfield 58	com/c/a/a/a/c/a/a/a/b$a$a:d	Ljava/lang/String;
        //   164: aload_0
        //   165: getfield 60	com/c/a/a/a/c/a/a/a/b$a$a:e	Ljava/lang/String;
        //   168: invokevirtual 136	java/lang/String:isEmpty	()Z
        //   171: ifne +1159 -> 1330
        //   174: iconst_1
        //   175: istore 5
        //   177: aload_0
        //   178: getfield 60	com/c/a/a/a/c/a/a/a/b$a$a:e	Ljava/lang/String;
        //   181: astore 8
        //   183: aload_3
        //   184: getfield 60	com/c/a/a/a/c/a/a/a/b$a$a:e	Ljava/lang/String;
        //   187: invokevirtual 136	java/lang/String:isEmpty	()Z
        //   190: ifne +1146 -> 1336
        //   193: iconst_1
        //   194: istore 6
        //   196: aload_0
        //   197: aload_2
        //   198: iload 5
        //   200: aload 8
        //   202: iload 6
        //   204: aload_3
        //   205: getfield 60	com/c/a/a/a/c/a/a/a/b$a$a:e	Ljava/lang/String;
        //   208: invokeinterface 139 5 0
        //   213: putfield 60	com/c/a/a/a/c/a/a/a/b$a$a:e	Ljava/lang/String;
        //   216: aload_0
        //   217: getfield 62	com/c/a/a/a/c/a/a/a/b$a$a:f	Ljava/lang/String;
        //   220: invokevirtual 136	java/lang/String:isEmpty	()Z
        //   223: ifne +1119 -> 1342
        //   226: iconst_1
        //   227: istore 5
        //   229: aload_0
        //   230: getfield 62	com/c/a/a/a/c/a/a/a/b$a$a:f	Ljava/lang/String;
        //   233: astore 8
        //   235: aload_3
        //   236: getfield 62	com/c/a/a/a/c/a/a/a/b$a$a:f	Ljava/lang/String;
        //   239: invokevirtual 136	java/lang/String:isEmpty	()Z
        //   242: ifne +1106 -> 1348
        //   245: iconst_1
        //   246: istore 6
        //   248: aload_0
        //   249: aload_2
        //   250: iload 5
        //   252: aload 8
        //   254: iload 6
        //   256: aload_3
        //   257: getfield 62	com/c/a/a/a/c/a/a/a/b$a$a:f	Ljava/lang/String;
        //   260: invokeinterface 139 5 0
        //   265: putfield 62	com/c/a/a/a/c/a/a/a/b$a$a:f	Ljava/lang/String;
        //   268: aload_0
        //   269: getfield 64	com/c/a/a/a/c/a/a/a/b$a$a:g	Ljava/lang/String;
        //   272: invokevirtual 136	java/lang/String:isEmpty	()Z
        //   275: ifne +1079 -> 1354
        //   278: iconst_1
        //   279: istore 5
        //   281: aload_0
        //   282: getfield 64	com/c/a/a/a/c/a/a/a/b$a$a:g	Ljava/lang/String;
        //   285: astore 8
        //   287: aload_3
        //   288: getfield 64	com/c/a/a/a/c/a/a/a/b$a$a:g	Ljava/lang/String;
        //   291: invokevirtual 136	java/lang/String:isEmpty	()Z
        //   294: ifne +1066 -> 1360
        //   297: iconst_1
        //   298: istore 6
        //   300: aload_0
        //   301: aload_2
        //   302: iload 5
        //   304: aload 8
        //   306: iload 6
        //   308: aload_3
        //   309: getfield 64	com/c/a/a/a/c/a/a/a/b$a$a:g	Ljava/lang/String;
        //   312: invokeinterface 139 5 0
        //   317: putfield 64	com/c/a/a/a/c/a/a/a/b$a$a:g	Ljava/lang/String;
        //   320: aload_0
        //   321: getfield 66	com/c/a/a/a/c/a/a/a/b$a$a:h	Ljava/lang/String;
        //   324: invokevirtual 136	java/lang/String:isEmpty	()Z
        //   327: ifne +1039 -> 1366
        //   330: iconst_1
        //   331: istore 5
        //   333: aload_0
        //   334: getfield 66	com/c/a/a/a/c/a/a/a/b$a$a:h	Ljava/lang/String;
        //   337: astore 8
        //   339: aload_3
        //   340: getfield 66	com/c/a/a/a/c/a/a/a/b$a$a:h	Ljava/lang/String;
        //   343: invokevirtual 136	java/lang/String:isEmpty	()Z
        //   346: ifne +1026 -> 1372
        //   349: iconst_1
        //   350: istore 6
        //   352: aload_0
        //   353: aload_2
        //   354: iload 5
        //   356: aload 8
        //   358: iload 6
        //   360: aload_3
        //   361: getfield 66	com/c/a/a/a/c/a/a/a/b$a$a:h	Ljava/lang/String;
        //   364: invokeinterface 139 5 0
        //   369: putfield 66	com/c/a/a/a/c/a/a/a/b$a$a:h	Ljava/lang/String;
        //   372: aload_0
        //   373: getfield 68	com/c/a/a/a/c/a/a/a/b$a$a:i	Ljava/lang/String;
        //   376: invokevirtual 136	java/lang/String:isEmpty	()Z
        //   379: ifne +999 -> 1378
        //   382: iconst_1
        //   383: istore 5
        //   385: aload_0
        //   386: getfield 68	com/c/a/a/a/c/a/a/a/b$a$a:i	Ljava/lang/String;
        //   389: astore 8
        //   391: aload_3
        //   392: getfield 68	com/c/a/a/a/c/a/a/a/b$a$a:i	Ljava/lang/String;
        //   395: invokevirtual 136	java/lang/String:isEmpty	()Z
        //   398: ifne +986 -> 1384
        //   401: iconst_1
        //   402: istore 6
        //   404: aload_0
        //   405: aload_2
        //   406: iload 5
        //   408: aload 8
        //   410: iload 6
        //   412: aload_3
        //   413: getfield 68	com/c/a/a/a/c/a/a/a/b$a$a:i	Ljava/lang/String;
        //   416: invokeinterface 139 5 0
        //   421: putfield 68	com/c/a/a/a/c/a/a/a/b$a$a:i	Ljava/lang/String;
        //   424: aload_0
        //   425: getfield 70	com/c/a/a/a/c/a/a/a/b$a$a:j	Ljava/lang/String;
        //   428: invokevirtual 136	java/lang/String:isEmpty	()Z
        //   431: ifne +959 -> 1390
        //   434: iconst_1
        //   435: istore 5
        //   437: aload_0
        //   438: getfield 70	com/c/a/a/a/c/a/a/a/b$a$a:j	Ljava/lang/String;
        //   441: astore 8
        //   443: aload_3
        //   444: getfield 70	com/c/a/a/a/c/a/a/a/b$a$a:j	Ljava/lang/String;
        //   447: invokevirtual 136	java/lang/String:isEmpty	()Z
        //   450: ifne +946 -> 1396
        //   453: iconst_1
        //   454: istore 6
        //   456: aload_0
        //   457: aload_2
        //   458: iload 5
        //   460: aload 8
        //   462: iload 6
        //   464: aload_3
        //   465: getfield 70	com/c/a/a/a/c/a/a/a/b$a$a:j	Ljava/lang/String;
        //   468: invokeinterface 139 5 0
        //   473: putfield 70	com/c/a/a/a/c/a/a/a/b$a$a:j	Ljava/lang/String;
        //   476: aload_0
        //   477: getfield 72	com/c/a/a/a/c/a/a/a/b$a$a:k	Ljava/lang/String;
        //   480: invokevirtual 136	java/lang/String:isEmpty	()Z
        //   483: ifne +919 -> 1402
        //   486: iconst_1
        //   487: istore 5
        //   489: aload_0
        //   490: getfield 72	com/c/a/a/a/c/a/a/a/b$a$a:k	Ljava/lang/String;
        //   493: astore 8
        //   495: aload_3
        //   496: getfield 72	com/c/a/a/a/c/a/a/a/b$a$a:k	Ljava/lang/String;
        //   499: invokevirtual 136	java/lang/String:isEmpty	()Z
        //   502: ifne +906 -> 1408
        //   505: iconst_1
        //   506: istore 6
        //   508: aload_0
        //   509: aload_2
        //   510: iload 5
        //   512: aload 8
        //   514: iload 6
        //   516: aload_3
        //   517: getfield 72	com/c/a/a/a/c/a/a/a/b$a$a:k	Ljava/lang/String;
        //   520: invokeinterface 139 5 0
        //   525: putfield 72	com/c/a/a/a/c/a/a/a/b$a$a:k	Ljava/lang/String;
        //   528: aload_0
        //   529: getfield 74	com/c/a/a/a/c/a/a/a/b$a$a:l	Ljava/lang/String;
        //   532: invokevirtual 136	java/lang/String:isEmpty	()Z
        //   535: ifne +879 -> 1414
        //   538: iconst_1
        //   539: istore 5
        //   541: aload_0
        //   542: getfield 74	com/c/a/a/a/c/a/a/a/b$a$a:l	Ljava/lang/String;
        //   545: astore 8
        //   547: aload_3
        //   548: getfield 74	com/c/a/a/a/c/a/a/a/b$a$a:l	Ljava/lang/String;
        //   551: invokevirtual 136	java/lang/String:isEmpty	()Z
        //   554: ifne +866 -> 1420
        //   557: iconst_1
        //   558: istore 6
        //   560: aload_0
        //   561: aload_2
        //   562: iload 5
        //   564: aload 8
        //   566: iload 6
        //   568: aload_3
        //   569: getfield 74	com/c/a/a/a/c/a/a/a/b$a$a:l	Ljava/lang/String;
        //   572: invokeinterface 139 5 0
        //   577: putfield 74	com/c/a/a/a/c/a/a/a/b$a$a:l	Ljava/lang/String;
        //   580: aload_0
        //   581: getfield 76	com/c/a/a/a/c/a/a/a/b$a$a:m	Ljava/lang/String;
        //   584: invokevirtual 136	java/lang/String:isEmpty	()Z
        //   587: ifne +839 -> 1426
        //   590: iconst_1
        //   591: istore 5
        //   593: aload_0
        //   594: getfield 76	com/c/a/a/a/c/a/a/a/b$a$a:m	Ljava/lang/String;
        //   597: astore 8
        //   599: aload_3
        //   600: getfield 76	com/c/a/a/a/c/a/a/a/b$a$a:m	Ljava/lang/String;
        //   603: invokevirtual 136	java/lang/String:isEmpty	()Z
        //   606: ifne +826 -> 1432
        //   609: iconst_1
        //   610: istore 6
        //   612: aload_0
        //   613: aload_2
        //   614: iload 5
        //   616: aload 8
        //   618: iload 6
        //   620: aload_3
        //   621: getfield 76	com/c/a/a/a/c/a/a/a/b$a$a:m	Ljava/lang/String;
        //   624: invokeinterface 139 5 0
        //   629: putfield 76	com/c/a/a/a/c/a/a/a/b$a$a:m	Ljava/lang/String;
        //   632: aload_0
        //   633: getfield 78	com/c/a/a/a/c/a/a/a/b$a$a:n	Ljava/lang/String;
        //   636: invokevirtual 136	java/lang/String:isEmpty	()Z
        //   639: ifne +799 -> 1438
        //   642: iconst_1
        //   643: istore 5
        //   645: aload_0
        //   646: getfield 78	com/c/a/a/a/c/a/a/a/b$a$a:n	Ljava/lang/String;
        //   649: astore 8
        //   651: aload_3
        //   652: getfield 78	com/c/a/a/a/c/a/a/a/b$a$a:n	Ljava/lang/String;
        //   655: invokevirtual 136	java/lang/String:isEmpty	()Z
        //   658: ifne +786 -> 1444
        //   661: iconst_1
        //   662: istore 6
        //   664: aload_0
        //   665: aload_2
        //   666: iload 5
        //   668: aload 8
        //   670: iload 6
        //   672: aload_3
        //   673: getfield 78	com/c/a/a/a/c/a/a/a/b$a$a:n	Ljava/lang/String;
        //   676: invokeinterface 139 5 0
        //   681: putfield 78	com/c/a/a/a/c/a/a/a/b$a$a:n	Ljava/lang/String;
        //   684: aload_0
        //   685: getfield 80	com/c/a/a/a/c/a/a/a/b$a$a:o	Ljava/lang/String;
        //   688: invokevirtual 136	java/lang/String:isEmpty	()Z
        //   691: ifne +759 -> 1450
        //   694: iconst_1
        //   695: istore 5
        //   697: aload_0
        //   698: getfield 80	com/c/a/a/a/c/a/a/a/b$a$a:o	Ljava/lang/String;
        //   701: astore 8
        //   703: aload_3
        //   704: getfield 80	com/c/a/a/a/c/a/a/a/b$a$a:o	Ljava/lang/String;
        //   707: invokevirtual 136	java/lang/String:isEmpty	()Z
        //   710: ifne +746 -> 1456
        //   713: iconst_1
        //   714: istore 6
        //   716: aload_0
        //   717: aload_2
        //   718: iload 5
        //   720: aload 8
        //   722: iload 6
        //   724: aload_3
        //   725: getfield 80	com/c/a/a/a/c/a/a/a/b$a$a:o	Ljava/lang/String;
        //   728: invokeinterface 139 5 0
        //   733: putfield 80	com/c/a/a/a/c/a/a/a/b$a$a:o	Ljava/lang/String;
        //   736: aload_0
        //   737: getfield 82	com/c/a/a/a/c/a/a/a/b$a$a:p	Ljava/lang/String;
        //   740: invokevirtual 136	java/lang/String:isEmpty	()Z
        //   743: ifne +719 -> 1462
        //   746: iconst_1
        //   747: istore 5
        //   749: aload_0
        //   750: getfield 82	com/c/a/a/a/c/a/a/a/b$a$a:p	Ljava/lang/String;
        //   753: astore 8
        //   755: aload_3
        //   756: getfield 82	com/c/a/a/a/c/a/a/a/b$a$a:p	Ljava/lang/String;
        //   759: invokevirtual 136	java/lang/String:isEmpty	()Z
        //   762: ifne +706 -> 1468
        //   765: iconst_1
        //   766: istore 6
        //   768: aload_0
        //   769: aload_2
        //   770: iload 5
        //   772: aload 8
        //   774: iload 6
        //   776: aload_3
        //   777: getfield 82	com/c/a/a/a/c/a/a/a/b$a$a:p	Ljava/lang/String;
        //   780: invokeinterface 139 5 0
        //   785: putfield 82	com/c/a/a/a/c/a/a/a/b$a$a:p	Ljava/lang/String;
        //   788: aload_0
        //   789: getfield 84	com/c/a/a/a/c/a/a/a/b$a$a:q	Ljava/lang/String;
        //   792: invokevirtual 136	java/lang/String:isEmpty	()Z
        //   795: ifne +679 -> 1474
        //   798: iconst_1
        //   799: istore 5
        //   801: aload_0
        //   802: getfield 84	com/c/a/a/a/c/a/a/a/b$a$a:q	Ljava/lang/String;
        //   805: astore 8
        //   807: aload_3
        //   808: getfield 84	com/c/a/a/a/c/a/a/a/b$a$a:q	Ljava/lang/String;
        //   811: invokevirtual 136	java/lang/String:isEmpty	()Z
        //   814: ifne +666 -> 1480
        //   817: iconst_1
        //   818: istore 6
        //   820: aload_0
        //   821: aload_2
        //   822: iload 5
        //   824: aload 8
        //   826: iload 6
        //   828: aload_3
        //   829: getfield 84	com/c/a/a/a/c/a/a/a/b$a$a:q	Ljava/lang/String;
        //   832: invokeinterface 139 5 0
        //   837: putfield 84	com/c/a/a/a/c/a/a/a/b$a$a:q	Ljava/lang/String;
        //   840: aload_0
        //   841: getfield 86	com/c/a/a/a/c/a/a/a/b$a$a:r	Ljava/lang/String;
        //   844: invokevirtual 136	java/lang/String:isEmpty	()Z
        //   847: ifne +639 -> 1486
        //   850: iconst_1
        //   851: istore 5
        //   853: aload_0
        //   854: getfield 86	com/c/a/a/a/c/a/a/a/b$a$a:r	Ljava/lang/String;
        //   857: astore 8
        //   859: aload_3
        //   860: getfield 86	com/c/a/a/a/c/a/a/a/b$a$a:r	Ljava/lang/String;
        //   863: invokevirtual 136	java/lang/String:isEmpty	()Z
        //   866: ifne +626 -> 1492
        //   869: iconst_1
        //   870: istore 6
        //   872: aload_0
        //   873: aload_2
        //   874: iload 5
        //   876: aload 8
        //   878: iload 6
        //   880: aload_3
        //   881: getfield 86	com/c/a/a/a/c/a/a/a/b$a$a:r	Ljava/lang/String;
        //   884: invokeinterface 139 5 0
        //   889: putfield 86	com/c/a/a/a/c/a/a/a/b$a$a:r	Ljava/lang/String;
        //   892: aload_0
        //   893: getfield 88	com/c/a/a/a/c/a/a/a/b$a$a:s	Ljava/lang/String;
        //   896: invokevirtual 136	java/lang/String:isEmpty	()Z
        //   899: ifne +599 -> 1498
        //   902: iconst_1
        //   903: istore 5
        //   905: aload_0
        //   906: getfield 88	com/c/a/a/a/c/a/a/a/b$a$a:s	Ljava/lang/String;
        //   909: astore 8
        //   911: aload_3
        //   912: getfield 88	com/c/a/a/a/c/a/a/a/b$a$a:s	Ljava/lang/String;
        //   915: invokevirtual 136	java/lang/String:isEmpty	()Z
        //   918: ifne +586 -> 1504
        //   921: iconst_1
        //   922: istore 6
        //   924: aload_0
        //   925: aload_2
        //   926: iload 5
        //   928: aload 8
        //   930: iload 6
        //   932: aload_3
        //   933: getfield 88	com/c/a/a/a/c/a/a/a/b$a$a:s	Ljava/lang/String;
        //   936: invokeinterface 139 5 0
        //   941: putfield 88	com/c/a/a/a/c/a/a/a/b$a$a:s	Ljava/lang/String;
        //   944: aload_0
        //   945: getfield 90	com/c/a/a/a/c/a/a/a/b$a$a:t	Ljava/lang/String;
        //   948: invokevirtual 136	java/lang/String:isEmpty	()Z
        //   951: ifne +559 -> 1510
        //   954: iconst_1
        //   955: istore 5
        //   957: aload_0
        //   958: getfield 90	com/c/a/a/a/c/a/a/a/b$a$a:t	Ljava/lang/String;
        //   961: astore 8
        //   963: aload_3
        //   964: getfield 90	com/c/a/a/a/c/a/a/a/b$a$a:t	Ljava/lang/String;
        //   967: invokevirtual 136	java/lang/String:isEmpty	()Z
        //   970: ifne +546 -> 1516
        //   973: iconst_1
        //   974: istore 6
        //   976: aload_0
        //   977: aload_2
        //   978: iload 5
        //   980: aload 8
        //   982: iload 6
        //   984: aload_3
        //   985: getfield 90	com/c/a/a/a/c/a/a/a/b$a$a:t	Ljava/lang/String;
        //   988: invokeinterface 139 5 0
        //   993: putfield 90	com/c/a/a/a/c/a/a/a/b$a$a:t	Ljava/lang/String;
        //   996: aload_0
        //   997: getfield 92	com/c/a/a/a/c/a/a/a/b$a$a:u	Ljava/lang/String;
        //   1000: invokevirtual 136	java/lang/String:isEmpty	()Z
        //   1003: ifne +519 -> 1522
        //   1006: iconst_1
        //   1007: istore 5
        //   1009: aload_0
        //   1010: getfield 92	com/c/a/a/a/c/a/a/a/b$a$a:u	Ljava/lang/String;
        //   1013: astore 8
        //   1015: aload_3
        //   1016: getfield 92	com/c/a/a/a/c/a/a/a/b$a$a:u	Ljava/lang/String;
        //   1019: invokevirtual 136	java/lang/String:isEmpty	()Z
        //   1022: ifne +506 -> 1528
        //   1025: iconst_1
        //   1026: istore 6
        //   1028: aload_0
        //   1029: aload_2
        //   1030: iload 5
        //   1032: aload 8
        //   1034: iload 6
        //   1036: aload_3
        //   1037: getfield 92	com/c/a/a/a/c/a/a/a/b$a$a:u	Ljava/lang/String;
        //   1040: invokeinterface 139 5 0
        //   1045: putfield 92	com/c/a/a/a/c/a/a/a/b$a$a:u	Ljava/lang/String;
        //   1048: aload_0
        //   1049: getfield 94	com/c/a/a/a/c/a/a/a/b$a$a:v	Ljava/lang/String;
        //   1052: invokevirtual 136	java/lang/String:isEmpty	()Z
        //   1055: ifne +479 -> 1534
        //   1058: iconst_1
        //   1059: istore 5
        //   1061: aload_0
        //   1062: getfield 94	com/c/a/a/a/c/a/a/a/b$a$a:v	Ljava/lang/String;
        //   1065: astore 8
        //   1067: aload_3
        //   1068: getfield 94	com/c/a/a/a/c/a/a/a/b$a$a:v	Ljava/lang/String;
        //   1071: invokevirtual 136	java/lang/String:isEmpty	()Z
        //   1074: ifne +466 -> 1540
        //   1077: iconst_1
        //   1078: istore 6
        //   1080: aload_0
        //   1081: aload_2
        //   1082: iload 5
        //   1084: aload 8
        //   1086: iload 6
        //   1088: aload_3
        //   1089: getfield 94	com/c/a/a/a/c/a/a/a/b$a$a:v	Ljava/lang/String;
        //   1092: invokeinterface 139 5 0
        //   1097: putfield 94	com/c/a/a/a/c/a/a/a/b$a$a:v	Ljava/lang/String;
        //   1100: aload_0
        //   1101: getfield 96	com/c/a/a/a/c/a/a/a/b$a$a:w	Ljava/lang/String;
        //   1104: invokevirtual 136	java/lang/String:isEmpty	()Z
        //   1107: ifne +439 -> 1546
        //   1110: iconst_1
        //   1111: istore 5
        //   1113: aload_0
        //   1114: getfield 96	com/c/a/a/a/c/a/a/a/b$a$a:w	Ljava/lang/String;
        //   1117: astore 8
        //   1119: aload_3
        //   1120: getfield 96	com/c/a/a/a/c/a/a/a/b$a$a:w	Ljava/lang/String;
        //   1123: invokevirtual 136	java/lang/String:isEmpty	()Z
        //   1126: ifne +426 -> 1552
        //   1129: iconst_1
        //   1130: istore 6
        //   1132: aload_0
        //   1133: aload_2
        //   1134: iload 5
        //   1136: aload 8
        //   1138: iload 6
        //   1140: aload_3
        //   1141: getfield 96	com/c/a/a/a/c/a/a/a/b$a$a:w	Ljava/lang/String;
        //   1144: invokeinterface 139 5 0
        //   1149: putfield 96	com/c/a/a/a/c/a/a/a/b$a$a:w	Ljava/lang/String;
        //   1152: aload_0
        //   1153: getfield 98	com/c/a/a/a/c/a/a/a/b$a$a:x	Ljava/lang/String;
        //   1156: invokevirtual 136	java/lang/String:isEmpty	()Z
        //   1159: ifne +399 -> 1558
        //   1162: iconst_1
        //   1163: istore 5
        //   1165: aload_0
        //   1166: getfield 98	com/c/a/a/a/c/a/a/a/b$a$a:x	Ljava/lang/String;
        //   1169: astore 8
        //   1171: aload_3
        //   1172: getfield 98	com/c/a/a/a/c/a/a/a/b$a$a:x	Ljava/lang/String;
        //   1175: invokevirtual 136	java/lang/String:isEmpty	()Z
        //   1178: ifne +386 -> 1564
        //   1181: iconst_1
        //   1182: istore 6
        //   1184: aload_0
        //   1185: aload_2
        //   1186: iload 5
        //   1188: aload 8
        //   1190: iload 6
        //   1192: aload_3
        //   1193: getfield 98	com/c/a/a/a/c/a/a/a/b$a$a:x	Ljava/lang/String;
        //   1196: invokeinterface 139 5 0
        //   1201: putfield 98	com/c/a/a/a/c/a/a/a/b$a$a:x	Ljava/lang/String;
        //   1204: aload_0
        //   1205: getfield 100	com/c/a/a/a/c/a/a/a/b$a$a:y	Ljava/lang/String;
        //   1208: invokevirtual 136	java/lang/String:isEmpty	()Z
        //   1211: ifne +359 -> 1570
        //   1214: iconst_1
        //   1215: istore 5
        //   1217: aload_0
        //   1218: getfield 100	com/c/a/a/a/c/a/a/a/b$a$a:y	Ljava/lang/String;
        //   1221: astore 8
        //   1223: aload_3
        //   1224: getfield 100	com/c/a/a/a/c/a/a/a/b$a$a:y	Ljava/lang/String;
        //   1227: invokevirtual 136	java/lang/String:isEmpty	()Z
        //   1230: ifne +346 -> 1576
        //   1233: iconst_1
        //   1234: istore 6
        //   1236: aload_0
        //   1237: aload_2
        //   1238: iload 5
        //   1240: aload 8
        //   1242: iload 6
        //   1244: aload_3
        //   1245: getfield 100	com/c/a/a/a/c/a/a/a/b$a$a:y	Ljava/lang/String;
        //   1248: invokeinterface 139 5 0
        //   1253: putfield 100	com/c/a/a/a/c/a/a/a/b$a$a:y	Ljava/lang/String;
        //   1256: aload_0
        //   1257: getfield 102	com/c/a/a/a/c/a/a/a/b$a$a:z	Ljava/lang/String;
        //   1260: invokevirtual 136	java/lang/String:isEmpty	()Z
        //   1263: ifne +319 -> 1582
        //   1266: iconst_1
        //   1267: istore 5
        //   1269: aload_0
        //   1270: getfield 102	com/c/a/a/a/c/a/a/a/b$a$a:z	Ljava/lang/String;
        //   1273: astore 8
        //   1275: aload_3
        //   1276: getfield 102	com/c/a/a/a/c/a/a/a/b$a$a:z	Ljava/lang/String;
        //   1279: invokevirtual 136	java/lang/String:isEmpty	()Z
        //   1282: ifne +306 -> 1588
        //   1285: iload 7
        //   1287: istore 6
        //   1289: aload_0
        //   1290: aload_2
        //   1291: iload 5
        //   1293: aload 8
        //   1295: iload 6
        //   1297: aload_3
        //   1298: getfield 102	com/c/a/a/a/c/a/a/a/b$a$a:z	Ljava/lang/String;
        //   1301: invokeinterface 139 5 0
        //   1306: putfield 102	com/c/a/a/a/c/a/a/a/b$a$a:z	Ljava/lang/String;
        //   1309: getstatic 144	com/b/b/m$h:a	Lcom/b/b/m$h;
        //   1312: astore_2
        //   1313: aload_0
        //   1314: astore_2
        //   1315: goto -1239 -> 76
        //   1318: iconst_0
        //   1319: istore 5
        //   1321: goto -1196 -> 125
        //   1324: iconst_0
        //   1325: istore 6
        //   1327: goto -1183 -> 144
        //   1330: iconst_0
        //   1331: istore 5
        //   1333: goto -1156 -> 177
        //   1336: iconst_0
        //   1337: istore 6
        //   1339: goto -1143 -> 196
        //   1342: iconst_0
        //   1343: istore 5
        //   1345: goto -1116 -> 229
        //   1348: iconst_0
        //   1349: istore 6
        //   1351: goto -1103 -> 248
        //   1354: iconst_0
        //   1355: istore 5
        //   1357: goto -1076 -> 281
        //   1360: iconst_0
        //   1361: istore 6
        //   1363: goto -1063 -> 300
        //   1366: iconst_0
        //   1367: istore 5
        //   1369: goto -1036 -> 333
        //   1372: iconst_0
        //   1373: istore 6
        //   1375: goto -1023 -> 352
        //   1378: iconst_0
        //   1379: istore 5
        //   1381: goto -996 -> 385
        //   1384: iconst_0
        //   1385: istore 6
        //   1387: goto -983 -> 404
        //   1390: iconst_0
        //   1391: istore 5
        //   1393: goto -956 -> 437
        //   1396: iconst_0
        //   1397: istore 6
        //   1399: goto -943 -> 456
        //   1402: iconst_0
        //   1403: istore 5
        //   1405: goto -916 -> 489
        //   1408: iconst_0
        //   1409: istore 6
        //   1411: goto -903 -> 508
        //   1414: iconst_0
        //   1415: istore 5
        //   1417: goto -876 -> 541
        //   1420: iconst_0
        //   1421: istore 6
        //   1423: goto -863 -> 560
        //   1426: iconst_0
        //   1427: istore 5
        //   1429: goto -836 -> 593
        //   1432: iconst_0
        //   1433: istore 6
        //   1435: goto -823 -> 612
        //   1438: iconst_0
        //   1439: istore 5
        //   1441: goto -796 -> 645
        //   1444: iconst_0
        //   1445: istore 6
        //   1447: goto -783 -> 664
        //   1450: iconst_0
        //   1451: istore 5
        //   1453: goto -756 -> 697
        //   1456: iconst_0
        //   1457: istore 6
        //   1459: goto -743 -> 716
        //   1462: iconst_0
        //   1463: istore 5
        //   1465: goto -716 -> 749
        //   1468: iconst_0
        //   1469: istore 6
        //   1471: goto -703 -> 768
        //   1474: iconst_0
        //   1475: istore 5
        //   1477: goto -676 -> 801
        //   1480: iconst_0
        //   1481: istore 6
        //   1483: goto -663 -> 820
        //   1486: iconst_0
        //   1487: istore 5
        //   1489: goto -636 -> 853
        //   1492: iconst_0
        //   1493: istore 6
        //   1495: goto -623 -> 872
        //   1498: iconst_0
        //   1499: istore 5
        //   1501: goto -596 -> 905
        //   1504: iconst_0
        //   1505: istore 6
        //   1507: goto -583 -> 924
        //   1510: iconst_0
        //   1511: istore 5
        //   1513: goto -556 -> 957
        //   1516: iconst_0
        //   1517: istore 6
        //   1519: goto -543 -> 976
        //   1522: iconst_0
        //   1523: istore 5
        //   1525: goto -516 -> 1009
        //   1528: iconst_0
        //   1529: istore 6
        //   1531: goto -503 -> 1028
        //   1534: iconst_0
        //   1535: istore 5
        //   1537: goto -476 -> 1061
        //   1540: iconst_0
        //   1541: istore 6
        //   1543: goto -463 -> 1080
        //   1546: iconst_0
        //   1547: istore 5
        //   1549: goto -436 -> 1113
        //   1552: iconst_0
        //   1553: istore 6
        //   1555: goto -423 -> 1132
        //   1558: iconst_0
        //   1559: istore 5
        //   1561: goto -396 -> 1165
        //   1564: iconst_0
        //   1565: istore 6
        //   1567: goto -383 -> 1184
        //   1570: iconst_0
        //   1571: istore 5
        //   1573: goto -356 -> 1217
        //   1576: iconst_0
        //   1577: istore 6
        //   1579: goto -343 -> 1236
        //   1582: iconst_0
        //   1583: istore 5
        //   1585: goto -316 -> 1269
        //   1588: iconst_0
        //   1589: istore 6
        //   1591: goto -302 -> 1289
        //   1594: aload_2
        //   1595: checkcast 146	com/b/b/g
        //   1598: astore_2
        //   1599: iload 4
        //   1601: istore_1
        //   1602: iload_1
        //   1603: ifne +535 -> 2138
        //   1606: aload_2
        //   1607: invokevirtual 149	com/b/b/g:a	()I
        //   1610: istore 4
        //   1612: iload 4
        //   1614: lookupswitch	default:+202->1816, 0:+216->1830, 10:+221->1835, 18:+251->1865, 26:+293->1907, 34:+304->1918, 42:+315->1929, 50:+326->1940, 58:+337->1951, 66:+348->1962, 74:+359->1973, 82:+370->1984, 90:+381->1995, 98:+392->2006, 106:+403->2017, 114:+414->2028, 122:+425->2039, 130:+436->2050, 138:+447->2061, 146:+458->2072, 154:+469->2083, 162:+480->2094, 170:+491->2105, 178:+502->2116, 186:+513->2127
        //   1816: aload_2
        //   1817: iload 4
        //   1819: invokevirtual 153	com/b/b/g:b	(I)Z
        //   1822: ifne -220 -> 1602
        //   1825: iconst_1
        //   1826: istore_1
        //   1827: goto -225 -> 1602
        //   1830: iconst_1
        //   1831: istore_1
        //   1832: goto -230 -> 1602
        //   1835: aload_0
        //   1836: aload_2
        //   1837: invokevirtual 155	com/b/b/g:k	()Ljava/lang/String;
        //   1840: putfield 58	com/c/a/a/a/c/a/a/a/b$a$a:d	Ljava/lang/String;
        //   1843: goto -241 -> 1602
        //   1846: astore_3
        //   1847: new 157	java/lang/RuntimeException
        //   1850: astore_2
        //   1851: aload_2
        //   1852: aload_3
        //   1853: aload_0
        //   1854: invokevirtual 160	com/b/b/o:a	(Lcom/b/b/u;)Lcom/b/b/o;
        //   1857: invokespecial 163	java/lang/RuntimeException:<init>	(Ljava/lang/Throwable;)V
        //   1860: aload_2
        //   1861: athrow
        //   1862: astore_2
        //   1863: aload_2
        //   1864: athrow
        //   1865: aload_0
        //   1866: aload_2
        //   1867: invokevirtual 155	com/b/b/g:k	()Ljava/lang/String;
        //   1870: putfield 60	com/c/a/a/a/c/a/a/a/b$a$a:e	Ljava/lang/String;
        //   1873: goto -271 -> 1602
        //   1876: astore_2
        //   1877: new 157	java/lang/RuntimeException
        //   1880: astore_3
        //   1881: new 115	com/b/b/o
        //   1884: astore 8
        //   1886: aload 8
        //   1888: aload_2
        //   1889: invokevirtual 166	java/io/IOException:getMessage	()Ljava/lang/String;
        //   1892: invokespecial 169	com/b/b/o:<init>	(Ljava/lang/String;)V
        //   1895: aload_3
        //   1896: aload 8
        //   1898: aload_0
        //   1899: invokevirtual 160	com/b/b/o:a	(Lcom/b/b/u;)Lcom/b/b/o;
        //   1902: invokespecial 163	java/lang/RuntimeException:<init>	(Ljava/lang/Throwable;)V
        //   1905: aload_3
        //   1906: athrow
        //   1907: aload_0
        //   1908: aload_2
        //   1909: invokevirtual 155	com/b/b/g:k	()Ljava/lang/String;
        //   1912: putfield 62	com/c/a/a/a/c/a/a/a/b$a$a:f	Ljava/lang/String;
        //   1915: goto -313 -> 1602
        //   1918: aload_0
        //   1919: aload_2
        //   1920: invokevirtual 155	com/b/b/g:k	()Ljava/lang/String;
        //   1923: putfield 64	com/c/a/a/a/c/a/a/a/b$a$a:g	Ljava/lang/String;
        //   1926: goto -324 -> 1602
        //   1929: aload_0
        //   1930: aload_2
        //   1931: invokevirtual 155	com/b/b/g:k	()Ljava/lang/String;
        //   1934: putfield 66	com/c/a/a/a/c/a/a/a/b$a$a:h	Ljava/lang/String;
        //   1937: goto -335 -> 1602
        //   1940: aload_0
        //   1941: aload_2
        //   1942: invokevirtual 155	com/b/b/g:k	()Ljava/lang/String;
        //   1945: putfield 68	com/c/a/a/a/c/a/a/a/b$a$a:i	Ljava/lang/String;
        //   1948: goto -346 -> 1602
        //   1951: aload_0
        //   1952: aload_2
        //   1953: invokevirtual 155	com/b/b/g:k	()Ljava/lang/String;
        //   1956: putfield 70	com/c/a/a/a/c/a/a/a/b$a$a:j	Ljava/lang/String;
        //   1959: goto -357 -> 1602
        //   1962: aload_0
        //   1963: aload_2
        //   1964: invokevirtual 155	com/b/b/g:k	()Ljava/lang/String;
        //   1967: putfield 72	com/c/a/a/a/c/a/a/a/b$a$a:k	Ljava/lang/String;
        //   1970: goto -368 -> 1602
        //   1973: aload_0
        //   1974: aload_2
        //   1975: invokevirtual 155	com/b/b/g:k	()Ljava/lang/String;
        //   1978: putfield 74	com/c/a/a/a/c/a/a/a/b$a$a:l	Ljava/lang/String;
        //   1981: goto -379 -> 1602
        //   1984: aload_0
        //   1985: aload_2
        //   1986: invokevirtual 155	com/b/b/g:k	()Ljava/lang/String;
        //   1989: putfield 76	com/c/a/a/a/c/a/a/a/b$a$a:m	Ljava/lang/String;
        //   1992: goto -390 -> 1602
        //   1995: aload_0
        //   1996: aload_2
        //   1997: invokevirtual 155	com/b/b/g:k	()Ljava/lang/String;
        //   2000: putfield 78	com/c/a/a/a/c/a/a/a/b$a$a:n	Ljava/lang/String;
        //   2003: goto -401 -> 1602
        //   2006: aload_0
        //   2007: aload_2
        //   2008: invokevirtual 155	com/b/b/g:k	()Ljava/lang/String;
        //   2011: putfield 80	com/c/a/a/a/c/a/a/a/b$a$a:o	Ljava/lang/String;
        //   2014: goto -412 -> 1602
        //   2017: aload_0
        //   2018: aload_2
        //   2019: invokevirtual 155	com/b/b/g:k	()Ljava/lang/String;
        //   2022: putfield 82	com/c/a/a/a/c/a/a/a/b$a$a:p	Ljava/lang/String;
        //   2025: goto -423 -> 1602
        //   2028: aload_0
        //   2029: aload_2
        //   2030: invokevirtual 155	com/b/b/g:k	()Ljava/lang/String;
        //   2033: putfield 84	com/c/a/a/a/c/a/a/a/b$a$a:q	Ljava/lang/String;
        //   2036: goto -434 -> 1602
        //   2039: aload_0
        //   2040: aload_2
        //   2041: invokevirtual 155	com/b/b/g:k	()Ljava/lang/String;
        //   2044: putfield 86	com/c/a/a/a/c/a/a/a/b$a$a:r	Ljava/lang/String;
        //   2047: goto -445 -> 1602
        //   2050: aload_0
        //   2051: aload_2
        //   2052: invokevirtual 155	com/b/b/g:k	()Ljava/lang/String;
        //   2055: putfield 88	com/c/a/a/a/c/a/a/a/b$a$a:s	Ljava/lang/String;
        //   2058: goto -456 -> 1602
        //   2061: aload_0
        //   2062: aload_2
        //   2063: invokevirtual 155	com/b/b/g:k	()Ljava/lang/String;
        //   2066: putfield 90	com/c/a/a/a/c/a/a/a/b$a$a:t	Ljava/lang/String;
        //   2069: goto -467 -> 1602
        //   2072: aload_0
        //   2073: aload_2
        //   2074: invokevirtual 155	com/b/b/g:k	()Ljava/lang/String;
        //   2077: putfield 92	com/c/a/a/a/c/a/a/a/b$a$a:u	Ljava/lang/String;
        //   2080: goto -478 -> 1602
        //   2083: aload_0
        //   2084: aload_2
        //   2085: invokevirtual 155	com/b/b/g:k	()Ljava/lang/String;
        //   2088: putfield 94	com/c/a/a/a/c/a/a/a/b$a$a:v	Ljava/lang/String;
        //   2091: goto -489 -> 1602
        //   2094: aload_0
        //   2095: aload_2
        //   2096: invokevirtual 155	com/b/b/g:k	()Ljava/lang/String;
        //   2099: putfield 96	com/c/a/a/a/c/a/a/a/b$a$a:w	Ljava/lang/String;
        //   2102: goto -500 -> 1602
        //   2105: aload_0
        //   2106: aload_2
        //   2107: invokevirtual 155	com/b/b/g:k	()Ljava/lang/String;
        //   2110: putfield 98	com/c/a/a/a/c/a/a/a/b$a$a:x	Ljava/lang/String;
        //   2113: goto -511 -> 1602
        //   2116: aload_0
        //   2117: aload_2
        //   2118: invokevirtual 155	com/b/b/g:k	()Ljava/lang/String;
        //   2121: putfield 100	com/c/a/a/a/c/a/a/a/b$a$a:y	Ljava/lang/String;
        //   2124: goto -522 -> 1602
        //   2127: aload_0
        //   2128: aload_2
        //   2129: invokevirtual 155	com/b/b/g:k	()Ljava/lang/String;
        //   2132: putfield 102	com/c/a/a/a/c/a/a/a/b$a$a:z	Ljava/lang/String;
        //   2135: goto -533 -> 1602
        //   2138: getstatic 50	com/c/a/a/a/c/a/a/a/b$a$a:A	Lcom/c/a/a/a/c/a/a/a/b$a$a;
        //   2141: astore_2
        //   2142: goto -2066 -> 76
        //   2145: getstatic 171	com/c/a/a/a/c/a/a/a/b$a$a:B	Lcom/b/b/x;
        //   2148: ifnonnull +30 -> 2178
        //   2151: ldc 2
        //   2153: monitorenter
        //   2154: getstatic 171	com/c/a/a/a/c/a/a/a/b$a$a:B	Lcom/b/b/x;
        //   2157: ifnonnull +18 -> 2175
        //   2160: new 173	com/b/b/m$b
        //   2163: astore_2
        //   2164: aload_2
        //   2165: getstatic 50	com/c/a/a/a/c/a/a/a/b$a$a:A	Lcom/c/a/a/a/c/a/a/a/b$a$a;
        //   2168: invokespecial 176	com/b/b/m$b:<init>	(Lcom/b/b/m;)V
        //   2171: aload_2
        //   2172: putstatic 171	com/c/a/a/a/c/a/a/a/b$a$a:B	Lcom/b/b/x;
        //   2175: ldc 2
        //   2177: monitorexit
        //   2178: getstatic 171	com/c/a/a/a/c/a/a/a/b$a$a:B	Lcom/b/b/x;
        //   2181: astore_2
        //   2182: goto -2106 -> 76
        //   2185: astore_2
        //   2186: ldc 2
        //   2188: monitorexit
        //   2189: aload_2
        //   2190: athrow
        // Local variable table:
        //   start	length	slot	name	signature
        //   0	2191	0	this	a
        //   0	2191	1	paramInt	int
        //   0	2191	2	paramObject1	Object
        //   0	2191	3	paramObject2	Object
        //   4	1814	4	i1	int
        //   123	1461	5	bool1	boolean
        //   142	1448	6	bool2	boolean
        //   1	1285	7	bool3	boolean
        //   129	1768	8	localObject	Object
        // Exception table:
        //   from	to	target	type
        //   1606	1612	1846	com/b/b/o
        //   1816	1825	1846	com/b/b/o
        //   1835	1843	1846	com/b/b/o
        //   1865	1873	1846	com/b/b/o
        //   1907	1915	1846	com/b/b/o
        //   1918	1926	1846	com/b/b/o
        //   1929	1937	1846	com/b/b/o
        //   1940	1948	1846	com/b/b/o
        //   1951	1959	1846	com/b/b/o
        //   1962	1970	1846	com/b/b/o
        //   1973	1981	1846	com/b/b/o
        //   1984	1992	1846	com/b/b/o
        //   1995	2003	1846	com/b/b/o
        //   2006	2014	1846	com/b/b/o
        //   2017	2025	1846	com/b/b/o
        //   2028	2036	1846	com/b/b/o
        //   2039	2047	1846	com/b/b/o
        //   2050	2058	1846	com/b/b/o
        //   2061	2069	1846	com/b/b/o
        //   2072	2080	1846	com/b/b/o
        //   2083	2091	1846	com/b/b/o
        //   2094	2102	1846	com/b/b/o
        //   2105	2113	1846	com/b/b/o
        //   2116	2124	1846	com/b/b/o
        //   2127	2135	1846	com/b/b/o
        //   1606	1612	1862	finally
        //   1816	1825	1862	finally
        //   1835	1843	1862	finally
        //   1847	1862	1862	finally
        //   1865	1873	1862	finally
        //   1877	1907	1862	finally
        //   1907	1915	1862	finally
        //   1918	1926	1862	finally
        //   1929	1937	1862	finally
        //   1940	1948	1862	finally
        //   1951	1959	1862	finally
        //   1962	1970	1862	finally
        //   1973	1981	1862	finally
        //   1984	1992	1862	finally
        //   1995	2003	1862	finally
        //   2006	2014	1862	finally
        //   2017	2025	1862	finally
        //   2028	2036	1862	finally
        //   2039	2047	1862	finally
        //   2050	2058	1862	finally
        //   2061	2069	1862	finally
        //   2072	2080	1862	finally
        //   2083	2091	1862	finally
        //   2094	2102	1862	finally
        //   2105	2113	1862	finally
        //   2116	2124	1862	finally
        //   2127	2135	1862	finally
        //   1606	1612	1876	java/io/IOException
        //   1816	1825	1876	java/io/IOException
        //   1835	1843	1876	java/io/IOException
        //   1865	1873	1876	java/io/IOException
        //   1907	1915	1876	java/io/IOException
        //   1918	1926	1876	java/io/IOException
        //   1929	1937	1876	java/io/IOException
        //   1940	1948	1876	java/io/IOException
        //   1951	1959	1876	java/io/IOException
        //   1962	1970	1876	java/io/IOException
        //   1973	1981	1876	java/io/IOException
        //   1984	1992	1876	java/io/IOException
        //   1995	2003	1876	java/io/IOException
        //   2006	2014	1876	java/io/IOException
        //   2017	2025	1876	java/io/IOException
        //   2028	2036	1876	java/io/IOException
        //   2039	2047	1876	java/io/IOException
        //   2050	2058	1876	java/io/IOException
        //   2061	2069	1876	java/io/IOException
        //   2072	2080	1876	java/io/IOException
        //   2083	2091	1876	java/io/IOException
        //   2094	2102	1876	java/io/IOException
        //   2105	2113	1876	java/io/IOException
        //   2116	2124	1876	java/io/IOException
        //   2127	2135	1876	java/io/IOException
        //   2154	2175	2185	finally
        //   2175	2178	2185	finally
        //   2186	2189	2185	finally
      }
      
      public final void a(h paramh)
      {
        if (!this.d.isEmpty()) {
          paramh.a(1, this.d);
        }
        if (!this.e.isEmpty()) {
          paramh.a(2, this.e);
        }
        if (!this.f.isEmpty()) {
          paramh.a(3, this.f);
        }
        if (!this.g.isEmpty()) {
          paramh.a(4, this.g);
        }
        if (!this.h.isEmpty()) {
          paramh.a(5, this.h);
        }
        if (!this.i.isEmpty()) {
          paramh.a(6, this.i);
        }
        if (!this.j.isEmpty()) {
          paramh.a(7, this.j);
        }
        if (!this.k.isEmpty()) {
          paramh.a(8, this.k);
        }
        if (!this.l.isEmpty()) {
          paramh.a(9, this.l);
        }
        if (!this.m.isEmpty()) {
          paramh.a(10, this.m);
        }
        if (!this.n.isEmpty()) {
          paramh.a(11, this.n);
        }
        if (!this.o.isEmpty()) {
          paramh.a(12, this.o);
        }
        if (!this.p.isEmpty()) {
          paramh.a(13, this.p);
        }
        if (!this.q.isEmpty()) {
          paramh.a(14, this.q);
        }
        if (!this.r.isEmpty()) {
          paramh.a(15, this.r);
        }
        if (!this.s.isEmpty()) {
          paramh.a(16, this.s);
        }
        if (!this.t.isEmpty()) {
          paramh.a(17, this.t);
        }
        if (!this.u.isEmpty()) {
          paramh.a(18, this.u);
        }
        if (!this.v.isEmpty()) {
          paramh.a(19, this.v);
        }
        if (!this.w.isEmpty()) {
          paramh.a(20, this.w);
        }
        if (!this.x.isEmpty()) {
          paramh.a(21, this.x);
        }
        if (!this.y.isEmpty()) {
          paramh.a(22, this.y);
        }
        if (!this.z.isEmpty()) {
          paramh.a(23, this.z);
        }
      }
      
      public final int k()
      {
        int i1 = this.c;
        if (i1 != -1) {}
        for (;;)
        {
          return i1;
          int i2 = 0;
          if (!this.d.isEmpty()) {
            i2 = h.b(1, this.d) + 0;
          }
          i1 = i2;
          if (!this.e.isEmpty()) {
            i1 = i2 + h.b(2, this.e);
          }
          i2 = i1;
          if (!this.f.isEmpty()) {
            i2 = i1 + h.b(3, this.f);
          }
          i1 = i2;
          if (!this.g.isEmpty()) {
            i1 = i2 + h.b(4, this.g);
          }
          i2 = i1;
          if (!this.h.isEmpty()) {
            i2 = i1 + h.b(5, this.h);
          }
          i1 = i2;
          if (!this.i.isEmpty()) {
            i1 = i2 + h.b(6, this.i);
          }
          i2 = i1;
          if (!this.j.isEmpty()) {
            i2 = i1 + h.b(7, this.j);
          }
          i1 = i2;
          if (!this.k.isEmpty()) {
            i1 = i2 + h.b(8, this.k);
          }
          i2 = i1;
          if (!this.l.isEmpty()) {
            i2 = i1 + h.b(9, this.l);
          }
          i1 = i2;
          if (!this.m.isEmpty()) {
            i1 = i2 + h.b(10, this.m);
          }
          i2 = i1;
          if (!this.n.isEmpty()) {
            i2 = i1 + h.b(11, this.n);
          }
          i1 = i2;
          if (!this.o.isEmpty()) {
            i1 = i2 + h.b(12, this.o);
          }
          i2 = i1;
          if (!this.p.isEmpty()) {
            i2 = i1 + h.b(13, this.p);
          }
          i1 = i2;
          if (!this.q.isEmpty()) {
            i1 = i2 + h.b(14, this.q);
          }
          int i3 = i1;
          if (!this.r.isEmpty()) {
            i3 = i1 + h.b(15, this.r);
          }
          i2 = i3;
          if (!this.s.isEmpty()) {
            i2 = i3 + h.b(16, this.s);
          }
          i1 = i2;
          if (!this.t.isEmpty()) {
            i1 = i2 + h.b(17, this.t);
          }
          i2 = i1;
          if (!this.u.isEmpty()) {
            i2 = i1 + h.b(18, this.u);
          }
          i1 = i2;
          if (!this.v.isEmpty()) {
            i1 = i2 + h.b(19, this.v);
          }
          i2 = i1;
          if (!this.w.isEmpty()) {
            i2 = i1 + h.b(20, this.w);
          }
          i1 = i2;
          if (!this.x.isEmpty()) {
            i1 = i2 + h.b(21, this.x);
          }
          i2 = i1;
          if (!this.y.isEmpty()) {
            i2 = i1 + h.b(22, this.y);
          }
          i1 = i2;
          if (!this.z.isEmpty()) {
            i1 = i2 + h.b(23, this.z);
          }
          this.c = i1;
        }
      }
      
      public final String l()
      {
        return this.d;
      }
      
      public final String m()
      {
        return this.e;
      }
      
      public final String n()
      {
        return this.f;
      }
      
      public final String o()
      {
        return this.g;
      }
      
      public final String p()
      {
        return this.h;
      }
      
      public final String q()
      {
        return this.i;
      }
      
      public final String r()
      {
        return this.j;
      }
      
      public final String s()
      {
        return this.k;
      }
      
      public final String t()
      {
        return this.l;
      }
      
      public final String u()
      {
        return this.m;
      }
      
      public final String v()
      {
        return this.n;
      }
      
      public final String w()
      {
        return this.o;
      }
      
      public final String x()
      {
        return this.p;
      }
      
      public final String y()
      {
        return this.q;
      }
      
      public final String z()
      {
        return this.r;
      }
      
      public static final class a
        extends m.a<b.a.a, a>
        implements b.a.b
      {
        private a()
        {
          super();
        }
      }
    }
    
    public static abstract interface b
      extends v
    {}
    
    private static final class c
    {
      static final r<String, b.a.a> a = r.a(ak.a.i, "", ak.a.k, b.a.a.I());
    }
    
    public static final class d
      extends m.a<b.a, d>
      implements b.b
    {
      private d()
      {
        super();
      }
    }
  }
  
  public static abstract interface b
    extends v
  {}
}


/* Location:              /Users/hanlian/Downloads/WiFidex1-dex2jar.jar!/com/c/a/a/a/c/a/a/a/b.class
 * Java compiler version: 6 (50.0)
 * JD-Core Version:       0.7.1
 */