package com.alipay.c.a.a.d;

public class a
{
  /* Error */
  public static String a(android.content.Context paramContext, String paramString1, String paramString2)
  {
    // Byte code:
    //   0: aconst_null
    //   1: astore 4
    //   3: aconst_null
    //   4: astore 5
    //   6: ldc 2
    //   8: monitorenter
    //   9: aload_0
    //   10: ifnull +17 -> 27
    //   13: aload_1
    //   14: invokestatic 18	com/alipay/c/a/a/a/a:a	(Ljava/lang/String;)Z
    //   17: ifne +10 -> 27
    //   20: aload_2
    //   21: invokestatic 18	com/alipay/c/a/a/a/a:a	(Ljava/lang/String;)Z
    //   24: ifeq +11 -> 35
    //   27: ldc 2
    //   29: monitorexit
    //   30: aload 5
    //   32: astore_0
    //   33: aload_0
    //   34: areturn
    //   35: aload_0
    //   36: aload_1
    //   37: aload_2
    //   38: ldc 20
    //   40: invokestatic 25	com/alipay/c/a/a/d/d:a	(Landroid/content/Context;Ljava/lang/String;Ljava/lang/String;Ljava/lang/String;)Ljava/lang/String;
    //   43: astore_0
    //   44: aload_0
    //   45: invokestatic 18	com/alipay/c/a/a/a/a:a	(Ljava/lang/String;)Z
    //   48: istore_3
    //   49: iload_3
    //   50: ifeq +18 -> 68
    //   53: ldc 2
    //   55: monitorexit
    //   56: aload 5
    //   58: astore_0
    //   59: goto -26 -> 33
    //   62: astore_0
    //   63: ldc 2
    //   65: monitorexit
    //   66: aload_0
    //   67: athrow
    //   68: invokestatic 30	com/alipay/c/a/a/a/a/c:a	()Ljava/lang/String;
    //   71: aload_0
    //   72: invokestatic 34	com/alipay/c/a/a/a/a/c:b	(Ljava/lang/String;Ljava/lang/String;)Ljava/lang/String;
    //   75: astore_0
    //   76: ldc 2
    //   78: monitorexit
    //   79: goto -46 -> 33
    //   82: astore_0
    //   83: aload 4
    //   85: astore_0
    //   86: goto -10 -> 76
    // Local variable table:
    //   start	length	slot	name	signature
    //   0	89	0	paramContext	android.content.Context
    //   0	89	1	paramString1	String
    //   0	89	2	paramString2	String
    //   48	2	3	bool	boolean
    //   1	83	4	localObject1	Object
    //   4	53	5	localObject2	Object
    // Exception table:
    //   from	to	target	type
    //   13	27	62	finally
    //   27	30	62	finally
    //   35	49	62	finally
    //   53	56	62	finally
    //   68	76	62	finally
    //   76	79	62	finally
    //   35	49	82	java/lang/Throwable
    //   68	76	82	java/lang/Throwable
  }
  
  /* Error */
  public static void a(android.content.Context paramContext, String paramString1, String paramString2, String paramString3)
  {
    // Byte code:
    //   0: ldc 2
    //   2: monitorenter
    //   3: aload_1
    //   4: invokestatic 18	com/alipay/c/a/a/a/a:a	(Ljava/lang/String;)Z
    //   7: ifne +14 -> 21
    //   10: aload_2
    //   11: invokestatic 18	com/alipay/c/a/a/a/a:a	(Ljava/lang/String;)Z
    //   14: ifne +7 -> 21
    //   17: aload_0
    //   18: ifnonnull +7 -> 25
    //   21: ldc 2
    //   23: monitorexit
    //   24: return
    //   25: invokestatic 30	com/alipay/c/a/a/a/a/c:a	()Ljava/lang/String;
    //   28: aload_3
    //   29: invokestatic 37	com/alipay/c/a/a/a/a/c:a	(Ljava/lang/String;Ljava/lang/String;)Ljava/lang/String;
    //   32: astore 4
    //   34: new 39	java/util/HashMap
    //   37: astore_3
    //   38: aload_3
    //   39: invokespecial 40	java/util/HashMap:<init>	()V
    //   42: aload_3
    //   43: aload_2
    //   44: aload 4
    //   46: invokeinterface 46 3 0
    //   51: pop
    //   52: aload_0
    //   53: aload_1
    //   54: aload_3
    //   55: invokestatic 49	com/alipay/c/a/a/d/d:a	(Landroid/content/Context;Ljava/lang/String;Ljava/util/Map;)V
    //   58: ldc 2
    //   60: monitorexit
    //   61: goto -37 -> 24
    //   64: astore_0
    //   65: ldc 2
    //   67: monitorexit
    //   68: aload_0
    //   69: athrow
    //   70: astore_0
    //   71: goto -13 -> 58
    // Local variable table:
    //   start	length	slot	name	signature
    //   0	74	0	paramContext	android.content.Context
    //   0	74	1	paramString1	String
    //   0	74	2	paramString2	String
    //   0	74	3	paramString3	String
    //   32	13	4	str	String
    // Exception table:
    //   from	to	target	type
    //   3	17	64	finally
    //   21	24	64	finally
    //   25	58	64	finally
    //   58	61	64	finally
    //   25	58	70	java/lang/Throwable
  }
}


/* Location:              /Users/hanlian/Downloads/WiFi万能钥匙dex1-dex2jar.jar!/com/alipay/c/a/a/d/a.class
 * Java compiler version: 6 (50.0)
 * JD-Core Version:       0.7.1
 */