package ct;

import android.os.SystemClock;
import android.text.TextUtils;
import java.net.InetAddress;
import java.net.MalformedURLException;
import java.net.URL;
import org.apache.http.impl.client.DefaultHttpClient;

public final class ae
  implements z
{
  private static DefaultHttpClient c = null;
  private Byte a;
  private a b;
  
  /* Error */
  private static DefaultHttpClient a(int paramInt1, int paramInt2)
  {
    // Byte code:
    //   0: ldc 2
    //   2: monitorenter
    //   3: getstatic 18	ct/ae:c	Lorg/apache/http/impl/client/DefaultHttpClient;
    //   6: ifnonnull +152 -> 158
    //   9: new 27	java/lang/StringBuilder
    //   12: astore_2
    //   13: aload_2
    //   14: ldc 29
    //   16: invokespecial 32	java/lang/StringBuilder:<init>	(Ljava/lang/String;)V
    //   19: ldc 34
    //   21: aload_2
    //   22: iload_0
    //   23: invokevirtual 38	java/lang/StringBuilder:append	(I)Ljava/lang/StringBuilder;
    //   26: ldc 40
    //   28: invokevirtual 43	java/lang/StringBuilder:append	(Ljava/lang/String;)Ljava/lang/StringBuilder;
    //   31: iload_1
    //   32: invokevirtual 38	java/lang/StringBuilder:append	(I)Ljava/lang/StringBuilder;
    //   35: invokevirtual 47	java/lang/StringBuilder:toString	()Ljava/lang/String;
    //   38: invokestatic 52	ct/bb:a	(Ljava/lang/String;Ljava/lang/String;)V
    //   41: new 54	org/apache/http/params/BasicHttpParams
    //   44: astore_2
    //   45: aload_2
    //   46: invokespecial 55	org/apache/http/params/BasicHttpParams:<init>	()V
    //   49: aload_2
    //   50: bipush 100
    //   52: invokestatic 61	org/apache/http/conn/params/ConnManagerParams:setMaxTotalConnections	(Lorg/apache/http/params/HttpParams;I)V
    //   55: new 63	org/apache/http/conn/params/ConnPerRouteBean
    //   58: astore_3
    //   59: aload_3
    //   60: bipush 30
    //   62: invokespecial 66	org/apache/http/conn/params/ConnPerRouteBean:<init>	(I)V
    //   65: aload_2
    //   66: aload_3
    //   67: invokestatic 70	org/apache/http/conn/params/ConnManagerParams:setMaxConnectionsPerRoute	(Lorg/apache/http/params/HttpParams;Lorg/apache/http/conn/params/ConnPerRoute;)V
    //   70: aload_2
    //   71: ldc2_w 71
    //   74: invokestatic 76	org/apache/http/conn/params/ConnManagerParams:setTimeout	(Lorg/apache/http/params/HttpParams;J)V
    //   77: aload_2
    //   78: iconst_0
    //   79: invokestatic 82	org/apache/http/params/HttpProtocolParams:setUseExpectContinue	(Lorg/apache/http/params/HttpParams;Z)V
    //   82: aload_2
    //   83: iconst_0
    //   84: invokestatic 87	org/apache/http/client/params/HttpClientParams:setRedirecting	(Lorg/apache/http/params/HttpParams;Z)V
    //   87: aload_2
    //   88: iload_0
    //   89: invokestatic 92	org/apache/http/params/HttpConnectionParams:setConnectionTimeout	(Lorg/apache/http/params/HttpParams;I)V
    //   92: aload_2
    //   93: iload_1
    //   94: invokestatic 95	org/apache/http/params/HttpConnectionParams:setSoTimeout	(Lorg/apache/http/params/HttpParams;I)V
    //   97: aload_2
    //   98: sipush 8192
    //   101: invokestatic 98	org/apache/http/params/HttpConnectionParams:setSocketBufferSize	(Lorg/apache/http/params/HttpParams;I)V
    //   104: getstatic 18	ct/ae:c	Lorg/apache/http/impl/client/DefaultHttpClient;
    //   107: astore_3
    //   108: new 100	ct/af
    //   111: astore 4
    //   113: aload 4
    //   115: invokespecial 101	ct/af:<init>	()V
    //   118: aload_3
    //   119: aload 4
    //   121: invokevirtual 107	org/apache/http/impl/client/DefaultHttpClient:setKeepAliveStrategy	(Lorg/apache/http/conn/ConnectionKeepAliveStrategy;)V
    //   124: new 103	org/apache/http/impl/client/DefaultHttpClient
    //   127: astore_3
    //   128: aload_3
    //   129: aload_2
    //   130: invokespecial 110	org/apache/http/impl/client/DefaultHttpClient:<init>	(Lorg/apache/http/params/HttpParams;)V
    //   133: aload_3
    //   134: putstatic 18	ct/ae:c	Lorg/apache/http/impl/client/DefaultHttpClient;
    //   137: new 112	org/apache/http/impl/client/DefaultHttpRequestRetryHandler
    //   140: astore_2
    //   141: aload_2
    //   142: iconst_0
    //   143: iconst_0
    //   144: invokespecial 115	org/apache/http/impl/client/DefaultHttpRequestRetryHandler:<init>	(IZ)V
    //   147: aload_3
    //   148: aload_2
    //   149: invokevirtual 119	org/apache/http/impl/client/DefaultHttpClient:setHttpRequestRetryHandler	(Lorg/apache/http/client/HttpRequestRetryHandler;)V
    //   152: getstatic 18	ct/ae:c	Lorg/apache/http/impl/client/DefaultHttpClient;
    //   155: invokestatic 124	ct/ba:a	(Lorg/apache/http/client/HttpClient;)V
    //   158: getstatic 18	ct/ae:c	Lorg/apache/http/impl/client/DefaultHttpClient;
    //   161: astore_2
    //   162: ldc 2
    //   164: monitorexit
    //   165: aload_2
    //   166: areturn
    //   167: astore_2
    //   168: ldc 2
    //   170: monitorexit
    //   171: aload_2
    //   172: athrow
    //   173: astore_3
    //   174: goto -50 -> 124
    // Local variable table:
    //   start	length	slot	name	signature
    //   0	177	0	paramInt1	int
    //   0	177	1	paramInt2	int
    //   12	154	2	localObject1	Object
    //   167	5	2	localObject2	Object
    //   58	90	3	localObject3	Object
    //   173	1	3	localThrowable	Throwable
    //   111	9	4	localaf	af
    // Exception table:
    //   from	to	target	type
    //   3	104	167	finally
    //   104	124	167	finally
    //   124	158	167	finally
    //   158	162	167	finally
    //   104	124	173	java/lang/Throwable
  }
  
  public static void a(ad paramad)
  {
    u localu;
    String str1;
    String str2;
    if (paramad != null)
    {
      localu = u.a();
      str1 = paramad.c;
      paramad = paramad.a;
      str2 = ba.a();
      if ((!TextUtils.isEmpty(str2)) && (!str2.equals("unknown"))) {
        break label60;
      }
      bb.c("AccessSchedulerStorageManager", "updateApnUserTime... failed with apnName:" + str2);
    }
    for (;;)
    {
      return;
      label60:
      localu.a.a(str2, str1, paramad.a());
      localu.a(true);
      bb.b("AccessSchedulerStorageManager", "updateApnUseTime... apnName:" + str2);
    }
  }
  
  private static ab b(String paramString, byte[] paramArrayOfByte)
  {
    try
    {
      URL localURL = new java/net/URL;
      localURL.<init>(bc.c(paramString));
      int i = localURL.getPort();
      ab localab = new ct/ab;
      localab.<init>(localURL.getHost(), new int[] { i });
      if ((!TextUtils.isEmpty(paramString)) && (paramString.toLowerCase().startsWith("https://"))) {
        localab.a = true;
      }
      localab.g = localURL.getFile();
      localab.k = paramArrayOfByte;
      localab.d = paramString;
      return localab;
    }
    catch (MalformedURLException paramArrayOfByte)
    {
      paramArrayOfByte.printStackTrace();
      throw new ag("url format error:" + paramString);
    }
  }
  
  /* Error */
  private ac b(ab paramab)
  {
    // Byte code:
    //   0: new 298	ct/ac
    //   3: dup
    //   4: invokespecial 299	ct/ac:<init>	()V
    //   7: astore 17
    //   9: invokestatic 303	ct/ba:e	()Z
    //   12: ifne +70 -> 82
    //   15: aload 17
    //   17: bipush -4
    //   19: putfield 305	ct/ac:a	I
    //   22: new 132	ct/ad
    //   25: dup
    //   26: invokespecial 306	ct/ad:<init>	()V
    //   29: astore 18
    //   31: aload 18
    //   33: aload_1
    //   34: getfield 283	ct/ab:d	Ljava/lang/String;
    //   37: putfield 307	ct/ad:d	Ljava/lang/String;
    //   40: aload 18
    //   42: ldc_w 309
    //   45: putfield 312	ct/ad:p	Ljava/lang/String;
    //   48: aload 18
    //   50: bipush -4
    //   52: putfield 195	ct/ad:i	I
    //   55: new 314	java/lang/Thread
    //   58: dup
    //   59: new 8	ct/ae$a
    //   62: dup
    //   63: aload_0
    //   64: aload 18
    //   66: invokespecial 317	ct/ae$a:<init>	(Lct/ae;Lct/ad;)V
    //   69: invokespecial 320	java/lang/Thread:<init>	(Ljava/lang/Runnable;)V
    //   72: invokevirtual 323	java/lang/Thread:start	()V
    //   75: aload 17
    //   77: astore 19
    //   79: aload 19
    //   81: areturn
    //   82: aload_0
    //   83: invokestatic 328	ct/i:a	()Lct/a;
    //   86: putfield 181	ct/ae:b	Lct/a;
    //   89: new 330	ct/x
    //   92: dup
    //   93: aload_1
    //   94: invokespecial 333	ct/x:<init>	(Lct/ab;)V
    //   97: astore 18
    //   99: new 335	ct/y
    //   102: dup
    //   103: invokestatic 337	ct/ba:c	()I
    //   106: invokespecial 338	ct/y:<init>	(I)V
    //   109: astore 27
    //   111: aload 18
    //   113: invokevirtual 341	ct/x:c	()Ljava/util/List;
    //   116: astore 28
    //   118: aload 18
    //   120: invokevirtual 344	ct/x:a	()Lct/s;
    //   123: astore 29
    //   125: ldc 34
    //   127: new 27	java/lang/StringBuilder
    //   130: dup
    //   131: ldc_w 346
    //   134: invokespecial 32	java/lang/StringBuilder:<init>	(Ljava/lang/String;)V
    //   137: aload 28
    //   139: invokevirtual 349	java/lang/StringBuilder:append	(Ljava/lang/Object;)Ljava/lang/StringBuilder;
    //   142: ldc_w 351
    //   145: invokevirtual 43	java/lang/StringBuilder:append	(Ljava/lang/String;)Ljava/lang/StringBuilder;
    //   148: aload 29
    //   150: invokevirtual 349	java/lang/StringBuilder:append	(Ljava/lang/Object;)Ljava/lang/StringBuilder;
    //   153: invokevirtual 47	java/lang/StringBuilder:toString	()Ljava/lang/String;
    //   156: invokestatic 52	ct/bb:a	(Ljava/lang/String;Ljava/lang/String;)V
    //   159: aload 28
    //   161: invokeinterface 356 1 0
    //   166: istore 7
    //   168: aload 28
    //   170: invokeinterface 356 1 0
    //   175: istore 8
    //   177: aload 18
    //   179: invokevirtual 358	ct/x:b	()Ljava/lang/String;
    //   182: astore 30
    //   184: iconst_0
    //   185: istore 4
    //   187: iconst_0
    //   188: istore 15
    //   190: ldc_w 360
    //   193: astore 19
    //   195: iconst_0
    //   196: istore 5
    //   198: ldc_w 360
    //   201: astore 20
    //   203: iconst_0
    //   204: istore_3
    //   205: aload 17
    //   207: astore 18
    //   209: aload 20
    //   211: astore 17
    //   213: iload 4
    //   215: aload_1
    //   216: getfield 363	ct/ab:q	I
    //   219: if_icmpgt +5098 -> 5317
    //   222: iload_3
    //   223: ifne +5094 -> 5317
    //   226: invokestatic 369	android/os/SystemClock:elapsedRealtime	()J
    //   229: lstore 10
    //   231: new 298	ct/ac
    //   234: dup
    //   235: invokespecial 299	ct/ac:<init>	()V
    //   238: astore 24
    //   240: new 132	ct/ad
    //   243: dup
    //   244: invokespecial 306	ct/ad:<init>	()V
    //   247: astore 26
    //   249: aload 26
    //   251: aload 30
    //   253: putfield 372	ct/ad:w	Ljava/lang/String;
    //   256: aload 26
    //   258: aload 29
    //   260: putfield 374	ct/ad:b	Lct/s;
    //   263: iconst_0
    //   264: istore 14
    //   266: iload 4
    //   268: aload_1
    //   269: getfield 363	ct/ab:q	I
    //   272: if_icmpne +6 -> 278
    //   275: iconst_1
    //   276: istore 14
    //   278: iload 4
    //   280: iload 8
    //   282: irem
    //   283: istore_2
    //   284: iload_2
    //   285: iload 7
    //   287: iconst_1
    //   288: isub
    //   289: if_icmpge +31 -> 320
    //   292: aload 26
    //   294: iconst_1
    //   295: putfield 377	ct/ad:v	Z
    //   298: aload_1
    //   299: ldc_w 379
    //   302: aload_1
    //   303: getfield 382	ct/ab:f	Ljava/lang/String;
    //   306: invokevirtual 383	ct/ab:a	(Ljava/lang/String;Ljava/lang/String;)V
    //   309: aload_1
    //   310: ldc_w 385
    //   313: aload_1
    //   314: getfield 382	ct/ab:f	Ljava/lang/String;
    //   317: invokevirtual 383	ct/ab:a	(Ljava/lang/String;Ljava/lang/String;)V
    //   320: aload 28
    //   322: iload_2
    //   323: invokeinterface 388 2 0
    //   328: checkcast 165	ct/s
    //   331: astore 25
    //   333: aload 26
    //   335: aload 25
    //   337: putfield 138	ct/ad:a	Lct/s;
    //   340: aload 26
    //   342: aload_1
    //   343: getfield 389	ct/ab:c	Ljava/lang/String;
    //   346: putfield 135	ct/ad:c	Ljava/lang/String;
    //   349: aload 26
    //   351: aload_1
    //   352: getfield 270	ct/ab:a	Z
    //   355: putfield 392	ct/ad:B	Z
    //   358: aload 26
    //   360: aload_1
    //   361: getfield 363	ct/ab:q	I
    //   364: putfield 395	ct/ad:s	I
    //   367: invokestatic 369	android/os/SystemClock:elapsedRealtime	()J
    //   370: aload_1
    //   371: getfield 399	ct/ab:l	J
    //   374: lsub
    //   375: aload_1
    //   376: getfield 401	ct/ab:p	I
    //   379: i2l
    //   380: lcmp
    //   381: ifle +5095 -> 5476
    //   384: aload 28
    //   386: aload 28
    //   388: invokeinterface 356 1 0
    //   393: iconst_1
    //   394: isub
    //   395: invokeinterface 388 2 0
    //   400: checkcast 165	ct/s
    //   403: astore 25
    //   405: iconst_1
    //   406: istore_3
    //   407: iconst_1
    //   408: istore_2
    //   409: aload 26
    //   411: iconst_1
    //   412: putfield 404	ct/ad:y	Z
    //   415: iload_2
    //   416: istore_3
    //   417: aload 17
    //   419: invokestatic 146	android/text/TextUtils:isEmpty	(Ljava/lang/CharSequence;)Z
    //   422: ifeq +1104 -> 1526
    //   425: iload_2
    //   426: istore_3
    //   427: aload_1
    //   428: getfield 270	ct/ab:a	Z
    //   431: ifne +954 -> 1385
    //   434: iload_2
    //   435: istore_3
    //   436: aload 25
    //   438: getfield 405	ct/s:b	I
    //   441: iconst_m1
    //   442: if_icmpeq +906 -> 1348
    //   445: iload_2
    //   446: istore_3
    //   447: new 27	java/lang/StringBuilder
    //   450: astore 18
    //   452: iload_2
    //   453: istore_3
    //   454: aload 18
    //   456: ldc_w 407
    //   459: invokespecial 32	java/lang/StringBuilder:<init>	(Ljava/lang/String;)V
    //   462: iload_2
    //   463: istore_3
    //   464: aload 18
    //   466: aload 25
    //   468: getfield 409	ct/s:a	Ljava/lang/String;
    //   471: invokevirtual 43	java/lang/StringBuilder:append	(Ljava/lang/String;)Ljava/lang/StringBuilder;
    //   474: ldc_w 411
    //   477: invokevirtual 43	java/lang/StringBuilder:append	(Ljava/lang/String;)Ljava/lang/StringBuilder;
    //   480: aload 25
    //   482: getfield 405	ct/s:b	I
    //   485: invokevirtual 38	java/lang/StringBuilder:append	(I)Ljava/lang/StringBuilder;
    //   488: invokevirtual 47	java/lang/StringBuilder:toString	()Ljava/lang/String;
    //   491: astore 18
    //   493: iload_2
    //   494: istore_3
    //   495: aload_1
    //   496: getfield 276	ct/ab:g	Ljava/lang/String;
    //   499: astore 21
    //   501: aload 18
    //   503: astore 20
    //   505: iload_2
    //   506: istore_3
    //   507: aload 21
    //   509: invokestatic 146	android/text/TextUtils:isEmpty	(Ljava/lang/CharSequence;)Z
    //   512: ifne +49 -> 561
    //   515: iload_2
    //   516: istore_3
    //   517: aload 21
    //   519: ldc_w 413
    //   522: invokevirtual 267	java/lang/String:startsWith	(Ljava/lang/String;)Z
    //   525: ifeq +959 -> 1484
    //   528: iload_2
    //   529: istore_3
    //   530: new 27	java/lang/StringBuilder
    //   533: astore 20
    //   535: iload_2
    //   536: istore_3
    //   537: aload 20
    //   539: invokespecial 414	java/lang/StringBuilder:<init>	()V
    //   542: iload_2
    //   543: istore_3
    //   544: aload 20
    //   546: aload 18
    //   548: invokevirtual 43	java/lang/StringBuilder:append	(Ljava/lang/String;)Ljava/lang/StringBuilder;
    //   551: aload 21
    //   553: invokevirtual 43	java/lang/StringBuilder:append	(Ljava/lang/String;)Ljava/lang/StringBuilder;
    //   556: invokevirtual 47	java/lang/StringBuilder:toString	()Ljava/lang/String;
    //   559: astore 20
    //   561: iload_2
    //   562: istore_3
    //   563: aload 26
    //   565: aload 20
    //   567: putfield 307	ct/ad:d	Ljava/lang/String;
    //   570: aload 20
    //   572: astore 18
    //   574: aload 17
    //   576: astore 21
    //   578: aload 19
    //   580: astore 23
    //   582: aload 17
    //   584: astore 20
    //   586: aload 19
    //   588: astore 22
    //   590: new 27	java/lang/StringBuilder
    //   593: astore 31
    //   595: aload 17
    //   597: astore 21
    //   599: aload 19
    //   601: astore 23
    //   603: aload 17
    //   605: astore 20
    //   607: aload 19
    //   609: astore 22
    //   611: aload 31
    //   613: ldc_w 416
    //   616: invokespecial 32	java/lang/StringBuilder:<init>	(Ljava/lang/String;)V
    //   619: aload 17
    //   621: astore 21
    //   623: aload 19
    //   625: astore 23
    //   627: aload 17
    //   629: astore 20
    //   631: aload 19
    //   633: astore 22
    //   635: ldc 34
    //   637: aload 31
    //   639: iload 4
    //   641: invokevirtual 38	java/lang/StringBuilder:append	(I)Ljava/lang/StringBuilder;
    //   644: ldc_w 418
    //   647: invokevirtual 43	java/lang/StringBuilder:append	(Ljava/lang/String;)Ljava/lang/StringBuilder;
    //   650: aload 18
    //   652: invokevirtual 43	java/lang/StringBuilder:append	(Ljava/lang/String;)Ljava/lang/StringBuilder;
    //   655: ldc_w 420
    //   658: invokevirtual 43	java/lang/StringBuilder:append	(Ljava/lang/String;)Ljava/lang/StringBuilder;
    //   661: iload 15
    //   663: invokevirtual 423	java/lang/StringBuilder:append	(Z)Ljava/lang/StringBuilder;
    //   666: ldc_w 425
    //   669: invokevirtual 43	java/lang/StringBuilder:append	(Ljava/lang/String;)Ljava/lang/StringBuilder;
    //   672: aload 25
    //   674: invokevirtual 349	java/lang/StringBuilder:append	(Ljava/lang/Object;)Ljava/lang/StringBuilder;
    //   677: invokevirtual 47	java/lang/StringBuilder:toString	()Ljava/lang/String;
    //   680: invokestatic 52	ct/bb:a	(Ljava/lang/String;Ljava/lang/String;)V
    //   683: aload 17
    //   685: astore 21
    //   687: aload 19
    //   689: astore 23
    //   691: aload 17
    //   693: astore 20
    //   695: aload 19
    //   697: astore 22
    //   699: new 427	org/apache/http/client/methods/HttpPost
    //   702: astore 25
    //   704: aload 17
    //   706: astore 21
    //   708: aload 19
    //   710: astore 23
    //   712: aload 17
    //   714: astore 20
    //   716: aload 19
    //   718: astore 22
    //   720: aload 25
    //   722: aload 18
    //   724: invokespecial 428	org/apache/http/client/methods/HttpPost:<init>	(Ljava/lang/String;)V
    //   727: aload 17
    //   729: astore 21
    //   731: aload 19
    //   733: astore 23
    //   735: aload 17
    //   737: astore 20
    //   739: aload 19
    //   741: astore 22
    //   743: new 430	java/util/HashMap
    //   746: astore 31
    //   748: aload 17
    //   750: astore 21
    //   752: aload 19
    //   754: astore 23
    //   756: aload 17
    //   758: astore 20
    //   760: aload 19
    //   762: astore 22
    //   764: aload 31
    //   766: invokespecial 431	java/util/HashMap:<init>	()V
    //   769: aload 17
    //   771: astore 21
    //   773: aload 19
    //   775: astore 23
    //   777: aload 17
    //   779: astore 20
    //   781: aload 19
    //   783: astore 22
    //   785: aload 31
    //   787: aload_1
    //   788: getfield 434	ct/ab:j	Ljava/util/Map;
    //   791: invokeinterface 438 2 0
    //   796: aload 17
    //   798: astore 21
    //   800: aload 19
    //   802: astore 23
    //   804: aload 17
    //   806: astore 20
    //   808: aload 19
    //   810: astore 22
    //   812: aload 31
    //   814: invokeinterface 439 1 0
    //   819: ifle +885 -> 1704
    //   822: iload 15
    //   824: ifne +880 -> 1704
    //   827: aload 17
    //   829: astore 21
    //   831: aload 19
    //   833: astore 23
    //   835: aload 17
    //   837: astore 20
    //   839: aload 19
    //   841: astore 22
    //   843: aload 31
    //   845: invokeinterface 443 1 0
    //   850: invokeinterface 449 1 0
    //   855: astore 32
    //   857: aload 17
    //   859: astore 21
    //   861: aload 19
    //   863: astore 23
    //   865: aload 17
    //   867: astore 20
    //   869: aload 19
    //   871: astore 22
    //   873: aload 32
    //   875: invokeinterface 454 1 0
    //   880: ifeq +669 -> 1549
    //   883: aload 17
    //   885: astore 21
    //   887: aload 19
    //   889: astore 23
    //   891: aload 17
    //   893: astore 20
    //   895: aload 19
    //   897: astore 22
    //   899: aload 32
    //   901: invokeinterface 458 1 0
    //   906: checkcast 150	java/lang/String
    //   909: astore 33
    //   911: aload 17
    //   913: astore 21
    //   915: aload 19
    //   917: astore 23
    //   919: aload 17
    //   921: astore 20
    //   923: aload 19
    //   925: astore 22
    //   927: aload 25
    //   929: aload 33
    //   931: aload 31
    //   933: aload 33
    //   935: invokeinterface 207 2 0
    //   940: checkcast 150	java/lang/String
    //   943: invokeinterface 463 3 0
    //   948: goto -91 -> 857
    //   951: astore 19
    //   953: aload 23
    //   955: astore 17
    //   957: iload 15
    //   959: istore 16
    //   961: aload 21
    //   963: astore 18
    //   965: iload 14
    //   967: istore 15
    //   969: iload 16
    //   971: istore 14
    //   973: iload_2
    //   974: istore_3
    //   975: ldc 34
    //   977: ldc_w 465
    //   980: aload 19
    //   982: invokestatic 468	ct/bb:a	(Ljava/lang/String;Ljava/lang/String;Ljava/lang/Throwable;)V
    //   985: aload 26
    //   987: aload 19
    //   989: invokevirtual 472	java/lang/Object:getClass	()Ljava/lang/Class;
    //   992: invokevirtual 477	java/lang/Class:getSimpleName	()Ljava/lang/String;
    //   995: putfield 480	ct/ad:o	Ljava/lang/String;
    //   998: aload 26
    //   1000: aload 19
    //   1002: invokestatic 483	ct/bc:a	(Ljava/lang/Exception;)Ljava/lang/String;
    //   1005: putfield 312	ct/ad:p	Ljava/lang/String;
    //   1008: invokestatic 303	ct/ba:e	()Z
    //   1011: ifeq +4226 -> 5237
    //   1014: ldc_w 485
    //   1017: invokestatic 489	ct/j:b	(Ljava/lang/String;)Z
    //   1020: ifeq +4211 -> 5231
    //   1023: aload 19
    //   1025: instanceof 491
    //   1028: ifeq +4067 -> 5095
    //   1031: bipush -10
    //   1033: istore_2
    //   1034: aload 24
    //   1036: iload_2
    //   1037: putfield 305	ct/ac:a	I
    //   1040: aload 26
    //   1042: getfield 312	ct/ad:p	Ljava/lang/String;
    //   1045: ldc_w 493
    //   1048: invokevirtual 496	java/lang/String:contains	(Ljava/lang/CharSequence;)Z
    //   1051: ifeq +10 -> 1061
    //   1054: aload 24
    //   1056: bipush -18
    //   1058: putfield 305	ct/ac:a	I
    //   1061: aload 26
    //   1063: new 27	java/lang/StringBuilder
    //   1066: dup
    //   1067: invokespecial 414	java/lang/StringBuilder:<init>	()V
    //   1070: aload_1
    //   1071: getfield 498	ct/ab:s	Ljava/lang/String;
    //   1074: invokevirtual 43	java/lang/StringBuilder:append	(Ljava/lang/String;)Ljava/lang/StringBuilder;
    //   1077: ldc_w 500
    //   1080: invokevirtual 43	java/lang/StringBuilder:append	(Ljava/lang/String;)Ljava/lang/StringBuilder;
    //   1083: iload 4
    //   1085: invokevirtual 38	java/lang/StringBuilder:append	(I)Ljava/lang/StringBuilder;
    //   1088: invokevirtual 47	java/lang/StringBuilder:toString	()Ljava/lang/String;
    //   1091: putfield 503	ct/ad:n	Ljava/lang/String;
    //   1094: aload 26
    //   1096: iload 4
    //   1098: putfield 504	ct/ad:q	I
    //   1101: aload 18
    //   1103: invokestatic 146	android/text/TextUtils:isEmpty	(Ljava/lang/CharSequence;)Z
    //   1106: ifeq +4137 -> 5243
    //   1109: iload 4
    //   1111: iconst_1
    //   1112: iadd
    //   1113: istore_2
    //   1114: iconst_0
    //   1115: istore 5
    //   1117: invokestatic 507	ct/p:b	()Ljava/lang/String;
    //   1120: invokestatic 146	android/text/TextUtils:isEmpty	(Ljava/lang/CharSequence;)Z
    //   1123: ifne +173 -> 1296
    //   1126: aload 24
    //   1128: getfield 305	ct/ac:a	I
    //   1131: bipush -21
    //   1133: if_icmpeq +163 -> 1296
    //   1136: aload 24
    //   1138: invokestatic 369	android/os/SystemClock:elapsedRealtime	()J
    //   1141: aload_1
    //   1142: getfield 399	ct/ab:l	J
    //   1145: lsub
    //   1146: l2i
    //   1147: putfield 509	ct/ac:f	I
    //   1150: aload 26
    //   1152: aload 24
    //   1154: getfield 305	ct/ac:a	I
    //   1157: putfield 195	ct/ad:i	I
    //   1160: aload 26
    //   1162: aload 17
    //   1164: putfield 512	ct/ad:A	Ljava/lang/String;
    //   1167: aload 26
    //   1169: aload 24
    //   1171: getfield 509	ct/ac:f	I
    //   1174: putfield 514	ct/ad:j	I
    //   1177: aload 26
    //   1179: invokestatic 369	android/os/SystemClock:elapsedRealtime	()J
    //   1182: lload 10
    //   1184: lsub
    //   1185: l2i
    //   1186: putfield 516	ct/ad:k	I
    //   1189: aload 26
    //   1191: aload 18
    //   1193: putfield 517	ct/ad:f	Ljava/lang/String;
    //   1196: aload_1
    //   1197: getfield 280	ct/ab:k	[B
    //   1200: ifnull +4081 -> 5281
    //   1203: aload 26
    //   1205: aload_1
    //   1206: getfield 280	ct/ab:k	[B
    //   1209: arraylength
    //   1210: i2l
    //   1211: putfield 518	ct/ad:l	J
    //   1214: aload 26
    //   1216: iload 15
    //   1218: putfield 521	ct/ad:x	Z
    //   1221: iload 15
    //   1223: ifeq +17 -> 1240
    //   1226: aload 26
    //   1228: getfield 195	ct/ad:i	I
    //   1231: ifeq +9 -> 1240
    //   1234: aload 26
    //   1236: iconst_1
    //   1237: putfield 524	ct/ad:u	I
    //   1240: aload 26
    //   1242: aload_1
    //   1243: getfield 526	ct/ab:i	Z
    //   1246: putfield 529	ct/ad:z	Z
    //   1249: aload_1
    //   1250: aload 26
    //   1252: invokevirtual 531	ct/ab:a	(Lct/ad;)V
    //   1255: new 314	java/lang/Thread
    //   1258: astore 19
    //   1260: new 8	ct/ae$a
    //   1263: astore 20
    //   1265: aload 20
    //   1267: aload_0
    //   1268: aload 26
    //   1270: invokespecial 317	ct/ae$a:<init>	(Lct/ae;Lct/ad;)V
    //   1273: aload 19
    //   1275: aload 20
    //   1277: invokespecial 320	java/lang/Thread:<init>	(Ljava/lang/Runnable;)V
    //   1280: aload 19
    //   1282: invokevirtual 323	java/lang/Thread:start	()V
    //   1285: ldc_w 533
    //   1288: aload 26
    //   1290: invokevirtual 534	ct/ad:toString	()Ljava/lang/String;
    //   1293: invokestatic 52	ct/bb:a	(Ljava/lang/String;Ljava/lang/String;)V
    //   1296: aload 24
    //   1298: astore 19
    //   1300: aload 24
    //   1302: getfield 305	ct/ac:a	I
    //   1305: bipush -17
    //   1307: if_icmpeq -1228 -> 79
    //   1310: aload 17
    //   1312: astore 19
    //   1314: aload 18
    //   1316: astore 17
    //   1318: iload 5
    //   1320: istore 4
    //   1322: aload 19
    //   1324: astore 18
    //   1326: aload 18
    //   1328: astore 19
    //   1330: iload 4
    //   1332: istore 5
    //   1334: aload 24
    //   1336: astore 18
    //   1338: iload 14
    //   1340: istore 15
    //   1342: iload_2
    //   1343: istore 4
    //   1345: goto -1132 -> 213
    //   1348: iload_2
    //   1349: istore_3
    //   1350: new 27	java/lang/StringBuilder
    //   1353: astore 18
    //   1355: iload_2
    //   1356: istore_3
    //   1357: aload 18
    //   1359: ldc_w 407
    //   1362: invokespecial 32	java/lang/StringBuilder:<init>	(Ljava/lang/String;)V
    //   1365: iload_2
    //   1366: istore_3
    //   1367: aload 18
    //   1369: aload 25
    //   1371: getfield 409	ct/s:a	Ljava/lang/String;
    //   1374: invokevirtual 43	java/lang/StringBuilder:append	(Ljava/lang/String;)Ljava/lang/StringBuilder;
    //   1377: invokevirtual 47	java/lang/StringBuilder:toString	()Ljava/lang/String;
    //   1380: astore 18
    //   1382: goto -889 -> 493
    //   1385: iload_2
    //   1386: istore_3
    //   1387: aload 25
    //   1389: getfield 405	ct/s:b	I
    //   1392: iconst_m1
    //   1393: if_icmpeq +54 -> 1447
    //   1396: iload_2
    //   1397: istore_3
    //   1398: new 27	java/lang/StringBuilder
    //   1401: astore 18
    //   1403: iload_2
    //   1404: istore_3
    //   1405: aload 18
    //   1407: ldc_w 263
    //   1410: invokespecial 32	java/lang/StringBuilder:<init>	(Ljava/lang/String;)V
    //   1413: iload_2
    //   1414: istore_3
    //   1415: aload 18
    //   1417: aload 25
    //   1419: getfield 409	ct/s:a	Ljava/lang/String;
    //   1422: invokevirtual 43	java/lang/StringBuilder:append	(Ljava/lang/String;)Ljava/lang/StringBuilder;
    //   1425: ldc_w 411
    //   1428: invokevirtual 43	java/lang/StringBuilder:append	(Ljava/lang/String;)Ljava/lang/StringBuilder;
    //   1431: aload 25
    //   1433: getfield 405	ct/s:b	I
    //   1436: invokevirtual 38	java/lang/StringBuilder:append	(I)Ljava/lang/StringBuilder;
    //   1439: invokevirtual 47	java/lang/StringBuilder:toString	()Ljava/lang/String;
    //   1442: astore 18
    //   1444: goto -951 -> 493
    //   1447: iload_2
    //   1448: istore_3
    //   1449: new 27	java/lang/StringBuilder
    //   1452: astore 18
    //   1454: iload_2
    //   1455: istore_3
    //   1456: aload 18
    //   1458: ldc_w 263
    //   1461: invokespecial 32	java/lang/StringBuilder:<init>	(Ljava/lang/String;)V
    //   1464: iload_2
    //   1465: istore_3
    //   1466: aload 18
    //   1468: aload 25
    //   1470: getfield 409	ct/s:a	Ljava/lang/String;
    //   1473: invokevirtual 43	java/lang/StringBuilder:append	(Ljava/lang/String;)Ljava/lang/StringBuilder;
    //   1476: invokevirtual 47	java/lang/StringBuilder:toString	()Ljava/lang/String;
    //   1479: astore 18
    //   1481: goto -988 -> 493
    //   1484: iload_2
    //   1485: istore_3
    //   1486: new 27	java/lang/StringBuilder
    //   1489: astore 20
    //   1491: iload_2
    //   1492: istore_3
    //   1493: aload 20
    //   1495: invokespecial 414	java/lang/StringBuilder:<init>	()V
    //   1498: iload_2
    //   1499: istore_3
    //   1500: aload 20
    //   1502: aload 18
    //   1504: invokevirtual 43	java/lang/StringBuilder:append	(Ljava/lang/String;)Ljava/lang/StringBuilder;
    //   1507: ldc_w 413
    //   1510: invokevirtual 43	java/lang/StringBuilder:append	(Ljava/lang/String;)Ljava/lang/StringBuilder;
    //   1513: aload 21
    //   1515: invokevirtual 43	java/lang/StringBuilder:append	(Ljava/lang/String;)Ljava/lang/StringBuilder;
    //   1518: invokevirtual 47	java/lang/StringBuilder:toString	()Ljava/lang/String;
    //   1521: astore 20
    //   1523: goto -962 -> 561
    //   1526: iload_2
    //   1527: istore_3
    //   1528: aload 26
    //   1530: aload 17
    //   1532: putfield 517	ct/ad:f	Ljava/lang/String;
    //   1535: aconst_null
    //   1536: astore 20
    //   1538: aload 17
    //   1540: astore 18
    //   1542: aload 20
    //   1544: astore 17
    //   1546: goto -972 -> 574
    //   1549: aload 17
    //   1551: astore 21
    //   1553: aload 19
    //   1555: astore 23
    //   1557: aload 17
    //   1559: astore 20
    //   1561: aload 19
    //   1563: astore 22
    //   1565: getstatic 536	ct/ba:c	Z
    //   1568: ifeq +33 -> 1601
    //   1571: aload 17
    //   1573: astore 21
    //   1575: aload 19
    //   1577: astore 23
    //   1579: aload 17
    //   1581: astore 20
    //   1583: aload 19
    //   1585: astore 22
    //   1587: aload 25
    //   1589: ldc_w 538
    //   1592: aload_1
    //   1593: getfield 382	ct/ab:f	Ljava/lang/String;
    //   1596: invokeinterface 463 3 0
    //   1601: aload 17
    //   1603: astore 21
    //   1605: aload 19
    //   1607: astore 23
    //   1609: aload 17
    //   1611: astore 20
    //   1613: aload 19
    //   1615: astore 22
    //   1617: new 27	java/lang/StringBuilder
    //   1620: astore 32
    //   1622: aload 17
    //   1624: astore 21
    //   1626: aload 19
    //   1628: astore 23
    //   1630: aload 17
    //   1632: astore 20
    //   1634: aload 19
    //   1636: astore 22
    //   1638: aload 32
    //   1640: ldc_w 540
    //   1643: invokespecial 32	java/lang/StringBuilder:<init>	(Ljava/lang/String;)V
    //   1646: aload 17
    //   1648: astore 21
    //   1650: aload 19
    //   1652: astore 23
    //   1654: aload 17
    //   1656: astore 20
    //   1658: aload 19
    //   1660: astore 22
    //   1662: aload_1
    //   1663: ldc_w 542
    //   1666: aload 32
    //   1668: invokestatic 544	ct/p:f	()Ljava/lang/String;
    //   1671: invokevirtual 43	java/lang/StringBuilder:append	(Ljava/lang/String;)Ljava/lang/StringBuilder;
    //   1674: ldc_w 546
    //   1677: invokevirtual 43	java/lang/StringBuilder:append	(Ljava/lang/String;)Ljava/lang/StringBuilder;
    //   1680: aload_1
    //   1681: getfield 498	ct/ab:s	Ljava/lang/String;
    //   1684: invokevirtual 43	java/lang/StringBuilder:append	(Ljava/lang/String;)Ljava/lang/StringBuilder;
    //   1687: ldc_w 500
    //   1690: invokevirtual 43	java/lang/StringBuilder:append	(Ljava/lang/String;)Ljava/lang/StringBuilder;
    //   1693: iload 4
    //   1695: invokevirtual 38	java/lang/StringBuilder:append	(I)Ljava/lang/StringBuilder;
    //   1698: invokevirtual 47	java/lang/StringBuilder:toString	()Ljava/lang/String;
    //   1701: invokevirtual 383	ct/ab:a	(Ljava/lang/String;Ljava/lang/String;)V
    //   1704: iload 15
    //   1706: ifeq +451 -> 2157
    //   1709: aload 17
    //   1711: astore 21
    //   1713: aload 19
    //   1715: astore 23
    //   1717: aload 17
    //   1719: astore 20
    //   1721: aload 19
    //   1723: astore 22
    //   1725: aload 31
    //   1727: invokeinterface 443 1 0
    //   1732: invokeinterface 449 1 0
    //   1737: astore 32
    //   1739: aload 17
    //   1741: astore 21
    //   1743: aload 19
    //   1745: astore 23
    //   1747: aload 17
    //   1749: astore 20
    //   1751: aload 19
    //   1753: astore 22
    //   1755: aload 32
    //   1757: invokeinterface 454 1 0
    //   1762: ifeq +342 -> 2104
    //   1765: aload 17
    //   1767: astore 21
    //   1769: aload 19
    //   1771: astore 23
    //   1773: aload 17
    //   1775: astore 20
    //   1777: aload 19
    //   1779: astore 22
    //   1781: aload 32
    //   1783: invokeinterface 458 1 0
    //   1788: checkcast 150	java/lang/String
    //   1791: astore 33
    //   1793: aload 17
    //   1795: astore 21
    //   1797: aload 19
    //   1799: astore 23
    //   1801: aload 17
    //   1803: astore 20
    //   1805: aload 19
    //   1807: astore 22
    //   1809: aload 25
    //   1811: aload 33
    //   1813: aload 31
    //   1815: aload 33
    //   1817: invokeinterface 207 2 0
    //   1822: checkcast 150	java/lang/String
    //   1825: invokeinterface 463 3 0
    //   1830: goto -91 -> 1739
    //   1833: astore 19
    //   1835: aload 22
    //   1837: astore 18
    //   1839: aload 20
    //   1841: astore 17
    //   1843: aload 19
    //   1845: astore 20
    //   1847: aload 26
    //   1849: new 27	java/lang/StringBuilder
    //   1852: dup
    //   1853: invokespecial 414	java/lang/StringBuilder:<init>	()V
    //   1856: aload_1
    //   1857: getfield 498	ct/ab:s	Ljava/lang/String;
    //   1860: invokevirtual 43	java/lang/StringBuilder:append	(Ljava/lang/String;)Ljava/lang/StringBuilder;
    //   1863: ldc_w 500
    //   1866: invokevirtual 43	java/lang/StringBuilder:append	(Ljava/lang/String;)Ljava/lang/StringBuilder;
    //   1869: iload 4
    //   1871: invokevirtual 38	java/lang/StringBuilder:append	(I)Ljava/lang/StringBuilder;
    //   1874: invokevirtual 47	java/lang/StringBuilder:toString	()Ljava/lang/String;
    //   1877: putfield 503	ct/ad:n	Ljava/lang/String;
    //   1880: aload 26
    //   1882: iload 4
    //   1884: putfield 504	ct/ad:q	I
    //   1887: aload 17
    //   1889: invokestatic 146	android/text/TextUtils:isEmpty	(Ljava/lang/CharSequence;)Z
    //   1892: ifne +19 -> 1911
    //   1895: iload 5
    //   1897: iconst_1
    //   1898: iadd
    //   1899: bipush 6
    //   1901: if_icmple +10 -> 1911
    //   1904: aload 24
    //   1906: bipush -5
    //   1908: putfield 305	ct/ac:a	I
    //   1911: invokestatic 507	ct/p:b	()Ljava/lang/String;
    //   1914: invokestatic 146	android/text/TextUtils:isEmpty	(Ljava/lang/CharSequence;)Z
    //   1917: ifne +170 -> 2087
    //   1920: aload 24
    //   1922: getfield 305	ct/ac:a	I
    //   1925: bipush -21
    //   1927: if_icmpeq +160 -> 2087
    //   1930: aload 24
    //   1932: invokestatic 369	android/os/SystemClock:elapsedRealtime	()J
    //   1935: aload_1
    //   1936: getfield 399	ct/ab:l	J
    //   1939: lsub
    //   1940: l2i
    //   1941: putfield 509	ct/ac:f	I
    //   1944: aload 26
    //   1946: aload 24
    //   1948: getfield 305	ct/ac:a	I
    //   1951: putfield 195	ct/ad:i	I
    //   1954: aload 26
    //   1956: aload 18
    //   1958: putfield 512	ct/ad:A	Ljava/lang/String;
    //   1961: aload 26
    //   1963: aload 24
    //   1965: getfield 509	ct/ac:f	I
    //   1968: putfield 514	ct/ad:j	I
    //   1971: aload 26
    //   1973: invokestatic 369	android/os/SystemClock:elapsedRealtime	()J
    //   1976: lload 10
    //   1978: lsub
    //   1979: l2i
    //   1980: putfield 516	ct/ad:k	I
    //   1983: aload 26
    //   1985: aload 17
    //   1987: putfield 517	ct/ad:f	Ljava/lang/String;
    //   1990: aload_1
    //   1991: getfield 280	ct/ab:k	[B
    //   1994: ifnull +3306 -> 5300
    //   1997: aload 26
    //   1999: aload_1
    //   2000: getfield 280	ct/ab:k	[B
    //   2003: arraylength
    //   2004: i2l
    //   2005: putfield 518	ct/ad:l	J
    //   2008: aload 26
    //   2010: iload 14
    //   2012: putfield 521	ct/ad:x	Z
    //   2015: iload 14
    //   2017: ifeq +17 -> 2034
    //   2020: aload 26
    //   2022: getfield 195	ct/ad:i	I
    //   2025: ifeq +9 -> 2034
    //   2028: aload 26
    //   2030: iconst_1
    //   2031: putfield 524	ct/ad:u	I
    //   2034: aload 26
    //   2036: aload_1
    //   2037: getfield 526	ct/ab:i	Z
    //   2040: putfield 529	ct/ad:z	Z
    //   2043: aload_1
    //   2044: aload 26
    //   2046: invokevirtual 531	ct/ab:a	(Lct/ad;)V
    //   2049: new 314	java/lang/Thread
    //   2052: astore 17
    //   2054: new 8	ct/ae$a
    //   2057: astore_1
    //   2058: aload_1
    //   2059: aload_0
    //   2060: aload 26
    //   2062: invokespecial 317	ct/ae$a:<init>	(Lct/ae;Lct/ad;)V
    //   2065: aload 17
    //   2067: aload_1
    //   2068: invokespecial 320	java/lang/Thread:<init>	(Ljava/lang/Runnable;)V
    //   2071: aload 17
    //   2073: invokevirtual 323	java/lang/Thread:start	()V
    //   2076: ldc_w 533
    //   2079: aload 26
    //   2081: invokevirtual 534	ct/ad:toString	()Ljava/lang/String;
    //   2084: invokestatic 52	ct/bb:a	(Ljava/lang/String;Ljava/lang/String;)V
    //   2087: aload 24
    //   2089: astore 19
    //   2091: aload 24
    //   2093: getfield 305	ct/ac:a	I
    //   2096: bipush -17
    //   2098: if_icmpeq -2019 -> 79
    //   2101: aload 20
    //   2103: athrow
    //   2104: aload 17
    //   2106: astore 21
    //   2108: aload 19
    //   2110: astore 23
    //   2112: aload 17
    //   2114: astore 20
    //   2116: aload 19
    //   2118: astore 22
    //   2120: getstatic 536	ct/ba:c	Z
    //   2123: ifeq +34 -> 2157
    //   2126: aload 17
    //   2128: astore 21
    //   2130: aload 19
    //   2132: astore 23
    //   2134: aload 17
    //   2136: astore 20
    //   2138: aload 19
    //   2140: astore 22
    //   2142: aload 25
    //   2144: ldc_w 538
    //   2147: aload 18
    //   2149: invokestatic 548	ct/bc:d	(Ljava/lang/String;)Ljava/lang/String;
    //   2152: invokeinterface 463 3 0
    //   2157: aload 17
    //   2159: astore 21
    //   2161: aload 19
    //   2163: astore 23
    //   2165: aload 17
    //   2167: astore 20
    //   2169: aload 19
    //   2171: astore 22
    //   2173: aload_1
    //   2174: getfield 280	ct/ab:k	[B
    //   2177: astore 32
    //   2179: aload 32
    //   2181: ifnull +115 -> 2296
    //   2184: aload 17
    //   2186: astore 21
    //   2188: aload 19
    //   2190: astore 23
    //   2192: aload 17
    //   2194: astore 20
    //   2196: aload 19
    //   2198: astore 22
    //   2200: aload 32
    //   2202: arraylength
    //   2203: ifle +93 -> 2296
    //   2206: aload 17
    //   2208: astore 21
    //   2210: aload 19
    //   2212: astore 23
    //   2214: aload 17
    //   2216: astore 20
    //   2218: aload 19
    //   2220: astore 22
    //   2222: aload 25
    //   2224: checkcast 427	org/apache/http/client/methods/HttpPost
    //   2227: astore 31
    //   2229: aload 17
    //   2231: astore 21
    //   2233: aload 19
    //   2235: astore 23
    //   2237: aload 17
    //   2239: astore 20
    //   2241: aload 19
    //   2243: astore 22
    //   2245: new 550	org/apache/http/entity/ByteArrayEntity
    //   2248: astore 18
    //   2250: aload 17
    //   2252: astore 21
    //   2254: aload 19
    //   2256: astore 23
    //   2258: aload 17
    //   2260: astore 20
    //   2262: aload 19
    //   2264: astore 22
    //   2266: aload 18
    //   2268: aload 32
    //   2270: invokespecial 553	org/apache/http/entity/ByteArrayEntity:<init>	([B)V
    //   2273: aload 17
    //   2275: astore 21
    //   2277: aload 19
    //   2279: astore 23
    //   2281: aload 17
    //   2283: astore 20
    //   2285: aload 19
    //   2287: astore 22
    //   2289: aload 31
    //   2291: aload 18
    //   2293: invokevirtual 557	org/apache/http/client/methods/HttpPost:setEntity	(Lorg/apache/http/HttpEntity;)V
    //   2296: aload 17
    //   2298: astore 21
    //   2300: aload 19
    //   2302: astore 23
    //   2304: aload 17
    //   2306: astore 20
    //   2308: aload 19
    //   2310: astore 22
    //   2312: new 27	java/lang/StringBuilder
    //   2315: astore 18
    //   2317: aload 17
    //   2319: astore 21
    //   2321: aload 19
    //   2323: astore 23
    //   2325: aload 17
    //   2327: astore 20
    //   2329: aload 19
    //   2331: astore 22
    //   2333: aload 18
    //   2335: ldc 29
    //   2337: invokespecial 32	java/lang/StringBuilder:<init>	(Ljava/lang/String;)V
    //   2340: aload 17
    //   2342: astore 21
    //   2344: aload 19
    //   2346: astore 23
    //   2348: aload 17
    //   2350: astore 20
    //   2352: aload 19
    //   2354: astore 22
    //   2356: ldc 34
    //   2358: aload 18
    //   2360: aload_1
    //   2361: getfield 559	ct/ab:n	I
    //   2364: invokevirtual 38	java/lang/StringBuilder:append	(I)Ljava/lang/StringBuilder;
    //   2367: ldc 40
    //   2369: invokevirtual 43	java/lang/StringBuilder:append	(Ljava/lang/String;)Ljava/lang/StringBuilder;
    //   2372: aload_1
    //   2373: getfield 561	ct/ab:o	I
    //   2376: invokevirtual 38	java/lang/StringBuilder:append	(I)Ljava/lang/StringBuilder;
    //   2379: invokevirtual 47	java/lang/StringBuilder:toString	()Ljava/lang/String;
    //   2382: invokestatic 52	ct/bb:a	(Ljava/lang/String;Ljava/lang/String;)V
    //   2385: aload 17
    //   2387: astore 21
    //   2389: aload 19
    //   2391: astore 23
    //   2393: aload 17
    //   2395: astore 20
    //   2397: aload 19
    //   2399: astore 22
    //   2401: aload_1
    //   2402: aload 27
    //   2404: getfield 562	ct/y:b	I
    //   2407: sipush 1000
    //   2410: imul
    //   2411: invokevirtual 564	ct/ab:a	(I)V
    //   2414: aload 17
    //   2416: astore 21
    //   2418: aload 19
    //   2420: astore 23
    //   2422: aload 17
    //   2424: astore 20
    //   2426: aload 19
    //   2428: astore 22
    //   2430: aload_1
    //   2431: aload 27
    //   2433: getfield 565	ct/y:a	I
    //   2436: sipush 1000
    //   2439: imul
    //   2440: invokevirtual 567	ct/ab:b	(I)V
    //   2443: aload 17
    //   2445: astore 21
    //   2447: aload 19
    //   2449: astore 23
    //   2451: aload 17
    //   2453: astore 20
    //   2455: aload 19
    //   2457: astore 22
    //   2459: aload_1
    //   2460: getfield 559	ct/ab:n	I
    //   2463: aload_1
    //   2464: getfield 561	ct/ab:o	I
    //   2467: invokestatic 569	ct/ae:a	(II)Lorg/apache/http/impl/client/DefaultHttpClient;
    //   2470: astore 18
    //   2472: aload 17
    //   2474: astore 21
    //   2476: aload 19
    //   2478: astore 23
    //   2480: aload 17
    //   2482: astore 20
    //   2484: aload 19
    //   2486: astore 22
    //   2488: invokestatic 369	android/os/SystemClock:elapsedRealtime	()J
    //   2491: lstore 12
    //   2493: aload 17
    //   2495: astore 21
    //   2497: aload 19
    //   2499: astore 23
    //   2501: aload 17
    //   2503: astore 20
    //   2505: aload 19
    //   2507: astore 22
    //   2509: aload 18
    //   2511: aload 25
    //   2513: invokevirtual 573	org/apache/http/impl/client/DefaultHttpClient:execute	(Lorg/apache/http/client/methods/HttpUriRequest;)Lorg/apache/http/HttpResponse;
    //   2516: astore 25
    //   2518: aload 17
    //   2520: astore 21
    //   2522: aload 19
    //   2524: astore 23
    //   2526: aload 17
    //   2528: astore 20
    //   2530: aload 19
    //   2532: astore 22
    //   2534: aload 24
    //   2536: invokestatic 369	android/os/SystemClock:elapsedRealtime	()J
    //   2539: lload 12
    //   2541: lsub
    //   2542: l2i
    //   2543: putfield 575	ct/ac:c	I
    //   2546: aload 17
    //   2548: astore 21
    //   2550: aload 19
    //   2552: astore 23
    //   2554: aload 17
    //   2556: astore 20
    //   2558: aload 19
    //   2560: astore 22
    //   2562: new 27	java/lang/StringBuilder
    //   2565: astore 18
    //   2567: aload 17
    //   2569: astore 21
    //   2571: aload 19
    //   2573: astore 23
    //   2575: aload 17
    //   2577: astore 20
    //   2579: aload 19
    //   2581: astore 22
    //   2583: aload 18
    //   2585: ldc_w 577
    //   2588: invokespecial 32	java/lang/StringBuilder:<init>	(Ljava/lang/String;)V
    //   2591: aload 17
    //   2593: astore 21
    //   2595: aload 19
    //   2597: astore 23
    //   2599: aload 17
    //   2601: astore 20
    //   2603: aload 19
    //   2605: astore 22
    //   2607: ldc 34
    //   2609: aload 18
    //   2611: aload 24
    //   2613: getfield 575	ct/ac:c	I
    //   2616: invokevirtual 38	java/lang/StringBuilder:append	(I)Ljava/lang/StringBuilder;
    //   2619: invokevirtual 47	java/lang/StringBuilder:toString	()Ljava/lang/String;
    //   2622: invokestatic 52	ct/bb:a	(Ljava/lang/String;Ljava/lang/String;)V
    //   2625: aload 17
    //   2627: astore 21
    //   2629: aload 19
    //   2631: astore 23
    //   2633: aload 17
    //   2635: astore 20
    //   2637: aload 19
    //   2639: astore 22
    //   2641: aload 25
    //   2643: invokeinterface 583 1 0
    //   2648: invokeinterface 588 1 0
    //   2653: istore_3
    //   2654: aload 17
    //   2656: astore 21
    //   2658: aload 19
    //   2660: astore 23
    //   2662: aload 17
    //   2664: astore 20
    //   2666: aload 19
    //   2668: astore 22
    //   2670: aload 24
    //   2672: aload 25
    //   2674: putfield 591	ct/ac:e	Lorg/apache/http/HttpResponse;
    //   2677: aload 19
    //   2679: astore 18
    //   2681: aload 25
    //   2683: ifnull +69 -> 2752
    //   2686: aload 17
    //   2688: astore 21
    //   2690: aload 19
    //   2692: astore 23
    //   2694: aload 17
    //   2696: astore 20
    //   2698: aload 19
    //   2700: astore 22
    //   2702: aload 19
    //   2704: astore 18
    //   2706: aload 25
    //   2708: ldc_w 593
    //   2711: invokeinterface 597 2 0
    //   2716: ifnull +36 -> 2752
    //   2719: aload 17
    //   2721: astore 21
    //   2723: aload 19
    //   2725: astore 23
    //   2727: aload 17
    //   2729: astore 20
    //   2731: aload 19
    //   2733: astore 22
    //   2735: aload 25
    //   2737: ldc_w 593
    //   2740: invokeinterface 597 2 0
    //   2745: invokeinterface 602 1 0
    //   2750: astore 18
    //   2752: aload 17
    //   2754: astore 21
    //   2756: aload 18
    //   2758: astore 23
    //   2760: aload 17
    //   2762: astore 20
    //   2764: aload 18
    //   2766: astore 22
    //   2768: aload 26
    //   2770: aload 24
    //   2772: getfield 575	ct/ac:c	I
    //   2775: putfield 604	ct/ad:g	I
    //   2778: iload_3
    //   2779: lookupswitch	default:+89->2868, 200:+384->3163, 204:+2234->5013, 301:+1708->4487, 302:+1708->4487, 303:+1708->4487, 307:+1708->4487, 408:+2234->5013, 502:+2234->5013, 503:+2234->5013, 504:+2234->5013
    //   2868: aload 17
    //   2870: astore 21
    //   2872: aload 18
    //   2874: astore 23
    //   2876: aload 17
    //   2878: astore 20
    //   2880: aload 18
    //   2882: astore 22
    //   2884: aload 24
    //   2886: iload_3
    //   2887: putfield 305	ct/ac:a	I
    //   2890: iload 14
    //   2892: istore 16
    //   2894: iload 15
    //   2896: istore 14
    //   2898: iload 16
    //   2900: istore 15
    //   2902: aload 26
    //   2904: new 27	java/lang/StringBuilder
    //   2907: dup
    //   2908: invokespecial 414	java/lang/StringBuilder:<init>	()V
    //   2911: aload_1
    //   2912: getfield 498	ct/ab:s	Ljava/lang/String;
    //   2915: invokevirtual 43	java/lang/StringBuilder:append	(Ljava/lang/String;)Ljava/lang/StringBuilder;
    //   2918: ldc_w 500
    //   2921: invokevirtual 43	java/lang/StringBuilder:append	(Ljava/lang/String;)Ljava/lang/StringBuilder;
    //   2924: iload 4
    //   2926: invokevirtual 38	java/lang/StringBuilder:append	(I)Ljava/lang/StringBuilder;
    //   2929: invokevirtual 47	java/lang/StringBuilder:toString	()Ljava/lang/String;
    //   2932: putfield 503	ct/ad:n	Ljava/lang/String;
    //   2935: aload 26
    //   2937: iload 4
    //   2939: putfield 504	ct/ad:q	I
    //   2942: aload 17
    //   2944: invokestatic 146	android/text/TextUtils:isEmpty	(Ljava/lang/CharSequence;)Z
    //   2947: ifeq +2103 -> 5050
    //   2950: iinc 4 1
    //   2953: iconst_0
    //   2954: istore_3
    //   2955: invokestatic 507	ct/p:b	()Ljava/lang/String;
    //   2958: invokestatic 146	android/text/TextUtils:isEmpty	(Ljava/lang/CharSequence;)Z
    //   2961: ifne +173 -> 3134
    //   2964: aload 24
    //   2966: getfield 305	ct/ac:a	I
    //   2969: bipush -21
    //   2971: if_icmpeq +163 -> 3134
    //   2974: aload 24
    //   2976: invokestatic 369	android/os/SystemClock:elapsedRealtime	()J
    //   2979: aload_1
    //   2980: getfield 399	ct/ab:l	J
    //   2983: lsub
    //   2984: l2i
    //   2985: putfield 509	ct/ac:f	I
    //   2988: aload 26
    //   2990: aload 24
    //   2992: getfield 305	ct/ac:a	I
    //   2995: putfield 195	ct/ad:i	I
    //   2998: aload 26
    //   3000: aload 18
    //   3002: putfield 512	ct/ad:A	Ljava/lang/String;
    //   3005: aload 26
    //   3007: aload 24
    //   3009: getfield 509	ct/ac:f	I
    //   3012: putfield 514	ct/ad:j	I
    //   3015: aload 26
    //   3017: invokestatic 369	android/os/SystemClock:elapsedRealtime	()J
    //   3020: lload 10
    //   3022: lsub
    //   3023: l2i
    //   3024: putfield 516	ct/ad:k	I
    //   3027: aload 26
    //   3029: aload 17
    //   3031: putfield 517	ct/ad:f	Ljava/lang/String;
    //   3034: aload_1
    //   3035: getfield 280	ct/ab:k	[B
    //   3038: ifnull +2038 -> 5076
    //   3041: aload 26
    //   3043: aload_1
    //   3044: getfield 280	ct/ab:k	[B
    //   3047: arraylength
    //   3048: i2l
    //   3049: putfield 518	ct/ad:l	J
    //   3052: aload 26
    //   3054: iload 15
    //   3056: putfield 521	ct/ad:x	Z
    //   3059: iload 15
    //   3061: ifeq +17 -> 3078
    //   3064: aload 26
    //   3066: getfield 195	ct/ad:i	I
    //   3069: ifeq +9 -> 3078
    //   3072: aload 26
    //   3074: iconst_1
    //   3075: putfield 524	ct/ad:u	I
    //   3078: aload 26
    //   3080: aload_1
    //   3081: getfield 526	ct/ab:i	Z
    //   3084: putfield 529	ct/ad:z	Z
    //   3087: aload_1
    //   3088: aload 26
    //   3090: invokevirtual 531	ct/ab:a	(Lct/ad;)V
    //   3093: new 314	java/lang/Thread
    //   3096: astore 20
    //   3098: new 8	ct/ae$a
    //   3101: astore 19
    //   3103: aload 19
    //   3105: aload_0
    //   3106: aload 26
    //   3108: invokespecial 317	ct/ae$a:<init>	(Lct/ae;Lct/ad;)V
    //   3111: aload 20
    //   3113: aload 19
    //   3115: invokespecial 320	java/lang/Thread:<init>	(Ljava/lang/Runnable;)V
    //   3118: aload 20
    //   3120: invokevirtual 323	java/lang/Thread:start	()V
    //   3123: ldc_w 533
    //   3126: aload 26
    //   3128: invokevirtual 534	ct/ad:toString	()Ljava/lang/String;
    //   3131: invokestatic 52	ct/bb:a	(Ljava/lang/String;Ljava/lang/String;)V
    //   3134: aload 24
    //   3136: astore 19
    //   3138: aload 24
    //   3140: getfield 305	ct/ac:a	I
    //   3143: bipush -17
    //   3145: if_icmpeq -3066 -> 79
    //   3148: iload_2
    //   3149: istore 5
    //   3151: iload 4
    //   3153: istore_2
    //   3154: iload_3
    //   3155: istore 4
    //   3157: iload 5
    //   3159: istore_3
    //   3160: goto -1834 -> 1326
    //   3163: aload 17
    //   3165: astore 21
    //   3167: aload 18
    //   3169: astore 23
    //   3171: aload 17
    //   3173: astore 20
    //   3175: aload 18
    //   3177: astore 22
    //   3179: aload 25
    //   3181: invokeinterface 608 1 0
    //   3186: invokeinterface 614 1 0
    //   3191: astore 19
    //   3193: iconst_1
    //   3194: istore 16
    //   3196: aload_1
    //   3197: getfield 617	ct/ab:h	Z
    //   3200: ifeq +1253 -> 4453
    //   3203: iconst_0
    //   3204: istore_3
    //   3205: aload_1
    //   3206: getfield 620	ct/ab:m	I
    //   3209: istore 6
    //   3211: iload 6
    //   3213: newarray <illegal type>
    //   3215: astore 20
    //   3217: invokestatic 369	android/os/SystemClock:elapsedRealtime	()J
    //   3220: lstore 12
    //   3222: iload_3
    //   3223: iload 6
    //   3225: if_icmpge +394 -> 3619
    //   3228: aload 19
    //   3230: aload 20
    //   3232: iload_3
    //   3233: iload 6
    //   3235: iload_3
    //   3236: isub
    //   3237: invokevirtual 626	java/io/InputStream:read	([BII)I
    //   3240: istore 9
    //   3242: iload 9
    //   3244: iconst_m1
    //   3245: if_icmpeq +374 -> 3619
    //   3248: iload_3
    //   3249: iload 9
    //   3251: iadd
    //   3252: istore_3
    //   3253: goto -31 -> 3222
    //   3256: astore 20
    //   3258: aload 20
    //   3260: invokevirtual 627	java/lang/OutOfMemoryError:printStackTrace	()V
    //   3263: aload 19
    //   3265: invokevirtual 630	java/io/InputStream:close	()V
    //   3268: aload 24
    //   3270: bipush -8
    //   3272: putfield 305	ct/ac:a	I
    //   3275: new 27	java/lang/StringBuilder
    //   3278: astore 19
    //   3280: aload 19
    //   3282: ldc_w 632
    //   3285: invokespecial 32	java/lang/StringBuilder:<init>	(Ljava/lang/String;)V
    //   3288: aload 26
    //   3290: aload 19
    //   3292: iload 6
    //   3294: invokevirtual 38	java/lang/StringBuilder:append	(I)Ljava/lang/StringBuilder;
    //   3297: invokevirtual 47	java/lang/StringBuilder:toString	()Ljava/lang/String;
    //   3300: putfield 312	ct/ad:p	Ljava/lang/String;
    //   3303: aload 26
    //   3305: iload 6
    //   3307: i2l
    //   3308: putfield 634	ct/ad:m	J
    //   3311: aload 26
    //   3313: new 27	java/lang/StringBuilder
    //   3316: dup
    //   3317: invokespecial 414	java/lang/StringBuilder:<init>	()V
    //   3320: aload_1
    //   3321: getfield 498	ct/ab:s	Ljava/lang/String;
    //   3324: invokevirtual 43	java/lang/StringBuilder:append	(Ljava/lang/String;)Ljava/lang/StringBuilder;
    //   3327: ldc_w 500
    //   3330: invokevirtual 43	java/lang/StringBuilder:append	(Ljava/lang/String;)Ljava/lang/StringBuilder;
    //   3333: iload 4
    //   3335: invokevirtual 38	java/lang/StringBuilder:append	(I)Ljava/lang/StringBuilder;
    //   3338: invokevirtual 47	java/lang/StringBuilder:toString	()Ljava/lang/String;
    //   3341: putfield 503	ct/ad:n	Ljava/lang/String;
    //   3344: aload 26
    //   3346: iload 4
    //   3348: putfield 504	ct/ad:q	I
    //   3351: aload 17
    //   3353: invokestatic 146	android/text/TextUtils:isEmpty	(Ljava/lang/CharSequence;)Z
    //   3356: ifne +19 -> 3375
    //   3359: iload 5
    //   3361: iconst_1
    //   3362: iadd
    //   3363: bipush 6
    //   3365: if_icmple +10 -> 3375
    //   3368: aload 24
    //   3370: bipush -5
    //   3372: putfield 305	ct/ac:a	I
    //   3375: invokestatic 507	ct/p:b	()Ljava/lang/String;
    //   3378: invokestatic 146	android/text/TextUtils:isEmpty	(Ljava/lang/CharSequence;)Z
    //   3381: ifne +164 -> 3545
    //   3384: aload 24
    //   3386: getfield 305	ct/ac:a	I
    //   3389: bipush -21
    //   3391: if_icmpeq +154 -> 3545
    //   3394: aload 24
    //   3396: invokestatic 369	android/os/SystemClock:elapsedRealtime	()J
    //   3399: aload_1
    //   3400: getfield 399	ct/ab:l	J
    //   3403: lsub
    //   3404: l2i
    //   3405: putfield 509	ct/ac:f	I
    //   3408: aload 26
    //   3410: aload 24
    //   3412: getfield 305	ct/ac:a	I
    //   3415: putfield 195	ct/ad:i	I
    //   3418: aload 26
    //   3420: aload 18
    //   3422: putfield 512	ct/ad:A	Ljava/lang/String;
    //   3425: aload 26
    //   3427: aload 24
    //   3429: getfield 509	ct/ac:f	I
    //   3432: putfield 514	ct/ad:j	I
    //   3435: aload 26
    //   3437: invokestatic 369	android/os/SystemClock:elapsedRealtime	()J
    //   3440: lload 10
    //   3442: lsub
    //   3443: l2i
    //   3444: putfield 516	ct/ad:k	I
    //   3447: aload 26
    //   3449: aload 17
    //   3451: putfield 517	ct/ad:f	Ljava/lang/String;
    //   3454: aload_1
    //   3455: getfield 280	ct/ab:k	[B
    //   3458: ifnull +144 -> 3602
    //   3461: aload 26
    //   3463: aload_1
    //   3464: getfield 280	ct/ab:k	[B
    //   3467: arraylength
    //   3468: i2l
    //   3469: putfield 518	ct/ad:l	J
    //   3472: aload 26
    //   3474: iconst_1
    //   3475: putfield 521	ct/ad:x	Z
    //   3478: aload 26
    //   3480: getfield 195	ct/ad:i	I
    //   3483: ifeq +9 -> 3492
    //   3486: aload 26
    //   3488: iconst_1
    //   3489: putfield 524	ct/ad:u	I
    //   3492: aload 26
    //   3494: aload_1
    //   3495: getfield 526	ct/ab:i	Z
    //   3498: putfield 529	ct/ad:z	Z
    //   3501: aload_1
    //   3502: aload 26
    //   3504: invokevirtual 531	ct/ab:a	(Lct/ad;)V
    //   3507: new 314	java/lang/Thread
    //   3510: astore 17
    //   3512: new 8	ct/ae$a
    //   3515: astore_1
    //   3516: aload_1
    //   3517: aload_0
    //   3518: aload 26
    //   3520: invokespecial 317	ct/ae$a:<init>	(Lct/ae;Lct/ad;)V
    //   3523: aload 17
    //   3525: aload_1
    //   3526: invokespecial 320	java/lang/Thread:<init>	(Ljava/lang/Runnable;)V
    //   3529: aload 17
    //   3531: invokevirtual 323	java/lang/Thread:start	()V
    //   3534: ldc_w 533
    //   3537: aload 26
    //   3539: invokevirtual 534	ct/ad:toString	()Ljava/lang/String;
    //   3542: invokestatic 52	ct/bb:a	(Ljava/lang/String;Ljava/lang/String;)V
    //   3545: aload 24
    //   3547: astore 19
    //   3549: aload 24
    //   3551: getfield 305	ct/ac:a	I
    //   3554: bipush -17
    //   3556: if_icmpne -3477 -> 79
    //   3559: aload 24
    //   3561: astore 19
    //   3563: goto -3484 -> 79
    //   3566: astore 19
    //   3568: aload 19
    //   3570: invokevirtual 635	java/lang/Exception:printStackTrace	()V
    //   3573: goto -305 -> 3268
    //   3576: astore 19
    //   3578: iload 15
    //   3580: istore 14
    //   3582: aload 17
    //   3584: astore 20
    //   3586: iconst_1
    //   3587: istore 15
    //   3589: iload_2
    //   3590: istore_3
    //   3591: aload 18
    //   3593: astore 17
    //   3595: aload 20
    //   3597: astore 18
    //   3599: goto -2624 -> 975
    //   3602: aload 26
    //   3604: lconst_0
    //   3605: putfield 518	ct/ad:l	J
    //   3608: goto -136 -> 3472
    //   3611: astore_1
    //   3612: aload_1
    //   3613: invokevirtual 627	java/lang/OutOfMemoryError:printStackTrace	()V
    //   3616: goto -71 -> 3545
    //   3619: aload 24
    //   3621: invokestatic 369	android/os/SystemClock:elapsedRealtime	()J
    //   3624: lload 12
    //   3626: lsub
    //   3627: l2i
    //   3628: putfield 637	ct/ac:d	I
    //   3631: aload 26
    //   3633: aload 24
    //   3635: getfield 637	ct/ac:d	I
    //   3638: putfield 639	ct/ad:h	I
    //   3641: aload 25
    //   3643: ifnull +419 -> 4062
    //   3646: aload 25
    //   3648: ldc_w 641
    //   3651: invokeinterface 597 2 0
    //   3656: ifnull +406 -> 4062
    //   3659: aload 25
    //   3661: ldc_w 641
    //   3664: invokeinterface 597 2 0
    //   3669: invokeinterface 602 1 0
    //   3674: astore 21
    //   3676: aload 21
    //   3678: invokestatic 146	android/text/TextUtils:isEmpty	(Ljava/lang/CharSequence;)Z
    //   3681: ifne +16 -> 3697
    //   3684: aload 26
    //   3686: aload 21
    //   3688: invokestatic 646	java/lang/Long:valueOf	(Ljava/lang/String;)Ljava/lang/Long;
    //   3691: invokevirtual 649	java/lang/Long:longValue	()J
    //   3694: putfield 634	ct/ad:m	J
    //   3697: new 27	java/lang/StringBuilder
    //   3700: astore 21
    //   3702: aload 21
    //   3704: ldc_w 651
    //   3707: invokespecial 32	java/lang/StringBuilder:<init>	(Ljava/lang/String;)V
    //   3710: ldc 34
    //   3712: aload 21
    //   3714: aload 24
    //   3716: getfield 637	ct/ac:d	I
    //   3719: invokevirtual 38	java/lang/StringBuilder:append	(I)Ljava/lang/StringBuilder;
    //   3722: ldc_w 653
    //   3725: invokevirtual 43	java/lang/StringBuilder:append	(Ljava/lang/String;)Ljava/lang/StringBuilder;
    //   3728: iload_3
    //   3729: invokevirtual 38	java/lang/StringBuilder:append	(I)Ljava/lang/StringBuilder;
    //   3732: ldc_w 655
    //   3735: invokevirtual 43	java/lang/StringBuilder:append	(Ljava/lang/String;)Ljava/lang/StringBuilder;
    //   3738: iload 6
    //   3740: invokevirtual 38	java/lang/StringBuilder:append	(I)Ljava/lang/StringBuilder;
    //   3743: invokevirtual 47	java/lang/StringBuilder:toString	()Ljava/lang/String;
    //   3746: invokestatic 52	ct/bb:a	(Ljava/lang/String;Ljava/lang/String;)V
    //   3749: iload_3
    //   3750: iload 6
    //   3752: if_icmplt +332 -> 4084
    //   3755: new 27	java/lang/StringBuilder
    //   3758: astore 20
    //   3760: aload 20
    //   3762: ldc_w 657
    //   3765: invokespecial 32	java/lang/StringBuilder:<init>	(Ljava/lang/String;)V
    //   3768: aload 26
    //   3770: aload 20
    //   3772: iload_3
    //   3773: invokevirtual 38	java/lang/StringBuilder:append	(I)Ljava/lang/StringBuilder;
    //   3776: invokevirtual 47	java/lang/StringBuilder:toString	()Ljava/lang/String;
    //   3779: putfield 312	ct/ad:p	Ljava/lang/String;
    //   3782: aload 24
    //   3784: iconst_m1
    //   3785: putfield 305	ct/ac:a	I
    //   3788: aload 19
    //   3790: invokevirtual 630	java/io/InputStream:close	()V
    //   3793: aload 24
    //   3795: getfield 305	ct/ac:a	I
    //   3798: ifne +1700 -> 5498
    //   3801: aload 26
    //   3803: iconst_0
    //   3804: putfield 524	ct/ad:u	I
    //   3807: aload 26
    //   3809: new 27	java/lang/StringBuilder
    //   3812: dup
    //   3813: invokespecial 414	java/lang/StringBuilder:<init>	()V
    //   3816: aload_1
    //   3817: getfield 498	ct/ab:s	Ljava/lang/String;
    //   3820: invokevirtual 43	java/lang/StringBuilder:append	(Ljava/lang/String;)Ljava/lang/StringBuilder;
    //   3823: ldc_w 500
    //   3826: invokevirtual 43	java/lang/StringBuilder:append	(Ljava/lang/String;)Ljava/lang/StringBuilder;
    //   3829: iload 4
    //   3831: invokevirtual 38	java/lang/StringBuilder:append	(I)Ljava/lang/StringBuilder;
    //   3834: invokevirtual 47	java/lang/StringBuilder:toString	()Ljava/lang/String;
    //   3837: putfield 503	ct/ad:n	Ljava/lang/String;
    //   3840: aload 26
    //   3842: iload 4
    //   3844: putfield 504	ct/ad:q	I
    //   3847: aload 17
    //   3849: invokestatic 146	android/text/TextUtils:isEmpty	(Ljava/lang/CharSequence;)Z
    //   3852: ifne +19 -> 3871
    //   3855: iload 5
    //   3857: iconst_1
    //   3858: iadd
    //   3859: bipush 6
    //   3861: if_icmple +10 -> 3871
    //   3864: aload 24
    //   3866: bipush -5
    //   3868: putfield 305	ct/ac:a	I
    //   3871: invokestatic 507	ct/p:b	()Ljava/lang/String;
    //   3874: invokestatic 146	android/text/TextUtils:isEmpty	(Ljava/lang/CharSequence;)Z
    //   3877: ifne +164 -> 4041
    //   3880: aload 24
    //   3882: getfield 305	ct/ac:a	I
    //   3885: bipush -21
    //   3887: if_icmpeq +154 -> 4041
    //   3890: aload 24
    //   3892: invokestatic 369	android/os/SystemClock:elapsedRealtime	()J
    //   3895: aload_1
    //   3896: getfield 399	ct/ab:l	J
    //   3899: lsub
    //   3900: l2i
    //   3901: putfield 509	ct/ac:f	I
    //   3904: aload 26
    //   3906: aload 24
    //   3908: getfield 305	ct/ac:a	I
    //   3911: putfield 195	ct/ad:i	I
    //   3914: aload 26
    //   3916: aload 18
    //   3918: putfield 512	ct/ad:A	Ljava/lang/String;
    //   3921: aload 26
    //   3923: aload 24
    //   3925: getfield 509	ct/ac:f	I
    //   3928: putfield 514	ct/ad:j	I
    //   3931: aload 26
    //   3933: invokestatic 369	android/os/SystemClock:elapsedRealtime	()J
    //   3936: lload 10
    //   3938: lsub
    //   3939: l2i
    //   3940: putfield 516	ct/ad:k	I
    //   3943: aload 26
    //   3945: aload 17
    //   3947: putfield 517	ct/ad:f	Ljava/lang/String;
    //   3950: aload_1
    //   3951: getfield 280	ct/ab:k	[B
    //   3954: ifnull +516 -> 4470
    //   3957: aload 26
    //   3959: aload_1
    //   3960: getfield 280	ct/ab:k	[B
    //   3963: arraylength
    //   3964: i2l
    //   3965: putfield 518	ct/ad:l	J
    //   3968: aload 26
    //   3970: iconst_1
    //   3971: putfield 521	ct/ad:x	Z
    //   3974: aload 26
    //   3976: getfield 195	ct/ad:i	I
    //   3979: ifeq +9 -> 3988
    //   3982: aload 26
    //   3984: iconst_1
    //   3985: putfield 524	ct/ad:u	I
    //   3988: aload 26
    //   3990: aload_1
    //   3991: getfield 526	ct/ab:i	Z
    //   3994: putfield 529	ct/ad:z	Z
    //   3997: aload_1
    //   3998: aload 26
    //   4000: invokevirtual 531	ct/ab:a	(Lct/ad;)V
    //   4003: new 314	java/lang/Thread
    //   4006: astore_1
    //   4007: new 8	ct/ae$a
    //   4010: astore 17
    //   4012: aload 17
    //   4014: aload_0
    //   4015: aload 26
    //   4017: invokespecial 317	ct/ae$a:<init>	(Lct/ae;Lct/ad;)V
    //   4020: aload_1
    //   4021: aload 17
    //   4023: invokespecial 320	java/lang/Thread:<init>	(Ljava/lang/Runnable;)V
    //   4026: aload_1
    //   4027: invokevirtual 323	java/lang/Thread:start	()V
    //   4030: ldc_w 533
    //   4033: aload 26
    //   4035: invokevirtual 534	ct/ad:toString	()Ljava/lang/String;
    //   4038: invokestatic 52	ct/bb:a	(Ljava/lang/String;Ljava/lang/String;)V
    //   4041: aload 24
    //   4043: astore 19
    //   4045: aload 24
    //   4047: getfield 305	ct/ac:a	I
    //   4050: bipush -17
    //   4052: if_icmpne -3973 -> 79
    //   4055: aload 24
    //   4057: astore 19
    //   4059: goto -3980 -> 79
    //   4062: iload_3
    //   4063: i2l
    //   4064: lstore 12
    //   4066: aload 26
    //   4068: lload 12
    //   4070: putfield 634	ct/ad:m	J
    //   4073: goto -376 -> 3697
    //   4076: astore 20
    //   4078: iconst_1
    //   4079: istore 14
    //   4081: goto -2234 -> 1847
    //   4084: aload 24
    //   4086: iload_3
    //   4087: newarray <illegal type>
    //   4089: putfield 659	ct/ac:b	[B
    //   4092: aload 20
    //   4094: iconst_0
    //   4095: aload 24
    //   4097: getfield 659	ct/ac:b	[B
    //   4100: iconst_0
    //   4101: iload_3
    //   4102: invokestatic 665	java/lang/System:arraycopy	(Ljava/lang/Object;ILjava/lang/Object;II)V
    //   4105: aload 24
    //   4107: iconst_0
    //   4108: putfield 305	ct/ac:a	I
    //   4111: goto -323 -> 3788
    //   4114: astore 20
    //   4116: aload 20
    //   4118: invokevirtual 627	java/lang/OutOfMemoryError:printStackTrace	()V
    //   4121: aload 19
    //   4123: invokevirtual 630	java/io/InputStream:close	()V
    //   4126: aload 24
    //   4128: bipush -8
    //   4130: putfield 305	ct/ac:a	I
    //   4133: new 27	java/lang/StringBuilder
    //   4136: astore 19
    //   4138: aload 19
    //   4140: ldc_w 632
    //   4143: invokespecial 32	java/lang/StringBuilder:<init>	(Ljava/lang/String;)V
    //   4146: aload 26
    //   4148: aload 19
    //   4150: iload 6
    //   4152: invokevirtual 38	java/lang/StringBuilder:append	(I)Ljava/lang/StringBuilder;
    //   4155: invokevirtual 47	java/lang/StringBuilder:toString	()Ljava/lang/String;
    //   4158: putfield 312	ct/ad:p	Ljava/lang/String;
    //   4161: aload 26
    //   4163: new 27	java/lang/StringBuilder
    //   4166: dup
    //   4167: invokespecial 414	java/lang/StringBuilder:<init>	()V
    //   4170: aload_1
    //   4171: getfield 498	ct/ab:s	Ljava/lang/String;
    //   4174: invokevirtual 43	java/lang/StringBuilder:append	(Ljava/lang/String;)Ljava/lang/StringBuilder;
    //   4177: ldc_w 500
    //   4180: invokevirtual 43	java/lang/StringBuilder:append	(Ljava/lang/String;)Ljava/lang/StringBuilder;
    //   4183: iload 4
    //   4185: invokevirtual 38	java/lang/StringBuilder:append	(I)Ljava/lang/StringBuilder;
    //   4188: invokevirtual 47	java/lang/StringBuilder:toString	()Ljava/lang/String;
    //   4191: putfield 503	ct/ad:n	Ljava/lang/String;
    //   4194: aload 26
    //   4196: iload 4
    //   4198: putfield 504	ct/ad:q	I
    //   4201: aload 17
    //   4203: invokestatic 146	android/text/TextUtils:isEmpty	(Ljava/lang/CharSequence;)Z
    //   4206: ifne +19 -> 4225
    //   4209: iload 5
    //   4211: iconst_1
    //   4212: iadd
    //   4213: bipush 6
    //   4215: if_icmple +10 -> 4225
    //   4218: aload 24
    //   4220: bipush -5
    //   4222: putfield 305	ct/ac:a	I
    //   4225: invokestatic 507	ct/p:b	()Ljava/lang/String;
    //   4228: invokestatic 146	android/text/TextUtils:isEmpty	(Ljava/lang/CharSequence;)Z
    //   4231: ifne +164 -> 4395
    //   4234: aload 24
    //   4236: getfield 305	ct/ac:a	I
    //   4239: bipush -21
    //   4241: if_icmpeq +154 -> 4395
    //   4244: aload 24
    //   4246: invokestatic 369	android/os/SystemClock:elapsedRealtime	()J
    //   4249: aload_1
    //   4250: getfield 399	ct/ab:l	J
    //   4253: lsub
    //   4254: l2i
    //   4255: putfield 509	ct/ac:f	I
    //   4258: aload 26
    //   4260: aload 24
    //   4262: getfield 305	ct/ac:a	I
    //   4265: putfield 195	ct/ad:i	I
    //   4268: aload 26
    //   4270: aload 18
    //   4272: putfield 512	ct/ad:A	Ljava/lang/String;
    //   4275: aload 26
    //   4277: aload 24
    //   4279: getfield 509	ct/ac:f	I
    //   4282: putfield 514	ct/ad:j	I
    //   4285: aload 26
    //   4287: invokestatic 369	android/os/SystemClock:elapsedRealtime	()J
    //   4290: lload 10
    //   4292: lsub
    //   4293: l2i
    //   4294: putfield 516	ct/ad:k	I
    //   4297: aload 26
    //   4299: aload 17
    //   4301: putfield 517	ct/ad:f	Ljava/lang/String;
    //   4304: aload_1
    //   4305: getfield 280	ct/ab:k	[B
    //   4308: ifnull +118 -> 4426
    //   4311: aload 26
    //   4313: aload_1
    //   4314: getfield 280	ct/ab:k	[B
    //   4317: arraylength
    //   4318: i2l
    //   4319: putfield 518	ct/ad:l	J
    //   4322: aload 26
    //   4324: iconst_1
    //   4325: putfield 521	ct/ad:x	Z
    //   4328: aload 26
    //   4330: getfield 195	ct/ad:i	I
    //   4333: ifeq +9 -> 4342
    //   4336: aload 26
    //   4338: iconst_1
    //   4339: putfield 524	ct/ad:u	I
    //   4342: aload 26
    //   4344: aload_1
    //   4345: getfield 526	ct/ab:i	Z
    //   4348: putfield 529	ct/ad:z	Z
    //   4351: aload_1
    //   4352: aload 26
    //   4354: invokevirtual 531	ct/ab:a	(Lct/ad;)V
    //   4357: new 314	java/lang/Thread
    //   4360: astore_1
    //   4361: new 8	ct/ae$a
    //   4364: astore 17
    //   4366: aload 17
    //   4368: aload_0
    //   4369: aload 26
    //   4371: invokespecial 317	ct/ae$a:<init>	(Lct/ae;Lct/ad;)V
    //   4374: aload_1
    //   4375: aload 17
    //   4377: invokespecial 320	java/lang/Thread:<init>	(Ljava/lang/Runnable;)V
    //   4380: aload_1
    //   4381: invokevirtual 323	java/lang/Thread:start	()V
    //   4384: ldc_w 533
    //   4387: aload 26
    //   4389: invokevirtual 534	ct/ad:toString	()Ljava/lang/String;
    //   4392: invokestatic 52	ct/bb:a	(Ljava/lang/String;Ljava/lang/String;)V
    //   4395: aload 24
    //   4397: astore 19
    //   4399: aload 24
    //   4401: getfield 305	ct/ac:a	I
    //   4404: bipush -17
    //   4406: if_icmpne -4327 -> 79
    //   4409: aload 24
    //   4411: astore 19
    //   4413: goto -4334 -> 79
    //   4416: astore 19
    //   4418: aload 19
    //   4420: invokevirtual 635	java/lang/Exception:printStackTrace	()V
    //   4423: goto -297 -> 4126
    //   4426: aload 26
    //   4428: lconst_0
    //   4429: putfield 518	ct/ad:l	J
    //   4432: goto -110 -> 4322
    //   4435: astore_1
    //   4436: aload_1
    //   4437: invokevirtual 627	java/lang/OutOfMemoryError:printStackTrace	()V
    //   4440: goto -45 -> 4395
    //   4443: astore 19
    //   4445: aload 19
    //   4447: invokevirtual 635	java/lang/Exception:printStackTrace	()V
    //   4450: goto -657 -> 3793
    //   4453: ldc 34
    //   4455: ldc_w 667
    //   4458: invokestatic 178	ct/bb:b	(Ljava/lang/String;Ljava/lang/String;)V
    //   4461: aload 24
    //   4463: iconst_0
    //   4464: putfield 305	ct/ac:a	I
    //   4467: goto -674 -> 3793
    //   4470: aload 26
    //   4472: lconst_0
    //   4473: putfield 518	ct/ad:l	J
    //   4476: goto -508 -> 3968
    //   4479: astore_1
    //   4480: aload_1
    //   4481: invokevirtual 627	java/lang/OutOfMemoryError:printStackTrace	()V
    //   4484: goto -443 -> 4041
    //   4487: aload 17
    //   4489: astore 21
    //   4491: aload 18
    //   4493: astore 23
    //   4495: aload 17
    //   4497: astore 20
    //   4499: aload 18
    //   4501: astore 22
    //   4503: aload 24
    //   4505: bipush -21
    //   4507: putfield 305	ct/ac:a	I
    //   4510: aload 17
    //   4512: astore 21
    //   4514: aload 18
    //   4516: astore 23
    //   4518: aload 17
    //   4520: astore 20
    //   4522: aload 18
    //   4524: astore 22
    //   4526: aload 25
    //   4528: ldc_w 669
    //   4531: invokeinterface 597 2 0
    //   4536: astore 19
    //   4538: aload 19
    //   4540: ifnull +146 -> 4686
    //   4543: aload 17
    //   4545: astore 21
    //   4547: aload 18
    //   4549: astore 23
    //   4551: aload 17
    //   4553: astore 20
    //   4555: aload 18
    //   4557: astore 22
    //   4559: aload 19
    //   4561: invokeinterface 602 1 0
    //   4566: astore 17
    //   4568: aload 17
    //   4570: astore 21
    //   4572: aload 18
    //   4574: astore 23
    //   4576: aload 17
    //   4578: astore 20
    //   4580: aload 18
    //   4582: astore 22
    //   4584: new 27	java/lang/StringBuilder
    //   4587: astore 19
    //   4589: aload 17
    //   4591: astore 21
    //   4593: aload 18
    //   4595: astore 23
    //   4597: aload 17
    //   4599: astore 20
    //   4601: aload 18
    //   4603: astore 22
    //   4605: aload 19
    //   4607: ldc_w 671
    //   4610: invokespecial 32	java/lang/StringBuilder:<init>	(Ljava/lang/String;)V
    //   4613: aload 17
    //   4615: astore 21
    //   4617: aload 18
    //   4619: astore 23
    //   4621: aload 17
    //   4623: astore 20
    //   4625: aload 18
    //   4627: astore 22
    //   4629: ldc 34
    //   4631: aload 19
    //   4633: aload 17
    //   4635: invokevirtual 43	java/lang/StringBuilder:append	(Ljava/lang/String;)Ljava/lang/StringBuilder;
    //   4638: invokevirtual 47	java/lang/StringBuilder:toString	()Ljava/lang/String;
    //   4641: invokestatic 178	ct/bb:b	(Ljava/lang/String;Ljava/lang/String;)V
    //   4644: aload 26
    //   4646: iconst_1
    //   4647: putfield 673	ct/ad:e	Z
    //   4650: aload 17
    //   4652: invokestatic 146	android/text/TextUtils:isEmpty	(Ljava/lang/CharSequence;)Z
    //   4655: istore 15
    //   4657: iload 15
    //   4659: ifeq +54 -> 4713
    //   4662: aload 24
    //   4664: bipush -6
    //   4666: putfield 305	ct/ac:a	I
    //   4669: aconst_null
    //   4670: astore 17
    //   4672: iconst_1
    //   4673: istore 16
    //   4675: iload 14
    //   4677: istore 15
    //   4679: iload 16
    //   4681: istore 14
    //   4683: goto -1781 -> 2902
    //   4686: aload 17
    //   4688: astore 21
    //   4690: aload 18
    //   4692: astore 23
    //   4694: aload 17
    //   4696: astore 20
    //   4698: aload 18
    //   4700: astore 22
    //   4702: ldc 34
    //   4704: ldc_w 675
    //   4707: invokestatic 160	ct/bb:c	(Ljava/lang/String;Ljava/lang/String;)V
    //   4710: goto -66 -> 4644
    //   4713: aload_1
    //   4714: getfield 677	ct/ab:r	Z
    //   4717: ifne +767 -> 5484
    //   4720: ldc 34
    //   4722: ldc_w 679
    //   4725: invokestatic 178	ct/bb:b	(Ljava/lang/String;Ljava/lang/String;)V
    //   4728: aload 24
    //   4730: bipush -7
    //   4732: putfield 305	ct/ac:a	I
    //   4735: aload 26
    //   4737: new 27	java/lang/StringBuilder
    //   4740: dup
    //   4741: invokespecial 414	java/lang/StringBuilder:<init>	()V
    //   4744: aload_1
    //   4745: getfield 498	ct/ab:s	Ljava/lang/String;
    //   4748: invokevirtual 43	java/lang/StringBuilder:append	(Ljava/lang/String;)Ljava/lang/StringBuilder;
    //   4751: ldc_w 500
    //   4754: invokevirtual 43	java/lang/StringBuilder:append	(Ljava/lang/String;)Ljava/lang/StringBuilder;
    //   4757: iload 4
    //   4759: invokevirtual 38	java/lang/StringBuilder:append	(I)Ljava/lang/StringBuilder;
    //   4762: invokevirtual 47	java/lang/StringBuilder:toString	()Ljava/lang/String;
    //   4765: putfield 503	ct/ad:n	Ljava/lang/String;
    //   4768: aload 26
    //   4770: iload 4
    //   4772: putfield 504	ct/ad:q	I
    //   4775: aload 17
    //   4777: invokestatic 146	android/text/TextUtils:isEmpty	(Ljava/lang/CharSequence;)Z
    //   4780: ifne +19 -> 4799
    //   4783: iload 5
    //   4785: iconst_1
    //   4786: iadd
    //   4787: bipush 6
    //   4789: if_icmple +10 -> 4799
    //   4792: aload 24
    //   4794: bipush -5
    //   4796: putfield 305	ct/ac:a	I
    //   4799: invokestatic 507	ct/p:b	()Ljava/lang/String;
    //   4802: invokestatic 146	android/text/TextUtils:isEmpty	(Ljava/lang/CharSequence;)Z
    //   4805: ifne +170 -> 4975
    //   4808: aload 24
    //   4810: getfield 305	ct/ac:a	I
    //   4813: bipush -21
    //   4815: if_icmpeq +160 -> 4975
    //   4818: aload 24
    //   4820: invokestatic 369	android/os/SystemClock:elapsedRealtime	()J
    //   4823: aload_1
    //   4824: getfield 399	ct/ab:l	J
    //   4827: lsub
    //   4828: l2i
    //   4829: putfield 509	ct/ac:f	I
    //   4832: aload 26
    //   4834: aload 24
    //   4836: getfield 305	ct/ac:a	I
    //   4839: putfield 195	ct/ad:i	I
    //   4842: aload 26
    //   4844: aload 18
    //   4846: putfield 512	ct/ad:A	Ljava/lang/String;
    //   4849: aload 26
    //   4851: aload 24
    //   4853: getfield 509	ct/ac:f	I
    //   4856: putfield 514	ct/ad:j	I
    //   4859: aload 26
    //   4861: invokestatic 369	android/os/SystemClock:elapsedRealtime	()J
    //   4864: lload 10
    //   4866: lsub
    //   4867: l2i
    //   4868: putfield 516	ct/ad:k	I
    //   4871: aload 26
    //   4873: aload 17
    //   4875: putfield 517	ct/ad:f	Ljava/lang/String;
    //   4878: aload_1
    //   4879: getfield 280	ct/ab:k	[B
    //   4882: ifnull +114 -> 4996
    //   4885: aload 26
    //   4887: aload_1
    //   4888: getfield 280	ct/ab:k	[B
    //   4891: arraylength
    //   4892: i2l
    //   4893: putfield 518	ct/ad:l	J
    //   4896: aload 26
    //   4898: iload 14
    //   4900: putfield 521	ct/ad:x	Z
    //   4903: iload 14
    //   4905: ifeq +17 -> 4922
    //   4908: aload 26
    //   4910: getfield 195	ct/ad:i	I
    //   4913: ifeq +9 -> 4922
    //   4916: aload 26
    //   4918: iconst_1
    //   4919: putfield 524	ct/ad:u	I
    //   4922: aload 26
    //   4924: aload_1
    //   4925: getfield 526	ct/ab:i	Z
    //   4928: putfield 529	ct/ad:z	Z
    //   4931: aload_1
    //   4932: aload 26
    //   4934: invokevirtual 531	ct/ab:a	(Lct/ad;)V
    //   4937: new 314	java/lang/Thread
    //   4940: astore_1
    //   4941: new 8	ct/ae$a
    //   4944: astore 17
    //   4946: aload 17
    //   4948: aload_0
    //   4949: aload 26
    //   4951: invokespecial 317	ct/ae$a:<init>	(Lct/ae;Lct/ad;)V
    //   4954: aload_1
    //   4955: aload 17
    //   4957: invokespecial 320	java/lang/Thread:<init>	(Ljava/lang/Runnable;)V
    //   4960: aload_1
    //   4961: invokevirtual 323	java/lang/Thread:start	()V
    //   4964: ldc_w 533
    //   4967: aload 26
    //   4969: invokevirtual 534	ct/ad:toString	()Ljava/lang/String;
    //   4972: invokestatic 52	ct/bb:a	(Ljava/lang/String;Ljava/lang/String;)V
    //   4975: aload 24
    //   4977: astore 19
    //   4979: aload 24
    //   4981: getfield 305	ct/ac:a	I
    //   4984: bipush -17
    //   4986: if_icmpne -4907 -> 79
    //   4989: aload 24
    //   4991: astore 19
    //   4993: goto -4914 -> 79
    //   4996: aload 26
    //   4998: lconst_0
    //   4999: putfield 518	ct/ad:l	J
    //   5002: goto -106 -> 4896
    //   5005: astore_1
    //   5006: aload_1
    //   5007: invokevirtual 627	java/lang/OutOfMemoryError:printStackTrace	()V
    //   5010: goto -35 -> 4975
    //   5013: aload 17
    //   5015: astore 21
    //   5017: aload 18
    //   5019: astore 23
    //   5021: aload 17
    //   5023: astore 20
    //   5025: aload 18
    //   5027: astore 22
    //   5029: aload 24
    //   5031: iload_3
    //   5032: putfield 305	ct/ac:a	I
    //   5035: iload 14
    //   5037: istore 16
    //   5039: iload 15
    //   5041: istore 14
    //   5043: iload 16
    //   5045: istore 15
    //   5047: goto -2145 -> 2902
    //   5050: iload 5
    //   5052: iconst_1
    //   5053: iadd
    //   5054: istore_3
    //   5055: iload_3
    //   5056: bipush 6
    //   5058: if_icmple +423 -> 5481
    //   5061: iinc 4 1
    //   5064: iconst_0
    //   5065: istore_3
    //   5066: aload 24
    //   5068: bipush -5
    //   5070: putfield 305	ct/ac:a	I
    //   5073: goto -2118 -> 2955
    //   5076: aload 26
    //   5078: lconst_0
    //   5079: putfield 518	ct/ad:l	J
    //   5082: goto -2030 -> 3052
    //   5085: astore 19
    //   5087: aload 19
    //   5089: invokevirtual 627	java/lang/OutOfMemoryError:printStackTrace	()V
    //   5092: goto -1958 -> 3134
    //   5095: aload 19
    //   5097: instanceof 681
    //   5100: ifeq +9 -> 5109
    //   5103: bipush -11
    //   5105: istore_2
    //   5106: goto -4072 -> 1034
    //   5109: aload 19
    //   5111: instanceof 683
    //   5114: ifeq +9 -> 5123
    //   5117: bipush -12
    //   5119: istore_2
    //   5120: goto -4086 -> 1034
    //   5123: aload 19
    //   5125: instanceof 685
    //   5128: ifeq +9 -> 5137
    //   5131: bipush -13
    //   5133: istore_2
    //   5134: goto -4100 -> 1034
    //   5137: aload 19
    //   5139: instanceof 687
    //   5142: ifeq +9 -> 5151
    //   5145: bipush -14
    //   5147: istore_2
    //   5148: goto -4114 -> 1034
    //   5151: aload 19
    //   5153: instanceof 689
    //   5156: ifeq +9 -> 5165
    //   5159: bipush -15
    //   5161: istore_2
    //   5162: goto -4128 -> 1034
    //   5165: aload 19
    //   5167: instanceof 691
    //   5170: ifeq +9 -> 5179
    //   5173: bipush -16
    //   5175: istore_2
    //   5176: goto -4142 -> 1034
    //   5179: aload 19
    //   5181: instanceof 693
    //   5184: ifeq +9 -> 5193
    //   5187: bipush -9
    //   5189: istore_2
    //   5190: goto -4156 -> 1034
    //   5193: aload 19
    //   5195: instanceof 695
    //   5198: ifeq +9 -> 5207
    //   5201: bipush -22
    //   5203: istore_2
    //   5204: goto -4170 -> 1034
    //   5207: aload 19
    //   5209: instanceof 697
    //   5212: istore 16
    //   5214: iload 16
    //   5216: ifeq +9 -> 5225
    //   5219: bipush -23
    //   5221: istore_2
    //   5222: goto -4188 -> 1034
    //   5225: bipush -3
    //   5227: istore_2
    //   5228: goto -4194 -> 1034
    //   5231: bipush -17
    //   5233: istore_2
    //   5234: goto -4200 -> 1034
    //   5237: bipush -4
    //   5239: istore_2
    //   5240: goto -4206 -> 1034
    //   5243: iload 5
    //   5245: iconst_1
    //   5246: iadd
    //   5247: istore 6
    //   5249: iload 6
    //   5251: istore 5
    //   5253: iload 4
    //   5255: istore_2
    //   5256: iload 6
    //   5258: bipush 6
    //   5260: if_icmple -4143 -> 1117
    //   5263: iload 4
    //   5265: iconst_1
    //   5266: iadd
    //   5267: istore_2
    //   5268: iconst_0
    //   5269: istore 5
    //   5271: aload 24
    //   5273: bipush -5
    //   5275: putfield 305	ct/ac:a	I
    //   5278: goto -4161 -> 1117
    //   5281: aload 26
    //   5283: lconst_0
    //   5284: putfield 518	ct/ad:l	J
    //   5287: goto -4073 -> 1214
    //   5290: astore 19
    //   5292: aload 19
    //   5294: invokevirtual 627	java/lang/OutOfMemoryError:printStackTrace	()V
    //   5297: goto -4001 -> 1296
    //   5300: aload 26
    //   5302: lconst_0
    //   5303: putfield 518	ct/ad:l	J
    //   5306: goto -3298 -> 2008
    //   5309: astore_1
    //   5310: aload_1
    //   5311: invokevirtual 627	java/lang/OutOfMemoryError:printStackTrace	()V
    //   5314: goto -3227 -> 2087
    //   5317: aload 18
    //   5319: astore 19
    //   5321: goto -5242 -> 79
    //   5324: astore 20
    //   5326: goto -3479 -> 1847
    //   5329: astore 20
    //   5331: aconst_null
    //   5332: astore 17
    //   5334: goto -3487 -> 1847
    //   5337: astore 20
    //   5339: iload 15
    //   5341: istore 14
    //   5343: aload 17
    //   5345: astore 19
    //   5347: aload 18
    //   5349: astore 17
    //   5351: aload 19
    //   5353: astore 18
    //   5355: goto -3508 -> 1847
    //   5358: astore 20
    //   5360: aload 19
    //   5362: astore 18
    //   5364: goto -3517 -> 1847
    //   5367: astore 19
    //   5369: iload 14
    //   5371: istore 15
    //   5373: aload 17
    //   5375: astore 20
    //   5377: iconst_1
    //   5378: istore 14
    //   5380: aload 18
    //   5382: astore 17
    //   5384: iload_2
    //   5385: istore_3
    //   5386: aload 20
    //   5388: astore 18
    //   5390: goto -4415 -> 975
    //   5393: astore 19
    //   5395: iload 14
    //   5397: istore 15
    //   5399: aconst_null
    //   5400: astore 20
    //   5402: iconst_1
    //   5403: istore 14
    //   5405: aload 18
    //   5407: astore 17
    //   5409: iload_2
    //   5410: istore_3
    //   5411: aload 20
    //   5413: astore 18
    //   5415: goto -4440 -> 975
    //   5418: astore 20
    //   5420: iload 14
    //   5422: istore 16
    //   5424: iload 15
    //   5426: istore 14
    //   5428: aload 17
    //   5430: astore 18
    //   5432: aload 19
    //   5434: astore 17
    //   5436: aload 20
    //   5438: astore 19
    //   5440: iload 16
    //   5442: istore 15
    //   5444: goto -4469 -> 975
    //   5447: astore 20
    //   5449: iload 14
    //   5451: istore 16
    //   5453: iload 15
    //   5455: istore 14
    //   5457: aload 17
    //   5459: astore 18
    //   5461: aload 19
    //   5463: astore 17
    //   5465: aload 20
    //   5467: astore 19
    //   5469: iload 16
    //   5471: istore 15
    //   5473: goto -4498 -> 975
    //   5476: iload_3
    //   5477: istore_2
    //   5478: goto -5063 -> 415
    //   5481: goto -2526 -> 2955
    //   5484: iconst_1
    //   5485: istore 16
    //   5487: iload 14
    //   5489: istore 15
    //   5491: iload 16
    //   5493: istore 14
    //   5495: goto -2593 -> 2902
    //   5498: iload 15
    //   5500: istore 14
    //   5502: iload 16
    //   5504: istore 15
    //   5506: goto -2604 -> 2902
    // Local variable table:
    //   start	length	slot	name	signature
    //   0	5509	0	this	ae
    //   0	5509	1	paramab	ab
    //   283	5195	2	i	int
    //   204	5273	3	j	int
    //   185	5082	4	k	int
    //   196	5074	5	m	int
    //   3209	2052	6	n	int
    //   166	123	7	i1	int
    //   175	108	8	i2	int
    //   3240	12	9	i3	int
    //   229	4636	10	l1	long
    //   2491	1578	12	l2	long
    //   264	5237	14	bool1	boolean
    //   188	5317	15	bool2	boolean
    //   959	4544	16	bool3	boolean
    //   7	5457	17	localObject1	Object
    //   29	5431	18	localObject2	Object
    //   77	847	19	localObject3	Object
    //   951	73	19	localException1	Exception
    //   1258	548	19	localObject4	Object
    //   1833	11	19	localObject5	Object
    //   2089	1473	19	localObject6	Object
    //   3566	3	19	localException2	Exception
    //   3576	213	19	localException3	Exception
    //   4043	369	19	localObject7	Object
    //   4416	3	19	localException4	Exception
    //   4443	3	19	localException5	Exception
    //   4536	456	19	localObject8	Object
    //   5085	123	19	localOutOfMemoryError1	OutOfMemoryError
    //   5290	3	19	localOutOfMemoryError2	OutOfMemoryError
    //   5319	42	19	localObject9	Object
    //   5367	1	19	localException6	Exception
    //   5393	40	19	localException7	Exception
    //   5438	30	19	localObject10	Object
    //   201	3030	20	localObject11	Object
    //   3256	3	20	localOutOfMemoryError3	OutOfMemoryError
    //   3584	187	20	localObject12	Object
    //   4076	17	20	localObject13	Object
    //   4114	3	20	localOutOfMemoryError4	OutOfMemoryError
    //   4497	527	20	localObject14	Object
    //   5324	1	20	localObject15	Object
    //   5329	1	20	localObject16	Object
    //   5337	1	20	localObject17	Object
    //   5358	1	20	localObject18	Object
    //   5375	37	20	localObject19	Object
    //   5418	19	20	localException8	Exception
    //   5447	19	20	localException9	Exception
    //   499	4517	21	localObject20	Object
    //   588	4440	22	localObject21	Object
    //   580	4440	23	localObject22	Object
    //   238	5034	24	localac	ac
    //   331	4196	25	localObject23	Object
    //   247	5054	26	localad	ad
    //   109	2323	27	localy	y
    //   116	271	28	localList	java.util.List
    //   123	136	29	locals	s
    //   182	70	30	str1	String
    //   593	1697	31	localObject24	Object
    //   855	1414	32	localObject25	Object
    //   909	907	33	str2	String
    // Exception table:
    //   from	to	target	type
    //   590	595	951	java/lang/Exception
    //   611	619	951	java/lang/Exception
    //   635	683	951	java/lang/Exception
    //   699	704	951	java/lang/Exception
    //   720	727	951	java/lang/Exception
    //   743	748	951	java/lang/Exception
    //   764	769	951	java/lang/Exception
    //   785	796	951	java/lang/Exception
    //   812	822	951	java/lang/Exception
    //   843	857	951	java/lang/Exception
    //   873	883	951	java/lang/Exception
    //   899	911	951	java/lang/Exception
    //   927	948	951	java/lang/Exception
    //   1565	1571	951	java/lang/Exception
    //   1587	1601	951	java/lang/Exception
    //   1617	1622	951	java/lang/Exception
    //   1638	1646	951	java/lang/Exception
    //   1662	1704	951	java/lang/Exception
    //   1725	1739	951	java/lang/Exception
    //   1755	1765	951	java/lang/Exception
    //   1781	1793	951	java/lang/Exception
    //   1809	1830	951	java/lang/Exception
    //   2120	2126	951	java/lang/Exception
    //   2142	2157	951	java/lang/Exception
    //   2173	2179	951	java/lang/Exception
    //   2200	2206	951	java/lang/Exception
    //   2222	2229	951	java/lang/Exception
    //   2245	2250	951	java/lang/Exception
    //   2266	2273	951	java/lang/Exception
    //   2289	2296	951	java/lang/Exception
    //   2312	2317	951	java/lang/Exception
    //   2333	2340	951	java/lang/Exception
    //   2356	2385	951	java/lang/Exception
    //   2401	2414	951	java/lang/Exception
    //   2430	2443	951	java/lang/Exception
    //   2459	2472	951	java/lang/Exception
    //   2488	2493	951	java/lang/Exception
    //   2509	2518	951	java/lang/Exception
    //   2534	2546	951	java/lang/Exception
    //   2562	2567	951	java/lang/Exception
    //   2583	2591	951	java/lang/Exception
    //   2607	2625	951	java/lang/Exception
    //   2641	2654	951	java/lang/Exception
    //   2670	2677	951	java/lang/Exception
    //   2706	2719	951	java/lang/Exception
    //   2735	2752	951	java/lang/Exception
    //   2768	2778	951	java/lang/Exception
    //   2884	2890	951	java/lang/Exception
    //   3179	3193	951	java/lang/Exception
    //   4503	4510	951	java/lang/Exception
    //   4526	4538	951	java/lang/Exception
    //   4559	4568	951	java/lang/Exception
    //   4584	4589	951	java/lang/Exception
    //   4605	4613	951	java/lang/Exception
    //   4629	4644	951	java/lang/Exception
    //   4702	4710	951	java/lang/Exception
    //   5029	5035	951	java/lang/Exception
    //   590	595	1833	finally
    //   611	619	1833	finally
    //   635	683	1833	finally
    //   699	704	1833	finally
    //   720	727	1833	finally
    //   743	748	1833	finally
    //   764	769	1833	finally
    //   785	796	1833	finally
    //   812	822	1833	finally
    //   843	857	1833	finally
    //   873	883	1833	finally
    //   899	911	1833	finally
    //   927	948	1833	finally
    //   1565	1571	1833	finally
    //   1587	1601	1833	finally
    //   1617	1622	1833	finally
    //   1638	1646	1833	finally
    //   1662	1704	1833	finally
    //   1725	1739	1833	finally
    //   1755	1765	1833	finally
    //   1781	1793	1833	finally
    //   1809	1830	1833	finally
    //   2120	2126	1833	finally
    //   2142	2157	1833	finally
    //   2173	2179	1833	finally
    //   2200	2206	1833	finally
    //   2222	2229	1833	finally
    //   2245	2250	1833	finally
    //   2266	2273	1833	finally
    //   2289	2296	1833	finally
    //   2312	2317	1833	finally
    //   2333	2340	1833	finally
    //   2356	2385	1833	finally
    //   2401	2414	1833	finally
    //   2430	2443	1833	finally
    //   2459	2472	1833	finally
    //   2488	2493	1833	finally
    //   2509	2518	1833	finally
    //   2534	2546	1833	finally
    //   2562	2567	1833	finally
    //   2583	2591	1833	finally
    //   2607	2625	1833	finally
    //   2641	2654	1833	finally
    //   2670	2677	1833	finally
    //   2706	2719	1833	finally
    //   2735	2752	1833	finally
    //   2768	2778	1833	finally
    //   2884	2890	1833	finally
    //   3179	3193	1833	finally
    //   4503	4510	1833	finally
    //   4526	4538	1833	finally
    //   4559	4568	1833	finally
    //   4584	4589	1833	finally
    //   4605	4613	1833	finally
    //   4629	4644	1833	finally
    //   4702	4710	1833	finally
    //   5029	5035	1833	finally
    //   3211	3217	3256	java/lang/OutOfMemoryError
    //   3263	3268	3566	java/lang/Exception
    //   3196	3203	3576	java/lang/Exception
    //   3205	3211	3576	java/lang/Exception
    //   3211	3217	3576	java/lang/Exception
    //   3217	3222	3576	java/lang/Exception
    //   3228	3242	3576	java/lang/Exception
    //   3258	3263	3576	java/lang/Exception
    //   3268	3311	3576	java/lang/Exception
    //   3568	3573	3576	java/lang/Exception
    //   3619	3641	3576	java/lang/Exception
    //   3646	3697	3576	java/lang/Exception
    //   3697	3749	3576	java/lang/Exception
    //   3755	3788	3576	java/lang/Exception
    //   3793	3807	3576	java/lang/Exception
    //   4066	4073	3576	java/lang/Exception
    //   4084	4092	3576	java/lang/Exception
    //   4092	4111	3576	java/lang/Exception
    //   4116	4121	3576	java/lang/Exception
    //   4126	4161	3576	java/lang/Exception
    //   4418	4423	3576	java/lang/Exception
    //   4445	4450	3576	java/lang/Exception
    //   4453	4467	3576	java/lang/Exception
    //   3501	3545	3611	java/lang/OutOfMemoryError
    //   3196	3203	4076	finally
    //   3205	3211	4076	finally
    //   3211	3217	4076	finally
    //   3217	3222	4076	finally
    //   3228	3242	4076	finally
    //   3258	3263	4076	finally
    //   3263	3268	4076	finally
    //   3268	3311	4076	finally
    //   3568	3573	4076	finally
    //   3619	3641	4076	finally
    //   3646	3697	4076	finally
    //   3697	3749	4076	finally
    //   3755	3788	4076	finally
    //   3788	3793	4076	finally
    //   3793	3807	4076	finally
    //   4066	4073	4076	finally
    //   4084	4092	4076	finally
    //   4092	4111	4076	finally
    //   4116	4121	4076	finally
    //   4121	4126	4076	finally
    //   4126	4161	4076	finally
    //   4418	4423	4076	finally
    //   4445	4450	4076	finally
    //   4453	4467	4076	finally
    //   4084	4092	4114	java/lang/OutOfMemoryError
    //   4121	4126	4416	java/lang/Exception
    //   4351	4395	4435	java/lang/OutOfMemoryError
    //   3788	3793	4443	java/lang/Exception
    //   3997	4041	4479	java/lang/OutOfMemoryError
    //   4931	4975	5005	java/lang/OutOfMemoryError
    //   3087	3134	5085	java/lang/OutOfMemoryError
    //   1249	1296	5290	java/lang/OutOfMemoryError
    //   2043	2087	5309	java/lang/OutOfMemoryError
    //   4644	4657	5324	finally
    //   4713	4735	5324	finally
    //   4662	4669	5329	finally
    //   975	1031	5337	finally
    //   1034	1061	5337	finally
    //   5095	5103	5337	finally
    //   5109	5117	5337	finally
    //   5123	5131	5337	finally
    //   5137	5145	5337	finally
    //   5151	5159	5337	finally
    //   5165	5173	5337	finally
    //   5179	5187	5337	finally
    //   5193	5201	5337	finally
    //   5207	5214	5337	finally
    //   292	320	5358	finally
    //   320	405	5358	finally
    //   409	415	5358	finally
    //   417	425	5358	finally
    //   427	434	5358	finally
    //   436	445	5358	finally
    //   447	452	5358	finally
    //   454	462	5358	finally
    //   464	493	5358	finally
    //   495	501	5358	finally
    //   507	515	5358	finally
    //   517	528	5358	finally
    //   530	535	5358	finally
    //   537	542	5358	finally
    //   544	561	5358	finally
    //   563	570	5358	finally
    //   1350	1355	5358	finally
    //   1357	1365	5358	finally
    //   1367	1382	5358	finally
    //   1387	1396	5358	finally
    //   1398	1403	5358	finally
    //   1405	1413	5358	finally
    //   1415	1444	5358	finally
    //   1449	1454	5358	finally
    //   1456	1464	5358	finally
    //   1466	1481	5358	finally
    //   1486	1491	5358	finally
    //   1493	1498	5358	finally
    //   1500	1523	5358	finally
    //   1528	1535	5358	finally
    //   4644	4657	5367	java/lang/Exception
    //   4713	4735	5367	java/lang/Exception
    //   4662	4669	5393	java/lang/Exception
    //   292	320	5418	java/lang/Exception
    //   320	405	5418	java/lang/Exception
    //   409	415	5447	java/lang/Exception
    //   417	425	5447	java/lang/Exception
    //   427	434	5447	java/lang/Exception
    //   436	445	5447	java/lang/Exception
    //   447	452	5447	java/lang/Exception
    //   454	462	5447	java/lang/Exception
    //   464	493	5447	java/lang/Exception
    //   495	501	5447	java/lang/Exception
    //   507	515	5447	java/lang/Exception
    //   517	528	5447	java/lang/Exception
    //   530	535	5447	java/lang/Exception
    //   537	542	5447	java/lang/Exception
    //   544	561	5447	java/lang/Exception
    //   563	570	5447	java/lang/Exception
    //   1350	1355	5447	java/lang/Exception
    //   1357	1365	5447	java/lang/Exception
    //   1367	1382	5447	java/lang/Exception
    //   1387	1396	5447	java/lang/Exception
    //   1398	1403	5447	java/lang/Exception
    //   1405	1413	5447	java/lang/Exception
    //   1415	1444	5447	java/lang/Exception
    //   1449	1454	5447	java/lang/Exception
    //   1456	1464	5447	java/lang/Exception
    //   1466	1481	5447	java/lang/Exception
    //   1486	1491	5447	java/lang/Exception
    //   1493	1498	5447	java/lang/Exception
    //   1500	1523	5447	java/lang/Exception
    //   1528	1535	5447	java/lang/Exception
  }
  
  public final ab a(String paramString, byte[] paramArrayOfByte)
  {
    return b(paramString, paramArrayOfByte);
  }
  
  public final ac a(ab paramab)
  {
    bb.b("HttpAccessClientImpl", "doRequest...");
    paramab.l = SystemClock.elapsedRealtime();
    try
    {
      paramab = b(paramab);
      return paramab;
    }
    catch (Exception paramab)
    {
      for (;;)
      {
        paramab = new ac();
        paramab.a = -19;
      }
    }
  }
  
  final class a
    implements Runnable
  {
    private ad a;
    
    a(ad paramad)
    {
      this.a = paramad;
    }
    
    public final void run()
    {
      for (;;)
      {
        try
        {
          Object localObject;
          if ((this.a != null) && (!this.a.v))
          {
            localObject = InetAddress.getByName(this.a.c);
            this.a.t = ((InetAddress)localObject).getHostAddress();
            ad localad = this.a;
            localObject = new ct/s;
            ((s)localObject).<init>(this.a.t, 80);
            localad.a = ((s)localObject);
          }
          if (this.a.i == 0)
          {
            localObject = this.a;
            if ((((ad)localObject).a == null) || (!((ad)localObject).a.a(((ad)localObject).b))) {
              continue;
            }
            i = 1;
            if (i == 0) {
              ae.a(this.a);
            }
          }
        }
        catch (Exception localException2)
        {
          int i;
          continue;
        }
        try
        {
          if ((this.a.z) && (ae.a(ae.this, this.a))) {
            ae.b(this.a);
          }
          return;
          i = 0;
        }
        catch (Exception localException1) {}
      }
    }
  }
}


/* Location:              /Users/hanlian/Downloads/WiFidex1-dex2jar.jar!/ct/ae.class
 * Java compiler version: 6 (50.0)
 * JD-Core Version:       0.7.1
 */