package ct;

public final class aq
{
  private static aq k = null;
  private String a = "";
  private String b = "";
  private String c = "";
  private String d = "";
  private String e = "";
  private String f = "";
  private String g = "";
  private String h = "";
  private String i = "";
  private String j = "";
  
  /* Error */
  public static void a(android.content.Context paramContext)
  {
    // Byte code:
    //   0: ldc 2
    //   2: monitorenter
    //   3: aload_0
    //   4: ifnull +235 -> 239
    //   7: getstatic 21	ct/aq:k	Lct/aq;
    //   10: ifnonnull +15 -> 25
    //   13: new 2	ct/aq
    //   16: astore_1
    //   17: aload_1
    //   18: invokespecial 49	ct/aq:<init>	()V
    //   21: aload_1
    //   22: putstatic 21	ct/aq:k	Lct/aq;
    //   25: getstatic 21	ct/aq:k	Lct/aq;
    //   28: astore_1
    //   29: aload_1
    //   30: monitorenter
    //   31: getstatic 21	ct/aq:k	Lct/aq;
    //   34: astore_2
    //   35: aload_0
    //   36: invokestatic 54	ct/ar:a	(Landroid/content/Context;)Lct/ar;
    //   39: pop
    //   40: new 56	java/lang/StringBuffer
    //   43: astore_3
    //   44: aload_3
    //   45: invokespecial 57	java/lang/StringBuffer:<init>	()V
    //   48: aload_3
    //   49: invokestatic 60	ct/ar:a	()Ljava/lang/String;
    //   52: invokevirtual 64	java/lang/StringBuffer:append	(Ljava/lang/String;)Ljava/lang/StringBuffer;
    //   55: pop
    //   56: aload_3
    //   57: ldc 66
    //   59: invokevirtual 64	java/lang/StringBuffer:append	(Ljava/lang/String;)Ljava/lang/StringBuffer;
    //   62: pop
    //   63: aload_3
    //   64: invokestatic 68	ct/ar:b	()Ljava/lang/String;
    //   67: invokevirtual 64	java/lang/StringBuffer:append	(Ljava/lang/String;)Ljava/lang/StringBuffer;
    //   70: pop
    //   71: aload_3
    //   72: ldc 70
    //   74: invokevirtual 64	java/lang/StringBuffer:append	(Ljava/lang/String;)Ljava/lang/StringBuffer;
    //   77: pop
    //   78: aload_3
    //   79: invokestatic 72	ct/ar:c	()Ljava/lang/String;
    //   82: invokevirtual 64	java/lang/StringBuffer:append	(Ljava/lang/String;)Ljava/lang/StringBuffer;
    //   85: pop
    //   86: aload_2
    //   87: aload_3
    //   88: invokevirtual 75	java/lang/StringBuffer:toString	()Ljava/lang/String;
    //   91: invokespecial 78	ct/aq:a	(Ljava/lang/String;)V
    //   94: getstatic 21	ct/aq:k	Lct/aq;
    //   97: invokespecial 81	ct/aq:l	()V
    //   100: getstatic 21	ct/aq:k	Lct/aq;
    //   103: ldc 83
    //   105: invokespecial 85	ct/aq:d	(Ljava/lang/String;)V
    //   108: getstatic 21	ct/aq:k	Lct/aq;
    //   111: aload_0
    //   112: invokestatic 90	ct/ap:c	(Landroid/content/Context;)Ljava/lang/String;
    //   115: invokespecial 92	ct/aq:c	(Ljava/lang/String;)V
    //   118: getstatic 21	ct/aq:k	Lct/aq;
    //   121: astore_2
    //   122: aload_0
    //   123: invokestatic 54	ct/ar:a	(Landroid/content/Context;)Lct/ar;
    //   126: pop
    //   127: aload_2
    //   128: aload_0
    //   129: invokestatic 94	ct/ar:b	(Landroid/content/Context;)Ljava/lang/String;
    //   132: invokespecial 96	ct/aq:e	(Ljava/lang/String;)V
    //   135: getstatic 21	ct/aq:k	Lct/aq;
    //   138: astore_2
    //   139: aload_0
    //   140: invokestatic 54	ct/ar:a	(Landroid/content/Context;)Lct/ar;
    //   143: pop
    //   144: aload_2
    //   145: aload_0
    //   146: invokestatic 97	ct/ar:c	(Landroid/content/Context;)Ljava/lang/String;
    //   149: putfield 37	ct/aq:e	Ljava/lang/String;
    //   152: getstatic 21	ct/aq:k	Lct/aq;
    //   155: astore_2
    //   156: aload_0
    //   157: invokestatic 54	ct/ar:a	(Landroid/content/Context;)Lct/ar;
    //   160: pop
    //   161: aload_2
    //   162: aload_0
    //   163: invokestatic 99	ct/ar:e	(Landroid/content/Context;)Ljava/lang/String;
    //   166: putfield 39	ct/aq:f	Ljava/lang/String;
    //   169: getstatic 21	ct/aq:k	Lct/aq;
    //   172: astore_2
    //   173: aload_0
    //   174: invokestatic 54	ct/ar:a	(Landroid/content/Context;)Lct/ar;
    //   177: pop
    //   178: aload_2
    //   179: aload_0
    //   180: invokestatic 101	ct/ar:d	(Landroid/content/Context;)Ljava/lang/String;
    //   183: putfield 41	ct/aq:g	Ljava/lang/String;
    //   186: getstatic 21	ct/aq:k	Lct/aq;
    //   189: invokestatic 105	ct/p:g	()Ljava/lang/String;
    //   192: invokespecial 107	ct/aq:f	(Ljava/lang/String;)V
    //   195: getstatic 21	ct/aq:k	Lct/aq;
    //   198: aload_0
    //   199: invokestatic 109	ct/ap:a	(Landroid/content/Context;)Ljava/lang/String;
    //   202: invokespecial 111	ct/aq:b	(Ljava/lang/String;)V
    //   205: getstatic 21	ct/aq:k	Lct/aq;
    //   208: astore_2
    //   209: aload_0
    //   210: invokestatic 54	ct/ar:a	(Landroid/content/Context;)Lct/ar;
    //   213: pop
    //   214: aload_2
    //   215: invokestatic 113	ct/ar:d	()Ljava/lang/String;
    //   218: putfield 45	ct/aq:i	Ljava/lang/String;
    //   221: getstatic 21	ct/aq:k	Lct/aq;
    //   224: astore_2
    //   225: aload_0
    //   226: invokestatic 54	ct/ar:a	(Landroid/content/Context;)Lct/ar;
    //   229: pop
    //   230: aload_2
    //   231: invokestatic 60	ct/ar:a	()Ljava/lang/String;
    //   234: putfield 47	ct/aq:j	Ljava/lang/String;
    //   237: aload_1
    //   238: monitorexit
    //   239: ldc 2
    //   241: monitorexit
    //   242: return
    //   243: astore_0
    //   244: aload_1
    //   245: monitorexit
    //   246: aload_0
    //   247: athrow
    //   248: astore_0
    //   249: ldc 2
    //   251: monitorexit
    //   252: aload_0
    //   253: athrow
    // Local variable table:
    //   start	length	slot	name	signature
    //   0	254	0	paramContext	android.content.Context
    //   34	197	2	localaq2	aq
    //   43	45	3	localStringBuffer	StringBuffer
    // Exception table:
    //   from	to	target	type
    //   31	239	243	finally
    //   7	25	248	finally
    //   25	31	248	finally
    //   244	248	248	finally
  }
  
  private void a(String paramString)
  {
    try
    {
      this.a = paramString;
      return;
    }
    finally
    {
      paramString = finally;
      throw paramString;
    }
  }
  
  private void b(String paramString)
  {
    try
    {
      this.b = paramString;
      return;
    }
    finally
    {
      paramString = finally;
      throw paramString;
    }
  }
  
  private void c(String paramString)
  {
    try
    {
      this.c = paramString;
      return;
    }
    finally
    {
      paramString = finally;
      throw paramString;
    }
  }
  
  private void d(String paramString) {}
  
  private void e(String paramString)
  {
    try
    {
      this.d = paramString;
      return;
    }
    finally
    {
      paramString = finally;
      throw paramString;
    }
  }
  
  private void f(String paramString)
  {
    try
    {
      this.h = paramString;
      return;
    }
    finally
    {
      paramString = finally;
      throw paramString;
    }
  }
  
  public static aq k()
  {
    try
    {
      aq localaq = k;
      return localaq;
    }
    finally
    {
      localObject = finally;
      throw ((Throwable)localObject);
    }
  }
  
  private void l() {}
  
  public final String a()
  {
    try
    {
      String str = this.a;
      return str;
    }
    finally
    {
      localObject = finally;
      throw ((Throwable)localObject);
    }
  }
  
  public final String b()
  {
    try
    {
      String str = this.b;
      return str;
    }
    finally
    {
      localObject = finally;
      throw ((Throwable)localObject);
    }
  }
  
  public final String c()
  {
    try
    {
      String str = this.c;
      return str;
    }
    finally
    {
      localObject = finally;
      throw ((Throwable)localObject);
    }
  }
  
  public final String d()
  {
    try
    {
      String str = this.d;
      return str;
    }
    finally
    {
      localObject = finally;
      throw ((Throwable)localObject);
    }
  }
  
  public final String e()
  {
    try
    {
      String str = this.h;
      return str;
    }
    finally
    {
      localObject = finally;
      throw ((Throwable)localObject);
    }
  }
  
  public final String f()
  {
    return this.e;
  }
  
  public final String g()
  {
    return this.f;
  }
  
  public final String h()
  {
    return this.g;
  }
  
  public final String i()
  {
    return this.i;
  }
  
  public final String j()
  {
    return this.j;
  }
}


/* Location:              /Users/hanlian/Downloads/WiFi万能钥匙dex1-dex2jar.jar!/ct/aq.class
 * Java compiler version: 6 (50.0)
 * JD-Core Version:       0.7.1
 */