package com.c.a.a.a.d.a.a;

import com.b.b.h;
import com.b.b.m;
import com.b.b.m.a;
import com.b.b.n.b;
import com.b.b.u;
import com.b.b.v;
import com.b.b.x;

public final class a
{
  public static final class a
    extends m<a, a>
    implements a.b
  {
    private static final a p;
    private static volatile x<a> q;
    private int d;
    private n.b<b> e = h();
    private String f = "";
    private int g;
    private int h;
    private int i;
    private String j = "";
    private String k = "";
    private String l = "";
    private String m = "";
    private String n = "";
    private String o = "";
    
    static
    {
      a locala = new a();
      p = locala;
      locala.e();
    }
    
    public static a l()
    {
      return (a)p.g();
    }
    
    /* Error */
    protected final Object a(int paramInt, Object paramObject1, Object paramObject2)
    {
      // Byte code:
      //   0: iconst_1
      //   1: istore 7
      //   3: iconst_0
      //   4: istore 4
      //   6: getstatic 110	com/c/a/a/a/d/a/a/a$1:a	[I
      //   9: iload_1
      //   10: iconst_1
      //   11: isub
      //   12: iaload
      //   13: tableswitch	default:+47->60, 1:+55->68, 2:+65->78, 3:+72->85, 4:+86->99, 5:+98->111, 6:+769->782, 7:+1122->1135, 8:+1129->1142
      //   60: new 112	java/lang/UnsupportedOperationException
      //   63: dup
      //   64: invokespecial 113	java/lang/UnsupportedOperationException:<init>	()V
      //   67: athrow
      //   68: new 2	com/c/a/a/a/d/a/a/a$a
      //   71: dup
      //   72: invokespecial 46	com/c/a/a/a/d/a/a/a$a:<init>	()V
      //   75: astore_2
      //   76: aload_2
      //   77: areturn
      //   78: getstatic 48	com/c/a/a/a/d/a/a/a$a:p	Lcom/c/a/a/a/d/a/a/a$a;
      //   81: astore_2
      //   82: goto -6 -> 76
      //   85: aload_0
      //   86: getfield 57	com/c/a/a/a/d/a/a/a$a:e	Lcom/b/b/n$b;
      //   89: invokeinterface 115 1 0
      //   94: aconst_null
      //   95: astore_2
      //   96: goto -20 -> 76
      //   99: new 12	com/c/a/a/a/d/a/a/a$a$a
      //   102: dup
      //   103: iconst_0
      //   104: invokespecial 118	com/c/a/a/a/d/a/a/a$a$a:<init>	(B)V
      //   107: astore_2
      //   108: goto -32 -> 76
      //   111: aload_2
      //   112: checkcast 120	com/b/b/m$j
      //   115: astore 8
      //   117: aload_3
      //   118: checkcast 2	com/c/a/a/a/d/a/a/a$a
      //   121: astore_3
      //   122: aload_0
      //   123: aload 8
      //   125: aload_0
      //   126: getfield 57	com/c/a/a/a/d/a/a/a$a:e	Lcom/b/b/n$b;
      //   129: aload_3
      //   130: getfield 57	com/c/a/a/a/d/a/a/a$a:e	Lcom/b/b/n$b;
      //   133: invokeinterface 123 3 0
      //   138: putfield 57	com/c/a/a/a/d/a/a/a$a:e	Lcom/b/b/n$b;
      //   141: aload_0
      //   142: getfield 61	com/c/a/a/a/d/a/a/a$a:f	Ljava/lang/String;
      //   145: invokevirtual 128	java/lang/String:isEmpty	()Z
      //   148: ifne +514 -> 662
      //   151: iconst_1
      //   152: istore 5
      //   154: aload_0
      //   155: getfield 61	com/c/a/a/a/d/a/a/a$a:f	Ljava/lang/String;
      //   158: astore_2
      //   159: aload_3
      //   160: getfield 61	com/c/a/a/a/d/a/a/a$a:f	Ljava/lang/String;
      //   163: invokevirtual 128	java/lang/String:isEmpty	()Z
      //   166: ifne +502 -> 668
      //   169: iconst_1
      //   170: istore 6
      //   172: aload_0
      //   173: aload 8
      //   175: iload 5
      //   177: aload_2
      //   178: iload 6
      //   180: aload_3
      //   181: getfield 61	com/c/a/a/a/d/a/a/a$a:f	Ljava/lang/String;
      //   184: invokeinterface 131 5 0
      //   189: putfield 61	com/c/a/a/a/d/a/a/a$a:f	Ljava/lang/String;
      //   192: aload_0
      //   193: getfield 76	com/c/a/a/a/d/a/a/a$a:g	I
      //   196: ifeq +478 -> 674
      //   199: iconst_1
      //   200: istore 5
      //   202: aload_0
      //   203: getfield 76	com/c/a/a/a/d/a/a/a$a:g	I
      //   206: istore_1
      //   207: aload_3
      //   208: getfield 76	com/c/a/a/a/d/a/a/a$a:g	I
      //   211: ifeq +469 -> 680
      //   214: iconst_1
      //   215: istore 6
      //   217: aload_0
      //   218: aload 8
      //   220: iload 5
      //   222: iload_1
      //   223: iload 6
      //   225: aload_3
      //   226: getfield 76	com/c/a/a/a/d/a/a/a$a:g	I
      //   229: invokeinterface 134 5 0
      //   234: putfield 76	com/c/a/a/a/d/a/a/a$a:g	I
      //   237: aload_0
      //   238: getfield 95	com/c/a/a/a/d/a/a/a$a:h	I
      //   241: ifeq +445 -> 686
      //   244: iconst_1
      //   245: istore 5
      //   247: aload_0
      //   248: getfield 95	com/c/a/a/a/d/a/a/a$a:h	I
      //   251: istore_1
      //   252: aload_3
      //   253: getfield 95	com/c/a/a/a/d/a/a/a$a:h	I
      //   256: ifeq +436 -> 692
      //   259: iconst_1
      //   260: istore 6
      //   262: aload_0
      //   263: aload 8
      //   265: iload 5
      //   267: iload_1
      //   268: iload 6
      //   270: aload_3
      //   271: getfield 95	com/c/a/a/a/d/a/a/a$a:h	I
      //   274: invokeinterface 134 5 0
      //   279: putfield 95	com/c/a/a/a/d/a/a/a$a:h	I
      //   282: aload_0
      //   283: getfield 136	com/c/a/a/a/d/a/a/a$a:i	I
      //   286: ifeq +412 -> 698
      //   289: iconst_1
      //   290: istore 5
      //   292: aload_0
      //   293: getfield 136	com/c/a/a/a/d/a/a/a$a:i	I
      //   296: istore_1
      //   297: aload_3
      //   298: getfield 136	com/c/a/a/a/d/a/a/a$a:i	I
      //   301: ifeq +403 -> 704
      //   304: iconst_1
      //   305: istore 6
      //   307: aload_0
      //   308: aload 8
      //   310: iload 5
      //   312: iload_1
      //   313: iload 6
      //   315: aload_3
      //   316: getfield 136	com/c/a/a/a/d/a/a/a$a:i	I
      //   319: invokeinterface 134 5 0
      //   324: putfield 136	com/c/a/a/a/d/a/a/a$a:i	I
      //   327: aload_0
      //   328: getfield 63	com/c/a/a/a/d/a/a/a$a:j	Ljava/lang/String;
      //   331: invokevirtual 128	java/lang/String:isEmpty	()Z
      //   334: ifne +376 -> 710
      //   337: iconst_1
      //   338: istore 5
      //   340: aload_0
      //   341: getfield 63	com/c/a/a/a/d/a/a/a$a:j	Ljava/lang/String;
      //   344: astore_2
      //   345: aload_3
      //   346: getfield 63	com/c/a/a/a/d/a/a/a$a:j	Ljava/lang/String;
      //   349: invokevirtual 128	java/lang/String:isEmpty	()Z
      //   352: ifne +364 -> 716
      //   355: iconst_1
      //   356: istore 6
      //   358: aload_0
      //   359: aload 8
      //   361: iload 5
      //   363: aload_2
      //   364: iload 6
      //   366: aload_3
      //   367: getfield 63	com/c/a/a/a/d/a/a/a$a:j	Ljava/lang/String;
      //   370: invokeinterface 131 5 0
      //   375: putfield 63	com/c/a/a/a/d/a/a/a$a:j	Ljava/lang/String;
      //   378: aload_0
      //   379: getfield 65	com/c/a/a/a/d/a/a/a$a:k	Ljava/lang/String;
      //   382: invokevirtual 128	java/lang/String:isEmpty	()Z
      //   385: ifne +337 -> 722
      //   388: iconst_1
      //   389: istore 5
      //   391: aload_0
      //   392: getfield 65	com/c/a/a/a/d/a/a/a$a:k	Ljava/lang/String;
      //   395: astore_2
      //   396: aload_3
      //   397: getfield 65	com/c/a/a/a/d/a/a/a$a:k	Ljava/lang/String;
      //   400: invokevirtual 128	java/lang/String:isEmpty	()Z
      //   403: ifne +325 -> 728
      //   406: iconst_1
      //   407: istore 6
      //   409: aload_0
      //   410: aload 8
      //   412: iload 5
      //   414: aload_2
      //   415: iload 6
      //   417: aload_3
      //   418: getfield 65	com/c/a/a/a/d/a/a/a$a:k	Ljava/lang/String;
      //   421: invokeinterface 131 5 0
      //   426: putfield 65	com/c/a/a/a/d/a/a/a$a:k	Ljava/lang/String;
      //   429: aload_0
      //   430: getfield 67	com/c/a/a/a/d/a/a/a$a:l	Ljava/lang/String;
      //   433: invokevirtual 128	java/lang/String:isEmpty	()Z
      //   436: ifne +298 -> 734
      //   439: iconst_1
      //   440: istore 5
      //   442: aload_0
      //   443: getfield 67	com/c/a/a/a/d/a/a/a$a:l	Ljava/lang/String;
      //   446: astore_2
      //   447: aload_3
      //   448: getfield 67	com/c/a/a/a/d/a/a/a$a:l	Ljava/lang/String;
      //   451: invokevirtual 128	java/lang/String:isEmpty	()Z
      //   454: ifne +286 -> 740
      //   457: iconst_1
      //   458: istore 6
      //   460: aload_0
      //   461: aload 8
      //   463: iload 5
      //   465: aload_2
      //   466: iload 6
      //   468: aload_3
      //   469: getfield 67	com/c/a/a/a/d/a/a/a$a:l	Ljava/lang/String;
      //   472: invokeinterface 131 5 0
      //   477: putfield 67	com/c/a/a/a/d/a/a/a$a:l	Ljava/lang/String;
      //   480: aload_0
      //   481: getfield 69	com/c/a/a/a/d/a/a/a$a:m	Ljava/lang/String;
      //   484: invokevirtual 128	java/lang/String:isEmpty	()Z
      //   487: ifne +259 -> 746
      //   490: iconst_1
      //   491: istore 5
      //   493: aload_0
      //   494: getfield 69	com/c/a/a/a/d/a/a/a$a:m	Ljava/lang/String;
      //   497: astore_2
      //   498: aload_3
      //   499: getfield 69	com/c/a/a/a/d/a/a/a$a:m	Ljava/lang/String;
      //   502: invokevirtual 128	java/lang/String:isEmpty	()Z
      //   505: ifne +247 -> 752
      //   508: iconst_1
      //   509: istore 6
      //   511: aload_0
      //   512: aload 8
      //   514: iload 5
      //   516: aload_2
      //   517: iload 6
      //   519: aload_3
      //   520: getfield 69	com/c/a/a/a/d/a/a/a$a:m	Ljava/lang/String;
      //   523: invokeinterface 131 5 0
      //   528: putfield 69	com/c/a/a/a/d/a/a/a$a:m	Ljava/lang/String;
      //   531: aload_0
      //   532: getfield 71	com/c/a/a/a/d/a/a/a$a:n	Ljava/lang/String;
      //   535: invokevirtual 128	java/lang/String:isEmpty	()Z
      //   538: ifne +220 -> 758
      //   541: iconst_1
      //   542: istore 5
      //   544: aload_0
      //   545: getfield 71	com/c/a/a/a/d/a/a/a$a:n	Ljava/lang/String;
      //   548: astore_2
      //   549: aload_3
      //   550: getfield 71	com/c/a/a/a/d/a/a/a$a:n	Ljava/lang/String;
      //   553: invokevirtual 128	java/lang/String:isEmpty	()Z
      //   556: ifne +208 -> 764
      //   559: iconst_1
      //   560: istore 6
      //   562: aload_0
      //   563: aload 8
      //   565: iload 5
      //   567: aload_2
      //   568: iload 6
      //   570: aload_3
      //   571: getfield 71	com/c/a/a/a/d/a/a/a$a:n	Ljava/lang/String;
      //   574: invokeinterface 131 5 0
      //   579: putfield 71	com/c/a/a/a/d/a/a/a$a:n	Ljava/lang/String;
      //   582: aload_0
      //   583: getfield 73	com/c/a/a/a/d/a/a/a$a:o	Ljava/lang/String;
      //   586: invokevirtual 128	java/lang/String:isEmpty	()Z
      //   589: ifne +181 -> 770
      //   592: iconst_1
      //   593: istore 5
      //   595: aload_0
      //   596: getfield 73	com/c/a/a/a/d/a/a/a$a:o	Ljava/lang/String;
      //   599: astore_2
      //   600: aload_3
      //   601: getfield 73	com/c/a/a/a/d/a/a/a$a:o	Ljava/lang/String;
      //   604: invokevirtual 128	java/lang/String:isEmpty	()Z
      //   607: ifne +169 -> 776
      //   610: iload 7
      //   612: istore 6
      //   614: aload_0
      //   615: aload 8
      //   617: iload 5
      //   619: aload_2
      //   620: iload 6
      //   622: aload_3
      //   623: getfield 73	com/c/a/a/a/d/a/a/a$a:o	Ljava/lang/String;
      //   626: invokeinterface 131 5 0
      //   631: putfield 73	com/c/a/a/a/d/a/a/a$a:o	Ljava/lang/String;
      //   634: aload_0
      //   635: astore_2
      //   636: aload 8
      //   638: getstatic 141	com/b/b/m$h:a	Lcom/b/b/m$h;
      //   641: if_acmpne -565 -> 76
      //   644: aload_0
      //   645: aload_0
      //   646: getfield 143	com/c/a/a/a/d/a/a/a$a:d	I
      //   649: aload_3
      //   650: getfield 143	com/c/a/a/a/d/a/a/a$a:d	I
      //   653: ior
      //   654: putfield 143	com/c/a/a/a/d/a/a/a$a:d	I
      //   657: aload_0
      //   658: astore_2
      //   659: goto -583 -> 76
      //   662: iconst_0
      //   663: istore 5
      //   665: goto -511 -> 154
      //   668: iconst_0
      //   669: istore 6
      //   671: goto -499 -> 172
      //   674: iconst_0
      //   675: istore 5
      //   677: goto -475 -> 202
      //   680: iconst_0
      //   681: istore 6
      //   683: goto -466 -> 217
      //   686: iconst_0
      //   687: istore 5
      //   689: goto -442 -> 247
      //   692: iconst_0
      //   693: istore 6
      //   695: goto -433 -> 262
      //   698: iconst_0
      //   699: istore 5
      //   701: goto -409 -> 292
      //   704: iconst_0
      //   705: istore 6
      //   707: goto -400 -> 307
      //   710: iconst_0
      //   711: istore 5
      //   713: goto -373 -> 340
      //   716: iconst_0
      //   717: istore 6
      //   719: goto -361 -> 358
      //   722: iconst_0
      //   723: istore 5
      //   725: goto -334 -> 391
      //   728: iconst_0
      //   729: istore 6
      //   731: goto -322 -> 409
      //   734: iconst_0
      //   735: istore 5
      //   737: goto -295 -> 442
      //   740: iconst_0
      //   741: istore 6
      //   743: goto -283 -> 460
      //   746: iconst_0
      //   747: istore 5
      //   749: goto -256 -> 493
      //   752: iconst_0
      //   753: istore 6
      //   755: goto -244 -> 511
      //   758: iconst_0
      //   759: istore 5
      //   761: goto -217 -> 544
      //   764: iconst_0
      //   765: istore 6
      //   767: goto -205 -> 562
      //   770: iconst_0
      //   771: istore 5
      //   773: goto -178 -> 595
      //   776: iconst_0
      //   777: istore 6
      //   779: goto -165 -> 614
      //   782: aload_2
      //   783: checkcast 145	com/b/b/g
      //   786: astore_2
      //   787: aload_3
      //   788: checkcast 147	com/b/b/j
      //   791: astore_3
      //   792: iload 4
      //   794: istore_1
      //   795: iload_1
      //   796: ifne +339 -> 1135
      //   799: aload_2
      //   800: invokevirtual 150	com/b/b/g:a	()I
      //   803: istore 4
      //   805: iload 4
      //   807: lookupswitch	default:+105->912, 0:+119->926, 10:+124->931, 18:+187->994, 24:+229->1036, 32:+240->1047, 40:+251->1058, 50:+262->1069, 58:+273->1080, 66:+284->1091, 74:+295->1102, 82:+306->1113, 90:+317->1124
      //   912: aload_2
      //   913: iload 4
      //   915: invokevirtual 153	com/b/b/g:b	(I)Z
      //   918: ifne -123 -> 795
      //   921: iconst_1
      //   922: istore_1
      //   923: goto -128 -> 795
      //   926: iconst_1
      //   927: istore_1
      //   928: goto -133 -> 795
      //   931: aload_0
      //   932: getfield 57	com/c/a/a/a/d/a/a/a$a:e	Lcom/b/b/n$b;
      //   935: invokeinterface 85 1 0
      //   940: ifne +14 -> 954
      //   943: aload_0
      //   944: aload_0
      //   945: getfield 57	com/c/a/a/a/d/a/a/a$a:e	Lcom/b/b/n$b;
      //   948: invokestatic 88	com/b/b/m:a	(Lcom/b/b/n$b;)Lcom/b/b/n$b;
      //   951: putfield 57	com/c/a/a/a/d/a/a/a$a:e	Lcom/b/b/n$b;
      //   954: aload_0
      //   955: getfield 57	com/c/a/a/a/d/a/a/a$a:e	Lcom/b/b/n$b;
      //   958: aload_2
      //   959: invokestatic 156	com/c/a/a/a/d/a/a/a$a$b:m	()Lcom/b/b/x;
      //   962: aload_3
      //   963: invokevirtual 159	com/b/b/g:a	(Lcom/b/b/x;Lcom/b/b/j;)Lcom/b/b/u;
      //   966: invokeinterface 92 2 0
      //   971: pop
      //   972: goto -177 -> 795
      //   975: astore_3
      //   976: new 161	java/lang/RuntimeException
      //   979: astore_2
      //   980: aload_2
      //   981: aload_3
      //   982: aload_0
      //   983: invokevirtual 164	com/b/b/o:a	(Lcom/b/b/u;)Lcom/b/b/o;
      //   986: invokespecial 167	java/lang/RuntimeException:<init>	(Ljava/lang/Throwable;)V
      //   989: aload_2
      //   990: athrow
      //   991: astore_2
      //   992: aload_2
      //   993: athrow
      //   994: aload_0
      //   995: aload_2
      //   996: invokevirtual 170	com/b/b/g:k	()Ljava/lang/String;
      //   999: putfield 61	com/c/a/a/a/d/a/a/a$a:f	Ljava/lang/String;
      //   1002: goto -207 -> 795
      //   1005: astore_3
      //   1006: new 161	java/lang/RuntimeException
      //   1009: astore 8
      //   1011: new 103	com/b/b/o
      //   1014: astore_2
      //   1015: aload_2
      //   1016: aload_3
      //   1017: invokevirtual 173	java/io/IOException:getMessage	()Ljava/lang/String;
      //   1020: invokespecial 176	com/b/b/o:<init>	(Ljava/lang/String;)V
      //   1023: aload 8
      //   1025: aload_2
      //   1026: aload_0
      //   1027: invokevirtual 164	com/b/b/o:a	(Lcom/b/b/u;)Lcom/b/b/o;
      //   1030: invokespecial 167	java/lang/RuntimeException:<init>	(Ljava/lang/Throwable;)V
      //   1033: aload 8
      //   1035: athrow
      //   1036: aload_0
      //   1037: aload_2
      //   1038: invokevirtual 178	com/b/b/g:q	()I
      //   1041: putfield 76	com/c/a/a/a/d/a/a/a$a:g	I
      //   1044: goto -249 -> 795
      //   1047: aload_0
      //   1048: aload_2
      //   1049: invokevirtual 178	com/b/b/g:q	()I
      //   1052: putfield 95	com/c/a/a/a/d/a/a/a$a:h	I
      //   1055: goto -260 -> 795
      //   1058: aload_0
      //   1059: aload_2
      //   1060: invokevirtual 178	com/b/b/g:q	()I
      //   1063: putfield 136	com/c/a/a/a/d/a/a/a$a:i	I
      //   1066: goto -271 -> 795
      //   1069: aload_0
      //   1070: aload_2
      //   1071: invokevirtual 170	com/b/b/g:k	()Ljava/lang/String;
      //   1074: putfield 63	com/c/a/a/a/d/a/a/a$a:j	Ljava/lang/String;
      //   1077: goto -282 -> 795
      //   1080: aload_0
      //   1081: aload_2
      //   1082: invokevirtual 170	com/b/b/g:k	()Ljava/lang/String;
      //   1085: putfield 65	com/c/a/a/a/d/a/a/a$a:k	Ljava/lang/String;
      //   1088: goto -293 -> 795
      //   1091: aload_0
      //   1092: aload_2
      //   1093: invokevirtual 170	com/b/b/g:k	()Ljava/lang/String;
      //   1096: putfield 67	com/c/a/a/a/d/a/a/a$a:l	Ljava/lang/String;
      //   1099: goto -304 -> 795
      //   1102: aload_0
      //   1103: aload_2
      //   1104: invokevirtual 170	com/b/b/g:k	()Ljava/lang/String;
      //   1107: putfield 69	com/c/a/a/a/d/a/a/a$a:m	Ljava/lang/String;
      //   1110: goto -315 -> 795
      //   1113: aload_0
      //   1114: aload_2
      //   1115: invokevirtual 170	com/b/b/g:k	()Ljava/lang/String;
      //   1118: putfield 71	com/c/a/a/a/d/a/a/a$a:n	Ljava/lang/String;
      //   1121: goto -326 -> 795
      //   1124: aload_0
      //   1125: aload_2
      //   1126: invokevirtual 170	com/b/b/g:k	()Ljava/lang/String;
      //   1129: putfield 73	com/c/a/a/a/d/a/a/a$a:o	Ljava/lang/String;
      //   1132: goto -337 -> 795
      //   1135: getstatic 48	com/c/a/a/a/d/a/a/a$a:p	Lcom/c/a/a/a/d/a/a/a$a;
      //   1138: astore_2
      //   1139: goto -1063 -> 76
      //   1142: getstatic 180	com/c/a/a/a/d/a/a/a$a:q	Lcom/b/b/x;
      //   1145: ifnonnull +30 -> 1175
      //   1148: ldc 2
      //   1150: monitorenter
      //   1151: getstatic 180	com/c/a/a/a/d/a/a/a$a:q	Lcom/b/b/x;
      //   1154: ifnonnull +18 -> 1172
      //   1157: new 182	com/b/b/m$b
      //   1160: astore_2
      //   1161: aload_2
      //   1162: getstatic 48	com/c/a/a/a/d/a/a/a$a:p	Lcom/c/a/a/a/d/a/a/a$a;
      //   1165: invokespecial 185	com/b/b/m$b:<init>	(Lcom/b/b/m;)V
      //   1168: aload_2
      //   1169: putstatic 180	com/c/a/a/a/d/a/a/a$a:q	Lcom/b/b/x;
      //   1172: ldc 2
      //   1174: monitorexit
      //   1175: getstatic 180	com/c/a/a/a/d/a/a/a$a:q	Lcom/b/b/x;
      //   1178: astore_2
      //   1179: goto -1103 -> 76
      //   1182: astore_2
      //   1183: ldc 2
      //   1185: monitorexit
      //   1186: aload_2
      //   1187: athrow
      // Local variable table:
      //   start	length	slot	name	signature
      //   0	1188	0	this	a
      //   0	1188	1	paramInt	int
      //   0	1188	2	paramObject1	Object
      //   0	1188	3	paramObject2	Object
      //   4	910	4	i1	int
      //   152	620	5	bool1	boolean
      //   170	608	6	bool2	boolean
      //   1	610	7	bool3	boolean
      //   115	919	8	localObject	Object
      // Exception table:
      //   from	to	target	type
      //   799	805	975	com/b/b/o
      //   912	921	975	com/b/b/o
      //   931	954	975	com/b/b/o
      //   954	972	975	com/b/b/o
      //   994	1002	975	com/b/b/o
      //   1036	1044	975	com/b/b/o
      //   1047	1055	975	com/b/b/o
      //   1058	1066	975	com/b/b/o
      //   1069	1077	975	com/b/b/o
      //   1080	1088	975	com/b/b/o
      //   1091	1099	975	com/b/b/o
      //   1102	1110	975	com/b/b/o
      //   1113	1121	975	com/b/b/o
      //   1124	1132	975	com/b/b/o
      //   799	805	991	finally
      //   912	921	991	finally
      //   931	954	991	finally
      //   954	972	991	finally
      //   976	991	991	finally
      //   994	1002	991	finally
      //   1006	1036	991	finally
      //   1036	1044	991	finally
      //   1047	1055	991	finally
      //   1058	1066	991	finally
      //   1069	1077	991	finally
      //   1080	1088	991	finally
      //   1091	1099	991	finally
      //   1102	1110	991	finally
      //   1113	1121	991	finally
      //   1124	1132	991	finally
      //   799	805	1005	java/io/IOException
      //   912	921	1005	java/io/IOException
      //   931	954	1005	java/io/IOException
      //   954	972	1005	java/io/IOException
      //   994	1002	1005	java/io/IOException
      //   1036	1044	1005	java/io/IOException
      //   1047	1055	1005	java/io/IOException
      //   1058	1066	1005	java/io/IOException
      //   1069	1077	1005	java/io/IOException
      //   1080	1088	1005	java/io/IOException
      //   1091	1099	1005	java/io/IOException
      //   1102	1110	1005	java/io/IOException
      //   1113	1121	1005	java/io/IOException
      //   1124	1132	1005	java/io/IOException
      //   1151	1172	1182	finally
      //   1172	1175	1182	finally
      //   1183	1186	1182	finally
    }
    
    public final void a(h paramh)
    {
      for (int i1 = 0; i1 < this.e.size(); i1++) {
        paramh.a(1, (u)this.e.get(i1));
      }
      if (!this.f.isEmpty()) {
        paramh.a(2, this.f);
      }
      if (this.g != 0) {
        paramh.c(3, this.g);
      }
      if (this.h != 0) {
        paramh.c(4, this.h);
      }
      if (this.i != 0) {
        paramh.c(5, this.i);
      }
      if (!this.j.isEmpty()) {
        paramh.a(6, this.j);
      }
      if (!this.k.isEmpty()) {
        paramh.a(7, this.k);
      }
      if (!this.l.isEmpty()) {
        paramh.a(8, this.l);
      }
      if (!this.m.isEmpty()) {
        paramh.a(9, this.m);
      }
      if (!this.n.isEmpty()) {
        paramh.a(10, this.n);
      }
      if (!this.o.isEmpty()) {
        paramh.a(11, this.o);
      }
    }
    
    public final int k()
    {
      int i2 = this.c;
      if (i2 != -1) {}
      for (;;)
      {
        return i2;
        i2 = 0;
        int i1 = 0;
        while (i2 < this.e.size())
        {
          i1 += h.b(1, (u)this.e.get(i2));
          i2++;
        }
        i2 = i1;
        if (!this.f.isEmpty()) {
          i2 = i1 + h.b(2, this.f);
        }
        i1 = i2;
        if (this.g != 0) {
          i1 = i2 + h.d(3, this.g);
        }
        int i3 = i1;
        if (this.h != 0) {
          i3 = i1 + h.d(4, this.h);
        }
        i2 = i3;
        if (this.i != 0) {
          i2 = i3 + h.d(5, this.i);
        }
        i1 = i2;
        if (!this.j.isEmpty()) {
          i1 = i2 + h.b(6, this.j);
        }
        i2 = i1;
        if (!this.k.isEmpty()) {
          i2 = i1 + h.b(7, this.k);
        }
        i1 = i2;
        if (!this.l.isEmpty()) {
          i1 = i2 + h.b(8, this.l);
        }
        i2 = i1;
        if (!this.m.isEmpty()) {
          i2 = i1 + h.b(9, this.m);
        }
        i1 = i2;
        if (!this.n.isEmpty()) {
          i1 = i2 + h.b(10, this.n);
        }
        i2 = i1;
        if (!this.o.isEmpty()) {
          i2 = i1 + h.b(11, this.o);
        }
        this.c = i2;
      }
    }
    
    public static final class a
      extends m.a<a.a, a>
      implements a.b
    {
      private a()
      {
        super();
      }
      
      public final a a(int paramInt)
      {
        b();
        a.a.a((a.a)this.a, paramInt);
        return this;
      }
      
      public final a a(a.a.b paramb)
      {
        b();
        a.a.a((a.a)this.a, paramb);
        return this;
      }
      
      public final a a(String paramString)
      {
        b();
        a.a.a((a.a)this.a, paramString);
        return this;
      }
      
      public final a b(int paramInt)
      {
        b();
        a.a.b((a.a)this.a, paramInt);
        return this;
      }
      
      public final a b(String paramString)
      {
        b();
        a.a.b((a.a)this.a, paramString);
        return this;
      }
      
      public final a c(String paramString)
      {
        b();
        a.a.c((a.a)this.a, paramString);
        return this;
      }
      
      public final a d(String paramString)
      {
        b();
        a.a.d((a.a)this.a, paramString);
        return this;
      }
      
      public final a e(String paramString)
      {
        b();
        a.a.e((a.a)this.a, paramString);
        return this;
      }
      
      public final a f(String paramString)
      {
        b();
        a.a.f((a.a)this.a, paramString);
        return this;
      }
      
      public final a g(String paramString)
      {
        b();
        a.a.g((a.a)this.a, paramString);
        return this;
      }
    }
    
    public static final class b
      extends m<b, a>
      implements a.a.c
    {
      private static final b h;
      private static volatile x<b> i;
      private String d = "";
      private String e = "";
      private String f = "";
      private int g;
      
      static
      {
        b localb = new b();
        h = localb;
        localb.e();
      }
      
      public static a l()
      {
        return (a)h.g();
      }
      
      public static x<b> m()
      {
        return h.c();
      }
      
      /* Error */
      protected final Object a(int paramInt, Object paramObject1, Object paramObject2)
      {
        // Byte code:
        //   0: iconst_1
        //   1: istore 7
        //   3: iconst_0
        //   4: istore 4
        //   6: getstatic 76	com/c/a/a/a/d/a/a/a$1:a	[I
        //   9: iload_1
        //   10: iconst_1
        //   11: isub
        //   12: iaload
        //   13: tableswitch	default:+47->60, 1:+55->68, 2:+65->78, 3:+72->85, 4:+77->90, 5:+89->102, 6:+357->370, 7:+540->553, 8:+547->560
        //   60: new 78	java/lang/UnsupportedOperationException
        //   63: dup
        //   64: invokespecial 79	java/lang/UnsupportedOperationException:<init>	()V
        //   67: athrow
        //   68: new 2	com/c/a/a/a/d/a/a/a$a$b
        //   71: dup
        //   72: invokespecial 31	com/c/a/a/a/d/a/a/a$a$b:<init>	()V
        //   75: astore_2
        //   76: aload_2
        //   77: areturn
        //   78: getstatic 33	com/c/a/a/a/d/a/a/a$a$b:h	Lcom/c/a/a/a/d/a/a/a$a$b;
        //   81: astore_2
        //   82: goto -6 -> 76
        //   85: aconst_null
        //   86: astore_2
        //   87: goto -11 -> 76
        //   90: new 15	com/c/a/a/a/d/a/a/a$a$b$a
        //   93: dup
        //   94: iconst_0
        //   95: invokespecial 82	com/c/a/a/a/d/a/a/a$a$b$a:<init>	(B)V
        //   98: astore_2
        //   99: goto -23 -> 76
        //   102: aload_2
        //   103: checkcast 84	com/b/b/m$j
        //   106: astore_2
        //   107: aload_3
        //   108: checkcast 2	com/c/a/a/a/d/a/a/a$a$b
        //   111: astore_3
        //   112: aload_0
        //   113: getfield 41	com/c/a/a/a/d/a/a/a$a$b:d	Ljava/lang/String;
        //   116: invokevirtual 90	java/lang/String:isEmpty	()Z
        //   119: ifne +203 -> 322
        //   122: iconst_1
        //   123: istore 5
        //   125: aload_0
        //   126: getfield 41	com/c/a/a/a/d/a/a/a$a$b:d	Ljava/lang/String;
        //   129: astore 8
        //   131: aload_3
        //   132: getfield 41	com/c/a/a/a/d/a/a/a$a$b:d	Ljava/lang/String;
        //   135: invokevirtual 90	java/lang/String:isEmpty	()Z
        //   138: ifne +190 -> 328
        //   141: iconst_1
        //   142: istore 6
        //   144: aload_0
        //   145: aload_2
        //   146: iload 5
        //   148: aload 8
        //   150: iload 6
        //   152: aload_3
        //   153: getfield 41	com/c/a/a/a/d/a/a/a$a$b:d	Ljava/lang/String;
        //   156: invokeinterface 93 5 0
        //   161: putfield 41	com/c/a/a/a/d/a/a/a$a$b:d	Ljava/lang/String;
        //   164: aload_0
        //   165: getfield 43	com/c/a/a/a/d/a/a/a$a$b:e	Ljava/lang/String;
        //   168: invokevirtual 90	java/lang/String:isEmpty	()Z
        //   171: ifne +163 -> 334
        //   174: iconst_1
        //   175: istore 5
        //   177: aload_0
        //   178: getfield 43	com/c/a/a/a/d/a/a/a$a$b:e	Ljava/lang/String;
        //   181: astore 8
        //   183: aload_3
        //   184: getfield 43	com/c/a/a/a/d/a/a/a$a$b:e	Ljava/lang/String;
        //   187: invokevirtual 90	java/lang/String:isEmpty	()Z
        //   190: ifne +150 -> 340
        //   193: iconst_1
        //   194: istore 6
        //   196: aload_0
        //   197: aload_2
        //   198: iload 5
        //   200: aload 8
        //   202: iload 6
        //   204: aload_3
        //   205: getfield 43	com/c/a/a/a/d/a/a/a$a$b:e	Ljava/lang/String;
        //   208: invokeinterface 93 5 0
        //   213: putfield 43	com/c/a/a/a/d/a/a/a$a$b:e	Ljava/lang/String;
        //   216: aload_0
        //   217: getfield 45	com/c/a/a/a/d/a/a/a$a$b:f	Ljava/lang/String;
        //   220: invokevirtual 90	java/lang/String:isEmpty	()Z
        //   223: ifne +123 -> 346
        //   226: iconst_1
        //   227: istore 5
        //   229: aload_0
        //   230: getfield 45	com/c/a/a/a/d/a/a/a$a$b:f	Ljava/lang/String;
        //   233: astore 8
        //   235: aload_3
        //   236: getfield 45	com/c/a/a/a/d/a/a/a$a$b:f	Ljava/lang/String;
        //   239: invokevirtual 90	java/lang/String:isEmpty	()Z
        //   242: ifne +110 -> 352
        //   245: iconst_1
        //   246: istore 6
        //   248: aload_0
        //   249: aload_2
        //   250: iload 5
        //   252: aload 8
        //   254: iload 6
        //   256: aload_3
        //   257: getfield 45	com/c/a/a/a/d/a/a/a$a$b:f	Ljava/lang/String;
        //   260: invokeinterface 93 5 0
        //   265: putfield 45	com/c/a/a/a/d/a/a/a$a$b:f	Ljava/lang/String;
        //   268: aload_0
        //   269: getfield 48	com/c/a/a/a/d/a/a/a$a$b:g	I
        //   272: ifeq +86 -> 358
        //   275: iconst_1
        //   276: istore 5
        //   278: aload_0
        //   279: getfield 48	com/c/a/a/a/d/a/a/a$a$b:g	I
        //   282: istore_1
        //   283: aload_3
        //   284: getfield 48	com/c/a/a/a/d/a/a/a$a$b:g	I
        //   287: ifeq +77 -> 364
        //   290: iload 7
        //   292: istore 6
        //   294: aload_0
        //   295: aload_2
        //   296: iload 5
        //   298: iload_1
        //   299: iload 6
        //   301: aload_3
        //   302: getfield 48	com/c/a/a/a/d/a/a/a$a$b:g	I
        //   305: invokeinterface 96 5 0
        //   310: putfield 48	com/c/a/a/a/d/a/a/a$a$b:g	I
        //   313: getstatic 101	com/b/b/m$h:a	Lcom/b/b/m$h;
        //   316: astore_2
        //   317: aload_0
        //   318: astore_2
        //   319: goto -243 -> 76
        //   322: iconst_0
        //   323: istore 5
        //   325: goto -200 -> 125
        //   328: iconst_0
        //   329: istore 6
        //   331: goto -187 -> 144
        //   334: iconst_0
        //   335: istore 5
        //   337: goto -160 -> 177
        //   340: iconst_0
        //   341: istore 6
        //   343: goto -147 -> 196
        //   346: iconst_0
        //   347: istore 5
        //   349: goto -120 -> 229
        //   352: iconst_0
        //   353: istore 6
        //   355: goto -107 -> 248
        //   358: iconst_0
        //   359: istore 5
        //   361: goto -83 -> 278
        //   364: iconst_0
        //   365: istore 6
        //   367: goto -73 -> 294
        //   370: aload_2
        //   371: checkcast 103	com/b/b/g
        //   374: astore_2
        //   375: iload 4
        //   377: istore_1
        //   378: iload_1
        //   379: ifne +174 -> 553
        //   382: aload_2
        //   383: invokevirtual 106	com/b/b/g:a	()I
        //   386: istore 4
        //   388: iload 4
        //   390: lookupswitch	default:+50->440, 0:+64->454, 10:+69->459, 18:+99->489, 26:+141->531, 32:+152->542
        //   440: aload_2
        //   441: iload 4
        //   443: invokevirtual 109	com/b/b/g:b	(I)Z
        //   446: ifne -68 -> 378
        //   449: iconst_1
        //   450: istore_1
        //   451: goto -73 -> 378
        //   454: iconst_1
        //   455: istore_1
        //   456: goto -78 -> 378
        //   459: aload_0
        //   460: aload_2
        //   461: invokevirtual 113	com/b/b/g:k	()Ljava/lang/String;
        //   464: putfield 41	com/c/a/a/a/d/a/a/a$a$b:d	Ljava/lang/String;
        //   467: goto -89 -> 378
        //   470: astore_3
        //   471: new 115	java/lang/RuntimeException
        //   474: astore_2
        //   475: aload_2
        //   476: aload_3
        //   477: aload_0
        //   478: invokevirtual 118	com/b/b/o:a	(Lcom/b/b/u;)Lcom/b/b/o;
        //   481: invokespecial 121	java/lang/RuntimeException:<init>	(Ljava/lang/Throwable;)V
        //   484: aload_2
        //   485: athrow
        //   486: astore_2
        //   487: aload_2
        //   488: athrow
        //   489: aload_0
        //   490: aload_2
        //   491: invokevirtual 113	com/b/b/g:k	()Ljava/lang/String;
        //   494: putfield 43	com/c/a/a/a/d/a/a/a$a$b:e	Ljava/lang/String;
        //   497: goto -119 -> 378
        //   500: astore_3
        //   501: new 115	java/lang/RuntimeException
        //   504: astore 8
        //   506: new 69	com/b/b/o
        //   509: astore_2
        //   510: aload_2
        //   511: aload_3
        //   512: invokevirtual 124	java/io/IOException:getMessage	()Ljava/lang/String;
        //   515: invokespecial 127	com/b/b/o:<init>	(Ljava/lang/String;)V
        //   518: aload 8
        //   520: aload_2
        //   521: aload_0
        //   522: invokevirtual 118	com/b/b/o:a	(Lcom/b/b/u;)Lcom/b/b/o;
        //   525: invokespecial 121	java/lang/RuntimeException:<init>	(Ljava/lang/Throwable;)V
        //   528: aload 8
        //   530: athrow
        //   531: aload_0
        //   532: aload_2
        //   533: invokevirtual 113	com/b/b/g:k	()Ljava/lang/String;
        //   536: putfield 45	com/c/a/a/a/d/a/a/a$a$b:f	Ljava/lang/String;
        //   539: goto -161 -> 378
        //   542: aload_0
        //   543: aload_2
        //   544: invokevirtual 130	com/b/b/g:q	()I
        //   547: putfield 48	com/c/a/a/a/d/a/a/a$a$b:g	I
        //   550: goto -172 -> 378
        //   553: getstatic 33	com/c/a/a/a/d/a/a/a$a$b:h	Lcom/c/a/a/a/d/a/a/a$a$b;
        //   556: astore_2
        //   557: goto -481 -> 76
        //   560: getstatic 132	com/c/a/a/a/d/a/a/a$a$b:i	Lcom/b/b/x;
        //   563: ifnonnull +30 -> 593
        //   566: ldc 2
        //   568: monitorenter
        //   569: getstatic 132	com/c/a/a/a/d/a/a/a$a$b:i	Lcom/b/b/x;
        //   572: ifnonnull +18 -> 590
        //   575: new 134	com/b/b/m$b
        //   578: astore_2
        //   579: aload_2
        //   580: getstatic 33	com/c/a/a/a/d/a/a/a$a$b:h	Lcom/c/a/a/a/d/a/a/a$a$b;
        //   583: invokespecial 137	com/b/b/m$b:<init>	(Lcom/b/b/m;)V
        //   586: aload_2
        //   587: putstatic 132	com/c/a/a/a/d/a/a/a$a$b:i	Lcom/b/b/x;
        //   590: ldc 2
        //   592: monitorexit
        //   593: getstatic 132	com/c/a/a/a/d/a/a/a$a$b:i	Lcom/b/b/x;
        //   596: astore_2
        //   597: goto -521 -> 76
        //   600: astore_2
        //   601: ldc 2
        //   603: monitorexit
        //   604: aload_2
        //   605: athrow
        // Local variable table:
        //   start	length	slot	name	signature
        //   0	606	0	this	b
        //   0	606	1	paramInt	int
        //   0	606	2	paramObject1	Object
        //   0	606	3	paramObject2	Object
        //   4	438	4	j	int
        //   123	237	5	bool1	boolean
        //   142	224	6	bool2	boolean
        //   1	290	7	bool3	boolean
        //   129	400	8	localObject	Object
        // Exception table:
        //   from	to	target	type
        //   382	388	470	com/b/b/o
        //   440	449	470	com/b/b/o
        //   459	467	470	com/b/b/o
        //   489	497	470	com/b/b/o
        //   531	539	470	com/b/b/o
        //   542	550	470	com/b/b/o
        //   382	388	486	finally
        //   440	449	486	finally
        //   459	467	486	finally
        //   471	486	486	finally
        //   489	497	486	finally
        //   501	531	486	finally
        //   531	539	486	finally
        //   542	550	486	finally
        //   382	388	500	java/io/IOException
        //   440	449	500	java/io/IOException
        //   459	467	500	java/io/IOException
        //   489	497	500	java/io/IOException
        //   531	539	500	java/io/IOException
        //   542	550	500	java/io/IOException
        //   569	590	600	finally
        //   590	593	600	finally
        //   601	604	600	finally
      }
      
      public final void a(h paramh)
      {
        if (!this.d.isEmpty()) {
          paramh.a(1, this.d);
        }
        if (!this.e.isEmpty()) {
          paramh.a(2, this.e);
        }
        if (!this.f.isEmpty()) {
          paramh.a(3, this.f);
        }
        if (this.g != 0) {
          paramh.c(4, this.g);
        }
      }
      
      public final int k()
      {
        int k = this.c;
        if (k != -1) {}
        for (;;)
        {
          return k;
          int j = 0;
          if (!this.d.isEmpty()) {
            j = h.b(1, this.d) + 0;
          }
          k = j;
          if (!this.e.isEmpty()) {
            k = j + h.b(2, this.e);
          }
          j = k;
          if (!this.f.isEmpty()) {
            j = k + h.b(3, this.f);
          }
          k = j;
          if (this.g != 0) {
            k = j + h.d(4, this.g);
          }
          this.c = k;
        }
      }
      
      public static final class a
        extends m.a<a.a.b, a>
        implements a.a.c
      {
        private a()
        {
          super();
        }
        
        public final a a(int paramInt)
        {
          b();
          a.a.b.a((a.a.b)this.a, paramInt);
          return this;
        }
        
        public final a a(String paramString)
        {
          b();
          a.a.b.a((a.a.b)this.a, paramString);
          return this;
        }
        
        public final a b(String paramString)
        {
          b();
          a.a.b.b((a.a.b)this.a, paramString);
          return this;
        }
        
        public final a c(String paramString)
        {
          b();
          a.a.b.c((a.a.b)this.a, paramString);
          return this;
        }
      }
    }
    
    public static abstract interface c
      extends v
    {}
  }
  
  public static abstract interface b
    extends v
  {}
}


/* Location:              /Users/hanlian/Downloads/WiFi万能钥匙dex1-dex2jar.jar!/com/c/a/a/a/d/a/a/a.class
 * Java compiler version: 6 (50.0)
 * JD-Core Version:       0.7.1
 */