package com.lantern.wifiseccheck;

import java.util.Map;

class WifiSecCheckImpl$5
  implements Runnable
{
  WifiSecCheckImpl$5(WifiSecCheckImpl paramWifiSecCheckImpl, String paramString, Map paramMap, String[] paramArrayOfString) {}
  
  /* Error */
  public void run()
  {
    // Byte code:
    //   0: aload_0
    //   1: getfield 20	com/lantern/wifiseccheck/WifiSecCheckImpl$5:val$url	Ljava/lang/String;
    //   4: invokestatic 37	com/lantern/wifiseccheck/SecCheckHttpApi:getHostCertsViaConnection	(Ljava/lang/String;)[Ljava/security/cert/Certificate;
    //   7: astore 5
    //   9: aload 5
    //   11: ifnull +375 -> 386
    //   14: aload 5
    //   16: arraylength
    //   17: ifle +369 -> 386
    //   20: aload 5
    //   22: iconst_0
    //   23: aaload
    //   24: invokevirtual 43	java/security/cert/Certificate:getEncoded	()[B
    //   27: iconst_0
    //   28: invokestatic 49	android/util/Base64:encodeToString	([BI)Ljava/lang/String;
    //   31: astore_3
    //   32: aload_3
    //   33: ldc 51
    //   35: ldc 53
    //   37: invokevirtual 59	java/lang/String:replaceAll	(Ljava/lang/String;Ljava/lang/String;)Ljava/lang/String;
    //   40: astore 4
    //   42: aload 4
    //   44: astore_3
    //   45: aload_3
    //   46: ldc 61
    //   48: invokestatic 66	com/lantern/wifiseccheck/Md5Utils:Digest	(Ljava/lang/String;Ljava/lang/String;)Ljava/lang/String;
    //   51: astore 7
    //   53: aload_0
    //   54: getfield 22	com/lantern/wifiseccheck/WifiSecCheckImpl$5:val$sslExtraDetails	Ljava/util/Map;
    //   57: astore 6
    //   59: aload 6
    //   61: monitorenter
    //   62: aload 5
    //   64: ifnull +9 -> 73
    //   67: aload 5
    //   69: arraylength
    //   70: ifne +202 -> 272
    //   73: aload_0
    //   74: getfield 22	com/lantern/wifiseccheck/WifiSecCheckImpl$5:val$sslExtraDetails	Ljava/util/Map;
    //   77: aload_0
    //   78: getfield 20	com/lantern/wifiseccheck/WifiSecCheckImpl$5:val$url	Ljava/lang/String;
    //   81: ldc 53
    //   83: invokeinterface 72 3 0
    //   88: pop
    //   89: aload_0
    //   90: getfield 22	com/lantern/wifiseccheck/WifiSecCheckImpl$5:val$sslExtraDetails	Ljava/util/Map;
    //   93: invokeinterface 76 1 0
    //   98: aload_0
    //   99: getfield 24	com/lantern/wifiseccheck/WifiSecCheckImpl$5:val$urls	[Ljava/lang/String;
    //   102: arraylength
    //   103: if_icmpne +27 -> 130
    //   106: ldc 78
    //   108: ldc 80
    //   110: invokestatic 86	com/lantern/wifiseccheck/LogUtils:d	(Ljava/lang/String;Ljava/lang/String;)V
    //   113: aload_0
    //   114: getfield 18	com/lantern/wifiseccheck/WifiSecCheckImpl$5:this$0	Lcom/lantern/wifiseccheck/WifiSecCheckImpl;
    //   117: invokestatic 92	com/lantern/wifiseccheck/WifiSecCheckImpl:access$000	(Lcom/lantern/wifiseccheck/WifiSecCheckImpl;)Lcom/lantern/wifiseccheck/WifiSecCheckManager$WifiCheckListener;
    //   120: getfield 98	com/lantern/wifiseccheck/WifiSecCheckManager$WifiCheckListener:wifiSecCheckCollectWarningmsg	Lcom/lantern/wifiseccheck/warningmsg/WifiSecCheckCollectWarningmsg;
    //   123: aload_0
    //   124: getfield 22	com/lantern/wifiseccheck/WifiSecCheckImpl$5:val$sslExtraDetails	Ljava/util/Map;
    //   127: invokevirtual 104	com/lantern/wifiseccheck/warningmsg/WifiSecCheckCollectWarningmsg:setSslExtraDetails	(Ljava/util/Map;)V
    //   130: new 106	java/lang/StringBuilder
    //   133: astore 4
    //   135: aload 4
    //   137: ldc 108
    //   139: invokespecial 111	java/lang/StringBuilder:<init>	(Ljava/lang/String;)V
    //   142: ldc 78
    //   144: aload 4
    //   146: aload_3
    //   147: invokevirtual 115	java/lang/StringBuilder:append	(Ljava/lang/String;)Ljava/lang/StringBuilder;
    //   150: ldc 117
    //   152: invokevirtual 115	java/lang/StringBuilder:append	(Ljava/lang/String;)Ljava/lang/StringBuilder;
    //   155: aload 7
    //   157: invokevirtual 115	java/lang/StringBuilder:append	(Ljava/lang/String;)Ljava/lang/StringBuilder;
    //   160: ldc 117
    //   162: invokevirtual 115	java/lang/StringBuilder:append	(Ljava/lang/String;)Ljava/lang/StringBuilder;
    //   165: aload_0
    //   166: getfield 20	com/lantern/wifiseccheck/WifiSecCheckImpl$5:val$url	Ljava/lang/String;
    //   169: invokevirtual 115	java/lang/StringBuilder:append	(Ljava/lang/String;)Ljava/lang/StringBuilder;
    //   172: invokevirtual 121	java/lang/StringBuilder:toString	()Ljava/lang/String;
    //   175: invokestatic 86	com/lantern/wifiseccheck/LogUtils:d	(Ljava/lang/String;Ljava/lang/String;)V
    //   178: aload 6
    //   180: monitorexit
    //   181: new 123	com/lantern/wifiseccheck/WifiSecCheckImpl$ItemResult
    //   184: dup
    //   185: aload_0
    //   186: getfield 18	com/lantern/wifiseccheck/WifiSecCheckImpl$5:this$0	Lcom/lantern/wifiseccheck/WifiSecCheckImpl;
    //   189: aconst_null
    //   190: invokespecial 126	com/lantern/wifiseccheck/WifiSecCheckImpl$ItemResult:<init>	(Lcom/lantern/wifiseccheck/WifiSecCheckImpl;Lcom/lantern/wifiseccheck/WifiSecCheckImpl$1;)V
    //   193: astore_3
    //   194: aload_3
    //   195: aload_0
    //   196: getfield 20	com/lantern/wifiseccheck/WifiSecCheckImpl$5:val$url	Ljava/lang/String;
    //   199: putfield 129	com/lantern/wifiseccheck/WifiSecCheckImpl$ItemResult:key	Ljava/lang/String;
    //   202: aload_3
    //   203: aload 7
    //   205: putfield 132	com/lantern/wifiseccheck/WifiSecCheckImpl$ItemResult:value	Ljava/lang/String;
    //   208: new 134	android/os/Message
    //   211: dup
    //   212: invokespecial 135	android/os/Message:<init>	()V
    //   215: astore 4
    //   217: aload 4
    //   219: aload_3
    //   220: putfield 139	android/os/Message:obj	Ljava/lang/Object;
    //   223: aload 4
    //   225: iconst_4
    //   226: putfield 143	android/os/Message:arg1	I
    //   229: aload 4
    //   231: bipush 15
    //   233: putfield 146	android/os/Message:what	I
    //   236: aload_0
    //   237: getfield 18	com/lantern/wifiseccheck/WifiSecCheckImpl$5:this$0	Lcom/lantern/wifiseccheck/WifiSecCheckImpl;
    //   240: invokestatic 150	com/lantern/wifiseccheck/WifiSecCheckImpl:access$400	(Lcom/lantern/wifiseccheck/WifiSecCheckImpl;)Landroid/os/Handler;
    //   243: ifnull +16 -> 259
    //   246: aload_0
    //   247: getfield 18	com/lantern/wifiseccheck/WifiSecCheckImpl$5:this$0	Lcom/lantern/wifiseccheck/WifiSecCheckImpl;
    //   250: invokestatic 150	com/lantern/wifiseccheck/WifiSecCheckImpl:access$400	(Lcom/lantern/wifiseccheck/WifiSecCheckImpl;)Landroid/os/Handler;
    //   253: aload 4
    //   255: invokevirtual 156	android/os/Handler:sendMessage	(Landroid/os/Message;)Z
    //   258: pop
    //   259: return
    //   260: astore 4
    //   262: aconst_null
    //   263: astore_3
    //   264: aload 4
    //   266: invokevirtual 159	java/security/cert/CertificateEncodingException:printStackTrace	()V
    //   269: goto -224 -> 45
    //   272: aload 5
    //   274: arraylength
    //   275: istore_2
    //   276: ldc 53
    //   278: astore 4
    //   280: iconst_0
    //   281: istore_1
    //   282: iload_1
    //   283: iload_2
    //   284: if_icmpge +72 -> 356
    //   287: aload 5
    //   289: iload_1
    //   290: aaload
    //   291: astore 8
    //   293: new 106	java/lang/StringBuilder
    //   296: astore 9
    //   298: aload 9
    //   300: invokespecial 160	java/lang/StringBuilder:<init>	()V
    //   303: aload 9
    //   305: aload 4
    //   307: invokevirtual 115	java/lang/StringBuilder:append	(Ljava/lang/String;)Ljava/lang/StringBuilder;
    //   310: aload 8
    //   312: invokevirtual 161	java/security/cert/Certificate:toString	()Ljava/lang/String;
    //   315: invokevirtual 115	java/lang/StringBuilder:append	(Ljava/lang/String;)Ljava/lang/StringBuilder;
    //   318: invokevirtual 121	java/lang/StringBuilder:toString	()Ljava/lang/String;
    //   321: astore 4
    //   323: new 106	java/lang/StringBuilder
    //   326: astore 8
    //   328: aload 8
    //   330: invokespecial 160	java/lang/StringBuilder:<init>	()V
    //   333: aload 8
    //   335: aload 4
    //   337: invokevirtual 115	java/lang/StringBuilder:append	(Ljava/lang/String;)Ljava/lang/StringBuilder;
    //   340: ldc -93
    //   342: invokevirtual 115	java/lang/StringBuilder:append	(Ljava/lang/String;)Ljava/lang/StringBuilder;
    //   345: invokevirtual 121	java/lang/StringBuilder:toString	()Ljava/lang/String;
    //   348: astore 4
    //   350: iinc 1 1
    //   353: goto -71 -> 282
    //   356: aload_0
    //   357: getfield 22	com/lantern/wifiseccheck/WifiSecCheckImpl$5:val$sslExtraDetails	Ljava/util/Map;
    //   360: aload_0
    //   361: getfield 20	com/lantern/wifiseccheck/WifiSecCheckImpl$5:val$url	Ljava/lang/String;
    //   364: aload 4
    //   366: invokeinterface 72 3 0
    //   371: pop
    //   372: goto -283 -> 89
    //   375: astore_3
    //   376: aload 6
    //   378: monitorexit
    //   379: aload_3
    //   380: athrow
    //   381: astore 4
    //   383: goto -119 -> 264
    //   386: aconst_null
    //   387: astore_3
    //   388: goto -343 -> 45
    // Local variable table:
    //   start	length	slot	name	signature
    //   0	391	0	this	5
    //   281	70	1	i	int
    //   275	10	2	j	int
    //   31	233	3	localObject1	Object
    //   375	5	3	localObject2	Object
    //   387	1	3	localObject3	Object
    //   40	214	4	localObject4	Object
    //   260	5	4	localCertificateEncodingException1	java.security.cert.CertificateEncodingException
    //   278	87	4	str1	String
    //   381	1	4	localCertificateEncodingException2	java.security.cert.CertificateEncodingException
    //   7	281	5	arrayOfCertificate	java.security.cert.Certificate[]
    //   57	320	6	localMap	Map
    //   51	153	7	str2	String
    //   291	43	8	localObject5	Object
    //   296	8	9	localStringBuilder	StringBuilder
    // Exception table:
    //   from	to	target	type
    //   14	32	260	java/security/cert/CertificateEncodingException
    //   67	73	375	finally
    //   73	89	375	finally
    //   89	130	375	finally
    //   130	181	375	finally
    //   272	276	375	finally
    //   293	350	375	finally
    //   356	372	375	finally
    //   376	379	375	finally
    //   32	42	381	java/security/cert/CertificateEncodingException
  }
}


/* Location:              /Users/hanlian/Downloads/WiFi万能钥匙dex1-dex2jar.jar!/com/lantern/wifiseccheck/WifiSecCheckImpl$5.class
 * Java compiler version: 6 (50.0)
 * JD-Core Version:       0.7.1
 */