package cm.pass.sdk.net.a;

import cm.pass.sdk.interfaces.d;

public class b
  extends i
{
  public static boolean b = false;
  d a;
  
  public b(d paramd)
  {
    this.a = paramd;
  }
  
  /* Error */
  public void a(a.a.a.c.b paramb)
  {
    // Byte code:
    //   0: aload_0
    //   1: aload_1
    //   2: invokespecial 24	cm/pass/sdk/net/a/i:a	(La/a/a/c/b;)V
    //   5: aconst_null
    //   6: astore 21
    //   8: aconst_null
    //   9: astore 20
    //   11: aconst_null
    //   12: astore 16
    //   14: aconst_null
    //   15: astore 11
    //   17: aconst_null
    //   18: astore 17
    //   20: aconst_null
    //   21: astore 8
    //   23: aconst_null
    //   24: astore 19
    //   26: aconst_null
    //   27: astore 12
    //   29: aconst_null
    //   30: astore 13
    //   32: aconst_null
    //   33: astore 9
    //   35: aconst_null
    //   36: astore 18
    //   38: aconst_null
    //   39: astore 10
    //   41: aconst_null
    //   42: astore 23
    //   44: aconst_null
    //   45: astore 14
    //   47: aconst_null
    //   48: astore 22
    //   50: aconst_null
    //   51: astore 15
    //   53: iconst_0
    //   54: istore 5
    //   56: iconst_0
    //   57: istore 4
    //   59: iconst_0
    //   60: istore 6
    //   62: iconst_0
    //   63: istore_2
    //   64: iconst_0
    //   65: putstatic 12	cm/pass/sdk/net/a/b:b	Z
    //   68: aload 23
    //   70: astore_1
    //   71: aload 22
    //   73: astore 7
    //   75: aload_0
    //   76: getfield 28	cm/pass/sdk/net/a/b:g	Lorg/json/JSONObject;
    //   79: ldc 30
    //   81: invokevirtual 36	org/json/JSONObject:has	(Ljava/lang/String;)Z
    //   84: ifeq +21 -> 105
    //   87: aload 23
    //   89: astore_1
    //   90: aload 22
    //   92: astore 7
    //   94: aload_0
    //   95: getfield 28	cm/pass/sdk/net/a/b:g	Lorg/json/JSONObject;
    //   98: ldc 30
    //   100: invokevirtual 40	org/json/JSONObject:getString	(Ljava/lang/String;)Ljava/lang/String;
    //   103: astore 14
    //   105: aload 14
    //   107: astore_1
    //   108: aload 22
    //   110: astore 7
    //   112: aload_0
    //   113: getfield 28	cm/pass/sdk/net/a/b:g	Lorg/json/JSONObject;
    //   116: ldc 42
    //   118: invokevirtual 36	org/json/JSONObject:has	(Ljava/lang/String;)Z
    //   121: ifeq +21 -> 142
    //   124: aload 14
    //   126: astore_1
    //   127: aload 22
    //   129: astore 7
    //   131: aload_0
    //   132: getfield 28	cm/pass/sdk/net/a/b:g	Lorg/json/JSONObject;
    //   135: ldc 42
    //   137: invokevirtual 40	org/json/JSONObject:getString	(Ljava/lang/String;)Ljava/lang/String;
    //   140: astore 15
    //   142: aload 14
    //   144: astore_1
    //   145: aload 15
    //   147: astore 7
    //   149: aload_0
    //   150: getfield 45	cm/pass/sdk/net/a/b:c	Z
    //   153: ifeq +322 -> 475
    //   156: aload 14
    //   158: astore_1
    //   159: aload 15
    //   161: astore 7
    //   163: aload_0
    //   164: getfield 28	cm/pass/sdk/net/a/b:g	Lorg/json/JSONObject;
    //   167: ldc 47
    //   169: invokevirtual 50	org/json/JSONObject:getBoolean	(Ljava/lang/String;)Z
    //   172: istore_3
    //   173: iload 6
    //   175: istore 4
    //   177: aload_0
    //   178: getfield 28	cm/pass/sdk/net/a/b:g	Lorg/json/JSONObject;
    //   181: ldc 52
    //   183: invokevirtual 36	org/json/JSONObject:has	(Ljava/lang/String;)Z
    //   186: ifeq +17 -> 203
    //   189: iload 6
    //   191: istore 4
    //   193: aload_0
    //   194: getfield 28	cm/pass/sdk/net/a/b:g	Lorg/json/JSONObject;
    //   197: ldc 52
    //   199: invokevirtual 50	org/json/JSONObject:getBoolean	(Ljava/lang/String;)Z
    //   202: istore_2
    //   203: aload 11
    //   205: astore_1
    //   206: iload_2
    //   207: istore 4
    //   209: aload_0
    //   210: getfield 28	cm/pass/sdk/net/a/b:g	Lorg/json/JSONObject;
    //   213: ldc 54
    //   215: invokevirtual 36	org/json/JSONObject:has	(Ljava/lang/String;)Z
    //   218: ifeq +16 -> 234
    //   221: iload_2
    //   222: istore 4
    //   224: aload_0
    //   225: getfield 28	cm/pass/sdk/net/a/b:g	Lorg/json/JSONObject;
    //   228: ldc 54
    //   230: invokevirtual 40	org/json/JSONObject:getString	(Ljava/lang/String;)Ljava/lang/String;
    //   233: astore_1
    //   234: aload 9
    //   236: astore 7
    //   238: aload_0
    //   239: getfield 28	cm/pass/sdk/net/a/b:g	Lorg/json/JSONObject;
    //   242: ldc 56
    //   244: invokevirtual 36	org/json/JSONObject:has	(Ljava/lang/String;)Z
    //   247: ifeq +14 -> 261
    //   250: aload_0
    //   251: getfield 28	cm/pass/sdk/net/a/b:g	Lorg/json/JSONObject;
    //   254: ldc 56
    //   256: invokevirtual 40	org/json/JSONObject:getString	(Ljava/lang/String;)Ljava/lang/String;
    //   259: astore 7
    //   261: aload_0
    //   262: getfield 28	cm/pass/sdk/net/a/b:g	Lorg/json/JSONObject;
    //   265: ldc 58
    //   267: invokevirtual 36	org/json/JSONObject:has	(Ljava/lang/String;)Z
    //   270: ifeq +14 -> 284
    //   273: aload_0
    //   274: getfield 28	cm/pass/sdk/net/a/b:g	Lorg/json/JSONObject;
    //   277: ldc 58
    //   279: invokevirtual 40	org/json/JSONObject:getString	(Ljava/lang/String;)Ljava/lang/String;
    //   282: astore 8
    //   284: aload_0
    //   285: getfield 28	cm/pass/sdk/net/a/b:g	Lorg/json/JSONObject;
    //   288: ldc 60
    //   290: invokevirtual 40	org/json/JSONObject:getString	(Ljava/lang/String;)Ljava/lang/String;
    //   293: astore 9
    //   295: aload_0
    //   296: getfield 28	cm/pass/sdk/net/a/b:g	Lorg/json/JSONObject;
    //   299: ldc 62
    //   301: invokevirtual 40	org/json/JSONObject:getString	(Ljava/lang/String;)Ljava/lang/String;
    //   304: astore 11
    //   306: aload_0
    //   307: getfield 28	cm/pass/sdk/net/a/b:g	Lorg/json/JSONObject;
    //   310: ldc 64
    //   312: invokevirtual 36	org/json/JSONObject:has	(Ljava/lang/String;)Z
    //   315: ifeq +14 -> 329
    //   318: aload_0
    //   319: getfield 28	cm/pass/sdk/net/a/b:g	Lorg/json/JSONObject;
    //   322: ldc 64
    //   324: invokevirtual 40	org/json/JSONObject:getString	(Ljava/lang/String;)Ljava/lang/String;
    //   327: astore 10
    //   329: aload_0
    //   330: getfield 28	cm/pass/sdk/net/a/b:g	Lorg/json/JSONObject;
    //   333: ldc 66
    //   335: invokevirtual 36	org/json/JSONObject:has	(Ljava/lang/String;)Z
    //   338: ifeq +14 -> 352
    //   341: aload_0
    //   342: getfield 28	cm/pass/sdk/net/a/b:g	Lorg/json/JSONObject;
    //   345: ldc 66
    //   347: invokevirtual 40	org/json/JSONObject:getString	(Ljava/lang/String;)Ljava/lang/String;
    //   350: astore 12
    //   352: iload_2
    //   353: istore 4
    //   355: iload_3
    //   356: istore 5
    //   358: aload 10
    //   360: astore 18
    //   362: aload 7
    //   364: astore 13
    //   366: aload 12
    //   368: astore 19
    //   370: aload 8
    //   372: astore 17
    //   374: aload_1
    //   375: astore 16
    //   377: aload 11
    //   379: astore 20
    //   381: aload 9
    //   383: astore 21
    //   385: aload_0
    //   386: getfield 28	cm/pass/sdk/net/a/b:g	Lorg/json/JSONObject;
    //   389: ldc 68
    //   391: invokevirtual 36	org/json/JSONObject:has	(Ljava/lang/String;)Z
    //   394: ifeq +81 -> 475
    //   397: aload_0
    //   398: getfield 28	cm/pass/sdk/net/a/b:g	Lorg/json/JSONObject;
    //   401: ldc 68
    //   403: invokevirtual 50	org/json/JSONObject:getBoolean	(Ljava/lang/String;)Z
    //   406: putstatic 12	cm/pass/sdk/net/a/b:b	Z
    //   409: getstatic 74	java/lang/System:out	Ljava/io/PrintStream;
    //   412: astore 13
    //   414: new 76	java/lang/StringBuilder
    //   417: astore 16
    //   419: aload 16
    //   421: ldc 78
    //   423: invokespecial 81	java/lang/StringBuilder:<init>	(Ljava/lang/String;)V
    //   426: aload 13
    //   428: aload 16
    //   430: getstatic 12	cm/pass/sdk/net/a/b:b	Z
    //   433: invokevirtual 85	java/lang/StringBuilder:append	(Z)Ljava/lang/StringBuilder;
    //   436: invokevirtual 89	java/lang/StringBuilder:toString	()Ljava/lang/String;
    //   439: invokevirtual 94	java/io/PrintStream:println	(Ljava/lang/String;)V
    //   442: aload 9
    //   444: astore 21
    //   446: aload 11
    //   448: astore 20
    //   450: aload_1
    //   451: astore 16
    //   453: aload 8
    //   455: astore 17
    //   457: aload 12
    //   459: astore 19
    //   461: aload 7
    //   463: astore 13
    //   465: aload 10
    //   467: astore 18
    //   469: iload_3
    //   470: istore 5
    //   472: iload_2
    //   473: istore 4
    //   475: aload 20
    //   477: astore 11
    //   479: aload 21
    //   481: astore 12
    //   483: aload 17
    //   485: astore 8
    //   487: aload 16
    //   489: astore 7
    //   491: iload 4
    //   493: istore_3
    //   494: aload 19
    //   496: astore 10
    //   498: aload 18
    //   500: astore 9
    //   502: aload 13
    //   504: astore_1
    //   505: iload 5
    //   507: istore_2
    //   508: aload_0
    //   509: getfield 19	cm/pass/sdk/net/a/b:a	Lcm/pass/sdk/interfaces/d;
    //   512: aload_0
    //   513: getfield 45	cm/pass/sdk/net/a/b:c	Z
    //   516: aload_0
    //   517: getfield 98	cm/pass/sdk/net/a/b:d	Ljava/lang/String;
    //   520: aload_0
    //   521: getfield 101	cm/pass/sdk/net/a/b:e	Ljava/lang/String;
    //   524: iload_2
    //   525: iload_3
    //   526: aload_1
    //   527: aload 7
    //   529: aload 8
    //   531: aload 9
    //   533: aload 10
    //   535: aload 11
    //   537: aload 12
    //   539: aload 14
    //   541: aload 15
    //   543: ldc 103
    //   545: getstatic 12	cm/pass/sdk/net/a/b:b	Z
    //   548: invokeinterface 108 17 0
    //   553: return
    //   554: astore 13
    //   556: aconst_null
    //   557: astore 10
    //   559: aconst_null
    //   560: astore 11
    //   562: aconst_null
    //   563: astore 12
    //   565: aconst_null
    //   566: astore 8
    //   568: aconst_null
    //   569: astore 17
    //   571: iconst_0
    //   572: istore_2
    //   573: aconst_null
    //   574: astore 16
    //   576: iconst_0
    //   577: istore_3
    //   578: aconst_null
    //   579: astore 9
    //   581: aload 7
    //   583: astore 15
    //   585: aload_1
    //   586: astore 14
    //   588: aload 17
    //   590: astore 7
    //   592: aload 16
    //   594: astore_1
    //   595: aload 13
    //   597: invokevirtual 111	java/lang/Exception:printStackTrace	()V
    //   600: goto -92 -> 508
    //   603: astore 13
    //   605: aconst_null
    //   606: astore 10
    //   608: aconst_null
    //   609: astore 11
    //   611: aconst_null
    //   612: astore 12
    //   614: aconst_null
    //   615: astore 8
    //   617: aconst_null
    //   618: astore 7
    //   620: iload_3
    //   621: istore_2
    //   622: aconst_null
    //   623: astore_1
    //   624: iload 4
    //   626: istore_3
    //   627: aconst_null
    //   628: astore 9
    //   630: goto -35 -> 595
    //   633: astore 13
    //   635: aconst_null
    //   636: astore 10
    //   638: aconst_null
    //   639: astore 11
    //   641: aconst_null
    //   642: astore 12
    //   644: aconst_null
    //   645: astore 8
    //   647: aload_1
    //   648: astore 7
    //   650: aconst_null
    //   651: astore_1
    //   652: iload_2
    //   653: istore 4
    //   655: aconst_null
    //   656: astore 9
    //   658: iload_3
    //   659: istore_2
    //   660: iload 4
    //   662: istore_3
    //   663: goto -68 -> 595
    //   666: astore 13
    //   668: aconst_null
    //   669: astore 10
    //   671: aconst_null
    //   672: astore 11
    //   674: aconst_null
    //   675: astore 12
    //   677: aconst_null
    //   678: astore 9
    //   680: aload_1
    //   681: astore 8
    //   683: iload_3
    //   684: istore 4
    //   686: aload 7
    //   688: astore_1
    //   689: iload_2
    //   690: istore_3
    //   691: aconst_null
    //   692: astore 16
    //   694: iload 4
    //   696: istore_2
    //   697: aload 8
    //   699: astore 7
    //   701: aload 9
    //   703: astore 8
    //   705: aload 16
    //   707: astore 9
    //   709: goto -114 -> 595
    //   712: astore 13
    //   714: aconst_null
    //   715: astore 10
    //   717: aconst_null
    //   718: astore 11
    //   720: aconst_null
    //   721: astore 12
    //   723: aload_1
    //   724: astore 9
    //   726: aload 7
    //   728: astore_1
    //   729: iload_2
    //   730: istore 4
    //   732: aconst_null
    //   733: astore 16
    //   735: iload_3
    //   736: istore_2
    //   737: iload 4
    //   739: istore_3
    //   740: aload 9
    //   742: astore 7
    //   744: aload 16
    //   746: astore 9
    //   748: goto -153 -> 595
    //   751: astore 13
    //   753: aconst_null
    //   754: astore 10
    //   756: aconst_null
    //   757: astore 11
    //   759: aload 9
    //   761: astore 12
    //   763: aload_1
    //   764: astore 9
    //   766: aload 7
    //   768: astore_1
    //   769: iload_2
    //   770: istore 4
    //   772: aconst_null
    //   773: astore 16
    //   775: iload_3
    //   776: istore_2
    //   777: iload 4
    //   779: istore_3
    //   780: aload 9
    //   782: astore 7
    //   784: aload 16
    //   786: astore 9
    //   788: goto -193 -> 595
    //   791: astore 13
    //   793: aconst_null
    //   794: astore 10
    //   796: aload 9
    //   798: astore 12
    //   800: aload_1
    //   801: astore 9
    //   803: iload_3
    //   804: istore 4
    //   806: aload 7
    //   808: astore_1
    //   809: iload_2
    //   810: istore_3
    //   811: aconst_null
    //   812: astore 16
    //   814: iload 4
    //   816: istore_2
    //   817: aload 9
    //   819: astore 7
    //   821: aload 16
    //   823: astore 9
    //   825: goto -230 -> 595
    //   828: astore 13
    //   830: aconst_null
    //   831: astore 16
    //   833: aload 9
    //   835: astore 12
    //   837: aload_1
    //   838: astore 9
    //   840: aload 7
    //   842: astore_1
    //   843: iload_2
    //   844: istore 4
    //   846: iload_3
    //   847: istore_2
    //   848: iload 4
    //   850: istore_3
    //   851: aload 9
    //   853: astore 7
    //   855: aload 10
    //   857: astore 9
    //   859: aload 16
    //   861: astore 10
    //   863: goto -268 -> 595
    //   866: astore 13
    //   868: aload 9
    //   870: astore 16
    //   872: aload_1
    //   873: astore 9
    //   875: iload_3
    //   876: istore 4
    //   878: aload 7
    //   880: astore_1
    //   881: iload_2
    //   882: istore_3
    //   883: iload 4
    //   885: istore_2
    //   886: aload 9
    //   888: astore 7
    //   890: aload 10
    //   892: astore 9
    //   894: aload 12
    //   896: astore 10
    //   898: aload 16
    //   900: astore 12
    //   902: goto -307 -> 595
    // Local variable table:
    //   start	length	slot	name	signature
    //   0	905	0	this	b
    //   0	905	1	paramb	a.a.a.c.b
    //   63	823	2	bool1	boolean
    //   172	711	3	bool2	boolean
    //   57	827	4	bool3	boolean
    //   54	452	5	bool4	boolean
    //   60	130	6	bool5	boolean
    //   73	816	7	localObject1	Object
    //   21	683	8	localObject2	Object
    //   33	860	9	localObject3	Object
    //   39	858	10	localObject4	Object
    //   15	743	11	localObject5	Object
    //   27	874	12	localObject6	Object
    //   30	473	13	localObject7	Object
    //   554	42	13	localException1	Exception
    //   603	1	13	localException2	Exception
    //   633	1	13	localException3	Exception
    //   666	1	13	localException4	Exception
    //   712	1	13	localException5	Exception
    //   751	1	13	localException6	Exception
    //   791	1	13	localException7	Exception
    //   828	1	13	localException8	Exception
    //   866	1	13	localException9	Exception
    //   45	542	14	localObject8	Object
    //   51	533	15	localObject9	Object
    //   12	887	16	localObject10	Object
    //   18	571	17	localObject11	Object
    //   36	463	18	localObject12	Object
    //   24	471	19	localObject13	Object
    //   9	467	20	localObject14	Object
    //   6	474	21	localObject15	Object
    //   48	80	22	localObject16	Object
    //   42	46	23	localObject17	Object
    // Exception table:
    //   from	to	target	type
    //   75	87	554	java/lang/Exception
    //   94	105	554	java/lang/Exception
    //   112	124	554	java/lang/Exception
    //   131	142	554	java/lang/Exception
    //   149	156	554	java/lang/Exception
    //   163	173	554	java/lang/Exception
    //   177	189	603	java/lang/Exception
    //   193	203	603	java/lang/Exception
    //   209	221	603	java/lang/Exception
    //   224	234	603	java/lang/Exception
    //   238	261	633	java/lang/Exception
    //   261	284	666	java/lang/Exception
    //   284	295	712	java/lang/Exception
    //   295	306	751	java/lang/Exception
    //   306	329	791	java/lang/Exception
    //   329	352	828	java/lang/Exception
    //   385	442	866	java/lang/Exception
  }
}


/* Location:              /Users/hanlian/Downloads/WiFi万能钥匙dex1-dex2jar.jar!/cm/pass/sdk/net/a/b.class
 * Java compiler version: 6 (50.0)
 * JD-Core Version:       0.7.1
 */