package com.c.a.a.a.e.a;

import com.b.b.h;
import com.b.b.m;
import com.b.b.m.a;
import com.b.b.n.b;
import com.b.b.u;
import com.b.b.v;
import com.b.b.x;

public final class a
{
  public static final class a
    extends m<a, a>
    implements a.b
  {
    private static final a e;
    private static volatile x<a> f;
    private n.b<b> d = h();
    
    static
    {
      a locala = new a();
      e = locala;
      locala.e();
    }
    
    public static a l()
    {
      return (a)e.g();
    }
    
    /* Error */
    protected final Object a(int paramInt, Object paramObject1, Object paramObject2)
    {
      // Byte code:
      //   0: iconst_0
      //   1: istore 4
      //   3: getstatic 85	com/c/a/a/a/e/a/a$1:a	[I
      //   6: iload_1
      //   7: iconst_1
      //   8: isub
      //   9: iaload
      //   10: tableswitch	default:+46->56, 1:+54->64, 2:+64->74, 3:+71->81, 4:+85->95, 5:+97->107, 6:+134->144, 7:+298->308, 8:+305->315
      //   56: new 87	java/lang/UnsupportedOperationException
      //   59: dup
      //   60: invokespecial 88	java/lang/UnsupportedOperationException:<init>	()V
      //   63: athrow
      //   64: new 2	com/c/a/a/a/e/a/a$a
      //   67: dup
      //   68: invokespecial 39	com/c/a/a/a/e/a/a$a:<init>	()V
      //   71: astore_2
      //   72: aload_2
      //   73: areturn
      //   74: getstatic 41	com/c/a/a/a/e/a/a$a:e	Lcom/c/a/a/a/e/a/a$a;
      //   77: astore_2
      //   78: goto -6 -> 72
      //   81: aload_0
      //   82: getfield 51	com/c/a/a/a/e/a/a$a:d	Lcom/b/b/n$b;
      //   85: invokeinterface 90 1 0
      //   90: aconst_null
      //   91: astore_2
      //   92: goto -20 -> 72
      //   95: new 12	com/c/a/a/a/e/a/a$a$a
      //   98: dup
      //   99: iconst_0
      //   100: invokespecial 93	com/c/a/a/a/e/a/a$a$a:<init>	(B)V
      //   103: astore_2
      //   104: goto -32 -> 72
      //   107: aload_2
      //   108: checkcast 95	com/b/b/m$j
      //   111: astore_2
      //   112: aload_3
      //   113: checkcast 2	com/c/a/a/a/e/a/a$a
      //   116: astore_3
      //   117: aload_0
      //   118: aload_2
      //   119: aload_0
      //   120: getfield 51	com/c/a/a/a/e/a/a$a:d	Lcom/b/b/n$b;
      //   123: aload_3
      //   124: getfield 51	com/c/a/a/a/e/a/a$a:d	Lcom/b/b/n$b;
      //   127: invokeinterface 98 3 0
      //   132: putfield 51	com/c/a/a/a/e/a/a$a:d	Lcom/b/b/n$b;
      //   135: getstatic 103	com/b/b/m$h:a	Lcom/b/b/m$h;
      //   138: astore_2
      //   139: aload_0
      //   140: astore_2
      //   141: goto -69 -> 72
      //   144: aload_2
      //   145: checkcast 105	com/b/b/g
      //   148: astore_2
      //   149: aload_3
      //   150: checkcast 107	com/b/b/j
      //   153: astore_3
      //   154: iload 4
      //   156: istore_1
      //   157: iload_1
      //   158: ifne +150 -> 308
      //   161: aload_2
      //   162: invokevirtual 110	com/b/b/g:a	()I
      //   165: istore 4
      //   167: iload 4
      //   169: lookupswitch	default:+27->196, 0:+41->210, 10:+46->215
      //   196: aload_2
      //   197: iload 4
      //   199: invokevirtual 113	com/b/b/g:b	(I)Z
      //   202: ifne -45 -> 157
      //   205: iconst_1
      //   206: istore_1
      //   207: goto -50 -> 157
      //   210: iconst_1
      //   211: istore_1
      //   212: goto -55 -> 157
      //   215: aload_0
      //   216: getfield 51	com/c/a/a/a/e/a/a$a:d	Lcom/b/b/n$b;
      //   219: invokeinterface 60 1 0
      //   224: ifne +14 -> 238
      //   227: aload_0
      //   228: aload_0
      //   229: getfield 51	com/c/a/a/a/e/a/a$a:d	Lcom/b/b/n$b;
      //   232: invokestatic 63	com/b/b/m:a	(Lcom/b/b/n$b;)Lcom/b/b/n$b;
      //   235: putfield 51	com/c/a/a/a/e/a/a$a:d	Lcom/b/b/n$b;
      //   238: aload_0
      //   239: getfield 51	com/c/a/a/a/e/a/a$a:d	Lcom/b/b/n$b;
      //   242: aload_2
      //   243: invokestatic 116	com/c/a/a/a/e/a/a$a$b:m	()Lcom/b/b/x;
      //   246: aload_3
      //   247: invokevirtual 119	com/b/b/g:a	(Lcom/b/b/x;Lcom/b/b/j;)Lcom/b/b/u;
      //   250: invokeinterface 67 2 0
      //   255: pop
      //   256: goto -99 -> 157
      //   259: astore_3
      //   260: new 121	java/lang/RuntimeException
      //   263: astore_2
      //   264: aload_2
      //   265: aload_3
      //   266: aload_0
      //   267: invokevirtual 124	com/b/b/o:a	(Lcom/b/b/u;)Lcom/b/b/o;
      //   270: invokespecial 127	java/lang/RuntimeException:<init>	(Ljava/lang/Throwable;)V
      //   273: aload_2
      //   274: athrow
      //   275: astore_2
      //   276: aload_2
      //   277: athrow
      //   278: astore 5
      //   280: new 121	java/lang/RuntimeException
      //   283: astore_3
      //   284: new 78	com/b/b/o
      //   287: astore_2
      //   288: aload_2
      //   289: aload 5
      //   291: invokevirtual 131	java/io/IOException:getMessage	()Ljava/lang/String;
      //   294: invokespecial 134	com/b/b/o:<init>	(Ljava/lang/String;)V
      //   297: aload_3
      //   298: aload_2
      //   299: aload_0
      //   300: invokevirtual 124	com/b/b/o:a	(Lcom/b/b/u;)Lcom/b/b/o;
      //   303: invokespecial 127	java/lang/RuntimeException:<init>	(Ljava/lang/Throwable;)V
      //   306: aload_3
      //   307: athrow
      //   308: getstatic 41	com/c/a/a/a/e/a/a$a:e	Lcom/c/a/a/a/e/a/a$a;
      //   311: astore_2
      //   312: goto -240 -> 72
      //   315: getstatic 136	com/c/a/a/a/e/a/a$a:f	Lcom/b/b/x;
      //   318: ifnonnull +30 -> 348
      //   321: ldc 2
      //   323: monitorenter
      //   324: getstatic 136	com/c/a/a/a/e/a/a$a:f	Lcom/b/b/x;
      //   327: ifnonnull +18 -> 345
      //   330: new 138	com/b/b/m$b
      //   333: astore_2
      //   334: aload_2
      //   335: getstatic 41	com/c/a/a/a/e/a/a$a:e	Lcom/c/a/a/a/e/a/a$a;
      //   338: invokespecial 141	com/b/b/m$b:<init>	(Lcom/b/b/m;)V
      //   341: aload_2
      //   342: putstatic 136	com/c/a/a/a/e/a/a$a:f	Lcom/b/b/x;
      //   345: ldc 2
      //   347: monitorexit
      //   348: getstatic 136	com/c/a/a/a/e/a/a$a:f	Lcom/b/b/x;
      //   351: astore_2
      //   352: goto -280 -> 72
      //   355: astore_2
      //   356: ldc 2
      //   358: monitorexit
      //   359: aload_2
      //   360: athrow
      // Local variable table:
      //   start	length	slot	name	signature
      //   0	361	0	this	a
      //   0	361	1	paramInt	int
      //   0	361	2	paramObject1	Object
      //   0	361	3	paramObject2	Object
      //   1	197	4	i	int
      //   278	12	5	localIOException	java.io.IOException
      // Exception table:
      //   from	to	target	type
      //   161	167	259	com/b/b/o
      //   196	205	259	com/b/b/o
      //   215	238	259	com/b/b/o
      //   238	256	259	com/b/b/o
      //   161	167	275	finally
      //   196	205	275	finally
      //   215	238	275	finally
      //   238	256	275	finally
      //   260	275	275	finally
      //   280	308	275	finally
      //   161	167	278	java/io/IOException
      //   196	205	278	java/io/IOException
      //   215	238	278	java/io/IOException
      //   238	256	278	java/io/IOException
      //   324	345	355	finally
      //   345	348	355	finally
      //   356	359	355	finally
    }
    
    public final void a(h paramh)
    {
      for (int i = 0; i < this.d.size(); i++) {
        paramh.a(1, (u)this.d.get(i));
      }
    }
    
    public final int k()
    {
      int i = this.c;
      if (i != -1) {}
      for (;;)
      {
        return i;
        int j = 0;
        i = 0;
        while (j < this.d.size())
        {
          i += h.b(1, (u)this.d.get(j));
          j++;
        }
        this.c = i;
      }
    }
    
    public static final class a
      extends m.a<a.a, a>
      implements a.b
    {
      private a()
      {
        super();
      }
      
      public final a a(a.a.b paramb)
      {
        b();
        a.a.a((a.a)this.a, paramb);
        return this;
      }
    }
    
    public static final class b
      extends m<b, a>
      implements a.a.c
    {
      private static final b n;
      private static volatile x<b> o;
      private int d;
      private String e = "";
      private String f = "";
      private String g = "";
      private String h = "";
      private String i = "";
      private String j = "";
      private String k = "";
      private String l = "";
      private n.b<a.a.d> m = h();
      
      static
      {
        b localb = new b();
        n = localb;
        localb.e();
      }
      
      public static a l()
      {
        return (a)n.g();
      }
      
      public static x<b> m()
      {
        return n.c();
      }
      
      /* Error */
      protected final Object a(int paramInt, Object paramObject1, Object paramObject2)
      {
        // Byte code:
        //   0: iconst_1
        //   1: istore 7
        //   3: iconst_0
        //   4: istore 4
        //   6: getstatic 106	com/c/a/a/a/e/a/a$1:a	[I
        //   9: iload_1
        //   10: iconst_1
        //   11: isub
        //   12: iaload
        //   13: tableswitch	default:+47->60, 1:+55->68, 2:+65->78, 3:+72->85, 4:+86->99, 5:+98->111, 6:+661->674, 7:+976->989, 8:+983->996
        //   60: new 108	java/lang/UnsupportedOperationException
        //   63: dup
        //   64: invokespecial 109	java/lang/UnsupportedOperationException:<init>	()V
        //   67: athrow
        //   68: new 2	com/c/a/a/a/e/a/a$a$b
        //   71: dup
        //   72: invokespecial 39	com/c/a/a/a/e/a/a$a$b:<init>	()V
        //   75: astore_2
        //   76: aload_2
        //   77: areturn
        //   78: getstatic 41	com/c/a/a/a/e/a/a$a$b:n	Lcom/c/a/a/a/e/a/a$a$b;
        //   81: astore_2
        //   82: goto -6 -> 76
        //   85: aload_0
        //   86: getfield 68	com/c/a/a/a/e/a/a$a$b:m	Lcom/b/b/n$b;
        //   89: invokeinterface 111 1 0
        //   94: aconst_null
        //   95: astore_2
        //   96: goto -20 -> 76
        //   99: new 15	com/c/a/a/a/e/a/a$a$b$a
        //   102: dup
        //   103: iconst_0
        //   104: invokespecial 114	com/c/a/a/a/e/a/a$a$b$a:<init>	(B)V
        //   107: astore_2
        //   108: goto -32 -> 76
        //   111: aload_2
        //   112: checkcast 116	com/b/b/m$j
        //   115: astore 8
        //   117: aload_3
        //   118: checkcast 2	com/c/a/a/a/e/a/a$a$b
        //   121: astore_3
        //   122: aload_0
        //   123: getfield 49	com/c/a/a/a/e/a/a$a$b:e	Ljava/lang/String;
        //   126: invokevirtual 121	java/lang/String:isEmpty	()Z
        //   129: ifne +449 -> 578
        //   132: iconst_1
        //   133: istore 5
        //   135: aload_0
        //   136: getfield 49	com/c/a/a/a/e/a/a$a$b:e	Ljava/lang/String;
        //   139: astore_2
        //   140: aload_3
        //   141: getfield 49	com/c/a/a/a/e/a/a$a$b:e	Ljava/lang/String;
        //   144: invokevirtual 121	java/lang/String:isEmpty	()Z
        //   147: ifne +437 -> 584
        //   150: iconst_1
        //   151: istore 6
        //   153: aload_0
        //   154: aload 8
        //   156: iload 5
        //   158: aload_2
        //   159: iload 6
        //   161: aload_3
        //   162: getfield 49	com/c/a/a/a/e/a/a$a$b:e	Ljava/lang/String;
        //   165: invokeinterface 124 5 0
        //   170: putfield 49	com/c/a/a/a/e/a/a$a$b:e	Ljava/lang/String;
        //   173: aload_0
        //   174: getfield 51	com/c/a/a/a/e/a/a$a$b:f	Ljava/lang/String;
        //   177: invokevirtual 121	java/lang/String:isEmpty	()Z
        //   180: ifne +410 -> 590
        //   183: iconst_1
        //   184: istore 5
        //   186: aload_0
        //   187: getfield 51	com/c/a/a/a/e/a/a$a$b:f	Ljava/lang/String;
        //   190: astore_2
        //   191: aload_3
        //   192: getfield 51	com/c/a/a/a/e/a/a$a$b:f	Ljava/lang/String;
        //   195: invokevirtual 121	java/lang/String:isEmpty	()Z
        //   198: ifne +398 -> 596
        //   201: iconst_1
        //   202: istore 6
        //   204: aload_0
        //   205: aload 8
        //   207: iload 5
        //   209: aload_2
        //   210: iload 6
        //   212: aload_3
        //   213: getfield 51	com/c/a/a/a/e/a/a$a$b:f	Ljava/lang/String;
        //   216: invokeinterface 124 5 0
        //   221: putfield 51	com/c/a/a/a/e/a/a$a$b:f	Ljava/lang/String;
        //   224: aload_0
        //   225: getfield 53	com/c/a/a/a/e/a/a$a$b:g	Ljava/lang/String;
        //   228: invokevirtual 121	java/lang/String:isEmpty	()Z
        //   231: ifne +371 -> 602
        //   234: iconst_1
        //   235: istore 5
        //   237: aload_0
        //   238: getfield 53	com/c/a/a/a/e/a/a$a$b:g	Ljava/lang/String;
        //   241: astore_2
        //   242: aload_3
        //   243: getfield 53	com/c/a/a/a/e/a/a$a$b:g	Ljava/lang/String;
        //   246: invokevirtual 121	java/lang/String:isEmpty	()Z
        //   249: ifne +359 -> 608
        //   252: iconst_1
        //   253: istore 6
        //   255: aload_0
        //   256: aload 8
        //   258: iload 5
        //   260: aload_2
        //   261: iload 6
        //   263: aload_3
        //   264: getfield 53	com/c/a/a/a/e/a/a$a$b:g	Ljava/lang/String;
        //   267: invokeinterface 124 5 0
        //   272: putfield 53	com/c/a/a/a/e/a/a$a$b:g	Ljava/lang/String;
        //   275: aload_0
        //   276: getfield 55	com/c/a/a/a/e/a/a$a$b:h	Ljava/lang/String;
        //   279: invokevirtual 121	java/lang/String:isEmpty	()Z
        //   282: ifne +332 -> 614
        //   285: iconst_1
        //   286: istore 5
        //   288: aload_0
        //   289: getfield 55	com/c/a/a/a/e/a/a$a$b:h	Ljava/lang/String;
        //   292: astore_2
        //   293: aload_3
        //   294: getfield 55	com/c/a/a/a/e/a/a$a$b:h	Ljava/lang/String;
        //   297: invokevirtual 121	java/lang/String:isEmpty	()Z
        //   300: ifne +320 -> 620
        //   303: iconst_1
        //   304: istore 6
        //   306: aload_0
        //   307: aload 8
        //   309: iload 5
        //   311: aload_2
        //   312: iload 6
        //   314: aload_3
        //   315: getfield 55	com/c/a/a/a/e/a/a$a$b:h	Ljava/lang/String;
        //   318: invokeinterface 124 5 0
        //   323: putfield 55	com/c/a/a/a/e/a/a$a$b:h	Ljava/lang/String;
        //   326: aload_0
        //   327: getfield 57	com/c/a/a/a/e/a/a$a$b:i	Ljava/lang/String;
        //   330: invokevirtual 121	java/lang/String:isEmpty	()Z
        //   333: ifne +293 -> 626
        //   336: iconst_1
        //   337: istore 5
        //   339: aload_0
        //   340: getfield 57	com/c/a/a/a/e/a/a$a$b:i	Ljava/lang/String;
        //   343: astore_2
        //   344: aload_3
        //   345: getfield 57	com/c/a/a/a/e/a/a$a$b:i	Ljava/lang/String;
        //   348: invokevirtual 121	java/lang/String:isEmpty	()Z
        //   351: ifne +281 -> 632
        //   354: iconst_1
        //   355: istore 6
        //   357: aload_0
        //   358: aload 8
        //   360: iload 5
        //   362: aload_2
        //   363: iload 6
        //   365: aload_3
        //   366: getfield 57	com/c/a/a/a/e/a/a$a$b:i	Ljava/lang/String;
        //   369: invokeinterface 124 5 0
        //   374: putfield 57	com/c/a/a/a/e/a/a$a$b:i	Ljava/lang/String;
        //   377: aload_0
        //   378: getfield 59	com/c/a/a/a/e/a/a$a$b:j	Ljava/lang/String;
        //   381: invokevirtual 121	java/lang/String:isEmpty	()Z
        //   384: ifne +254 -> 638
        //   387: iconst_1
        //   388: istore 5
        //   390: aload_0
        //   391: getfield 59	com/c/a/a/a/e/a/a$a$b:j	Ljava/lang/String;
        //   394: astore_2
        //   395: aload_3
        //   396: getfield 59	com/c/a/a/a/e/a/a$a$b:j	Ljava/lang/String;
        //   399: invokevirtual 121	java/lang/String:isEmpty	()Z
        //   402: ifne +242 -> 644
        //   405: iconst_1
        //   406: istore 6
        //   408: aload_0
        //   409: aload 8
        //   411: iload 5
        //   413: aload_2
        //   414: iload 6
        //   416: aload_3
        //   417: getfield 59	com/c/a/a/a/e/a/a$a$b:j	Ljava/lang/String;
        //   420: invokeinterface 124 5 0
        //   425: putfield 59	com/c/a/a/a/e/a/a$a$b:j	Ljava/lang/String;
        //   428: aload_0
        //   429: getfield 61	com/c/a/a/a/e/a/a$a$b:k	Ljava/lang/String;
        //   432: invokevirtual 121	java/lang/String:isEmpty	()Z
        //   435: ifne +215 -> 650
        //   438: iconst_1
        //   439: istore 5
        //   441: aload_0
        //   442: getfield 61	com/c/a/a/a/e/a/a$a$b:k	Ljava/lang/String;
        //   445: astore_2
        //   446: aload_3
        //   447: getfield 61	com/c/a/a/a/e/a/a$a$b:k	Ljava/lang/String;
        //   450: invokevirtual 121	java/lang/String:isEmpty	()Z
        //   453: ifne +203 -> 656
        //   456: iconst_1
        //   457: istore 6
        //   459: aload_0
        //   460: aload 8
        //   462: iload 5
        //   464: aload_2
        //   465: iload 6
        //   467: aload_3
        //   468: getfield 61	com/c/a/a/a/e/a/a$a$b:k	Ljava/lang/String;
        //   471: invokeinterface 124 5 0
        //   476: putfield 61	com/c/a/a/a/e/a/a$a$b:k	Ljava/lang/String;
        //   479: aload_0
        //   480: getfield 63	com/c/a/a/a/e/a/a$a$b:l	Ljava/lang/String;
        //   483: invokevirtual 121	java/lang/String:isEmpty	()Z
        //   486: ifne +176 -> 662
        //   489: iconst_1
        //   490: istore 5
        //   492: aload_0
        //   493: getfield 63	com/c/a/a/a/e/a/a$a$b:l	Ljava/lang/String;
        //   496: astore_2
        //   497: aload_3
        //   498: getfield 63	com/c/a/a/a/e/a/a$a$b:l	Ljava/lang/String;
        //   501: invokevirtual 121	java/lang/String:isEmpty	()Z
        //   504: ifne +164 -> 668
        //   507: iload 7
        //   509: istore 6
        //   511: aload_0
        //   512: aload 8
        //   514: iload 5
        //   516: aload_2
        //   517: iload 6
        //   519: aload_3
        //   520: getfield 63	com/c/a/a/a/e/a/a$a$b:l	Ljava/lang/String;
        //   523: invokeinterface 124 5 0
        //   528: putfield 63	com/c/a/a/a/e/a/a$a$b:l	Ljava/lang/String;
        //   531: aload_0
        //   532: aload 8
        //   534: aload_0
        //   535: getfield 68	com/c/a/a/a/e/a/a$a$b:m	Lcom/b/b/n$b;
        //   538: aload_3
        //   539: getfield 68	com/c/a/a/a/e/a/a$a$b:m	Lcom/b/b/n$b;
        //   542: invokeinterface 127 3 0
        //   547: putfield 68	com/c/a/a/a/e/a/a$a$b:m	Lcom/b/b/n$b;
        //   550: aload_0
        //   551: astore_2
        //   552: aload 8
        //   554: getstatic 132	com/b/b/m$h:a	Lcom/b/b/m$h;
        //   557: if_acmpne -481 -> 76
        //   560: aload_0
        //   561: aload_0
        //   562: getfield 134	com/c/a/a/a/e/a/a$a$b:d	I
        //   565: aload_3
        //   566: getfield 134	com/c/a/a/a/e/a/a$a$b:d	I
        //   569: ior
        //   570: putfield 134	com/c/a/a/a/e/a/a$a$b:d	I
        //   573: aload_0
        //   574: astore_2
        //   575: goto -499 -> 76
        //   578: iconst_0
        //   579: istore 5
        //   581: goto -446 -> 135
        //   584: iconst_0
        //   585: istore 6
        //   587: goto -434 -> 153
        //   590: iconst_0
        //   591: istore 5
        //   593: goto -407 -> 186
        //   596: iconst_0
        //   597: istore 6
        //   599: goto -395 -> 204
        //   602: iconst_0
        //   603: istore 5
        //   605: goto -368 -> 237
        //   608: iconst_0
        //   609: istore 6
        //   611: goto -356 -> 255
        //   614: iconst_0
        //   615: istore 5
        //   617: goto -329 -> 288
        //   620: iconst_0
        //   621: istore 6
        //   623: goto -317 -> 306
        //   626: iconst_0
        //   627: istore 5
        //   629: goto -290 -> 339
        //   632: iconst_0
        //   633: istore 6
        //   635: goto -278 -> 357
        //   638: iconst_0
        //   639: istore 5
        //   641: goto -251 -> 390
        //   644: iconst_0
        //   645: istore 6
        //   647: goto -239 -> 408
        //   650: iconst_0
        //   651: istore 5
        //   653: goto -212 -> 441
        //   656: iconst_0
        //   657: istore 6
        //   659: goto -200 -> 459
        //   662: iconst_0
        //   663: istore 5
        //   665: goto -173 -> 492
        //   668: iconst_0
        //   669: istore 6
        //   671: goto -160 -> 511
        //   674: aload_2
        //   675: checkcast 136	com/b/b/g
        //   678: astore_2
        //   679: aload_3
        //   680: checkcast 138	com/b/b/j
        //   683: astore_3
        //   684: iload 4
        //   686: istore_1
        //   687: iload_1
        //   688: ifne +301 -> 989
        //   691: aload_2
        //   692: invokevirtual 141	com/b/b/g:a	()I
        //   695: istore 4
        //   697: iload 4
        //   699: lookupswitch	default:+89->788, 0:+103->802, 10:+108->807, 18:+138->837, 26:+180->879, 34:+191->890, 42:+202->901, 50:+213->912, 58:+224->923, 66:+235->934, 74:+246->945
        //   788: aload_2
        //   789: iload 4
        //   791: invokevirtual 144	com/b/b/g:b	(I)Z
        //   794: ifne -107 -> 687
        //   797: iconst_1
        //   798: istore_1
        //   799: goto -112 -> 687
        //   802: iconst_1
        //   803: istore_1
        //   804: goto -117 -> 687
        //   807: aload_0
        //   808: aload_2
        //   809: invokevirtual 147	com/b/b/g:k	()Ljava/lang/String;
        //   812: putfield 49	com/c/a/a/a/e/a/a$a$b:e	Ljava/lang/String;
        //   815: goto -128 -> 687
        //   818: astore_2
        //   819: new 149	java/lang/RuntimeException
        //   822: astore_3
        //   823: aload_3
        //   824: aload_2
        //   825: aload_0
        //   826: invokevirtual 152	com/b/b/o:a	(Lcom/b/b/u;)Lcom/b/b/o;
        //   829: invokespecial 155	java/lang/RuntimeException:<init>	(Ljava/lang/Throwable;)V
        //   832: aload_3
        //   833: athrow
        //   834: astore_2
        //   835: aload_2
        //   836: athrow
        //   837: aload_0
        //   838: aload_2
        //   839: invokevirtual 147	com/b/b/g:k	()Ljava/lang/String;
        //   842: putfield 51	com/c/a/a/a/e/a/a$a$b:f	Ljava/lang/String;
        //   845: goto -158 -> 687
        //   848: astore_2
        //   849: new 149	java/lang/RuntimeException
        //   852: astore_3
        //   853: new 99	com/b/b/o
        //   856: astore 8
        //   858: aload 8
        //   860: aload_2
        //   861: invokevirtual 158	java/io/IOException:getMessage	()Ljava/lang/String;
        //   864: invokespecial 161	com/b/b/o:<init>	(Ljava/lang/String;)V
        //   867: aload_3
        //   868: aload 8
        //   870: aload_0
        //   871: invokevirtual 152	com/b/b/o:a	(Lcom/b/b/u;)Lcom/b/b/o;
        //   874: invokespecial 155	java/lang/RuntimeException:<init>	(Ljava/lang/Throwable;)V
        //   877: aload_3
        //   878: athrow
        //   879: aload_0
        //   880: aload_2
        //   881: invokevirtual 147	com/b/b/g:k	()Ljava/lang/String;
        //   884: putfield 53	com/c/a/a/a/e/a/a$a$b:g	Ljava/lang/String;
        //   887: goto -200 -> 687
        //   890: aload_0
        //   891: aload_2
        //   892: invokevirtual 147	com/b/b/g:k	()Ljava/lang/String;
        //   895: putfield 55	com/c/a/a/a/e/a/a$a$b:h	Ljava/lang/String;
        //   898: goto -211 -> 687
        //   901: aload_0
        //   902: aload_2
        //   903: invokevirtual 147	com/b/b/g:k	()Ljava/lang/String;
        //   906: putfield 57	com/c/a/a/a/e/a/a$a$b:i	Ljava/lang/String;
        //   909: goto -222 -> 687
        //   912: aload_0
        //   913: aload_2
        //   914: invokevirtual 147	com/b/b/g:k	()Ljava/lang/String;
        //   917: putfield 59	com/c/a/a/a/e/a/a$a$b:j	Ljava/lang/String;
        //   920: goto -233 -> 687
        //   923: aload_0
        //   924: aload_2
        //   925: invokevirtual 147	com/b/b/g:k	()Ljava/lang/String;
        //   928: putfield 61	com/c/a/a/a/e/a/a$a$b:k	Ljava/lang/String;
        //   931: goto -244 -> 687
        //   934: aload_0
        //   935: aload_2
        //   936: invokevirtual 147	com/b/b/g:k	()Ljava/lang/String;
        //   939: putfield 63	com/c/a/a/a/e/a/a$a$b:l	Ljava/lang/String;
        //   942: goto -255 -> 687
        //   945: aload_0
        //   946: getfield 68	com/c/a/a/a/e/a/a$a$b:m	Lcom/b/b/n$b;
        //   949: invokeinterface 77 1 0
        //   954: ifne +14 -> 968
        //   957: aload_0
        //   958: aload_0
        //   959: getfield 68	com/c/a/a/a/e/a/a$a$b:m	Lcom/b/b/n$b;
        //   962: invokestatic 80	com/b/b/m:a	(Lcom/b/b/n$b;)Lcom/b/b/n$b;
        //   965: putfield 68	com/c/a/a/a/e/a/a$a$b:m	Lcom/b/b/n$b;
        //   968: aload_0
        //   969: getfield 68	com/c/a/a/a/e/a/a$a$b:m	Lcom/b/b/n$b;
        //   972: aload_2
        //   973: invokestatic 165	com/c/a/a/a/e/a/a$a$d:m	()Lcom/b/b/x;
        //   976: aload_3
        //   977: invokevirtual 168	com/b/b/g:a	(Lcom/b/b/x;Lcom/b/b/j;)Lcom/b/b/u;
        //   980: invokeinterface 84 2 0
        //   985: pop
        //   986: goto -299 -> 687
        //   989: getstatic 41	com/c/a/a/a/e/a/a$a$b:n	Lcom/c/a/a/a/e/a/a$a$b;
        //   992: astore_2
        //   993: goto -917 -> 76
        //   996: getstatic 170	com/c/a/a/a/e/a/a$a$b:o	Lcom/b/b/x;
        //   999: ifnonnull +30 -> 1029
        //   1002: ldc 2
        //   1004: monitorenter
        //   1005: getstatic 170	com/c/a/a/a/e/a/a$a$b:o	Lcom/b/b/x;
        //   1008: ifnonnull +18 -> 1026
        //   1011: new 172	com/b/b/m$b
        //   1014: astore_2
        //   1015: aload_2
        //   1016: getstatic 41	com/c/a/a/a/e/a/a$a$b:n	Lcom/c/a/a/a/e/a/a$a$b;
        //   1019: invokespecial 175	com/b/b/m$b:<init>	(Lcom/b/b/m;)V
        //   1022: aload_2
        //   1023: putstatic 170	com/c/a/a/a/e/a/a$a$b:o	Lcom/b/b/x;
        //   1026: ldc 2
        //   1028: monitorexit
        //   1029: getstatic 170	com/c/a/a/a/e/a/a$a$b:o	Lcom/b/b/x;
        //   1032: astore_2
        //   1033: goto -957 -> 76
        //   1036: astore_2
        //   1037: ldc 2
        //   1039: monitorexit
        //   1040: aload_2
        //   1041: athrow
        // Local variable table:
        //   start	length	slot	name	signature
        //   0	1042	0	this	b
        //   0	1042	1	paramInt	int
        //   0	1042	2	paramObject1	Object
        //   0	1042	3	paramObject2	Object
        //   4	786	4	i1	int
        //   133	531	5	bool1	boolean
        //   151	519	6	bool2	boolean
        //   1	507	7	bool3	boolean
        //   115	754	8	localObject	Object
        // Exception table:
        //   from	to	target	type
        //   691	697	818	com/b/b/o
        //   788	797	818	com/b/b/o
        //   807	815	818	com/b/b/o
        //   837	845	818	com/b/b/o
        //   879	887	818	com/b/b/o
        //   890	898	818	com/b/b/o
        //   901	909	818	com/b/b/o
        //   912	920	818	com/b/b/o
        //   923	931	818	com/b/b/o
        //   934	942	818	com/b/b/o
        //   945	968	818	com/b/b/o
        //   968	986	818	com/b/b/o
        //   691	697	834	finally
        //   788	797	834	finally
        //   807	815	834	finally
        //   819	834	834	finally
        //   837	845	834	finally
        //   849	879	834	finally
        //   879	887	834	finally
        //   890	898	834	finally
        //   901	909	834	finally
        //   912	920	834	finally
        //   923	931	834	finally
        //   934	942	834	finally
        //   945	968	834	finally
        //   968	986	834	finally
        //   691	697	848	java/io/IOException
        //   788	797	848	java/io/IOException
        //   807	815	848	java/io/IOException
        //   837	845	848	java/io/IOException
        //   879	887	848	java/io/IOException
        //   890	898	848	java/io/IOException
        //   901	909	848	java/io/IOException
        //   912	920	848	java/io/IOException
        //   923	931	848	java/io/IOException
        //   934	942	848	java/io/IOException
        //   945	968	848	java/io/IOException
        //   968	986	848	java/io/IOException
        //   1005	1026	1036	finally
        //   1026	1029	1036	finally
        //   1037	1040	1036	finally
      }
      
      public final void a(h paramh)
      {
        if (!this.e.isEmpty()) {
          paramh.a(1, this.e);
        }
        if (!this.f.isEmpty()) {
          paramh.a(2, this.f);
        }
        if (!this.g.isEmpty()) {
          paramh.a(3, this.g);
        }
        if (!this.h.isEmpty()) {
          paramh.a(4, this.h);
        }
        if (!this.i.isEmpty()) {
          paramh.a(5, this.i);
        }
        if (!this.j.isEmpty()) {
          paramh.a(6, this.j);
        }
        if (!this.k.isEmpty()) {
          paramh.a(7, this.k);
        }
        if (!this.l.isEmpty()) {
          paramh.a(8, this.l);
        }
        for (int i1 = 0; i1 < this.m.size(); i1++) {
          paramh.a(9, (u)this.m.get(i1));
        }
      }
      
      public final int k()
      {
        int i4 = 0;
        int i1 = this.c;
        if (i1 != -1) {
          return i1;
        }
        if (!this.e.isEmpty()) {}
        for (int i2 = h.b(1, this.e) + 0;; i2 = 0)
        {
          i1 = i2;
          if (!this.f.isEmpty()) {
            i1 = i2 + h.b(2, this.f);
          }
          i2 = i1;
          if (!this.g.isEmpty()) {
            i2 = i1 + h.b(3, this.g);
          }
          int i3 = i2;
          if (!this.h.isEmpty()) {
            i3 = i2 + h.b(4, this.h);
          }
          i1 = i3;
          if (!this.i.isEmpty()) {
            i1 = i3 + h.b(5, this.i);
          }
          i2 = i1;
          if (!this.j.isEmpty()) {
            i2 = i1 + h.b(6, this.j);
          }
          i1 = i2;
          if (!this.k.isEmpty()) {
            i1 = i2 + h.b(7, this.k);
          }
          i2 = i1;
          if (!this.l.isEmpty()) {
            i2 = i1 + h.b(8, this.l);
          }
          i1 = i2;
          i2 = i4;
          while (i2 < this.m.size())
          {
            i3 = h.b(9, (u)this.m.get(i2));
            i2++;
            i1 = i3 + i1;
          }
          this.c = i1;
          break;
        }
      }
      
      public static final class a
        extends m.a<a.a.b, a>
        implements a.a.c
      {
        private a()
        {
          super();
        }
        
        public final a a(a.a.d paramd)
        {
          b();
          a.a.b.a((a.a.b)this.a, paramd);
          return this;
        }
        
        public final a a(String paramString)
        {
          b();
          a.a.b.a((a.a.b)this.a, paramString);
          return this;
        }
        
        public final a b(String paramString)
        {
          b();
          a.a.b.b((a.a.b)this.a, paramString);
          return this;
        }
        
        public final a c(String paramString)
        {
          b();
          a.a.b.c((a.a.b)this.a, paramString);
          return this;
        }
        
        public final a d(String paramString)
        {
          b();
          a.a.b.d((a.a.b)this.a, paramString);
          return this;
        }
      }
    }
    
    public static abstract interface c
      extends v
    {}
    
    public static final class d
      extends m<d, a>
      implements a.a.e
    {
      private static final d h;
      private static volatile x<d> i;
      private String d = "";
      private String e = "";
      private String f = "";
      private String g = "";
      
      static
      {
        d locald = new d();
        h = locald;
        locald.e();
      }
      
      public static a l()
      {
        return (a)h.g();
      }
      
      public static x<d> m()
      {
        return h.c();
      }
      
      /* Error */
      protected final Object a(int paramInt, Object paramObject1, Object paramObject2)
      {
        // Byte code:
        //   0: iconst_1
        //   1: istore 7
        //   3: iconst_0
        //   4: istore 4
        //   6: getstatic 74	com/c/a/a/a/e/a/a$1:a	[I
        //   9: iload_1
        //   10: iconst_1
        //   11: isub
        //   12: iaload
        //   13: tableswitch	default:+47->60, 1:+55->68, 2:+65->78, 3:+72->85, 4:+77->90, 5:+89->102, 6:+365->378, 7:+548->561, 8:+555->568
        //   60: new 76	java/lang/UnsupportedOperationException
        //   63: dup
        //   64: invokespecial 77	java/lang/UnsupportedOperationException:<init>	()V
        //   67: athrow
        //   68: new 2	com/c/a/a/a/e/a/a$a$d
        //   71: dup
        //   72: invokespecial 29	com/c/a/a/a/e/a/a$a$d:<init>	()V
        //   75: astore_2
        //   76: aload_2
        //   77: areturn
        //   78: getstatic 31	com/c/a/a/a/e/a/a$a$d:h	Lcom/c/a/a/a/e/a/a$a$d;
        //   81: astore_2
        //   82: goto -6 -> 76
        //   85: aconst_null
        //   86: astore_2
        //   87: goto -11 -> 76
        //   90: new 15	com/c/a/a/a/e/a/a$a$d$a
        //   93: dup
        //   94: iconst_0
        //   95: invokespecial 80	com/c/a/a/a/e/a/a$a$d$a:<init>	(B)V
        //   98: astore_2
        //   99: goto -23 -> 76
        //   102: aload_2
        //   103: checkcast 82	com/b/b/m$j
        //   106: astore_2
        //   107: aload_3
        //   108: checkcast 2	com/c/a/a/a/e/a/a$a$d
        //   111: astore_3
        //   112: aload_0
        //   113: getfield 39	com/c/a/a/a/e/a/a$a$d:d	Ljava/lang/String;
        //   116: invokevirtual 88	java/lang/String:isEmpty	()Z
        //   119: ifne +211 -> 330
        //   122: iconst_1
        //   123: istore 5
        //   125: aload_0
        //   126: getfield 39	com/c/a/a/a/e/a/a$a$d:d	Ljava/lang/String;
        //   129: astore 8
        //   131: aload_3
        //   132: getfield 39	com/c/a/a/a/e/a/a$a$d:d	Ljava/lang/String;
        //   135: invokevirtual 88	java/lang/String:isEmpty	()Z
        //   138: ifne +198 -> 336
        //   141: iconst_1
        //   142: istore 6
        //   144: aload_0
        //   145: aload_2
        //   146: iload 5
        //   148: aload 8
        //   150: iload 6
        //   152: aload_3
        //   153: getfield 39	com/c/a/a/a/e/a/a$a$d:d	Ljava/lang/String;
        //   156: invokeinterface 91 5 0
        //   161: putfield 39	com/c/a/a/a/e/a/a$a$d:d	Ljava/lang/String;
        //   164: aload_0
        //   165: getfield 41	com/c/a/a/a/e/a/a$a$d:e	Ljava/lang/String;
        //   168: invokevirtual 88	java/lang/String:isEmpty	()Z
        //   171: ifne +171 -> 342
        //   174: iconst_1
        //   175: istore 5
        //   177: aload_0
        //   178: getfield 41	com/c/a/a/a/e/a/a$a$d:e	Ljava/lang/String;
        //   181: astore 8
        //   183: aload_3
        //   184: getfield 41	com/c/a/a/a/e/a/a$a$d:e	Ljava/lang/String;
        //   187: invokevirtual 88	java/lang/String:isEmpty	()Z
        //   190: ifne +158 -> 348
        //   193: iconst_1
        //   194: istore 6
        //   196: aload_0
        //   197: aload_2
        //   198: iload 5
        //   200: aload 8
        //   202: iload 6
        //   204: aload_3
        //   205: getfield 41	com/c/a/a/a/e/a/a$a$d:e	Ljava/lang/String;
        //   208: invokeinterface 91 5 0
        //   213: putfield 41	com/c/a/a/a/e/a/a$a$d:e	Ljava/lang/String;
        //   216: aload_0
        //   217: getfield 43	com/c/a/a/a/e/a/a$a$d:f	Ljava/lang/String;
        //   220: invokevirtual 88	java/lang/String:isEmpty	()Z
        //   223: ifne +131 -> 354
        //   226: iconst_1
        //   227: istore 5
        //   229: aload_0
        //   230: getfield 43	com/c/a/a/a/e/a/a$a$d:f	Ljava/lang/String;
        //   233: astore 8
        //   235: aload_3
        //   236: getfield 43	com/c/a/a/a/e/a/a$a$d:f	Ljava/lang/String;
        //   239: invokevirtual 88	java/lang/String:isEmpty	()Z
        //   242: ifne +118 -> 360
        //   245: iconst_1
        //   246: istore 6
        //   248: aload_0
        //   249: aload_2
        //   250: iload 5
        //   252: aload 8
        //   254: iload 6
        //   256: aload_3
        //   257: getfield 43	com/c/a/a/a/e/a/a$a$d:f	Ljava/lang/String;
        //   260: invokeinterface 91 5 0
        //   265: putfield 43	com/c/a/a/a/e/a/a$a$d:f	Ljava/lang/String;
        //   268: aload_0
        //   269: getfield 45	com/c/a/a/a/e/a/a$a$d:g	Ljava/lang/String;
        //   272: invokevirtual 88	java/lang/String:isEmpty	()Z
        //   275: ifne +91 -> 366
        //   278: iconst_1
        //   279: istore 5
        //   281: aload_0
        //   282: getfield 45	com/c/a/a/a/e/a/a$a$d:g	Ljava/lang/String;
        //   285: astore 8
        //   287: aload_3
        //   288: getfield 45	com/c/a/a/a/e/a/a$a$d:g	Ljava/lang/String;
        //   291: invokevirtual 88	java/lang/String:isEmpty	()Z
        //   294: ifne +78 -> 372
        //   297: iload 7
        //   299: istore 6
        //   301: aload_0
        //   302: aload_2
        //   303: iload 5
        //   305: aload 8
        //   307: iload 6
        //   309: aload_3
        //   310: getfield 45	com/c/a/a/a/e/a/a$a$d:g	Ljava/lang/String;
        //   313: invokeinterface 91 5 0
        //   318: putfield 45	com/c/a/a/a/e/a/a$a$d:g	Ljava/lang/String;
        //   321: getstatic 96	com/b/b/m$h:a	Lcom/b/b/m$h;
        //   324: astore_2
        //   325: aload_0
        //   326: astore_2
        //   327: goto -251 -> 76
        //   330: iconst_0
        //   331: istore 5
        //   333: goto -208 -> 125
        //   336: iconst_0
        //   337: istore 6
        //   339: goto -195 -> 144
        //   342: iconst_0
        //   343: istore 5
        //   345: goto -168 -> 177
        //   348: iconst_0
        //   349: istore 6
        //   351: goto -155 -> 196
        //   354: iconst_0
        //   355: istore 5
        //   357: goto -128 -> 229
        //   360: iconst_0
        //   361: istore 6
        //   363: goto -115 -> 248
        //   366: iconst_0
        //   367: istore 5
        //   369: goto -88 -> 281
        //   372: iconst_0
        //   373: istore 6
        //   375: goto -74 -> 301
        //   378: aload_2
        //   379: checkcast 98	com/b/b/g
        //   382: astore_2
        //   383: iload 4
        //   385: istore_1
        //   386: iload_1
        //   387: ifne +174 -> 561
        //   390: aload_2
        //   391: invokevirtual 101	com/b/b/g:a	()I
        //   394: istore 4
        //   396: iload 4
        //   398: lookupswitch	default:+50->448, 0:+64->462, 10:+69->467, 18:+99->497, 26:+141->539, 34:+152->550
        //   448: aload_2
        //   449: iload 4
        //   451: invokevirtual 104	com/b/b/g:b	(I)Z
        //   454: ifne -68 -> 386
        //   457: iconst_1
        //   458: istore_1
        //   459: goto -73 -> 386
        //   462: iconst_1
        //   463: istore_1
        //   464: goto -78 -> 386
        //   467: aload_0
        //   468: aload_2
        //   469: invokevirtual 108	com/b/b/g:k	()Ljava/lang/String;
        //   472: putfield 39	com/c/a/a/a/e/a/a$a$d:d	Ljava/lang/String;
        //   475: goto -89 -> 386
        //   478: astore_2
        //   479: new 110	java/lang/RuntimeException
        //   482: astore_3
        //   483: aload_3
        //   484: aload_2
        //   485: aload_0
        //   486: invokevirtual 113	com/b/b/o:a	(Lcom/b/b/u;)Lcom/b/b/o;
        //   489: invokespecial 116	java/lang/RuntimeException:<init>	(Ljava/lang/Throwable;)V
        //   492: aload_3
        //   493: athrow
        //   494: astore_2
        //   495: aload_2
        //   496: athrow
        //   497: aload_0
        //   498: aload_2
        //   499: invokevirtual 108	com/b/b/g:k	()Ljava/lang/String;
        //   502: putfield 41	com/c/a/a/a/e/a/a$a$d:e	Ljava/lang/String;
        //   505: goto -119 -> 386
        //   508: astore_3
        //   509: new 110	java/lang/RuntimeException
        //   512: astore_2
        //   513: new 67	com/b/b/o
        //   516: astore 8
        //   518: aload 8
        //   520: aload_3
        //   521: invokevirtual 119	java/io/IOException:getMessage	()Ljava/lang/String;
        //   524: invokespecial 122	com/b/b/o:<init>	(Ljava/lang/String;)V
        //   527: aload_2
        //   528: aload 8
        //   530: aload_0
        //   531: invokevirtual 113	com/b/b/o:a	(Lcom/b/b/u;)Lcom/b/b/o;
        //   534: invokespecial 116	java/lang/RuntimeException:<init>	(Ljava/lang/Throwable;)V
        //   537: aload_2
        //   538: athrow
        //   539: aload_0
        //   540: aload_2
        //   541: invokevirtual 108	com/b/b/g:k	()Ljava/lang/String;
        //   544: putfield 43	com/c/a/a/a/e/a/a$a$d:f	Ljava/lang/String;
        //   547: goto -161 -> 386
        //   550: aload_0
        //   551: aload_2
        //   552: invokevirtual 108	com/b/b/g:k	()Ljava/lang/String;
        //   555: putfield 45	com/c/a/a/a/e/a/a$a$d:g	Ljava/lang/String;
        //   558: goto -172 -> 386
        //   561: getstatic 31	com/c/a/a/a/e/a/a$a$d:h	Lcom/c/a/a/a/e/a/a$a$d;
        //   564: astore_2
        //   565: goto -489 -> 76
        //   568: getstatic 124	com/c/a/a/a/e/a/a$a$d:i	Lcom/b/b/x;
        //   571: ifnonnull +30 -> 601
        //   574: ldc 2
        //   576: monitorenter
        //   577: getstatic 124	com/c/a/a/a/e/a/a$a$d:i	Lcom/b/b/x;
        //   580: ifnonnull +18 -> 598
        //   583: new 126	com/b/b/m$b
        //   586: astore_2
        //   587: aload_2
        //   588: getstatic 31	com/c/a/a/a/e/a/a$a$d:h	Lcom/c/a/a/a/e/a/a$a$d;
        //   591: invokespecial 129	com/b/b/m$b:<init>	(Lcom/b/b/m;)V
        //   594: aload_2
        //   595: putstatic 124	com/c/a/a/a/e/a/a$a$d:i	Lcom/b/b/x;
        //   598: ldc 2
        //   600: monitorexit
        //   601: getstatic 124	com/c/a/a/a/e/a/a$a$d:i	Lcom/b/b/x;
        //   604: astore_2
        //   605: goto -529 -> 76
        //   608: astore_2
        //   609: ldc 2
        //   611: monitorexit
        //   612: aload_2
        //   613: athrow
        // Local variable table:
        //   start	length	slot	name	signature
        //   0	614	0	this	d
        //   0	614	1	paramInt	int
        //   0	614	2	paramObject1	Object
        //   0	614	3	paramObject2	Object
        //   4	446	4	j	int
        //   123	245	5	bool1	boolean
        //   142	232	6	bool2	boolean
        //   1	297	7	bool3	boolean
        //   129	400	8	localObject	Object
        // Exception table:
        //   from	to	target	type
        //   390	396	478	com/b/b/o
        //   448	457	478	com/b/b/o
        //   467	475	478	com/b/b/o
        //   497	505	478	com/b/b/o
        //   539	547	478	com/b/b/o
        //   550	558	478	com/b/b/o
        //   390	396	494	finally
        //   448	457	494	finally
        //   467	475	494	finally
        //   479	494	494	finally
        //   497	505	494	finally
        //   509	539	494	finally
        //   539	547	494	finally
        //   550	558	494	finally
        //   390	396	508	java/io/IOException
        //   448	457	508	java/io/IOException
        //   467	475	508	java/io/IOException
        //   497	505	508	java/io/IOException
        //   539	547	508	java/io/IOException
        //   550	558	508	java/io/IOException
        //   577	598	608	finally
        //   598	601	608	finally
        //   609	612	608	finally
      }
      
      public final void a(h paramh)
      {
        if (!this.d.isEmpty()) {
          paramh.a(1, this.d);
        }
        if (!this.e.isEmpty()) {
          paramh.a(2, this.e);
        }
        if (!this.f.isEmpty()) {
          paramh.a(3, this.f);
        }
        if (!this.g.isEmpty()) {
          paramh.a(4, this.g);
        }
      }
      
      public final int k()
      {
        int j = this.c;
        if (j != -1) {}
        for (;;)
        {
          return j;
          int k = 0;
          if (!this.d.isEmpty()) {
            k = h.b(1, this.d) + 0;
          }
          j = k;
          if (!this.e.isEmpty()) {
            j = k + h.b(2, this.e);
          }
          k = j;
          if (!this.f.isEmpty()) {
            k = j + h.b(3, this.f);
          }
          j = k;
          if (!this.g.isEmpty()) {
            j = k + h.b(4, this.g);
          }
          this.c = j;
        }
      }
      
      public static final class a
        extends m.a<a.a.d, a>
        implements a.a.e
      {
        private a()
        {
          super();
        }
        
        public final a a(String paramString)
        {
          b();
          a.a.d.a((a.a.d)this.a, paramString);
          return this;
        }
        
        public final a b(String paramString)
        {
          b();
          a.a.d.b((a.a.d)this.a, paramString);
          return this;
        }
        
        public final a c(String paramString)
        {
          b();
          a.a.d.c((a.a.d)this.a, paramString);
          return this;
        }
        
        public final a d(String paramString)
        {
          b();
          a.a.d.d((a.a.d)this.a, paramString);
          return this;
        }
      }
    }
    
    public static abstract interface e
      extends v
    {}
  }
  
  public static abstract interface b
    extends v
  {}
}


/* Location:              /Users/hanlian/Downloads/WiFi万能钥匙dex1-dex2jar.jar!/com/c/a/a/a/e/a/a.class
 * Java compiler version: 6 (50.0)
 * JD-Core Version:       0.7.1
 */