package com.alipay.sdk.c;

import android.content.Context;

final class b
  implements Runnable
{
  b(a parama, Context paramContext) {}
  
  /* Error */
  public final void run()
  {
    // Byte code:
    //   0: new 27	com/alipay/sdk/f/a/b
    //   3: astore_3
    //   4: aload_3
    //   5: invokespecial 28	com/alipay/sdk/f/a/b:<init>	()V
    //   8: aload_0
    //   9: getfield 16	com/alipay/sdk/c/b:a	Landroid/content/Context;
    //   12: astore_2
    //   13: aload_3
    //   14: aload_2
    //   15: ldc 30
    //   17: aload_2
    //   18: invokestatic 35	com/alipay/sdk/j/j:a	(Landroid/content/Context;)Ljava/lang/String;
    //   21: iconst_1
    //   22: invokevirtual 40	com/alipay/sdk/f/d:a	(Landroid/content/Context;Ljava/lang/String;Ljava/lang/String;Z)Lcom/alipay/sdk/f/b;
    //   25: astore_3
    //   26: aload_3
    //   27: ifnull +119 -> 146
    //   30: aload_0
    //   31: getfield 14	com/alipay/sdk/c/b:b	Lcom/alipay/sdk/c/a;
    //   34: astore_2
    //   35: aload_3
    //   36: getfield 45	com/alipay/sdk/f/b:b	Ljava/lang/String;
    //   39: astore 4
    //   41: aload 4
    //   43: invokestatic 51	android/text/TextUtils:isEmpty	(Ljava/lang/CharSequence;)Z
    //   46: istore_1
    //   47: iload_1
    //   48: ifne +48 -> 96
    //   51: new 53	org/json/JSONObject
    //   54: astore_3
    //   55: aload_3
    //   56: aload 4
    //   58: invokespecial 56	org/json/JSONObject:<init>	(Ljava/lang/String;)V
    //   61: aload_3
    //   62: ldc 58
    //   64: invokevirtual 62	org/json/JSONObject:optJSONObject	(Ljava/lang/String;)Lorg/json/JSONObject;
    //   67: astore_3
    //   68: aload_2
    //   69: aload_3
    //   70: ldc 64
    //   72: sipush 3500
    //   75: invokevirtual 68	org/json/JSONObject:optInt	(Ljava/lang/String;I)I
    //   78: putfield 73	com/alipay/sdk/c/a:a	I
    //   81: aload_2
    //   82: aload_3
    //   83: ldc 75
    //   85: ldc 77
    //   87: invokevirtual 81	org/json/JSONObject:optString	(Ljava/lang/String;Ljava/lang/String;)Ljava/lang/String;
    //   90: invokevirtual 87	java/lang/String:trim	()Ljava/lang/String;
    //   93: putfield 88	com/alipay/sdk/c/a:b	Ljava/lang/String;
    //   96: aload_0
    //   97: getfield 14	com/alipay/sdk/c/b:b	Lcom/alipay/sdk/c/a;
    //   100: astore_3
    //   101: new 53	org/json/JSONObject
    //   104: astore_2
    //   105: aload_2
    //   106: invokespecial 89	org/json/JSONObject:<init>	()V
    //   109: aload_2
    //   110: ldc 64
    //   112: aload_3
    //   113: invokevirtual 92	com/alipay/sdk/c/a:a	()I
    //   116: invokevirtual 96	org/json/JSONObject:put	(Ljava/lang/String;I)Lorg/json/JSONObject;
    //   119: pop
    //   120: aload_2
    //   121: ldc 75
    //   123: aload_3
    //   124: getfield 88	com/alipay/sdk/c/a:b	Ljava/lang/String;
    //   127: invokevirtual 99	org/json/JSONObject:put	(Ljava/lang/String;Ljava/lang/Object;)Lorg/json/JSONObject;
    //   130: pop
    //   131: invokestatic 104	com/alipay/sdk/h/b:a	()Lcom/alipay/sdk/h/b;
    //   134: getfield 105	com/alipay/sdk/h/b:a	Landroid/content/Context;
    //   137: ldc 107
    //   139: aload_2
    //   140: invokevirtual 110	org/json/JSONObject:toString	()Ljava/lang/String;
    //   143: invokestatic 115	com/alipay/sdk/j/h:a	(Landroid/content/Context;Ljava/lang/String;Ljava/lang/String;)V
    //   146: return
    //   147: astore_2
    //   148: goto -2 -> 146
    //   151: astore_2
    //   152: goto -6 -> 146
    //   155: astore_2
    //   156: goto -60 -> 96
    // Local variable table:
    //   start	length	slot	name	signature
    //   0	159	0	this	b
    //   46	2	1	bool	boolean
    //   12	128	2	localObject1	Object
    //   147	1	2	localThrowable1	Throwable
    //   151	1	2	localException	Exception
    //   155	1	2	localThrowable2	Throwable
    //   3	121	3	localObject2	Object
    //   39	18	4	str	String
    // Exception table:
    //   from	to	target	type
    //   0	26	147	java/lang/Throwable
    //   30	47	147	java/lang/Throwable
    //   96	101	147	java/lang/Throwable
    //   101	146	147	java/lang/Throwable
    //   101	146	151	java/lang/Exception
    //   51	96	155	java/lang/Throwable
  }
}


/* Location:              /Users/hanlian/Downloads/WiFi万能钥匙dex1-dex2jar.jar!/com/alipay/sdk/c/b.class
 * Java compiler version: 6 (50.0)
 * JD-Core Version:       0.7.1
 */