package com.tencent.wxop.stat;

import android.content.Context;
import com.tencent.wxop.stat.a.d;
import com.tencent.wxop.stat.b.b;
import com.tencent.wxop.stat.b.f;
import com.tencent.wxop.stat.b.l;
import java.util.Arrays;
import java.util.List;
import org.apache.http.impl.client.DefaultHttpClient;

class ak
{
  private static b cx = ;
  private static ak dj = null;
  private static Context dk = null;
  private long cv;
  DefaultHttpClient dg;
  f dh;
  StringBuilder di;
  
  /* Error */
  private ak(Context paramContext)
  {
    // Byte code:
    //   0: aload_0
    //   1: invokespecial 39	java/lang/Object:<init>	()V
    //   4: aload_0
    //   5: aconst_null
    //   6: putfield 41	com/tencent/wxop/stat/ak:dg	Lorg/apache/http/impl/client/DefaultHttpClient;
    //   9: aload_0
    //   10: aconst_null
    //   11: putfield 43	com/tencent/wxop/stat/ak:dh	Lcom/tencent/wxop/stat/b/f;
    //   14: aload_0
    //   15: new 45	java/lang/StringBuilder
    //   18: dup
    //   19: sipush 4096
    //   22: invokespecial 48	java/lang/StringBuilder:<init>	(I)V
    //   25: putfield 50	com/tencent/wxop/stat/ak:di	Ljava/lang/StringBuilder;
    //   28: aload_0
    //   29: lconst_0
    //   30: putfield 52	com/tencent/wxop/stat/ak:cv	J
    //   33: aload_1
    //   34: invokevirtual 58	android/content/Context:getApplicationContext	()Landroid/content/Context;
    //   37: putstatic 32	com/tencent/wxop/stat/ak:dk	Landroid/content/Context;
    //   40: aload_0
    //   41: invokestatic 64	java/lang/System:currentTimeMillis	()J
    //   44: ldc2_w 65
    //   47: ldiv
    //   48: putfield 52	com/tencent/wxop/stat/ak:cv	J
    //   51: new 68	com/tencent/wxop/stat/b/f
    //   54: astore_1
    //   55: aload_1
    //   56: invokespecial 69	com/tencent/wxop/stat/b/f:<init>	()V
    //   59: aload_0
    //   60: aload_1
    //   61: putfield 43	com/tencent/wxop/stat/ak:dh	Lcom/tencent/wxop/stat/b/f;
    //   64: invokestatic 75	com/tencent/wxop/stat/c:k	()Z
    //   67: istore_2
    //   68: iload_2
    //   69: ifeq +65 -> 134
    //   72: ldc 77
    //   74: invokestatic 83	java/util/logging/Logger:getLogger	(Ljava/lang/String;)Ljava/util/logging/Logger;
    //   77: getstatic 89	java/util/logging/Level:FINER	Ljava/util/logging/Level;
    //   80: invokevirtual 93	java/util/logging/Logger:setLevel	(Ljava/util/logging/Level;)V
    //   83: ldc 95
    //   85: invokestatic 83	java/util/logging/Logger:getLogger	(Ljava/lang/String;)Ljava/util/logging/Logger;
    //   88: getstatic 89	java/util/logging/Level:FINER	Ljava/util/logging/Level;
    //   91: invokevirtual 93	java/util/logging/Logger:setLevel	(Ljava/util/logging/Level;)V
    //   94: ldc 97
    //   96: ldc 99
    //   98: invokestatic 103	java/lang/System:setProperty	(Ljava/lang/String;Ljava/lang/String;)Ljava/lang/String;
    //   101: pop
    //   102: ldc 105
    //   104: ldc 107
    //   106: invokestatic 103	java/lang/System:setProperty	(Ljava/lang/String;Ljava/lang/String;)Ljava/lang/String;
    //   109: pop
    //   110: ldc 109
    //   112: ldc 111
    //   114: invokestatic 103	java/lang/System:setProperty	(Ljava/lang/String;Ljava/lang/String;)Ljava/lang/String;
    //   117: pop
    //   118: ldc 113
    //   120: ldc 111
    //   122: invokestatic 103	java/lang/System:setProperty	(Ljava/lang/String;Ljava/lang/String;)Ljava/lang/String;
    //   125: pop
    //   126: ldc 115
    //   128: ldc 111
    //   130: invokestatic 103	java/lang/System:setProperty	(Ljava/lang/String;Ljava/lang/String;)Ljava/lang/String;
    //   133: pop
    //   134: new 117	org/apache/http/params/BasicHttpParams
    //   137: astore_3
    //   138: aload_3
    //   139: invokespecial 118	org/apache/http/params/BasicHttpParams:<init>	()V
    //   142: aload_3
    //   143: iconst_0
    //   144: invokestatic 124	org/apache/http/params/HttpConnectionParams:setStaleCheckingEnabled	(Lorg/apache/http/params/HttpParams;Z)V
    //   147: aload_3
    //   148: sipush 10000
    //   151: invokestatic 128	org/apache/http/params/HttpConnectionParams:setConnectionTimeout	(Lorg/apache/http/params/HttpParams;I)V
    //   154: aload_3
    //   155: sipush 10000
    //   158: invokestatic 131	org/apache/http/params/HttpConnectionParams:setSoTimeout	(Lorg/apache/http/params/HttpParams;I)V
    //   161: new 133	org/apache/http/impl/client/DefaultHttpClient
    //   164: astore_1
    //   165: aload_1
    //   166: aload_3
    //   167: invokespecial 136	org/apache/http/impl/client/DefaultHttpClient:<init>	(Lorg/apache/http/params/HttpParams;)V
    //   170: aload_0
    //   171: aload_1
    //   172: putfield 41	com/tencent/wxop/stat/ak:dg	Lorg/apache/http/impl/client/DefaultHttpClient;
    //   175: aload_0
    //   176: getfield 41	com/tencent/wxop/stat/ak:dg	Lorg/apache/http/impl/client/DefaultHttpClient;
    //   179: astore_3
    //   180: new 138	com/tencent/wxop/stat/al
    //   183: astore_1
    //   184: aload_1
    //   185: aload_0
    //   186: invokespecial 141	com/tencent/wxop/stat/al:<init>	(Lcom/tencent/wxop/stat/ak;)V
    //   189: aload_3
    //   190: aload_1
    //   191: invokevirtual 145	org/apache/http/impl/client/DefaultHttpClient:setKeepAliveStrategy	(Lorg/apache/http/conn/ConnectionKeepAliveStrategy;)V
    //   194: return
    //   195: astore_1
    //   196: getstatic 28	com/tencent/wxop/stat/ak:cx	Lcom/tencent/wxop/stat/b/b;
    //   199: aload_1
    //   200: invokevirtual 151	com/tencent/wxop/stat/b/b:b	(Ljava/lang/Throwable;)V
    //   203: goto -9 -> 194
    //   206: astore_1
    //   207: goto -73 -> 134
    // Local variable table:
    //   start	length	slot	name	signature
    //   0	210	0	this	ak
    //   0	210	1	paramContext	Context
    //   67	2	2	bool	boolean
    //   137	53	3	localObject	Object
    // Exception table:
    //   from	to	target	type
    //   33	68	195	java/lang/Throwable
    //   134	194	195	java/lang/Throwable
    //   72	134	206	java/lang/Throwable
  }
  
  static ak Z(Context paramContext)
  {
    if (dj == null) {}
    try
    {
      if (dj == null)
      {
        ak localak = new com/tencent/wxop/stat/ak;
        localak.<init>(paramContext);
        dj = localak;
      }
      return dj;
    }
    finally {}
  }
  
  static Context aB()
  {
    return dk;
  }
  
  static void j(Context paramContext)
  {
    dk = paramContext.getApplicationContext();
  }
  
  final void a(d paramd, aj paramaj)
  {
    b(Arrays.asList(new String[] { paramd.af() }), paramaj);
  }
  
  /* Error */
  final void a(List<?> paramList, aj paramaj)
  {
    // Byte code:
    //   0: iconst_0
    //   1: istore 4
    //   3: aload_1
    //   4: ifnull +12 -> 16
    //   7: aload_1
    //   8: invokeinterface 181 1 0
    //   13: ifeq +4 -> 17
    //   16: return
    //   17: aload_1
    //   18: invokeinterface 185 1 0
    //   23: istore 5
    //   25: aload_1
    //   26: iconst_0
    //   27: invokeinterface 189 2 0
    //   32: pop
    //   33: aload_0
    //   34: getfield 50	com/tencent/wxop/stat/ak:di	Ljava/lang/StringBuilder;
    //   37: iconst_0
    //   38: aload_0
    //   39: getfield 50	com/tencent/wxop/stat/ak:di	Ljava/lang/StringBuilder;
    //   42: invokevirtual 192	java/lang/StringBuilder:length	()I
    //   45: invokevirtual 196	java/lang/StringBuilder:delete	(II)Ljava/lang/StringBuilder;
    //   48: pop
    //   49: aload_0
    //   50: getfield 50	com/tencent/wxop/stat/ak:di	Ljava/lang/StringBuilder;
    //   53: ldc -58
    //   55: invokevirtual 202	java/lang/StringBuilder:append	(Ljava/lang/String;)Ljava/lang/StringBuilder;
    //   58: pop
    //   59: iconst_0
    //   60: istore_3
    //   61: iload_3
    //   62: iload 5
    //   64: if_icmpge +45 -> 109
    //   67: aload_0
    //   68: getfield 50	com/tencent/wxop/stat/ak:di	Ljava/lang/StringBuilder;
    //   71: aload_1
    //   72: iload_3
    //   73: invokeinterface 189 2 0
    //   78: invokevirtual 205	java/lang/Object:toString	()Ljava/lang/String;
    //   81: invokevirtual 202	java/lang/StringBuilder:append	(Ljava/lang/String;)Ljava/lang/StringBuilder;
    //   84: pop
    //   85: iload_3
    //   86: iload 5
    //   88: iconst_1
    //   89: isub
    //   90: if_icmpeq +13 -> 103
    //   93: aload_0
    //   94: getfield 50	com/tencent/wxop/stat/ak:di	Ljava/lang/StringBuilder;
    //   97: ldc -49
    //   99: invokevirtual 202	java/lang/StringBuilder:append	(Ljava/lang/String;)Ljava/lang/StringBuilder;
    //   102: pop
    //   103: iinc 3 1
    //   106: goto -45 -> 61
    //   109: aload_0
    //   110: getfield 50	com/tencent/wxop/stat/ak:di	Ljava/lang/StringBuilder;
    //   113: ldc -47
    //   115: invokevirtual 202	java/lang/StringBuilder:append	(Ljava/lang/String;)Ljava/lang/StringBuilder;
    //   118: pop
    //   119: aload_0
    //   120: getfield 50	com/tencent/wxop/stat/ak:di	Ljava/lang/StringBuilder;
    //   123: invokevirtual 210	java/lang/StringBuilder:toString	()Ljava/lang/String;
    //   126: astore_1
    //   127: aload_1
    //   128: invokevirtual 211	java/lang/String:length	()I
    //   131: istore 6
    //   133: new 45	java/lang/StringBuilder
    //   136: astore 9
    //   138: aload 9
    //   140: invokespecial 212	java/lang/StringBuilder:<init>	()V
    //   143: aload 9
    //   145: invokestatic 215	com/tencent/wxop/stat/c:y	()Ljava/lang/String;
    //   148: invokevirtual 202	java/lang/StringBuilder:append	(Ljava/lang/String;)Ljava/lang/StringBuilder;
    //   151: ldc -39
    //   153: invokevirtual 202	java/lang/StringBuilder:append	(Ljava/lang/String;)Ljava/lang/StringBuilder;
    //   156: aload_0
    //   157: getfield 52	com/tencent/wxop/stat/ak:cv	J
    //   160: invokevirtual 220	java/lang/StringBuilder:append	(J)Ljava/lang/StringBuilder;
    //   163: invokevirtual 210	java/lang/StringBuilder:toString	()Ljava/lang/String;
    //   166: astore 9
    //   168: aload_0
    //   169: aload_0
    //   170: getfield 52	com/tencent/wxop/stat/ak:cv	J
    //   173: lconst_1
    //   174: ladd
    //   175: putfield 52	com/tencent/wxop/stat/ak:cv	J
    //   178: invokestatic 75	com/tencent/wxop/stat/c:k	()Z
    //   181: ifeq +54 -> 235
    //   184: getstatic 28	com/tencent/wxop/stat/ak:cx	Lcom/tencent/wxop/stat/b/b;
    //   187: astore 11
    //   189: new 45	java/lang/StringBuilder
    //   192: astore 10
    //   194: aload 10
    //   196: ldc -58
    //   198: invokespecial 223	java/lang/StringBuilder:<init>	(Ljava/lang/String;)V
    //   201: aload 11
    //   203: aload 10
    //   205: aload 9
    //   207: invokevirtual 202	java/lang/StringBuilder:append	(Ljava/lang/String;)Ljava/lang/StringBuilder;
    //   210: ldc -31
    //   212: invokevirtual 202	java/lang/StringBuilder:append	(Ljava/lang/String;)Ljava/lang/StringBuilder;
    //   215: iload 6
    //   217: invokevirtual 228	java/lang/StringBuilder:append	(I)Ljava/lang/StringBuilder;
    //   220: ldc -26
    //   222: invokevirtual 202	java/lang/StringBuilder:append	(Ljava/lang/String;)Ljava/lang/StringBuilder;
    //   225: aload_1
    //   226: invokevirtual 202	java/lang/StringBuilder:append	(Ljava/lang/String;)Ljava/lang/StringBuilder;
    //   229: invokevirtual 210	java/lang/StringBuilder:toString	()Ljava/lang/String;
    //   232: invokevirtual 233	com/tencent/wxop/stat/b/b:b	(Ljava/lang/Object;)V
    //   235: new 235	org/apache/http/client/methods/HttpPost
    //   238: astore 11
    //   240: aload 11
    //   242: aload 9
    //   244: invokespecial 236	org/apache/http/client/methods/HttpPost:<init>	(Ljava/lang/String;)V
    //   247: aload 11
    //   249: ldc -18
    //   251: ldc -16
    //   253: invokevirtual 244	org/apache/http/client/methods/HttpPost:addHeader	(Ljava/lang/String;Ljava/lang/String;)V
    //   256: aload 11
    //   258: ldc -10
    //   260: ldc -8
    //   262: invokevirtual 251	org/apache/http/client/methods/HttpPost:setHeader	(Ljava/lang/String;Ljava/lang/String;)V
    //   265: aload 11
    //   267: ldc -3
    //   269: invokevirtual 256	org/apache/http/client/methods/HttpPost:removeHeaders	(Ljava/lang/String;)V
    //   272: getstatic 32	com/tencent/wxop/stat/ak:dk	Landroid/content/Context;
    //   275: invokestatic 262	com/tencent/wxop/stat/g:r	(Landroid/content/Context;)Lcom/tencent/wxop/stat/g;
    //   278: invokevirtual 266	com/tencent/wxop/stat/g:V	()Lorg/apache/http/HttpHost;
    //   281: astore 12
    //   283: aload 11
    //   285: ldc_w 268
    //   288: ldc_w 270
    //   291: invokevirtual 244	org/apache/http/client/methods/HttpPost:addHeader	(Ljava/lang/String;Ljava/lang/String;)V
    //   294: aload 12
    //   296: ifnonnull +446 -> 742
    //   299: aload_0
    //   300: getfield 41	com/tencent/wxop/stat/ak:dg	Lorg/apache/http/impl/client/DefaultHttpClient;
    //   303: invokevirtual 274	org/apache/http/impl/client/DefaultHttpClient:getParams	()Lorg/apache/http/params/HttpParams;
    //   306: ldc_w 276
    //   309: invokeinterface 282 2 0
    //   314: pop
    //   315: new 284	java/io/ByteArrayOutputStream
    //   318: astore 10
    //   320: aload 10
    //   322: iload 6
    //   324: invokespecial 285	java/io/ByteArrayOutputStream:<init>	(I)V
    //   327: aload_1
    //   328: ldc_w 287
    //   331: invokevirtual 291	java/lang/String:getBytes	(Ljava/lang/String;)[B
    //   334: astore 9
    //   336: aload 9
    //   338: arraylength
    //   339: istore 5
    //   341: iload 4
    //   343: istore_3
    //   344: iload 6
    //   346: getstatic 295	com/tencent/wxop/stat/c:aA	I
    //   349: if_icmple +5 -> 354
    //   352: iconst_1
    //   353: istore_3
    //   354: aload 9
    //   356: astore_1
    //   357: iload_3
    //   358: ifeq +176 -> 534
    //   361: aload 11
    //   363: ldc_w 268
    //   366: invokevirtual 256	org/apache/http/client/methods/HttpPost:removeHeaders	(Ljava/lang/String;)V
    //   369: new 45	java/lang/StringBuilder
    //   372: astore_1
    //   373: aload_1
    //   374: invokespecial 212	java/lang/StringBuilder:<init>	()V
    //   377: aload_1
    //   378: ldc_w 270
    //   381: invokevirtual 202	java/lang/StringBuilder:append	(Ljava/lang/String;)Ljava/lang/StringBuilder;
    //   384: ldc_w 297
    //   387: invokevirtual 202	java/lang/StringBuilder:append	(Ljava/lang/String;)Ljava/lang/StringBuilder;
    //   390: invokevirtual 210	java/lang/StringBuilder:toString	()Ljava/lang/String;
    //   393: astore_1
    //   394: aload 11
    //   396: ldc_w 268
    //   399: aload_1
    //   400: invokevirtual 244	org/apache/http/client/methods/HttpPost:addHeader	(Ljava/lang/String;Ljava/lang/String;)V
    //   403: aload 12
    //   405: ifnull +20 -> 425
    //   408: aload 11
    //   410: ldc_w 299
    //   413: invokevirtual 256	org/apache/http/client/methods/HttpPost:removeHeaders	(Ljava/lang/String;)V
    //   416: aload 11
    //   418: ldc_w 299
    //   421: aload_1
    //   422: invokevirtual 244	org/apache/http/client/methods/HttpPost:addHeader	(Ljava/lang/String;Ljava/lang/String;)V
    //   425: aload 10
    //   427: iconst_4
    //   428: newarray <illegal type>
    //   430: invokevirtual 303	java/io/ByteArrayOutputStream:write	([B)V
    //   433: new 305	java/util/zip/GZIPOutputStream
    //   436: astore_1
    //   437: aload_1
    //   438: aload 10
    //   440: invokespecial 308	java/util/zip/GZIPOutputStream:<init>	(Ljava/io/OutputStream;)V
    //   443: aload_1
    //   444: aload 9
    //   446: invokevirtual 309	java/util/zip/GZIPOutputStream:write	([B)V
    //   449: aload_1
    //   450: invokevirtual 312	java/util/zip/GZIPOutputStream:close	()V
    //   453: aload 10
    //   455: invokevirtual 316	java/io/ByteArrayOutputStream:toByteArray	()[B
    //   458: astore 9
    //   460: aload 9
    //   462: iconst_0
    //   463: iconst_4
    //   464: invokestatic 322	java/nio/ByteBuffer:wrap	([BII)Ljava/nio/ByteBuffer;
    //   467: iload 5
    //   469: invokevirtual 326	java/nio/ByteBuffer:putInt	(I)Ljava/nio/ByteBuffer;
    //   472: pop
    //   473: aload 9
    //   475: astore_1
    //   476: invokestatic 75	com/tencent/wxop/stat/c:k	()Z
    //   479: ifeq +55 -> 534
    //   482: getstatic 28	com/tencent/wxop/stat/ak:cx	Lcom/tencent/wxop/stat/b/b;
    //   485: astore_1
    //   486: new 45	java/lang/StringBuilder
    //   489: astore 12
    //   491: aload 12
    //   493: ldc_w 328
    //   496: invokespecial 223	java/lang/StringBuilder:<init>	(Ljava/lang/String;)V
    //   499: aload_1
    //   500: aload 12
    //   502: iload 5
    //   504: invokevirtual 228	java/lang/StringBuilder:append	(I)Ljava/lang/StringBuilder;
    //   507: ldc_w 330
    //   510: invokevirtual 202	java/lang/StringBuilder:append	(Ljava/lang/String;)Ljava/lang/StringBuilder;
    //   513: aload 9
    //   515: arraylength
    //   516: invokevirtual 228	java/lang/StringBuilder:append	(I)Ljava/lang/StringBuilder;
    //   519: ldc_w 332
    //   522: invokevirtual 202	java/lang/StringBuilder:append	(Ljava/lang/String;)Ljava/lang/StringBuilder;
    //   525: invokevirtual 210	java/lang/StringBuilder:toString	()Ljava/lang/String;
    //   528: invokevirtual 335	com/tencent/wxop/stat/b/b:e	(Ljava/lang/Object;)V
    //   531: aload 9
    //   533: astore_1
    //   534: aload_1
    //   535: invokestatic 340	com/tencent/wxop/stat/b/g:b	([B)[B
    //   538: astore 9
    //   540: new 342	org/apache/http/entity/ByteArrayEntity
    //   543: astore_1
    //   544: aload_1
    //   545: aload 9
    //   547: invokespecial 344	org/apache/http/entity/ByteArrayEntity:<init>	([B)V
    //   550: aload 11
    //   552: aload_1
    //   553: invokevirtual 348	org/apache/http/client/methods/HttpPost:setEntity	(Lorg/apache/http/HttpEntity;)V
    //   556: aload_0
    //   557: getfield 41	com/tencent/wxop/stat/ak:dg	Lorg/apache/http/impl/client/DefaultHttpClient;
    //   560: aload 11
    //   562: invokevirtual 352	org/apache/http/impl/client/DefaultHttpClient:execute	(Lorg/apache/http/client/methods/HttpUriRequest;)Lorg/apache/http/HttpResponse;
    //   565: astore_1
    //   566: aload_1
    //   567: invokeinterface 358 1 0
    //   572: astore 9
    //   574: aload_1
    //   575: invokeinterface 362 1 0
    //   580: invokeinterface 367 1 0
    //   585: istore_3
    //   586: aload 9
    //   588: invokeinterface 372 1 0
    //   593: lstore 7
    //   595: invokestatic 75	com/tencent/wxop/stat/c:k	()Z
    //   598: ifeq +46 -> 644
    //   601: getstatic 28	com/tencent/wxop/stat/ak:cx	Lcom/tencent/wxop/stat/b/b;
    //   604: astore 11
    //   606: new 45	java/lang/StringBuilder
    //   609: astore 12
    //   611: aload 12
    //   613: ldc_w 374
    //   616: invokespecial 223	java/lang/StringBuilder:<init>	(Ljava/lang/String;)V
    //   619: aload 11
    //   621: aload 12
    //   623: iload_3
    //   624: invokevirtual 228	java/lang/StringBuilder:append	(I)Ljava/lang/StringBuilder;
    //   627: ldc_w 376
    //   630: invokevirtual 202	java/lang/StringBuilder:append	(Ljava/lang/String;)Ljava/lang/StringBuilder;
    //   633: lload 7
    //   635: invokevirtual 220	java/lang/StringBuilder:append	(J)Ljava/lang/StringBuilder;
    //   638: invokevirtual 210	java/lang/StringBuilder:toString	()Ljava/lang/String;
    //   641: invokevirtual 233	com/tencent/wxop/stat/b/b:b	(Ljava/lang/Object;)V
    //   644: lload 7
    //   646: lconst_0
    //   647: lcmp
    //   648: ifgt +204 -> 852
    //   651: getstatic 28	com/tencent/wxop/stat/ak:cx	Lcom/tencent/wxop/stat/b/b;
    //   654: ldc_w 378
    //   657: invokevirtual 381	com/tencent/wxop/stat/b/b:d	(Ljava/lang/Object;)V
    //   660: aload_2
    //   661: ifnull +9 -> 670
    //   664: aload_2
    //   665: invokeinterface 386 1 0
    //   670: aload 9
    //   672: invokestatic 391	org/apache/http/util/EntityUtils:toString	(Lorg/apache/http/HttpEntity;)Ljava/lang/String;
    //   675: pop
    //   676: goto -660 -> 16
    //   679: astore_1
    //   680: aload_1
    //   681: ifnull -665 -> 16
    //   684: getstatic 28	com/tencent/wxop/stat/ak:cx	Lcom/tencent/wxop/stat/b/b;
    //   687: aload_1
    //   688: invokevirtual 393	com/tencent/wxop/stat/b/b:a	(Ljava/lang/Throwable;)V
    //   691: aload_2
    //   692: ifnull +9 -> 701
    //   695: aload_2
    //   696: invokeinterface 386 1 0
    //   701: aload_1
    //   702: instanceof 395
    //   705: ifeq +25 -> 730
    //   708: invokestatic 398	java/lang/System:gc	()V
    //   711: aload_0
    //   712: aconst_null
    //   713: putfield 50	com/tencent/wxop/stat/ak:di	Ljava/lang/StringBuilder;
    //   716: aload_0
    //   717: new 45	java/lang/StringBuilder
    //   720: dup
    //   721: sipush 2048
    //   724: invokespecial 48	java/lang/StringBuilder:<init>	(I)V
    //   727: putfield 50	com/tencent/wxop/stat/ak:di	Ljava/lang/StringBuilder;
    //   730: getstatic 32	com/tencent/wxop/stat/ak:dk	Landroid/content/Context;
    //   733: invokestatic 262	com/tencent/wxop/stat/g:r	(Landroid/content/Context;)Lcom/tencent/wxop/stat/g;
    //   736: invokevirtual 400	com/tencent/wxop/stat/g:I	()V
    //   739: goto -723 -> 16
    //   742: invokestatic 75	com/tencent/wxop/stat/c:k	()Z
    //   745: ifeq +39 -> 784
    //   748: getstatic 28	com/tencent/wxop/stat/ak:cx	Lcom/tencent/wxop/stat/b/b;
    //   751: astore 10
    //   753: new 45	java/lang/StringBuilder
    //   756: astore 9
    //   758: aload 9
    //   760: ldc_w 402
    //   763: invokespecial 223	java/lang/StringBuilder:<init>	(Ljava/lang/String;)V
    //   766: aload 10
    //   768: aload 9
    //   770: aload 12
    //   772: invokevirtual 407	org/apache/http/HttpHost:toHostString	()Ljava/lang/String;
    //   775: invokevirtual 202	java/lang/StringBuilder:append	(Ljava/lang/String;)Ljava/lang/StringBuilder;
    //   778: invokevirtual 210	java/lang/StringBuilder:toString	()Ljava/lang/String;
    //   781: invokevirtual 335	com/tencent/wxop/stat/b/b:e	(Ljava/lang/Object;)V
    //   784: aload 11
    //   786: ldc_w 299
    //   789: ldc_w 270
    //   792: invokevirtual 244	org/apache/http/client/methods/HttpPost:addHeader	(Ljava/lang/String;Ljava/lang/String;)V
    //   795: aload_0
    //   796: getfield 41	com/tencent/wxop/stat/ak:dg	Lorg/apache/http/impl/client/DefaultHttpClient;
    //   799: invokevirtual 274	org/apache/http/impl/client/DefaultHttpClient:getParams	()Lorg/apache/http/params/HttpParams;
    //   802: ldc_w 276
    //   805: aload 12
    //   807: invokeinterface 411 3 0
    //   812: pop
    //   813: aload 11
    //   815: ldc_w 413
    //   818: getstatic 417	com/tencent/wxop/stat/c:al	Ljava/lang/String;
    //   821: invokevirtual 244	org/apache/http/client/methods/HttpPost:addHeader	(Ljava/lang/String;Ljava/lang/String;)V
    //   824: aload 11
    //   826: ldc_w 419
    //   829: ldc_w 421
    //   832: invokevirtual 244	org/apache/http/client/methods/HttpPost:addHeader	(Ljava/lang/String;Ljava/lang/String;)V
    //   835: aload 11
    //   837: ldc_w 423
    //   840: ldc_w 425
    //   843: invokevirtual 244	org/apache/http/client/methods/HttpPost:addHeader	(Ljava/lang/String;Ljava/lang/String;)V
    //   846: goto -531 -> 315
    //   849: astore_1
    //   850: aload_1
    //   851: athrow
    //   852: lload 7
    //   854: lconst_0
    //   855: lcmp
    //   856: ifle +573 -> 1429
    //   859: aload 9
    //   861: invokeinterface 429 1 0
    //   866: astore 11
    //   868: new 431	java/io/DataInputStream
    //   871: astore 12
    //   873: aload 12
    //   875: aload 11
    //   877: invokespecial 434	java/io/DataInputStream:<init>	(Ljava/io/InputStream;)V
    //   880: aload 9
    //   882: invokeinterface 372 1 0
    //   887: l2i
    //   888: newarray <illegal type>
    //   890: astore 9
    //   892: aload 12
    //   894: aload 9
    //   896: invokevirtual 437	java/io/DataInputStream:readFully	([B)V
    //   899: aload 11
    //   901: invokevirtual 440	java/io/InputStream:close	()V
    //   904: aload 12
    //   906: invokevirtual 441	java/io/DataInputStream:close	()V
    //   909: aload_1
    //   910: ldc_w 268
    //   913: invokeinterface 445 2 0
    //   918: astore 12
    //   920: aload 9
    //   922: astore_1
    //   923: aload 12
    //   925: ifnull +28 -> 953
    //   928: aload 12
    //   930: invokeinterface 450 1 0
    //   935: ldc_w 452
    //   938: invokevirtual 455	java/lang/String:equalsIgnoreCase	(Ljava/lang/String;)Z
    //   941: ifeq +305 -> 1246
    //   944: aload 9
    //   946: invokestatic 456	com/tencent/wxop/stat/b/l:b	([B)[B
    //   949: invokestatic 459	com/tencent/wxop/stat/b/g:c	([B)[B
    //   952: astore_1
    //   953: new 161	java/lang/String
    //   956: astore 12
    //   958: aload 12
    //   960: aload_1
    //   961: ldc_w 287
    //   964: invokespecial 462	java/lang/String:<init>	([BLjava/lang/String;)V
    //   967: invokestatic 75	com/tencent/wxop/stat/c:k	()Z
    //   970: ifeq +36 -> 1006
    //   973: getstatic 28	com/tencent/wxop/stat/ak:cx	Lcom/tencent/wxop/stat/b/b;
    //   976: astore 9
    //   978: new 45	java/lang/StringBuilder
    //   981: astore 13
    //   983: aload 13
    //   985: ldc_w 464
    //   988: invokespecial 223	java/lang/StringBuilder:<init>	(Ljava/lang/String;)V
    //   991: aload 9
    //   993: aload 13
    //   995: aload 12
    //   997: invokevirtual 202	java/lang/StringBuilder:append	(Ljava/lang/String;)Ljava/lang/StringBuilder;
    //   1000: invokevirtual 210	java/lang/StringBuilder:toString	()Ljava/lang/String;
    //   1003: invokevirtual 233	com/tencent/wxop/stat/b/b:b	(Ljava/lang/Object;)V
    //   1006: new 466	org/json/JSONObject
    //   1009: astore 9
    //   1011: aload 9
    //   1013: aload 12
    //   1015: invokespecial 467	org/json/JSONObject:<init>	(Ljava/lang/String;)V
    //   1018: iload_3
    //   1019: sipush 200
    //   1022: if_icmpne +333 -> 1355
    //   1025: aload 9
    //   1027: ldc_w 469
    //   1030: invokevirtual 473	org/json/JSONObject:optString	(Ljava/lang/String;)Ljava/lang/String;
    //   1033: astore 12
    //   1035: aload 12
    //   1037: invokestatic 477	com/tencent/a/a/a/a/h:e	(Ljava/lang/String;)Z
    //   1040: ifeq +50 -> 1090
    //   1043: invokestatic 75	com/tencent/wxop/stat/c:k	()Z
    //   1046: ifeq +33 -> 1079
    //   1049: getstatic 28	com/tencent/wxop/stat/ak:cx	Lcom/tencent/wxop/stat/b/b;
    //   1052: astore 13
    //   1054: new 45	java/lang/StringBuilder
    //   1057: astore_1
    //   1058: aload_1
    //   1059: ldc_w 479
    //   1062: invokespecial 223	java/lang/StringBuilder:<init>	(Ljava/lang/String;)V
    //   1065: aload 13
    //   1067: aload_1
    //   1068: aload 12
    //   1070: invokevirtual 202	java/lang/StringBuilder:append	(Ljava/lang/String;)Ljava/lang/StringBuilder;
    //   1073: invokevirtual 210	java/lang/StringBuilder:toString	()Ljava/lang/String;
    //   1076: invokevirtual 233	com/tencent/wxop/stat/b/b:b	(Ljava/lang/Object;)V
    //   1079: getstatic 32	com/tencent/wxop/stat/ak:dk	Landroid/content/Context;
    //   1082: invokestatic 484	com/tencent/a/a/a/a/g:a	(Landroid/content/Context;)Lcom/tencent/a/a/a/a/g;
    //   1085: aload 12
    //   1087: invokevirtual 486	com/tencent/a/a/a/a/g:b	(Ljava/lang/String;)V
    //   1090: aload 9
    //   1092: ldc_w 488
    //   1095: invokevirtual 491	org/json/JSONObject:isNull	(Ljava/lang/String;)Z
    //   1098: ifne +19 -> 1117
    //   1101: aload 9
    //   1103: ldc_w 488
    //   1106: invokevirtual 495	org/json/JSONObject:getJSONObject	(Ljava/lang/String;)Lorg/json/JSONObject;
    //   1109: astore_1
    //   1110: getstatic 32	com/tencent/wxop/stat/ak:dk	Landroid/content/Context;
    //   1113: aload_1
    //   1114: invokestatic 498	com/tencent/wxop/stat/c:a	(Landroid/content/Context;Lorg/json/JSONObject;)V
    //   1117: aload 9
    //   1119: ldc_w 500
    //   1122: invokevirtual 491	org/json/JSONObject:isNull	(Ljava/lang/String;)Z
    //   1125: ifne +85 -> 1210
    //   1128: aload 9
    //   1130: ldc_w 500
    //   1133: invokevirtual 504	org/json/JSONObject:getInt	(Ljava/lang/String;)I
    //   1136: istore_3
    //   1137: iload_3
    //   1138: i2l
    //   1139: invokestatic 64	java/lang/System:currentTimeMillis	()J
    //   1142: ldc2_w 65
    //   1145: ldiv
    //   1146: lsub
    //   1147: l2i
    //   1148: istore 4
    //   1150: invokestatic 75	com/tencent/wxop/stat/c:k	()Z
    //   1153: ifeq +43 -> 1196
    //   1156: getstatic 28	com/tencent/wxop/stat/ak:cx	Lcom/tencent/wxop/stat/b/b;
    //   1159: astore 12
    //   1161: new 45	java/lang/StringBuilder
    //   1164: astore_1
    //   1165: aload_1
    //   1166: ldc_w 506
    //   1169: invokespecial 223	java/lang/StringBuilder:<init>	(Ljava/lang/String;)V
    //   1172: aload 12
    //   1174: aload_1
    //   1175: iload_3
    //   1176: invokevirtual 228	java/lang/StringBuilder:append	(I)Ljava/lang/StringBuilder;
    //   1179: ldc_w 508
    //   1182: invokevirtual 202	java/lang/StringBuilder:append	(Ljava/lang/String;)Ljava/lang/StringBuilder;
    //   1185: iload 4
    //   1187: invokevirtual 228	java/lang/StringBuilder:append	(I)Ljava/lang/StringBuilder;
    //   1190: invokevirtual 210	java/lang/StringBuilder:toString	()Ljava/lang/String;
    //   1193: invokevirtual 233	com/tencent/wxop/stat/b/b:b	(Ljava/lang/Object;)V
    //   1196: getstatic 32	com/tencent/wxop/stat/ak:dk	Landroid/content/Context;
    //   1199: invokestatic 511	com/tencent/wxop/stat/b/l:Q	(Landroid/content/Context;)V
    //   1202: getstatic 32	com/tencent/wxop/stat/ak:dk	Landroid/content/Context;
    //   1205: iload 4
    //   1207: invokestatic 514	com/tencent/wxop/stat/b/l:a	(Landroid/content/Context;I)V
    //   1210: aload_2
    //   1211: ifnull +20 -> 1231
    //   1214: aload 9
    //   1216: ldc_w 516
    //   1219: invokevirtual 519	org/json/JSONObject:optInt	(Ljava/lang/String;)I
    //   1222: ifne +115 -> 1337
    //   1225: aload_2
    //   1226: invokeinterface 522 1 0
    //   1231: aload 11
    //   1233: invokevirtual 440	java/io/InputStream:close	()V
    //   1236: aload 10
    //   1238: invokevirtual 523	java/io/ByteArrayOutputStream:close	()V
    //   1241: aconst_null
    //   1242: astore_1
    //   1243: goto -563 -> 680
    //   1246: aload 12
    //   1248: invokeinterface 450 1 0
    //   1253: ldc_w 525
    //   1256: invokevirtual 455	java/lang/String:equalsIgnoreCase	(Ljava/lang/String;)Z
    //   1259: ifeq +15 -> 1274
    //   1262: aload 9
    //   1264: invokestatic 459	com/tencent/wxop/stat/b/g:c	([B)[B
    //   1267: invokestatic 456	com/tencent/wxop/stat/b/l:b	([B)[B
    //   1270: astore_1
    //   1271: goto -318 -> 953
    //   1274: aload 12
    //   1276: invokeinterface 450 1 0
    //   1281: ldc -16
    //   1283: invokevirtual 455	java/lang/String:equalsIgnoreCase	(Ljava/lang/String;)Z
    //   1286: ifeq +12 -> 1298
    //   1289: aload 9
    //   1291: invokestatic 456	com/tencent/wxop/stat/b/l:b	([B)[B
    //   1294: astore_1
    //   1295: goto -342 -> 953
    //   1298: aload 9
    //   1300: astore_1
    //   1301: aload 12
    //   1303: invokeinterface 450 1 0
    //   1308: ldc_w 270
    //   1311: invokevirtual 455	java/lang/String:equalsIgnoreCase	(Ljava/lang/String;)Z
    //   1314: ifeq -361 -> 953
    //   1317: aload 9
    //   1319: invokestatic 459	com/tencent/wxop/stat/b/g:c	([B)[B
    //   1322: astore_1
    //   1323: goto -370 -> 953
    //   1326: astore_1
    //   1327: getstatic 28	com/tencent/wxop/stat/ak:cx	Lcom/tencent/wxop/stat/b/b;
    //   1330: aload_1
    //   1331: invokevirtual 527	com/tencent/wxop/stat/b/b:c	(Ljava/lang/Object;)V
    //   1334: goto -124 -> 1210
    //   1337: getstatic 28	com/tencent/wxop/stat/ak:cx	Lcom/tencent/wxop/stat/b/b;
    //   1340: ldc_w 529
    //   1343: invokevirtual 532	com/tencent/wxop/stat/b/b:error	(Ljava/lang/Object;)V
    //   1346: aload_2
    //   1347: invokeinterface 386 1 0
    //   1352: goto -121 -> 1231
    //   1355: getstatic 28	com/tencent/wxop/stat/ak:cx	Lcom/tencent/wxop/stat/b/b;
    //   1358: astore 9
    //   1360: new 45	java/lang/StringBuilder
    //   1363: astore 12
    //   1365: aload 12
    //   1367: ldc_w 534
    //   1370: invokespecial 223	java/lang/StringBuilder:<init>	(Ljava/lang/String;)V
    //   1373: aload 12
    //   1375: iload_3
    //   1376: invokevirtual 228	java/lang/StringBuilder:append	(I)Ljava/lang/StringBuilder;
    //   1379: ldc_w 536
    //   1382: invokevirtual 202	java/lang/StringBuilder:append	(Ljava/lang/String;)Ljava/lang/StringBuilder;
    //   1385: astore 12
    //   1387: new 161	java/lang/String
    //   1390: astore 13
    //   1392: aload 13
    //   1394: aload_1
    //   1395: ldc_w 287
    //   1398: invokespecial 462	java/lang/String:<init>	([BLjava/lang/String;)V
    //   1401: aload 9
    //   1403: aload 12
    //   1405: aload 13
    //   1407: invokevirtual 202	java/lang/StringBuilder:append	(Ljava/lang/String;)Ljava/lang/StringBuilder;
    //   1410: invokevirtual 210	java/lang/StringBuilder:toString	()Ljava/lang/String;
    //   1413: invokevirtual 532	com/tencent/wxop/stat/b/b:error	(Ljava/lang/Object;)V
    //   1416: aload_2
    //   1417: ifnull -186 -> 1231
    //   1420: aload_2
    //   1421: invokeinterface 386 1 0
    //   1426: goto -195 -> 1231
    //   1429: aload 9
    //   1431: invokestatic 391	org/apache/http/util/EntityUtils:toString	(Lorg/apache/http/HttpEntity;)Ljava/lang/String;
    //   1434: pop
    //   1435: goto -199 -> 1236
    //   1438: astore_2
    //   1439: getstatic 28	com/tencent/wxop/stat/ak:cx	Lcom/tencent/wxop/stat/b/b;
    //   1442: aload_2
    //   1443: invokevirtual 151	com/tencent/wxop/stat/b/b:b	(Ljava/lang/Throwable;)V
    //   1446: goto -745 -> 701
    // Local variable table:
    //   start	length	slot	name	signature
    //   0	1449	0	this	ak
    //   0	1449	1	paramList	List<?>
    //   0	1449	2	paramaj	aj
    //   60	1316	3	i	int
    //   1	1205	4	j	int
    //   23	480	5	k	int
    //   131	219	6	m	int
    //   593	260	7	l	long
    //   136	1294	9	localObject1	Object
    //   192	1045	10	localObject2	Object
    //   187	1045	11	localObject3	Object
    //   281	1123	12	localObject4	Object
    //   981	425	13	localObject5	Object
    // Exception table:
    //   from	to	target	type
    //   33	59	679	java/lang/Throwable
    //   67	85	679	java/lang/Throwable
    //   93	103	679	java/lang/Throwable
    //   109	235	679	java/lang/Throwable
    //   235	294	679	java/lang/Throwable
    //   299	315	679	java/lang/Throwable
    //   315	341	679	java/lang/Throwable
    //   344	352	679	java/lang/Throwable
    //   361	403	679	java/lang/Throwable
    //   408	425	679	java/lang/Throwable
    //   425	473	679	java/lang/Throwable
    //   476	531	679	java/lang/Throwable
    //   534	644	679	java/lang/Throwable
    //   651	660	679	java/lang/Throwable
    //   664	670	679	java/lang/Throwable
    //   670	676	679	java/lang/Throwable
    //   742	784	679	java/lang/Throwable
    //   784	846	679	java/lang/Throwable
    //   859	920	679	java/lang/Throwable
    //   928	953	679	java/lang/Throwable
    //   953	1006	679	java/lang/Throwable
    //   1006	1018	679	java/lang/Throwable
    //   1214	1231	679	java/lang/Throwable
    //   1231	1236	679	java/lang/Throwable
    //   1236	1241	679	java/lang/Throwable
    //   1246	1271	679	java/lang/Throwable
    //   1274	1295	679	java/lang/Throwable
    //   1301	1323	679	java/lang/Throwable
    //   1327	1334	679	java/lang/Throwable
    //   1337	1352	679	java/lang/Throwable
    //   1355	1416	679	java/lang/Throwable
    //   1420	1426	679	java/lang/Throwable
    //   1429	1435	679	java/lang/Throwable
    //   33	59	849	finally
    //   67	85	849	finally
    //   93	103	849	finally
    //   109	235	849	finally
    //   235	294	849	finally
    //   299	315	849	finally
    //   315	341	849	finally
    //   344	352	849	finally
    //   361	403	849	finally
    //   408	425	849	finally
    //   425	473	849	finally
    //   476	531	849	finally
    //   534	644	849	finally
    //   651	660	849	finally
    //   664	670	849	finally
    //   670	676	849	finally
    //   742	784	849	finally
    //   784	846	849	finally
    //   859	920	849	finally
    //   928	953	849	finally
    //   953	1006	849	finally
    //   1006	1018	849	finally
    //   1025	1079	849	finally
    //   1079	1090	849	finally
    //   1090	1117	849	finally
    //   1117	1196	849	finally
    //   1196	1210	849	finally
    //   1214	1231	849	finally
    //   1231	1236	849	finally
    //   1236	1241	849	finally
    //   1246	1271	849	finally
    //   1274	1295	849	finally
    //   1301	1323	849	finally
    //   1327	1334	849	finally
    //   1337	1352	849	finally
    //   1355	1416	849	finally
    //   1420	1426	849	finally
    //   1429	1435	849	finally
    //   1025	1079	1326	java/lang/Throwable
    //   1079	1090	1326	java/lang/Throwable
    //   1090	1117	1326	java/lang/Throwable
    //   1117	1196	1326	java/lang/Throwable
    //   1196	1210	1326	java/lang/Throwable
    //   695	701	1438	java/lang/Throwable
  }
  
  final void b(List<?> paramList, aj paramaj)
  {
    if (this.dh != null) {
      this.dh.a(new am(this, paramList, paramaj));
    }
  }
}


/* Location:              /Users/hanlian/Downloads/WiFi万能钥匙dex1-dex2jar.jar!/com/tencent/wxop/stat/ak.class
 * Java compiler version: 6 (50.0)
 * JD-Core Version:       0.7.1
 */