package com.tencent.wxop.stat;

import android.content.Context;

final class as
  implements Runnable
{
  as(String paramString, Context paramContext, f paramf) {}
  
  /* Error */
  public final void run()
  {
    // Byte code:
    //   0: invokestatic 33	com/tencent/wxop/stat/e:M	()Ljava/util/Map;
    //   3: astore_1
    //   4: aload_1
    //   5: monitorenter
    //   6: invokestatic 33	com/tencent/wxop/stat/e:M	()Ljava/util/Map;
    //   9: invokeinterface 39 1 0
    //   14: invokestatic 44	com/tencent/wxop/stat/c:v	()I
    //   17: if_icmplt +37 -> 54
    //   20: invokestatic 48	com/tencent/wxop/stat/e:K	()Lcom/tencent/wxop/stat/b/b;
    //   23: astore_2
    //   24: new 50	java/lang/StringBuilder
    //   27: astore_3
    //   28: aload_3
    //   29: ldc 52
    //   31: invokespecial 55	java/lang/StringBuilder:<init>	(Ljava/lang/String;)V
    //   34: aload_2
    //   35: aload_3
    //   36: invokestatic 44	com/tencent/wxop/stat/c:v	()I
    //   39: invokestatic 61	java/lang/Integer:toString	(I)Ljava/lang/String;
    //   42: invokevirtual 65	java/lang/StringBuilder:append	(Ljava/lang/String;)Ljava/lang/StringBuilder;
    //   45: invokevirtual 68	java/lang/StringBuilder:toString	()Ljava/lang/String;
    //   48: invokevirtual 74	com/tencent/wxop/stat/b/b:error	(Ljava/lang/Object;)V
    //   51: aload_1
    //   52: monitorexit
    //   53: return
    //   54: aload_0
    //   55: getfield 16	com/tencent/wxop/stat/as:a	Ljava/lang/String;
    //   58: invokestatic 78	com/tencent/wxop/stat/e:q	(Ljava/lang/String;)Ljava/lang/String;
    //   61: pop
    //   62: invokestatic 33	com/tencent/wxop/stat/e:M	()Ljava/util/Map;
    //   65: invokestatic 81	com/tencent/wxop/stat/e:N	()Ljava/lang/String;
    //   68: invokeinterface 85 2 0
    //   73: ifeq +65 -> 138
    //   76: invokestatic 48	com/tencent/wxop/stat/e:K	()Lcom/tencent/wxop/stat/b/b;
    //   79: astore_2
    //   80: new 50	java/lang/StringBuilder
    //   83: astore_3
    //   84: aload_3
    //   85: ldc 87
    //   87: invokespecial 55	java/lang/StringBuilder:<init>	(Ljava/lang/String;)V
    //   90: aload_2
    //   91: aload_3
    //   92: invokestatic 81	com/tencent/wxop/stat/e:N	()Ljava/lang/String;
    //   95: invokevirtual 65	java/lang/StringBuilder:append	(Ljava/lang/String;)Ljava/lang/StringBuilder;
    //   98: ldc 89
    //   100: invokevirtual 65	java/lang/StringBuilder:append	(Ljava/lang/String;)Ljava/lang/StringBuilder;
    //   103: invokevirtual 68	java/lang/StringBuilder:toString	()Ljava/lang/String;
    //   106: invokevirtual 92	com/tencent/wxop/stat/b/b:d	(Ljava/lang/Object;)V
    //   109: aload_1
    //   110: monitorexit
    //   111: goto -58 -> 53
    //   114: astore_2
    //   115: aload_1
    //   116: monitorexit
    //   117: aload_2
    //   118: athrow
    //   119: astore_1
    //   120: invokestatic 48	com/tencent/wxop/stat/e:K	()Lcom/tencent/wxop/stat/b/b;
    //   123: aload_1
    //   124: invokevirtual 96	com/tencent/wxop/stat/b/b:b	(Ljava/lang/Throwable;)V
    //   127: aload_0
    //   128: getfield 18	com/tencent/wxop/stat/as:co	Landroid/content/Context;
    //   131: aload_1
    //   132: invokestatic 99	com/tencent/wxop/stat/e:a	(Landroid/content/Context;Ljava/lang/Throwable;)V
    //   135: goto -82 -> 53
    //   138: invokestatic 33	com/tencent/wxop/stat/e:M	()Ljava/util/Map;
    //   141: invokestatic 81	com/tencent/wxop/stat/e:N	()Ljava/lang/String;
    //   144: invokestatic 105	java/lang/System:currentTimeMillis	()J
    //   147: invokestatic 111	java/lang/Long:valueOf	(J)Ljava/lang/Long;
    //   150: invokeinterface 115 3 0
    //   155: pop
    //   156: aload_1
    //   157: monitorexit
    //   158: aload_0
    //   159: getfield 18	com/tencent/wxop/stat/as:co	Landroid/content/Context;
    //   162: iconst_1
    //   163: aload_0
    //   164: getfield 20	com/tencent/wxop/stat/as:bM	Lcom/tencent/wxop/stat/f;
    //   167: invokestatic 118	com/tencent/wxop/stat/e:a	(Landroid/content/Context;ZLcom/tencent/wxop/stat/f;)I
    //   170: pop
    //   171: goto -118 -> 53
    // Local variable table:
    //   start	length	slot	name	signature
    //   0	174	0	this	as
    //   119	38	1	localThrowable	Throwable
    //   23	68	2	localb	com.tencent.wxop.stat.b.b
    //   114	4	2	localObject	Object
    //   27	65	3	localStringBuilder	StringBuilder
    // Exception table:
    //   from	to	target	type
    //   6	53	114	finally
    //   54	111	114	finally
    //   138	158	114	finally
    //   0	6	119	java/lang/Throwable
    //   115	119	119	java/lang/Throwable
    //   158	171	119	java/lang/Throwable
  }
}


/* Location:              /Users/hanlian/Downloads/WiFi万能钥匙dex1-dex2jar.jar!/com/tencent/wxop/stat/as.class
 * Java compiler version: 6 (50.0)
 * JD-Core Version:       0.7.1
 */