package com.c.e.a.a.a.a;

import com.b.b.ak.a;
import com.b.b.h;
import com.b.b.m;
import com.b.b.m.a;
import com.b.b.r;
import com.b.b.t;
import com.b.b.v;
import com.b.b.x;
import java.util.Iterator;
import java.util.Map;
import java.util.Map.Entry;
import java.util.Set;

public final class a
{
  public static final class a
    extends m<a, a>
    implements a.b
  {
    private static final a r;
    private static volatile x<a> s;
    private int d;
    private String e = "";
    private String f = "";
    private String g = "";
    private String h = "";
    private String i = "";
    private String j = "";
    private String k = "";
    private String l = "";
    private String m = "";
    private String n = "";
    private String o = "";
    private String p = "";
    private t<String, String> q = t.a();
    
    static
    {
      a locala = new a();
      r = locala;
      locala.e();
    }
    
    public static a l()
    {
      return (a)r.g();
    }
    
    /* Error */
    protected final Object a(int paramInt, Object paramObject1, Object paramObject2)
    {
      // Byte code:
      //   0: iconst_1
      //   1: istore 7
      //   3: iconst_0
      //   4: istore 4
      //   6: getstatic 108	com/c/e/a/a/a/a/a$1:a	[I
      //   9: iload_1
      //   10: iconst_1
      //   11: isub
      //   12: iaload
      //   13: tableswitch	default:+47->60, 1:+55->68, 2:+65->78, 3:+72->85, 4:+84->97, 5:+96->109, 6:+911->924, 7:+1295->1308, 8:+1302->1315
      //   60: new 110	java/lang/UnsupportedOperationException
      //   63: dup
      //   64: invokespecial 111	java/lang/UnsupportedOperationException:<init>	()V
      //   67: athrow
      //   68: new 2	com/c/e/a/a/a/a/a$a
      //   71: dup
      //   72: invokespecial 43	com/c/e/a/a/a/a/a$a:<init>	()V
      //   75: astore_2
      //   76: aload_2
      //   77: areturn
      //   78: getstatic 45	com/c/e/a/a/a/a/a$a:r	Lcom/c/e/a/a/a/a/a$a;
      //   81: astore_2
      //   82: goto -6 -> 76
      //   85: aload_0
      //   86: getfield 56	com/c/e/a/a/a/a/a$a:q	Lcom/b/b/t;
      //   89: invokevirtual 113	com/b/b/t:c	()V
      //   92: aconst_null
      //   93: astore_2
      //   94: goto -18 -> 76
      //   97: new 12	com/c/e/a/a/a/a/a$a$a
      //   100: dup
      //   101: iconst_0
      //   102: invokespecial 116	com/c/e/a/a/a/a/a$a$a:<init>	(B)V
      //   105: astore_2
      //   106: goto -30 -> 76
      //   109: aload_2
      //   110: checkcast 118	com/b/b/m$j
      //   113: astore 8
      //   115: aload_3
      //   116: checkcast 2	com/c/e/a/a/a/a/a$a
      //   119: astore_3
      //   120: aload_0
      //   121: getfield 60	com/c/e/a/a/a/a/a$a:e	Ljava/lang/String;
      //   124: invokevirtual 123	java/lang/String:isEmpty	()Z
      //   127: ifne +653 -> 780
      //   130: iconst_1
      //   131: istore 5
      //   133: aload_0
      //   134: getfield 60	com/c/e/a/a/a/a/a$a:e	Ljava/lang/String;
      //   137: astore_2
      //   138: aload_3
      //   139: getfield 60	com/c/e/a/a/a/a/a$a:e	Ljava/lang/String;
      //   142: invokevirtual 123	java/lang/String:isEmpty	()Z
      //   145: ifne +641 -> 786
      //   148: iconst_1
      //   149: istore 6
      //   151: aload_0
      //   152: aload 8
      //   154: iload 5
      //   156: aload_2
      //   157: iload 6
      //   159: aload_3
      //   160: getfield 60	com/c/e/a/a/a/a/a$a:e	Ljava/lang/String;
      //   163: invokeinterface 126 5 0
      //   168: putfield 60	com/c/e/a/a/a/a/a$a:e	Ljava/lang/String;
      //   171: aload_0
      //   172: getfield 62	com/c/e/a/a/a/a/a$a:f	Ljava/lang/String;
      //   175: invokevirtual 123	java/lang/String:isEmpty	()Z
      //   178: ifne +614 -> 792
      //   181: iconst_1
      //   182: istore 5
      //   184: aload_0
      //   185: getfield 62	com/c/e/a/a/a/a/a$a:f	Ljava/lang/String;
      //   188: astore_2
      //   189: aload_3
      //   190: getfield 62	com/c/e/a/a/a/a/a$a:f	Ljava/lang/String;
      //   193: invokevirtual 123	java/lang/String:isEmpty	()Z
      //   196: ifne +602 -> 798
      //   199: iconst_1
      //   200: istore 6
      //   202: aload_0
      //   203: aload 8
      //   205: iload 5
      //   207: aload_2
      //   208: iload 6
      //   210: aload_3
      //   211: getfield 62	com/c/e/a/a/a/a/a$a:f	Ljava/lang/String;
      //   214: invokeinterface 126 5 0
      //   219: putfield 62	com/c/e/a/a/a/a/a$a:f	Ljava/lang/String;
      //   222: aload_0
      //   223: getfield 64	com/c/e/a/a/a/a/a$a:g	Ljava/lang/String;
      //   226: invokevirtual 123	java/lang/String:isEmpty	()Z
      //   229: ifne +575 -> 804
      //   232: iconst_1
      //   233: istore 5
      //   235: aload_0
      //   236: getfield 64	com/c/e/a/a/a/a/a$a:g	Ljava/lang/String;
      //   239: astore_2
      //   240: aload_3
      //   241: getfield 64	com/c/e/a/a/a/a/a$a:g	Ljava/lang/String;
      //   244: invokevirtual 123	java/lang/String:isEmpty	()Z
      //   247: ifne +563 -> 810
      //   250: iconst_1
      //   251: istore 6
      //   253: aload_0
      //   254: aload 8
      //   256: iload 5
      //   258: aload_2
      //   259: iload 6
      //   261: aload_3
      //   262: getfield 64	com/c/e/a/a/a/a/a$a:g	Ljava/lang/String;
      //   265: invokeinterface 126 5 0
      //   270: putfield 64	com/c/e/a/a/a/a/a$a:g	Ljava/lang/String;
      //   273: aload_0
      //   274: getfield 66	com/c/e/a/a/a/a/a$a:h	Ljava/lang/String;
      //   277: invokevirtual 123	java/lang/String:isEmpty	()Z
      //   280: ifne +536 -> 816
      //   283: iconst_1
      //   284: istore 5
      //   286: aload_0
      //   287: getfield 66	com/c/e/a/a/a/a/a$a:h	Ljava/lang/String;
      //   290: astore_2
      //   291: aload_3
      //   292: getfield 66	com/c/e/a/a/a/a/a$a:h	Ljava/lang/String;
      //   295: invokevirtual 123	java/lang/String:isEmpty	()Z
      //   298: ifne +524 -> 822
      //   301: iconst_1
      //   302: istore 6
      //   304: aload_0
      //   305: aload 8
      //   307: iload 5
      //   309: aload_2
      //   310: iload 6
      //   312: aload_3
      //   313: getfield 66	com/c/e/a/a/a/a/a$a:h	Ljava/lang/String;
      //   316: invokeinterface 126 5 0
      //   321: putfield 66	com/c/e/a/a/a/a/a$a:h	Ljava/lang/String;
      //   324: aload_0
      //   325: getfield 68	com/c/e/a/a/a/a/a$a:i	Ljava/lang/String;
      //   328: invokevirtual 123	java/lang/String:isEmpty	()Z
      //   331: ifne +497 -> 828
      //   334: iconst_1
      //   335: istore 5
      //   337: aload_0
      //   338: getfield 68	com/c/e/a/a/a/a/a$a:i	Ljava/lang/String;
      //   341: astore_2
      //   342: aload_3
      //   343: getfield 68	com/c/e/a/a/a/a/a$a:i	Ljava/lang/String;
      //   346: invokevirtual 123	java/lang/String:isEmpty	()Z
      //   349: ifne +485 -> 834
      //   352: iconst_1
      //   353: istore 6
      //   355: aload_0
      //   356: aload 8
      //   358: iload 5
      //   360: aload_2
      //   361: iload 6
      //   363: aload_3
      //   364: getfield 68	com/c/e/a/a/a/a/a$a:i	Ljava/lang/String;
      //   367: invokeinterface 126 5 0
      //   372: putfield 68	com/c/e/a/a/a/a/a$a:i	Ljava/lang/String;
      //   375: aload_0
      //   376: getfield 70	com/c/e/a/a/a/a/a$a:j	Ljava/lang/String;
      //   379: invokevirtual 123	java/lang/String:isEmpty	()Z
      //   382: ifne +458 -> 840
      //   385: iconst_1
      //   386: istore 5
      //   388: aload_0
      //   389: getfield 70	com/c/e/a/a/a/a/a$a:j	Ljava/lang/String;
      //   392: astore_2
      //   393: aload_3
      //   394: getfield 70	com/c/e/a/a/a/a/a$a:j	Ljava/lang/String;
      //   397: invokevirtual 123	java/lang/String:isEmpty	()Z
      //   400: ifne +446 -> 846
      //   403: iconst_1
      //   404: istore 6
      //   406: aload_0
      //   407: aload 8
      //   409: iload 5
      //   411: aload_2
      //   412: iload 6
      //   414: aload_3
      //   415: getfield 70	com/c/e/a/a/a/a/a$a:j	Ljava/lang/String;
      //   418: invokeinterface 126 5 0
      //   423: putfield 70	com/c/e/a/a/a/a/a$a:j	Ljava/lang/String;
      //   426: aload_0
      //   427: getfield 72	com/c/e/a/a/a/a/a$a:k	Ljava/lang/String;
      //   430: invokevirtual 123	java/lang/String:isEmpty	()Z
      //   433: ifne +419 -> 852
      //   436: iconst_1
      //   437: istore 5
      //   439: aload_0
      //   440: getfield 72	com/c/e/a/a/a/a/a$a:k	Ljava/lang/String;
      //   443: astore_2
      //   444: aload_3
      //   445: getfield 72	com/c/e/a/a/a/a/a$a:k	Ljava/lang/String;
      //   448: invokevirtual 123	java/lang/String:isEmpty	()Z
      //   451: ifne +407 -> 858
      //   454: iconst_1
      //   455: istore 6
      //   457: aload_0
      //   458: aload 8
      //   460: iload 5
      //   462: aload_2
      //   463: iload 6
      //   465: aload_3
      //   466: getfield 72	com/c/e/a/a/a/a/a$a:k	Ljava/lang/String;
      //   469: invokeinterface 126 5 0
      //   474: putfield 72	com/c/e/a/a/a/a/a$a:k	Ljava/lang/String;
      //   477: aload_0
      //   478: getfield 74	com/c/e/a/a/a/a/a$a:l	Ljava/lang/String;
      //   481: invokevirtual 123	java/lang/String:isEmpty	()Z
      //   484: ifne +380 -> 864
      //   487: iconst_1
      //   488: istore 5
      //   490: aload_0
      //   491: getfield 74	com/c/e/a/a/a/a/a$a:l	Ljava/lang/String;
      //   494: astore_2
      //   495: aload_3
      //   496: getfield 74	com/c/e/a/a/a/a/a$a:l	Ljava/lang/String;
      //   499: invokevirtual 123	java/lang/String:isEmpty	()Z
      //   502: ifne +368 -> 870
      //   505: iconst_1
      //   506: istore 6
      //   508: aload_0
      //   509: aload 8
      //   511: iload 5
      //   513: aload_2
      //   514: iload 6
      //   516: aload_3
      //   517: getfield 74	com/c/e/a/a/a/a/a$a:l	Ljava/lang/String;
      //   520: invokeinterface 126 5 0
      //   525: putfield 74	com/c/e/a/a/a/a/a$a:l	Ljava/lang/String;
      //   528: aload_0
      //   529: getfield 76	com/c/e/a/a/a/a/a$a:m	Ljava/lang/String;
      //   532: invokevirtual 123	java/lang/String:isEmpty	()Z
      //   535: ifne +341 -> 876
      //   538: iconst_1
      //   539: istore 5
      //   541: aload_0
      //   542: getfield 76	com/c/e/a/a/a/a/a$a:m	Ljava/lang/String;
      //   545: astore_2
      //   546: aload_3
      //   547: getfield 76	com/c/e/a/a/a/a/a$a:m	Ljava/lang/String;
      //   550: invokevirtual 123	java/lang/String:isEmpty	()Z
      //   553: ifne +329 -> 882
      //   556: iconst_1
      //   557: istore 6
      //   559: aload_0
      //   560: aload 8
      //   562: iload 5
      //   564: aload_2
      //   565: iload 6
      //   567: aload_3
      //   568: getfield 76	com/c/e/a/a/a/a/a$a:m	Ljava/lang/String;
      //   571: invokeinterface 126 5 0
      //   576: putfield 76	com/c/e/a/a/a/a/a$a:m	Ljava/lang/String;
      //   579: aload_0
      //   580: getfield 78	com/c/e/a/a/a/a/a$a:n	Ljava/lang/String;
      //   583: invokevirtual 123	java/lang/String:isEmpty	()Z
      //   586: ifne +302 -> 888
      //   589: iconst_1
      //   590: istore 5
      //   592: aload_0
      //   593: getfield 78	com/c/e/a/a/a/a/a$a:n	Ljava/lang/String;
      //   596: astore_2
      //   597: aload_3
      //   598: getfield 78	com/c/e/a/a/a/a/a$a:n	Ljava/lang/String;
      //   601: invokevirtual 123	java/lang/String:isEmpty	()Z
      //   604: ifne +290 -> 894
      //   607: iconst_1
      //   608: istore 6
      //   610: aload_0
      //   611: aload 8
      //   613: iload 5
      //   615: aload_2
      //   616: iload 6
      //   618: aload_3
      //   619: getfield 78	com/c/e/a/a/a/a/a$a:n	Ljava/lang/String;
      //   622: invokeinterface 126 5 0
      //   627: putfield 78	com/c/e/a/a/a/a/a$a:n	Ljava/lang/String;
      //   630: aload_0
      //   631: getfield 80	com/c/e/a/a/a/a/a$a:o	Ljava/lang/String;
      //   634: invokevirtual 123	java/lang/String:isEmpty	()Z
      //   637: ifne +263 -> 900
      //   640: iconst_1
      //   641: istore 5
      //   643: aload_0
      //   644: getfield 80	com/c/e/a/a/a/a/a$a:o	Ljava/lang/String;
      //   647: astore_2
      //   648: aload_3
      //   649: getfield 80	com/c/e/a/a/a/a/a$a:o	Ljava/lang/String;
      //   652: invokevirtual 123	java/lang/String:isEmpty	()Z
      //   655: ifne +251 -> 906
      //   658: iconst_1
      //   659: istore 6
      //   661: aload_0
      //   662: aload 8
      //   664: iload 5
      //   666: aload_2
      //   667: iload 6
      //   669: aload_3
      //   670: getfield 80	com/c/e/a/a/a/a/a$a:o	Ljava/lang/String;
      //   673: invokeinterface 126 5 0
      //   678: putfield 80	com/c/e/a/a/a/a/a$a:o	Ljava/lang/String;
      //   681: aload_0
      //   682: getfield 82	com/c/e/a/a/a/a/a$a:p	Ljava/lang/String;
      //   685: invokevirtual 123	java/lang/String:isEmpty	()Z
      //   688: ifne +224 -> 912
      //   691: iconst_1
      //   692: istore 5
      //   694: aload_0
      //   695: getfield 82	com/c/e/a/a/a/a/a$a:p	Ljava/lang/String;
      //   698: astore_2
      //   699: aload_3
      //   700: getfield 82	com/c/e/a/a/a/a/a$a:p	Ljava/lang/String;
      //   703: invokevirtual 123	java/lang/String:isEmpty	()Z
      //   706: ifne +212 -> 918
      //   709: iload 7
      //   711: istore 6
      //   713: aload_0
      //   714: aload 8
      //   716: iload 5
      //   718: aload_2
      //   719: iload 6
      //   721: aload_3
      //   722: getfield 82	com/c/e/a/a/a/a/a$a:p	Ljava/lang/String;
      //   725: invokeinterface 126 5 0
      //   730: putfield 82	com/c/e/a/a/a/a/a$a:p	Ljava/lang/String;
      //   733: aload_0
      //   734: aload 8
      //   736: aload_0
      //   737: getfield 56	com/c/e/a/a/a/a/a$a:q	Lcom/b/b/t;
      //   740: aload_3
      //   741: getfield 56	com/c/e/a/a/a/a/a$a:q	Lcom/b/b/t;
      //   744: invokeinterface 129 3 0
      //   749: putfield 56	com/c/e/a/a/a/a/a$a:q	Lcom/b/b/t;
      //   752: aload_0
      //   753: astore_2
      //   754: aload 8
      //   756: getstatic 134	com/b/b/m$h:a	Lcom/b/b/m$h;
      //   759: if_acmpne -683 -> 76
      //   762: aload_0
      //   763: aload_0
      //   764: getfield 136	com/c/e/a/a/a/a/a$a:d	I
      //   767: aload_3
      //   768: getfield 136	com/c/e/a/a/a/a/a$a:d	I
      //   771: ior
      //   772: putfield 136	com/c/e/a/a/a/a/a$a:d	I
      //   775: aload_0
      //   776: astore_2
      //   777: goto -701 -> 76
      //   780: iconst_0
      //   781: istore 5
      //   783: goto -650 -> 133
      //   786: iconst_0
      //   787: istore 6
      //   789: goto -638 -> 151
      //   792: iconst_0
      //   793: istore 5
      //   795: goto -611 -> 184
      //   798: iconst_0
      //   799: istore 6
      //   801: goto -599 -> 202
      //   804: iconst_0
      //   805: istore 5
      //   807: goto -572 -> 235
      //   810: iconst_0
      //   811: istore 6
      //   813: goto -560 -> 253
      //   816: iconst_0
      //   817: istore 5
      //   819: goto -533 -> 286
      //   822: iconst_0
      //   823: istore 6
      //   825: goto -521 -> 304
      //   828: iconst_0
      //   829: istore 5
      //   831: goto -494 -> 337
      //   834: iconst_0
      //   835: istore 6
      //   837: goto -482 -> 355
      //   840: iconst_0
      //   841: istore 5
      //   843: goto -455 -> 388
      //   846: iconst_0
      //   847: istore 6
      //   849: goto -443 -> 406
      //   852: iconst_0
      //   853: istore 5
      //   855: goto -416 -> 439
      //   858: iconst_0
      //   859: istore 6
      //   861: goto -404 -> 457
      //   864: iconst_0
      //   865: istore 5
      //   867: goto -377 -> 490
      //   870: iconst_0
      //   871: istore 6
      //   873: goto -365 -> 508
      //   876: iconst_0
      //   877: istore 5
      //   879: goto -338 -> 541
      //   882: iconst_0
      //   883: istore 6
      //   885: goto -326 -> 559
      //   888: iconst_0
      //   889: istore 5
      //   891: goto -299 -> 592
      //   894: iconst_0
      //   895: istore 6
      //   897: goto -287 -> 610
      //   900: iconst_0
      //   901: istore 5
      //   903: goto -260 -> 643
      //   906: iconst_0
      //   907: istore 6
      //   909: goto -248 -> 661
      //   912: iconst_0
      //   913: istore 5
      //   915: goto -221 -> 694
      //   918: iconst_0
      //   919: istore 6
      //   921: goto -208 -> 713
      //   924: aload_2
      //   925: checkcast 138	com/b/b/g
      //   928: astore_2
      //   929: aload_3
      //   930: checkcast 140	com/b/b/j
      //   933: astore_3
      //   934: iload 4
      //   936: istore_1
      //   937: iload_1
      //   938: ifne +370 -> 1308
      //   941: aload_2
      //   942: invokevirtual 143	com/b/b/g:a	()I
      //   945: istore 4
      //   947: iload 4
      //   949: lookupswitch	default:+123->1072, 0:+137->1086, 10:+142->1091, 18:+172->1121, 26:+213->1162, 34:+224->1173, 42:+235->1184, 50:+246->1195, 58:+257->1206, 66:+268->1217, 74:+279->1228, 82:+290->1239, 90:+301->1250, 98:+312->1261, 106:+323->1272
      //   1072: aload_2
      //   1073: iload 4
      //   1075: invokevirtual 146	com/b/b/g:b	(I)Z
      //   1078: ifne -141 -> 937
      //   1081: iconst_1
      //   1082: istore_1
      //   1083: goto -146 -> 937
      //   1086: iconst_1
      //   1087: istore_1
      //   1088: goto -151 -> 937
      //   1091: aload_0
      //   1092: aload_2
      //   1093: invokevirtual 149	com/b/b/g:k	()Ljava/lang/String;
      //   1096: putfield 60	com/c/e/a/a/a/a/a$a:e	Ljava/lang/String;
      //   1099: goto -162 -> 937
      //   1102: astore_3
      //   1103: new 151	java/lang/RuntimeException
      //   1106: astore_2
      //   1107: aload_2
      //   1108: aload_3
      //   1109: aload_0
      //   1110: invokevirtual 154	com/b/b/o:a	(Lcom/b/b/u;)Lcom/b/b/o;
      //   1113: invokespecial 157	java/lang/RuntimeException:<init>	(Ljava/lang/Throwable;)V
      //   1116: aload_2
      //   1117: athrow
      //   1118: astore_2
      //   1119: aload_2
      //   1120: athrow
      //   1121: aload_0
      //   1122: aload_2
      //   1123: invokevirtual 149	com/b/b/g:k	()Ljava/lang/String;
      //   1126: putfield 62	com/c/e/a/a/a/a/a$a:f	Ljava/lang/String;
      //   1129: goto -192 -> 937
      //   1132: astore 8
      //   1134: new 151	java/lang/RuntimeException
      //   1137: astore_2
      //   1138: new 101	com/b/b/o
      //   1141: astore_3
      //   1142: aload_3
      //   1143: aload 8
      //   1145: invokevirtual 160	java/io/IOException:getMessage	()Ljava/lang/String;
      //   1148: invokespecial 163	com/b/b/o:<init>	(Ljava/lang/String;)V
      //   1151: aload_2
      //   1152: aload_3
      //   1153: aload_0
      //   1154: invokevirtual 154	com/b/b/o:a	(Lcom/b/b/u;)Lcom/b/b/o;
      //   1157: invokespecial 157	java/lang/RuntimeException:<init>	(Ljava/lang/Throwable;)V
      //   1160: aload_2
      //   1161: athrow
      //   1162: aload_0
      //   1163: aload_2
      //   1164: invokevirtual 149	com/b/b/g:k	()Ljava/lang/String;
      //   1167: putfield 64	com/c/e/a/a/a/a/a$a:g	Ljava/lang/String;
      //   1170: goto -233 -> 937
      //   1173: aload_0
      //   1174: aload_2
      //   1175: invokevirtual 149	com/b/b/g:k	()Ljava/lang/String;
      //   1178: putfield 66	com/c/e/a/a/a/a/a$a:h	Ljava/lang/String;
      //   1181: goto -244 -> 937
      //   1184: aload_0
      //   1185: aload_2
      //   1186: invokevirtual 149	com/b/b/g:k	()Ljava/lang/String;
      //   1189: putfield 68	com/c/e/a/a/a/a/a$a:i	Ljava/lang/String;
      //   1192: goto -255 -> 937
      //   1195: aload_0
      //   1196: aload_2
      //   1197: invokevirtual 149	com/b/b/g:k	()Ljava/lang/String;
      //   1200: putfield 70	com/c/e/a/a/a/a/a$a:j	Ljava/lang/String;
      //   1203: goto -266 -> 937
      //   1206: aload_0
      //   1207: aload_2
      //   1208: invokevirtual 149	com/b/b/g:k	()Ljava/lang/String;
      //   1211: putfield 72	com/c/e/a/a/a/a/a$a:k	Ljava/lang/String;
      //   1214: goto -277 -> 937
      //   1217: aload_0
      //   1218: aload_2
      //   1219: invokevirtual 149	com/b/b/g:k	()Ljava/lang/String;
      //   1222: putfield 74	com/c/e/a/a/a/a/a$a:l	Ljava/lang/String;
      //   1225: goto -288 -> 937
      //   1228: aload_0
      //   1229: aload_2
      //   1230: invokevirtual 149	com/b/b/g:k	()Ljava/lang/String;
      //   1233: putfield 76	com/c/e/a/a/a/a/a$a:m	Ljava/lang/String;
      //   1236: goto -299 -> 937
      //   1239: aload_0
      //   1240: aload_2
      //   1241: invokevirtual 149	com/b/b/g:k	()Ljava/lang/String;
      //   1244: putfield 78	com/c/e/a/a/a/a/a$a:n	Ljava/lang/String;
      //   1247: goto -310 -> 937
      //   1250: aload_0
      //   1251: aload_2
      //   1252: invokevirtual 149	com/b/b/g:k	()Ljava/lang/String;
      //   1255: putfield 80	com/c/e/a/a/a/a/a$a:o	Ljava/lang/String;
      //   1258: goto -321 -> 937
      //   1261: aload_0
      //   1262: aload_2
      //   1263: invokevirtual 149	com/b/b/g:k	()Ljava/lang/String;
      //   1266: putfield 82	com/c/e/a/a/a/a/a$a:p	Ljava/lang/String;
      //   1269: goto -332 -> 937
      //   1272: aload_0
      //   1273: getfield 56	com/c/e/a/a/a/a/a$a:q	Lcom/b/b/t;
      //   1276: invokevirtual 86	com/b/b/t:d	()Z
      //   1279: ifne +14 -> 1293
      //   1282: aload_0
      //   1283: aload_0
      //   1284: getfield 56	com/c/e/a/a/a/a/a$a:q	Lcom/b/b/t;
      //   1287: invokevirtual 88	com/b/b/t:b	()Lcom/b/b/t;
      //   1290: putfield 56	com/c/e/a/a/a/a/a$a:q	Lcom/b/b/t;
      //   1293: getstatic 166	com/c/e/a/a/a/a/a$a$b:a	Lcom/b/b/r;
      //   1296: aload_0
      //   1297: getfield 56	com/c/e/a/a/a/a/a$a:q	Lcom/b/b/t;
      //   1300: aload_2
      //   1301: aload_3
      //   1302: invokevirtual 171	com/b/b/r:a	(Lcom/b/b/t;Lcom/b/b/g;Lcom/b/b/j;)V
      //   1305: goto -368 -> 937
      //   1308: getstatic 45	com/c/e/a/a/a/a/a$a:r	Lcom/c/e/a/a/a/a/a$a;
      //   1311: astore_2
      //   1312: goto -1236 -> 76
      //   1315: getstatic 173	com/c/e/a/a/a/a/a$a:s	Lcom/b/b/x;
      //   1318: ifnonnull +30 -> 1348
      //   1321: ldc 2
      //   1323: monitorenter
      //   1324: getstatic 173	com/c/e/a/a/a/a/a$a:s	Lcom/b/b/x;
      //   1327: ifnonnull +18 -> 1345
      //   1330: new 175	com/b/b/m$b
      //   1333: astore_2
      //   1334: aload_2
      //   1335: getstatic 45	com/c/e/a/a/a/a/a$a:r	Lcom/c/e/a/a/a/a/a$a;
      //   1338: invokespecial 178	com/b/b/m$b:<init>	(Lcom/b/b/m;)V
      //   1341: aload_2
      //   1342: putstatic 173	com/c/e/a/a/a/a/a$a:s	Lcom/b/b/x;
      //   1345: ldc 2
      //   1347: monitorexit
      //   1348: getstatic 173	com/c/e/a/a/a/a/a$a:s	Lcom/b/b/x;
      //   1351: astore_2
      //   1352: goto -1276 -> 76
      //   1355: astore_2
      //   1356: ldc 2
      //   1358: monitorexit
      //   1359: aload_2
      //   1360: athrow
      // Local variable table:
      //   start	length	slot	name	signature
      //   0	1361	0	this	a
      //   0	1361	1	paramInt	int
      //   0	1361	2	paramObject1	Object
      //   0	1361	3	paramObject2	Object
      //   4	1070	4	i1	int
      //   131	783	5	bool1	boolean
      //   149	771	6	bool2	boolean
      //   1	709	7	bool3	boolean
      //   113	642	8	localj	com.b.b.m.j
      //   1132	12	8	localIOException	java.io.IOException
      // Exception table:
      //   from	to	target	type
      //   941	947	1102	com/b/b/o
      //   1072	1081	1102	com/b/b/o
      //   1091	1099	1102	com/b/b/o
      //   1121	1129	1102	com/b/b/o
      //   1162	1170	1102	com/b/b/o
      //   1173	1181	1102	com/b/b/o
      //   1184	1192	1102	com/b/b/o
      //   1195	1203	1102	com/b/b/o
      //   1206	1214	1102	com/b/b/o
      //   1217	1225	1102	com/b/b/o
      //   1228	1236	1102	com/b/b/o
      //   1239	1247	1102	com/b/b/o
      //   1250	1258	1102	com/b/b/o
      //   1261	1269	1102	com/b/b/o
      //   1272	1293	1102	com/b/b/o
      //   1293	1305	1102	com/b/b/o
      //   941	947	1118	finally
      //   1072	1081	1118	finally
      //   1091	1099	1118	finally
      //   1103	1118	1118	finally
      //   1121	1129	1118	finally
      //   1134	1162	1118	finally
      //   1162	1170	1118	finally
      //   1173	1181	1118	finally
      //   1184	1192	1118	finally
      //   1195	1203	1118	finally
      //   1206	1214	1118	finally
      //   1217	1225	1118	finally
      //   1228	1236	1118	finally
      //   1239	1247	1118	finally
      //   1250	1258	1118	finally
      //   1261	1269	1118	finally
      //   1272	1293	1118	finally
      //   1293	1305	1118	finally
      //   941	947	1132	java/io/IOException
      //   1072	1081	1132	java/io/IOException
      //   1091	1099	1132	java/io/IOException
      //   1121	1129	1132	java/io/IOException
      //   1162	1170	1132	java/io/IOException
      //   1173	1181	1132	java/io/IOException
      //   1184	1192	1132	java/io/IOException
      //   1195	1203	1132	java/io/IOException
      //   1206	1214	1132	java/io/IOException
      //   1217	1225	1132	java/io/IOException
      //   1228	1236	1132	java/io/IOException
      //   1239	1247	1132	java/io/IOException
      //   1250	1258	1132	java/io/IOException
      //   1261	1269	1132	java/io/IOException
      //   1272	1293	1132	java/io/IOException
      //   1293	1305	1132	java/io/IOException
      //   1324	1345	1355	finally
      //   1345	1348	1355	finally
      //   1356	1359	1355	finally
    }
    
    public final void a(h paramh)
    {
      if (!this.e.isEmpty()) {
        paramh.a(1, this.e);
      }
      if (!this.f.isEmpty()) {
        paramh.a(2, this.f);
      }
      if (!this.g.isEmpty()) {
        paramh.a(3, this.g);
      }
      if (!this.h.isEmpty()) {
        paramh.a(4, this.h);
      }
      if (!this.i.isEmpty()) {
        paramh.a(5, this.i);
      }
      if (!this.j.isEmpty()) {
        paramh.a(6, this.j);
      }
      if (!this.k.isEmpty()) {
        paramh.a(7, this.k);
      }
      if (!this.l.isEmpty()) {
        paramh.a(8, this.l);
      }
      if (!this.m.isEmpty()) {
        paramh.a(9, this.m);
      }
      if (!this.n.isEmpty()) {
        paramh.a(10, this.n);
      }
      if (!this.o.isEmpty()) {
        paramh.a(11, this.o);
      }
      if (!this.p.isEmpty()) {
        paramh.a(12, this.p);
      }
      Iterator localIterator = this.q.entrySet().iterator();
      while (localIterator.hasNext())
      {
        Map.Entry localEntry = (Map.Entry)localIterator.next();
        b.a.a(paramh, 13, localEntry.getKey(), localEntry.getValue());
      }
    }
    
    public final int k()
    {
      int i1 = this.c;
      if (i1 != -1) {}
      for (;;)
      {
        return i1;
        int i2 = 0;
        if (!this.e.isEmpty()) {
          i2 = h.b(1, this.e) + 0;
        }
        i1 = i2;
        if (!this.f.isEmpty()) {
          i1 = i2 + h.b(2, this.f);
        }
        i2 = i1;
        if (!this.g.isEmpty()) {
          i2 = i1 + h.b(3, this.g);
        }
        i1 = i2;
        if (!this.h.isEmpty()) {
          i1 = i2 + h.b(4, this.h);
        }
        i2 = i1;
        if (!this.i.isEmpty()) {
          i2 = i1 + h.b(5, this.i);
        }
        i1 = i2;
        if (!this.j.isEmpty()) {
          i1 = i2 + h.b(6, this.j);
        }
        i2 = i1;
        if (!this.k.isEmpty()) {
          i2 = i1 + h.b(7, this.k);
        }
        i1 = i2;
        if (!this.l.isEmpty()) {
          i1 = i2 + h.b(8, this.l);
        }
        i2 = i1;
        if (!this.m.isEmpty()) {
          i2 = i1 + h.b(9, this.m);
        }
        int i3 = i2;
        if (!this.n.isEmpty()) {
          i3 = i2 + h.b(10, this.n);
        }
        i1 = i3;
        if (!this.o.isEmpty()) {
          i1 = i3 + h.b(11, this.o);
        }
        i2 = i1;
        if (!this.p.isEmpty()) {
          i2 = i1 + h.b(12, this.p);
        }
        Iterator localIterator = this.q.entrySet().iterator();
        Map.Entry localEntry;
        for (i1 = i2; localIterator.hasNext(); i1 = b.a.a(13, localEntry.getKey(), localEntry.getValue()) + i1) {
          localEntry = (Map.Entry)localIterator.next();
        }
        this.c = i1;
      }
    }
    
    public static final class a
      extends m.a<a.a, a>
      implements a.b
    {
      private a()
      {
        super();
      }
      
      public final a a(String paramString)
      {
        b();
        a.a.a((a.a)this.a, paramString);
        return this;
      }
      
      public final a a(String paramString1, String paramString2)
      {
        if (paramString1 == null) {
          throw new NullPointerException();
        }
        if (paramString2 == null) {
          throw new NullPointerException();
        }
        b();
        a.a.a((a.a)this.a).put(paramString1, paramString2);
        return this;
      }
      
      public final a b(String paramString)
      {
        b();
        a.a.b((a.a)this.a, paramString);
        return this;
      }
      
      public final a c(String paramString)
      {
        b();
        a.a.c((a.a)this.a, paramString);
        return this;
      }
      
      public final a d(String paramString)
      {
        b();
        a.a.d((a.a)this.a, paramString);
        return this;
      }
      
      public final a e(String paramString)
      {
        b();
        a.a.e((a.a)this.a, paramString);
        return this;
      }
      
      public final a f(String paramString)
      {
        b();
        a.a.f((a.a)this.a, paramString);
        return this;
      }
      
      public final a g(String paramString)
      {
        b();
        a.a.g((a.a)this.a, paramString);
        return this;
      }
      
      public final a h(String paramString)
      {
        b();
        a.a.h((a.a)this.a, paramString);
        return this;
      }
      
      public final a i(String paramString)
      {
        b();
        a.a.i((a.a)this.a, paramString);
        return this;
      }
      
      public final a j(String paramString)
      {
        b();
        a.a.j((a.a)this.a, paramString);
        return this;
      }
      
      public final a k(String paramString)
      {
        b();
        a.a.k((a.a)this.a, paramString);
        return this;
      }
      
      public final a l(String paramString)
      {
        b();
        a.a.l((a.a)this.a, paramString);
        return this;
      }
    }
    
    private static final class b
    {
      static final r<String, String> a = r.a(ak.a.i, "", ak.a.i, "");
    }
  }
  
  public static abstract interface b
    extends v
  {}
}


/* Location:              /Users/hanlian/Downloads/WiFi万能钥匙dex1-dex2jar.jar!/com/c/e/a/a/a/a/a.class
 * Java compiler version: 6 (50.0)
 * JD-Core Version:       0.7.1
 */