package com.lantern.settings.diagnose;

public class b
{
  private static final String a = b.class.getSimpleName();
  private String b;
  private int c = 5000;
  private int d = 5000;
  private int e = -1;
  
  public b(String paramString)
  {
    this.b = paramString;
  }
  
  /* Error */
  public final String a(java.util.Map<String, String> paramMap)
  {
    // Byte code:
    //   0: new 41	org/apache/http/client/methods/HttpPost
    //   3: dup
    //   4: aload_0
    //   5: getfield 34	com/lantern/settings/diagnose/b:b	Ljava/lang/String;
    //   8: invokespecial 43	org/apache/http/client/methods/HttpPost:<init>	(Ljava/lang/String;)V
    //   11: astore_2
    //   12: new 45	java/lang/StringBuilder
    //   15: dup
    //   16: ldc 47
    //   18: invokespecial 48	java/lang/StringBuilder:<init>	(Ljava/lang/String;)V
    //   21: aload_0
    //   22: getfield 34	com/lantern/settings/diagnose/b:b	Ljava/lang/String;
    //   25: invokevirtual 52	java/lang/StringBuilder:append	(Ljava/lang/String;)Ljava/lang/StringBuilder;
    //   28: invokevirtual 55	java/lang/StringBuilder:toString	()Ljava/lang/String;
    //   31: iconst_0
    //   32: anewarray 4	java/lang/Object
    //   35: invokestatic 60	com/bluefay/b/h:a	(Ljava/lang/String;[Ljava/lang/Object;)V
    //   38: new 62	java/util/ArrayList
    //   41: astore_3
    //   42: aload_3
    //   43: invokespecial 63	java/util/ArrayList:<init>	()V
    //   46: aload_1
    //   47: invokeinterface 69 1 0
    //   52: invokeinterface 75 1 0
    //   57: astore 6
    //   59: aload 6
    //   61: invokeinterface 81 1 0
    //   66: ifeq +58 -> 124
    //   69: aload 6
    //   71: invokeinterface 85 1 0
    //   76: checkcast 87	java/util/Map$Entry
    //   79: astore 4
    //   81: new 89	org/apache/http/message/BasicNameValuePair
    //   84: astore 5
    //   86: aload 5
    //   88: aload 4
    //   90: invokeinterface 92 1 0
    //   95: checkcast 94	java/lang/String
    //   98: aload 4
    //   100: invokeinterface 97 1 0
    //   105: checkcast 94	java/lang/String
    //   108: invokespecial 100	org/apache/http/message/BasicNameValuePair:<init>	(Ljava/lang/String;Ljava/lang/String;)V
    //   111: aload_3
    //   112: aload 5
    //   114: invokevirtual 104	java/util/ArrayList:add	(Ljava/lang/Object;)Z
    //   117: pop
    //   118: goto -59 -> 59
    //   121: astore_1
    //   122: aload_1
    //   123: athrow
    //   124: new 106	org/apache/http/client/entity/UrlEncodedFormEntity
    //   127: astore 4
    //   129: aload 4
    //   131: aload_3
    //   132: ldc 108
    //   134: invokespecial 111	org/apache/http/client/entity/UrlEncodedFormEntity:<init>	(Ljava/util/List;Ljava/lang/String;)V
    //   137: aload_2
    //   138: aload 4
    //   140: invokevirtual 115	org/apache/http/client/methods/HttpPost:setEntity	(Lorg/apache/http/HttpEntity;)V
    //   143: new 45	java/lang/StringBuilder
    //   146: astore_3
    //   147: aload_3
    //   148: ldc 117
    //   150: invokespecial 48	java/lang/StringBuilder:<init>	(Ljava/lang/String;)V
    //   153: aload_3
    //   154: aload_1
    //   155: invokevirtual 118	java/lang/Object:toString	()Ljava/lang/String;
    //   158: invokevirtual 52	java/lang/StringBuilder:append	(Ljava/lang/String;)Ljava/lang/StringBuilder;
    //   161: invokevirtual 55	java/lang/StringBuilder:toString	()Ljava/lang/String;
    //   164: iconst_0
    //   165: anewarray 4	java/lang/Object
    //   168: invokestatic 60	com/bluefay/b/h:a	(Ljava/lang/String;[Ljava/lang/Object;)V
    //   171: new 120	org/apache/http/params/BasicHttpParams
    //   174: astore_3
    //   175: aload_3
    //   176: invokespecial 121	org/apache/http/params/BasicHttpParams:<init>	()V
    //   179: aload_3
    //   180: aload_0
    //   181: getfield 28	com/lantern/settings/diagnose/b:c	I
    //   184: invokestatic 127	org/apache/http/params/HttpConnectionParams:setConnectionTimeout	(Lorg/apache/http/params/HttpParams;I)V
    //   187: aload_3
    //   188: aload_0
    //   189: getfield 30	com/lantern/settings/diagnose/b:d	I
    //   192: invokestatic 130	org/apache/http/params/HttpConnectionParams:setSoTimeout	(Lorg/apache/http/params/HttpParams;I)V
    //   195: aload_2
    //   196: aload_3
    //   197: invokevirtual 134	org/apache/http/client/methods/HttpPost:setParams	(Lorg/apache/http/params/HttpParams;)V
    //   200: new 136	org/apache/http/impl/client/DefaultHttpClient
    //   203: astore_1
    //   204: aload_1
    //   205: aload_3
    //   206: invokespecial 138	org/apache/http/impl/client/DefaultHttpClient:<init>	(Lorg/apache/http/params/HttpParams;)V
    //   209: aload_1
    //   210: aload_2
    //   211: invokeinterface 144 2 0
    //   216: astore_1
    //   217: aload_1
    //   218: invokeinterface 150 1 0
    //   223: ifnull +18 -> 241
    //   226: aload_0
    //   227: aload_1
    //   228: invokeinterface 150 1 0
    //   233: invokeinterface 156 1 0
    //   238: putfield 32	com/lantern/settings/diagnose/b:e	I
    //   241: aload_1
    //   242: invokeinterface 160 1 0
    //   247: ldc 108
    //   249: invokestatic 165	org/apache/http/util/EntityUtils:toString	(Lorg/apache/http/HttpEntity;Ljava/lang/String;)Ljava/lang/String;
    //   252: astore_1
    //   253: aload_1
    //   254: areturn
    //   255: astore_1
    //   256: new 167	com/lantern/settings/diagnose/f
    //   259: dup
    //   260: aload_1
    //   261: invokespecial 170	com/lantern/settings/diagnose/f:<init>	(Ljava/lang/Exception;)V
    //   264: athrow
    // Local variable table:
    //   start	length	slot	name	signature
    //   0	265	0	this	b
    //   0	265	1	paramMap	java.util.Map<String, String>
    //   11	200	2	localHttpPost	org.apache.http.client.methods.HttpPost
    //   41	165	3	localObject1	Object
    //   79	60	4	localObject2	Object
    //   84	29	5	localBasicNameValuePair	org.apache.http.message.BasicNameValuePair
    //   57	13	6	localIterator	java.util.Iterator
    // Exception table:
    //   from	to	target	type
    //   38	59	121	java/net/SocketTimeoutException
    //   59	118	121	java/net/SocketTimeoutException
    //   124	241	121	java/net/SocketTimeoutException
    //   241	253	121	java/net/SocketTimeoutException
    //   38	59	255	java/lang/Exception
    //   59	118	255	java/lang/Exception
    //   124	241	255	java/lang/Exception
    //   241	253	255	java/lang/Exception
  }
}


/* Location:              /Users/hanlian/Downloads/WiFi万能钥匙dex1-dex2jar.jar!/com/lantern/settings/diagnose/b.class
 * Java compiler version: 6 (50.0)
 * JD-Core Version:       0.7.1
 */